Workbook

Sheet 封面
B2: AI应用概念深度清洗报告
B3: 复核日期：2026-10-27｜范围：117只｜重点：真实AI产品、商业化、分类边界与详细理由
B6: 复核股票（只） | C6: =COUNTA('清洗总表'!$B$5:$B$121)
B7: 保留AI应用（只） | C7: =COUNTA('AI应用'!$B$5:$B$88)
B8: 跨分类迁移（只） | C8: =COUNTA('跨分类迁移'!$B$5:$B$24)
B9: 完全摘除（只） | C9: =COUNTA('摘除清单'!$B$5:$B$21)
B10: 核心判词（只） | C10: =COUNTIF('清洗总表'!$H$5:$H$121,"核心")
B11: 纠错动作（只） | C11: =COUNTIF('清洗总表'!$E$5:$E$121,"纠错")
B14: 工作表索引
B15: 清洗总表 | C15: 117只旧概念、新概念、动作、判词、详细理由和证据
B16: AI应用 | C16: 84只清洗后AI应用公司
B17: 跨分类迁移 | C17: 20只物理AI或数据要素迁移公司
B18: 摘除清单 | C18: 17只错标、传统业务或落地不足公司
B19: 概念统计 | C19: 各二级概念核心/相关数量，底层为精确展开数据
B22: 核心：AI是明确主营、重要收入或规模化核心产品；相关：有真实产品、客户、项目或收入，但仍属新业务或收入占比较低。
B23: 普通短剧不等于AI影视，普通数字营销不等于AI营销，一般数字化不等于AI应用；仅有战略、研发或内部探索的从严退出。
B24: 实体交互终端、物理视觉和控制归物理AI；可授权训练数据集和内容数据归数据要素，避免同一业务重复贴标。
B25: 主营资料：iFinD ifind_get_stock_info（2026-10-27）；逐股证据名称、日期及URL见Source列。

Sheet 清洗总表
B2: AI应用 · 117只逐项复核
B3: 重新审核产品直接性和商业化证据；详细说明保留、纠错、迁移或摘除理由。
B4: 代码 | C4: 名称 | D4: 旧AI应用概念 | E4: 动作 | F4: 新一级分类 | G4: 新概念 | H4: 判词 | I4: 详细理由 | J4: 证据名称 | K4: 证据日期 | L4: Source Name | M4: Source URL
B5: 000526 | C5: 学大教育 | D5: AI应用：AI教育 | E5: 摘除 | F5: — | G5: — | H5: 摘除 | I5: 公司主营个性化教育培训，2025年半年报披露约330所学习中心及“双螺旋”线上线下融合教学模式，但未见可核验的自营AI教育产品、AI客户交付或AI收入。“个性化教学”和数字化授课不能直接等同于人工智能应用，缺少真实AI产品及商业化证据，因此原AI教育关联属于概念误推，应予摘除。 | J5: 学大（厦门）教育科技集团股份有限公司2025年半年度报告 | K5: 2025-08-28 | L5: iFinD ifind_get_stock_info (as of 2026-10-27)；学大（厦门）教育科技集团股份有限公司2025年半年度报告 | M5: https://static.cninfo.com.cn/finalpage/2025-08-28/1224598398.PDF
B6: 000607 | C6: 华媒控股 | D6: AI应用：AI影视短剧 | E6: 摘除 | F6: — | G6: — | H6: 摘除 | I6: 公司主营广告、报刊、印刷及教育业务，2025年报虽提及数字人、“审点芯”“杭州迹忆”等探索，但仍属初步尝试且暂无明显业绩贡献，未披露可核验的AI短剧产品、客户项目或收入。AIGC内容工具体验不能直接认定为AI影视短剧商业化，更不足以支撑核心定级，因此摘除原有关联。 | J6: 浙江华媒控股股份有限公司2025年年度报告摘要 | K6: 2026-04-24 | L6: iFinD ifind_get_stock_info (as of 2026-10-27)；浙江华媒控股股份有限公司2025年年度报告摘要 | M6: https://static.cninfo.com.cn/finalpage/2026-04-24/1225163833.PDF
B7: 000676 | C7: 智度股份 | D7: AI应用：AI营销 | E7: 保留 | F7: AI应用 | G7: AI营销 | H7: 相关 | I7: 公司主营互联网媒体与数字营销，2025年半年报披露已在营销内容生产中使用文心一言、DeepSeek及文生文、文生图、文生视频和Agent能力提升客户营销效果，并有Wave AI Assistant等真实产品。AI直接服务于主营营销流程，但AIGC商业模式仍在探索、独立收入未披露，故保留AI营销并定为相关而非核心。 | J7: 智度股份：2025年半年度报告 | K7: 2025-08-28 | L7: iFinD ifind_get_stock_info (as of 2026-10-27)；智度股份：2025年半年度报告 | M7: https://money.finance.sina.com.cn/corp/view/vCB_AllBulletinDetail.php?stockid=000676&id=11397020
B8: 000681 | C8: 视觉中国 | D8: AI应用：字节生态 | E8: 迁移 | F8: AI应用、数据要素 | G8: AI视觉；数据要素_训练数据、数据要素_内容数据 | H8: 核心 | I8: 公司主营正版视觉内容及增值服务，2025年报已将数据服务列为主营产品，拥有超7亿多模态合规数据，提供采集、确权、标注、授权及API、沙箱交付，并与阿里、腾讯、微软、快手等签署训练数据服务协议、完成上游授权收益分配；AIGC创意定制亦已向荣耀、奔驰等客户交付。真实主营、产品交付和收入均成立，故取消“字节生态”，保留AI视觉并新增训练数据、内容数据，定核心。 | J8: 视觉中国：2025年年度报告 | K8: 2026-03-31 | L8: iFinD ifind_get_stock_info (as of 2026-10-27)；视觉中国：2025年年度报告 | M8: https://money.finance.sina.com.cn/corp/view/vCB_AllBulletinDetail.php?stockid=000681&id=12047786
B9: 000802 | C9: 北京文化 | D9: AI应用：AI影视短剧 | E9: 摘除 | F9: — | G9: — | H9: 摘除 | I9: 公司主营电影、电视剧、网剧、演艺经纪及旅游业务，2025年年度报告摘要仍围绕影视内容投资、制作与发行披露经营情况，未见公司自研AI影视产品、AI短剧项目、客户交付或相关收入。传统影视制作及行业“人工智能+视听”政策不能替代公司层面的业务证据，原核心定级主要由影视主业误推，因此应予摘除。 | J9: 北京文化：2025年年度报告摘要 | K9: 2026-04-18 | L9: iFinD ifind_get_stock_info (as of 2026-10-27)；北京文化：2025年年度报告摘要 | M9: https://data.eastmoney.com/notices/detail/000802/AN202604171821301219,JUU1JThDJTk3JUU0JUJBJUFDJUU2JTk2JTg3JUU1JThDJTk2.html
B10: 000892 | C10: 欢瑞世纪 | D10: AI应用：短剧；AI应用：AI影视短剧 | E10: 纠错 | F10: AI应用 | G10: AI影视短剧 | H10: 相关 | I10: 公司主营影视剧制作发行及艺人经纪，2025年报披露与阶跃星辰共建“麟跃”AI联合实验室，技术覆盖剧本、分镜、制作、剪辑和配音，已上线《十州三境》AI短剧概念片及江西人文宣传片《传承江西》，并引入Glowave X平台。产品与项目真实存在，但公司明确AI收入占比极低，故合并“短剧”和“AI影视短剧”为后者，并由核心降为相关。 | J10: 欢瑞世纪：2025年年度报告 | K10: 2026-04-30 | L10: iFinD ifind_get_stock_info (as of 2026-10-27)；欢瑞世纪：2025年年度报告 | M10: https://money.finance.sina.com.cn/corp/view/vCB_AllBulletinDetail.php?stockid=000892&id=12287047
B11: 000917 | C11: 电广传媒 | D11: AI应用：AI营销 | E11: 摘除 | F11: — | G11: — | H11: 摘除 | I11: 公司业务涵盖文旅、投资、广告及游戏，广告运营虽是2025年主要收入来源，但年报对人工智能仅表述为“探索AI赋能广告业务转型路径”，其余多为行业泛述、文旅内容工具或达晨投资项目，未形成可核验的自有AI营销产品和客户交付。普通信息流广告不能直接贴AI标签，探索性表述亦不足以支持商业化定级，因此摘除。 | J11: 电广传媒：2025年年度报告 | K11: 2026-04-28 | L11: iFinD ifind_get_stock_info (as of 2026-10-27)；电广传媒：2025年年度报告 | M11: https://money.finance.sina.com.cn/corp/view/vCB_AllBulletinDetail.php?stockid=000917&id=12233295
B12: 001229 | C12: 魅视科技 | D12: AI应用：AI应用 | E12: 迁移 | F12: 物理AI | G12: 物理AI_机器视觉 | H12: 相关 | I12: 公司主营专业视听产品，AI边缘智能分析平台面向高速路段、收费场景等真实物理视频环境，具备人、车、物、环境检测、抓拍和告警能力，并已有交投集团项目案例。2025年AI系列收入2534.22万元、同比增长212.59%，但仍处推广期且约占总营收11%，故将泛AI应用细化为物理环境机器视觉，迁移至物理AI_机器视觉并定为相关。 | J12: 广东魅视科技股份有限公司投资者关系活动记录表 | K12: 2026-06-10 | L12: iFinD ifind_get_stock_info (as of 2026-10-27)；广东魅视科技股份有限公司投资者关系活动记录表 | M12: http://pdf.dfcfw.com/pdf/H2_AN202606101823425361_1.PDF
B13: 001314 | C13: 亿道信息 | D13: AI应用：AI终端 | E13: 迁移 | F13: 物理AI | G13: 物理AI_智能终端 | H13: 相关 | I13: 公司主营智能硬件研发制造，子公司亿境虚拟已布局AI音频、拍照、显示眼镜、多模态记录设备及SW3035方案和端边云系统，具备较短周期量产交付能力。2025年XR及AIoT收入4.208亿元、占比9.18%，但未单列AI眼镜收入，整体仍以传统智能硬件为主，因此由原AI终端规范迁移为物理AI_智能终端，并由核心降为相关。 | J13: 亿道信息：2025年年度报告 | K13: 2026-04-23 | L13: iFinD ifind_get_stock_info (as of 2026-10-27)；亿道信息：2025年年度报告 | M13: https://money.finance.sina.com.cn/corp/view/vCB_AllBulletinDetail.php?stockid=001314&id=12154989
B14: 001330 | C14: 博纳影业 | D14: AI应用：短剧；AI应用：AI影视短剧 | E14: 纠错 | F14: AI应用 | G14: AI影视短剧 | H14: 相关 | I14: 公司主营电影投资制作、发行及影院业务，已建设AIGMS、博越星纪蓝图和博卡云片场等AI影视能力，推出《三星堆：未来启示录》，AI长片《三星堆：未来往事》取得公映许可并于2026年10月23日上映。相关业务具备真实产品和商业发行，但2025年AI影视剧收入仅238.7万元，尚非主要收入来源，故合并重复短剧标签并保留AI影视短剧，由核心降为相关。 | J14: AI造电影|博纳影业|三星堆 | K14: 2026-10-24 | L14: iFinD ifind_get_stock_info (as of 2026-10-27)；AI造电影|博纳影业|三星堆 | M14: https://k.sina.com.cn/article_5953466437_162dab0450670bfuxm.html?from=ent
B15: 002027 | C15: 分众传媒 | D15: AI应用：AI营销 | E15: 保留 | F15: AI应用 | G15: AI营销 | H15: 相关 | I15: 公司主营楼宇及影院等生活圈媒体，已基于通义百炼推出“众智AI”，覆盖客户洞察、创意生成、策略制定和投放优化；后续“分众智投”面向本地生活客户提供潜客筛选、点位优选、智能监播及效果评估，“众小智”已在内部使用。AI产品直接服务主营广告营销且已有客户应用，但AI收入未单独披露，故保留AI营销并定为相关。 | J15: 分众传媒2025年财报：主营业务稳健增长多维亮点赋能未来 | K15: 2026-04-29 | L15: iFinD ifind_get_stock_info (as of 2026-10-27)；分众传媒2025年财报：主营业务稳健增长多维亮点赋能未来 | M15: https://www.xinhuanet.com/tech/20260429/d6d2346440414e388f9a2c55d5d5ba9a/c.html
... B121: 688787 | C121: 海天瑞声 | D121: AI应用：AI语料 | E121: 迁移 | F121: 数据要素 | G121: 数据要素_训练数据 | H121: 核心 | I121: 公司主营就是AI训练数据研发、生产和销售，语音、视觉及自然语言数据集经采集、清洗、标注后交付；标准数据集按使用授权收费，定制数据集按项目收取服务费，客户和商业模式清晰，维持核心。原AI语料属于AI应用泛化标签，实际直接产品为可授权及定制交付的训练数据，因此迁移至数据要素_训练数据。 | J121: 海天瑞声：2025年年度报告 | K121: 2026-04-24 | L121: iFinD ifind_get_stock_info (as of 2026-10-27)；海天瑞声：2025年年度报告 | M121: https://money.finance.sina.com.cn/corp/view/vCB_AllBulletinDetail.php?stockid=688787&id=12167706

Sheet AI应用
B2: AI应用 · 清洗后股池
B3: 传统短剧、普通营销、一般数字化不直接贴AI；泛标签已细化到具体应用。
B4: 代码 | C4: 名称 | D4: 旧AI应用概念 | E4: 动作 | F4: 新一级分类 | G4: 新概念 | H4: 判词 | I4: 详细理由 | J4: 证据名称 | K4: 证据日期 | L4: Source Name | M4: Source URL
B5: 000676 | C5: 智度股份 | D5: AI应用：AI营销 | E5: 保留 | F5: AI应用 | G5: AI营销 | H5: 相关 | I5: 公司主营互联网媒体与数字营销，2025年半年报披露已在营销内容生产中使用文心一言、DeepSeek及文生文、文生图、文生视频和Agent能力提升客户营销效果，并有Wave AI Assistant等真实产品。AI直接服务于主营营销流程，但AIGC商业模式仍在探索、独立收入未披露，故保留AI营销并定为相关而非核心。 | J5: 智度股份：2025年半年度报告 | K5: 2025-08-28 | L5: iFinD ifind_get_stock_info (as of 2026-10-27)；智度股份：2025年半年度报告 | M5: https://money.finance.sina.com.cn/corp/view/vCB_AllBulletinDetail.php?stockid=000676&id=11397020
B6: 000681 | C6: 视觉中国 | D6: AI应用：字节生态 | E6: 迁移 | F6: AI应用 | G6: AI视觉 | H6: 核心 | I6: 公司主营正版视觉内容及增值服务，2025年报已将数据服务列为主营产品，拥有超7亿多模态合规数据，提供采集、确权、标注、授权及API、沙箱交付，并与阿里、腾讯、微软、快手等签署训练数据服务协议、完成上游授权收益分配；AIGC创意定制亦已向荣耀、奔驰等客户交付。真实主营、产品交付和收入均成立，故取消“字节生态”，保留AI视觉并新增训练数据、内容数据，定核心。 | J6: 视觉中国：2025年年度报告 | K6: 2026-03-31 | L6: iFinD ifind_get_stock_info (as of 2026-10-27)；视觉中国：2025年年度报告 | M6: https://money.finance.sina.com.cn/corp/view/vCB_AllBulletinDetail.php?stockid=000681&id=12047786
B7: 000892 | C7: 欢瑞世纪 | D7: AI应用：短剧；AI应用：AI影视短剧 | E7: 纠错 | F7: AI应用 | G7: AI影视短剧 | H7: 相关 | I7: 公司主营影视剧制作发行及艺人经纪，2025年报披露与阶跃星辰共建“麟跃”AI联合实验室，技术覆盖剧本、分镜、制作、剪辑和配音，已上线《十州三境》AI短剧概念片及江西人文宣传片《传承江西》，并引入Glowave X平台。产品与项目真实存在，但公司明确AI收入占比极低，故合并“短剧”和“AI影视短剧”为后者，并由核心降为相关。 | J7: 欢瑞世纪：2025年年度报告 | K7: 2026-04-30 | L7: iFinD ifind_get_stock_info (as of 2026-10-27)；欢瑞世纪：2025年年度报告 | M7: https://money.finance.sina.com.cn/corp/view/vCB_AllBulletinDetail.php?stockid=000892&id=12287047
B8: 001330 | C8: 博纳影业 | D8: AI应用：短剧；AI应用：AI影视短剧 | E8: 纠错 | F8: AI应用 | G8: AI影视短剧 | H8: 相关 | I8: 公司主营电影投资制作、发行及影院业务，已建设AIGMS、博越星纪蓝图和博卡云片场等AI影视能力，推出《三星堆：未来启示录》，AI长片《三星堆：未来往事》取得公映许可并于2026年10月23日上映。相关业务具备真实产品和商业发行，但2025年AI影视剧收入仅238.7万元，尚非主要收入来源，故合并重复短剧标签并保留AI影视短剧，由核心降为相关。 | J8: AI造电影|博纳影业|三星堆 | K8: 2026-10-24 | L8: iFinD ifind_get_stock_info (as of 2026-10-27)；AI造电影|博纳影业|三星堆 | M8: https://k.sina.com.cn/article_5953466437_162dab0450670bfuxm.html?from=ent
B9: 002027 | C9: 分众传媒 | D9: AI应用：AI营销 | E9: 保留 | F9: AI应用 | G9: AI营销 | H9: 相关 | I9: 公司主营楼宇及影院等生活圈媒体，已基于通义百炼推出“众智AI”，覆盖客户洞察、创意生成、策略制定和投放优化；后续“分众智投”面向本地生活客户提供潜客筛选、点位优选、智能监播及效果评估，“众小智”已在内部使用。AI产品直接服务主营广告营销且已有客户应用，但AI收入未单独披露，故保留AI营销并定为相关。 | J9: 分众传媒2025年财报：主营业务稳健增长多维亮点赋能未来 | K9: 2026-04-29 | L9: iFinD ifind_get_stock_info (as of 2026-10-27)；分众传媒2025年财报：主营业务稳健增长多维亮点赋能未来 | M9: https://www.xinhuanet.com/tech/20260429/d6d2346440414e388f9a2c55d5d5ba9a/c.html
B10: 002093 | C10: 国脉科技 | D10: AI应用：AI应用；AI应用：AI应用 | E10: 纠错 | F10: AI应用 | G10: AI养老 | H10: 相关 | I10: 公司主营ICT、物联网咨询及教育业务，2025年6月发布居家养老AI智能体，可依据长者健康状况和兴趣推荐活动，并率先用于“国脉大学养老”社区；2025年报进一步确认智能体与身联网社区形成协同生态。该产品具有明确养老服务场景和实际载体，但仍处商业化早期，未见可验证的规模收入，因此删除重复泛标签，细化为AI养老并定为相关。 | J10: 国脉科技股份有限公司2025年年度报告全文 | K10: 2026-04-24 | L10: iFinD ifind_get_stock_info (as of 2026-10-27)；国脉科技股份有限公司2025年年度报告全文 | M10: http://static.cninfo.com.cn/finalpage/2026-04-24/1225169085.PDF
B11: 002131 | C11: 利欧股份 | D11: AI应用：AI营销 | E11: 纠错 | F11: AI应用 | G11: AI营销 | H11: 相关 | I11: 公司形成机械制造与互联网服务双主业，数字营销板块已推出AI创意工厂、AI广告投手及策略、创意、投放、运营智能体，并在汽车、金融、电商、母婴客户落地，LEO AIAD完成算法备案。产品直接嵌入主营营销流程，但年报明确AI主要以间接方式融入业务，直接收入很小且难以拆分，因此将原“边缘”纠正为“相关”，不定核心。 | J11: 利欧股份：2025年年度报告 | K11: 2026-04-29 | L11: iFinD ifind_get_stock_info (as of 2026-10-27)；利欧股份：2025年年度报告 | M11: https://money.finance.sina.com.cn/corp/view/vCB_AllBulletinDetail.php?stockid=002131&id=12249389
B12: 002174 | C12: 游族网络 | D12: AI应用：AI游戏 | E12: 纠错 | F12: AI应用 | G12: AI游戏 | H12: 相关 | I12: 公司主营游戏研发与运营，2025年YOOZOO.AI已覆盖美术、代码、翻译、测试和投放等研运环节，AI玩伴“小游酱”覆盖国内15款游戏，《绯色回响》上线AI NPC“魔女之间”，具备真实游戏内应用。可是AI原生游戏《我的三体：2277》仍在研发，AI收入未单列，主要收入仍来自传统游戏，因此纠正核心定级，保留AI游戏并定为相关。 | J12: 游族网络股份有限公司2025年年度报告全文 | K12: 2026-04-29 | L12: iFinD ifind_get_stock_info (as of 2026-10-27)；游族网络股份有限公司2025年年度报告全文 | M12: http://file.finance.sina.com.cn/211.154.219.97:9494/MRGG/CNSESZ_STOCK/2026/2026-4/2026-04-29/12254629.PDF
B13: 002178 | C13: 延华智能 | D13: AI应用：AI应用 | E13: 纠错 | F13: AI应用 | G13: AI运维 | H13: 相关 | I13: 公司主营智慧城市设计施工运维、智慧医疗及智慧能源，自研云平台融合大模型，具备智能决策、自学习和可视化运维能力；智慧康养平台完成公测并加入自然语言AI助手，碳排放预测算法项目进入验收，且存在建筑和园区实际运维场景。AI属于新嵌入的产品能力，未披露独立收入，故删除泛标签并细化为AI运维，定为相关而非核心。 | J13: 延华智能：2025年年度报告 | K13: 2026-04-23 | L13: iFinD ifind_get_stock_info (as of 2026-10-27)；延华智能：2025年年度报告 | M13: https://money.finance.sina.com.cn/corp/view/vCB_AllBulletinDetail.php?stockid=002178&id=12153543
B14: 002181 | C14: 粤传媒 | D14: AI应用：AI营销 | E14: 纠错 | F14: AI应用 | G14: AI影视短剧、AI营销 | H14: 相关 | I14: 公司主营广告、印刷及媒体业务，2025年报单列AI视频影视业务，自研“妙音”AI音乐模型已完成算法及大模型备案，G视频建立AI视频工作流，数字人产品已有销售，广报智媒空间支持订阅、托管和本地部署；同时组建真人短剧与AI漫剧团队。AI短剧仍处拓展早期、整体收入贡献有限，故补充AI影视短剧并保留AI营销，统一定为相关。 | J14: 粤传媒：2025年年度报告摘要 | K14: 2026-04-02 | L14: iFinD ifind_get_stock_info (as of 2026-10-27)；粤传媒：2025年年度报告摘要 | M14: https://money.finance.sina.com.cn/corp/view/vCB_AllBulletinDetail.php?stockid=002181&id=12056308
B15: 002195 | C15: 岩山科技 | D15: AI应用：AI大模型 | E15: 纠错 | F15: AI应用 | G15: AI大模型 | H15: 相关 | I15: 公司原主营互联网信息服务并开展多元投资，RockAI已自研非Transformer、非Attention的Yan架构，2024年完成备案，2025年发布Yan 2.0 Preview；技术已用于企业本地部署、定制AI PC海外销售及多家医院生成式智慧病历。原“边缘、依据弱”判断已过时，但2025年全部AI业务收入仅1587.80万元、占2.43%，商业化不及预期，因此纠正为AI大模型相关而非核心。 | J15: 岩山科技：2025年年度报告 | K15: 2026-04-28 | L15: iFinD ifind_get_stock_info (as of 2026-10-27)；岩山科技：2025年年度报告 | M15: http://money.finance.sina.com.cn/corp/view/vCB_AllBulletinDetail.php?stockid=002195&id=12230671
... B88: 688500 | C88: 慧辰股份 | D88: AI应用：AI营销 | E88: 纠错 | F88: AI应用 | G88: AI数据分析 | H88: 相关 | I88: 公司主营基于数据的经营分析和行业解决方案，已推出慧AI、ChatBI、DataAgent及定性研究智能体，服务企业数据分析与决策，存在真实产品和客户交付；但2025年半年报仍将AIGC、Agent等列为创新业务战略重点，未证明AI营销成为主要收入。原AI营销范围过窄，改为AI数据分析，并由核心下调为相关。 | J88: 北京慧辰资道资讯股份有限公司2025年半年度报告 | K88: 2025-08-29 | L88: iFinD ifind_get_stock_info (as of 2026-10-27)；北京慧辰资道资讯股份有限公司2025年半年度报告 | M88: http://static.cninfo.com.cn/finalpage/2025-08-29/1224610112.PDF

Sheet 跨分类迁移
B2: 跨分类迁移 · 物理AI与数据要素
B3: 实体交互终端和物理感知控制迁物理AI；训练数据集和可授权内容数据迁数据要素。
B4: 代码 | C4: 名称 | D4: 旧AI应用概念 | E4: 动作 | F4: 新一级分类 | G4: 新概念 | H4: 判词 | I4: 详细理由 | J4: 证据名称 | K4: 证据日期 | L4: Source Name | M4: Source URL
B5: 000681 | C5: 视觉中国 | D5: AI应用：字节生态 | E5: 迁移 | F5: 数据要素 | G5: 数据要素_训练数据、数据要素_内容数据 | H5: 核心 | I5: 公司主营正版视觉内容及增值服务，2025年报已将数据服务列为主营产品，拥有超7亿多模态合规数据，提供采集、确权、标注、授权及API、沙箱交付，并与阿里、腾讯、微软、快手等签署训练数据服务协议、完成上游授权收益分配；AIGC创意定制亦已向荣耀、奔驰等客户交付。真实主营、产品交付和收入均成立，故取消“字节生态”，保留AI视觉并新增训练数据、内容数据，定核心。 | J5: 视觉中国：2025年年度报告 | K5: 2026-03-31 | L5: iFinD ifind_get_stock_info (as of 2026-10-27)；视觉中国：2025年年度报告 | M5: https://money.finance.sina.com.cn/corp/view/vCB_AllBulletinDetail.php?stockid=000681&id=12047786
B6: 001229 | C6: 魅视科技 | D6: AI应用：AI应用 | E6: 迁移 | F6: 物理AI | G6: 物理AI_机器视觉 | H6: 相关 | I6: 公司主营专业视听产品，AI边缘智能分析平台面向高速路段、收费场景等真实物理视频环境，具备人、车、物、环境检测、抓拍和告警能力，并已有交投集团项目案例。2025年AI系列收入2534.22万元、同比增长212.59%，但仍处推广期且约占总营收11%，故将泛AI应用细化为物理环境机器视觉，迁移至物理AI_机器视觉并定为相关。 | J6: 广东魅视科技股份有限公司投资者关系活动记录表 | K6: 2026-06-10 | L6: iFinD ifind_get_stock_info (as of 2026-10-27)；广东魅视科技股份有限公司投资者关系活动记录表 | M6: http://pdf.dfcfw.com/pdf/H2_AN202606101823425361_1.PDF
B7: 001314 | C7: 亿道信息 | D7: AI应用：AI终端 | E7: 迁移 | F7: 物理AI | G7: 物理AI_智能终端 | H7: 相关 | I7: 公司主营智能硬件研发制造，子公司亿境虚拟已布局AI音频、拍照、显示眼镜、多模态记录设备及SW3035方案和端边云系统，具备较短周期量产交付能力。2025年XR及AIoT收入4.208亿元、占比9.18%，但未单列AI眼镜收入，整体仍以传统智能硬件为主，因此由原AI终端规范迁移为物理AI_智能终端，并由核心降为相关。 | J7: 亿道信息：2025年年度报告 | K7: 2026-04-23 | L7: iFinD ifind_get_stock_info (as of 2026-10-27)；亿道信息：2025年年度报告 | M7: https://money.finance.sina.com.cn/corp/view/vCB_AllBulletinDetail.php?stockid=001314&id=12154989
B8: 002292 | C8: 奥飞娱乐 | D8: AI应用：AI玩具 | E8: 迁移 | F8: 物理AI | G8: 物理AI_智能终端 | H8: 相关 | I8: 公司主营IP内容、玩具及婴童产品，已推出并实际销售“AI智趣喜羊羊”“AI智趣懒羊羊”等产品，具备对话交互等AI玩具属性，属于真实新品线而非仅有概念。不过相关产品尚非公司主要收入来源，且其核心载体是实体玩具，不宜继续泛列AI应用，故迁移至物理AI_智能终端并定为相关。 | J8: 奥飞娱乐：公司已推出“AI智趣喜羊羊”、“AI智趣懒羊羊”等产品 | K8: 2025-08-07 | L8: iFinD ifind_get_stock_info (as of 2026-10-27)；奥飞娱乐：公司已推出“AI智趣喜羊羊”、“AI智趣懒羊羊”等产品 | M8: http://m.10jqka.com.cn/20250807/c670220612.shtml
B9: 002313 | C9: 日海智能 | D9: AI应用：AI终端 | E9: 迁移 | F9: 物理AI | G9: 物理AI_通信模组 | H9: 相关 | I9: 公司主营通信模组、通信设备及工程服务，已推出不同算力的智能模组，并应用于视觉分拣、割草机器人和陪伴机器人，体现真实AIoT模组能力。相关产品仍依托端侧硬件与模组交付，未单列AI收入，不能仅凭普通通信模组认定为AI核心标的，故迁移至物理AI_通信模组并定为相关。 | J9: 日海智能：以AI+IoT 重构万物智联未来 | K9: 2025-03-24 | L9: iFinD ifind_get_stock_info (as of 2026-10-27)；日海智能：以AI+IoT 重构万物智联未来 | M9: http://www.xinhuanet.com/info/20250324/26292d4d85df4e349a2de3157dc11543/c.html
B10: 002351 | C10: 漫步者 | D10: AI应用：AI终端 | E10: 迁移 | F10: 物理AI | G10: 物理AI_智能终端 | H10: 相关 | I10: 公司主营耳机和音响产品，Lolli Pro 3i已正式发布并具备AI翻译功能，属于在售智能终端而非纯概念布局。不过该能力仍是传统音频产品的功能延伸，未证明AI产品已经成为主要收入来源，也不宜继续泛归软件类AI应用，故迁移至物理AI_智能终端并定为相关。 | J10: 漫步者发布新款蓝牙耳机Lolli Pro 3i：蓝牙6.0与AI翻译功能加持 | K10: 2025-04-13 | L10: iFinD ifind_get_stock_info (as of 2026-10-27)；漫步者发布新款蓝牙耳机Lolli Pro 3i：蓝牙6.0与AI翻译功能加持 | M10: https://finance.sina.com.cn/tech/roll/2025-04-13/doc-inesyumu2952545.shtml
B11: 002421 | C11: 达实智能 | D11: AI应用：AIoT | E11: 迁移 | F11: 物理AI | G11: 物理AI_智能控制 | H11: 核心 | I11: 公司主营自研AIoT平台及智慧空间服务，V7平台内嵌AI Agent，已在银行总部、汽车园区和酒企上线，可整合空间与设备数据实施智慧管控。2025年上半年直接相关平台收入1355.99万元、签约2504.39万元，已有明确商业交付，核心能力是物理空间智能控制，故由泛AIoT迁移至物理AI_智能控制并保持核心。 | J11: 达实智能2025半年报出炉：短期承压 AI业务成增长新引擎 | K11: 2025-08-15 | L11: iFinD ifind_get_stock_info (as of 2026-10-27)；达实智能2025半年报出炉：短期承压 AI业务成增长新引擎 | M11: https://finance.eastmoney.com/a/202508153485207823.html
B12: 002835 | C12: 同为股份 | D12: AI应用：AI视觉 | E12: 迁移 | F12: 物理AI | G12: 物理AI_机器视觉 | H12: 核心 | I12: 公司主营安防摄像机、录像机和视频管理平台，已量产全系列场景智能摄像机、边缘分析盒子和服务器。2025年大模型在摄像机、NVR等嵌入式终端规模化落地，AI视觉感知已成为主要产品能力并随硬件实现商业交付。原AI视觉方向具有真实依据，但本质属于端侧机器视觉，故迁移至物理AI_机器视觉并保持核心。 | J12: 深圳市同为数码科技股份有限公司2025年年度报告摘要 | K12: 2026-04-24 | L12: iFinD ifind_get_stock_info (as of 2026-10-27)；深圳市同为数码科技股份有限公司2025年年度报告摘要 | M12: http://static.cninfo.com.cn/finalpage/2026-04-24/1225170506.PDF
B13: 002841 | C13: 视源股份 | D13: AI应用：AI终端 | E13: 迁移 | F13: 物理AI | G13: 物理AI_智能终端 | H13: 核心 | I13: 公司主营显示板卡和交互智能平板，希沃教学大模型已部署在教室AI设备端并生成课堂反馈。截至2025年末，AI备课激活用户超过100万，课堂反馈系统建成19个重点示范区，希沃全年收入55.81亿元，说明AI已随智能终端规模部署并深度嵌入主营产品，故由泛AI应用迁至物理AI_智能终端并保持核心。 | J13: 视源股份2025年营收244亿：教室里的AI | K13: 2026-03-27 | L13: iFinD ifind_get_stock_info (as of 2026-10-27)；视源股份2025年营收244亿：教室里的AI | M13: http://www.eeo.com.cn/2026/0327/820207.shtml
B14: 002862 | C14: 实丰文化 | D14: AI应用：AI玩具 | E14: 迁移 | F14: 物理AI | G14: 物理AI_智能终端 | H14: 相关 | I14: 公司2025年玩具、游戏和光伏收入分别占58.07%、33.01%和6.92%，AI魔法星、AI飞飞兔及多款AI+IP玩具已经推出销售，具备对话、情感陪伴和多模态交互能力。相关产品属于传统玩具主业的新产品线，但尚未单列AI收入，核心载体也是实体玩具，故迁移至物理AI_智能终端并将原核心降为相关。 | J14: 实丰文化：2025年年度报告 | K14: 2026-04-25 | L14: iFinD ifind_get_stock_info (as of 2026-10-27)；实丰文化：2025年年度报告 | M14: http://money.finance.sina.com.cn/corp/view/vCB_AllBulletinDetail.php?stockid=002862&id=12193762
B15: 002981 | C15: 朝阳科技 | D15: AI应用：AI终端 | E15: 迁移 | F15: 物理AI | G15: 物理AI_智能终端 | H15: 相关 | I15: 公司主营耳机、音响及精密零组件，2025年耳机收入占66.67%，传统声学硬件仍是基本盘。AI智能拍摄头戴耳机和AI拍摄眼镜已完成开发，具备AI对话、翻译、识物及总结功能，AR眼镜仍在研发，说明存在真实的端侧交互硬件项目；但尚未证明规模量产和收入贡献，故不定核心，并由泛化的AI终端概念迁移至更准确的物理AI_智能终端、维持相关。 | J15: 朝阳科技：2025年年度报告 | K15: 2026-03-10 | L15: iFinD ifind_get_stock_info (as of 2026-10-27)；朝阳科技：2025年年度报告 | M15: https://money.finance.sina.com.cn/corp/view/vCB_AllBulletinDetail.php?stockid=002981&id=11987457
... B24: 688787 | C24: 海天瑞声 | D24: AI应用：AI语料 | E24: 迁移 | F24: 数据要素 | G24: 数据要素_训练数据 | H24: 核心 | I24: 公司主营就是AI训练数据研发、生产和销售，语音、视觉及自然语言数据集经采集、清洗、标注后交付；标准数据集按使用授权收费，定制数据集按项目收取服务费，客户和商业模式清晰，维持核心。原AI语料属于AI应用泛化标签，实际直接产品为可授权及定制交付的训练数据，因此迁移至数据要素_训练数据。 | J24: 海天瑞声：2025年年度报告 | K24: 2026-04-24 | L24: iFinD ifind_get_stock_info (as of 2026-10-27)；海天瑞声：2025年年度报告 | M24: https://money.finance.sina.com.cn/corp/view/vCB_AllBulletinDetail.php?stockid=688787&id=12167706

Sheet 摘除清单
B2: 摘除清单 · 错标与落地不足
B3: 仅传统业务、行业趋势、战略探索、内部试用或缺乏直接AI产品证据的标签退出。
B4: 代码 | C4: 名称 | D4: 旧AI应用概念 | E4: 动作 | F4: 新一级分类 | G4: 新概念 | H4: 判词 | I4: 详细理由 | J4: 证据名称 | K4: 证据日期 | L4: Source Name | M4: Source URL
B5: 000526 | C5: 学大教育 | D5: AI应用：AI教育 | E5: 摘除 | F5: — | G5: — | H5: 摘除 | I5: 公司主营个性化教育培训，2025年半年报披露约330所学习中心及“双螺旋”线上线下融合教学模式，但未见可核验的自营AI教育产品、AI客户交付或AI收入。“个性化教学”和数字化授课不能直接等同于人工智能应用，缺少真实AI产品及商业化证据，因此原AI教育关联属于概念误推，应予摘除。 | J5: 学大（厦门）教育科技集团股份有限公司2025年半年度报告 | K5: 2025-08-28 | L5: iFinD ifind_get_stock_info (as of 2026-10-27)；学大（厦门）教育科技集团股份有限公司2025年半年度报告 | M5: https://static.cninfo.com.cn/finalpage/2025-08-28/1224598398.PDF
B6: 000607 | C6: 华媒控股 | D6: AI应用：AI影视短剧 | E6: 摘除 | F6: — | G6: — | H6: 摘除 | I6: 公司主营广告、报刊、印刷及教育业务，2025年报虽提及数字人、“审点芯”“杭州迹忆”等探索，但仍属初步尝试且暂无明显业绩贡献，未披露可核验的AI短剧产品、客户项目或收入。AIGC内容工具体验不能直接认定为AI影视短剧商业化，更不足以支撑核心定级，因此摘除原有关联。 | J6: 浙江华媒控股股份有限公司2025年年度报告摘要 | K6: 2026-04-24 | L6: iFinD ifind_get_stock_info (as of 2026-10-27)；浙江华媒控股股份有限公司2025年年度报告摘要 | M6: https://static.cninfo.com.cn/finalpage/2026-04-24/1225163833.PDF
B7: 000802 | C7: 北京文化 | D7: AI应用：AI影视短剧 | E7: 摘除 | F7: — | G7: — | H7: 摘除 | I7: 公司主营电影、电视剧、网剧、演艺经纪及旅游业务，2025年年度报告摘要仍围绕影视内容投资、制作与发行披露经营情况，未见公司自研AI影视产品、AI短剧项目、客户交付或相关收入。传统影视制作及行业“人工智能+视听”政策不能替代公司层面的业务证据，原核心定级主要由影视主业误推，因此应予摘除。 | J7: 北京文化：2025年年度报告摘要 | K7: 2026-04-18 | L7: iFinD ifind_get_stock_info (as of 2026-10-27)；北京文化：2025年年度报告摘要 | M7: https://data.eastmoney.com/notices/detail/000802/AN202604171821301219,JUU1JThDJTk3JUU0JUJBJUFDJUU2JTk2JTg3JUU1JThDJTk2.html
B8: 000917 | C8: 电广传媒 | D8: AI应用：AI营销 | E8: 摘除 | F8: — | G8: — | H8: 摘除 | I8: 公司业务涵盖文旅、投资、广告及游戏，广告运营虽是2025年主要收入来源，但年报对人工智能仅表述为“探索AI赋能广告业务转型路径”，其余多为行业泛述、文旅内容工具或达晨投资项目，未形成可核验的自有AI营销产品和客户交付。普通信息流广告不能直接贴AI标签，探索性表述亦不足以支持商业化定级，因此摘除。 | J8: 电广传媒：2025年年度报告 | K8: 2026-04-28 | L8: iFinD ifind_get_stock_info (as of 2026-10-27)；电广传媒：2025年年度报告 | M8: https://money.finance.sina.com.cn/corp/view/vCB_AllBulletinDetail.php?stockid=000917&id=12233295
B9: 002103 | C9: 广博股份 | D9: AI应用：AI营销 | E9: 摘除 | F9: — | G9: — | H9: 摘除 | I9: 公司主营文教办公用品、文创潮玩及跨境电商，原依据互联网营销业务推导AI营销缺乏公司事实支持。公司已在互动平台明确说明子公司灵云传媒不涉及AI营销相关业务，亦未披露其他可核验的AI营销产品、客户交付或收入，因此不能把一般互联网营销、内容推广或文具业务直接贴成AI应用，原标签应整体摘除。 | J9: 广博股份：子公司灵云传媒不涉及AI营销相关业务 | K9: 2026-04-20 | L9: iFinD ifind_get_stock_info (as of 2026-10-27)；广博股份：子公司灵云传媒不涉及AI营销相关业务 | M9: https://news.qq.com/rain/a/20260420A063ZK00
B10: 002235 | C10: 安妮股份 | D10: AI应用：短剧 | E10: 摘除 | F10: — | G10: — | H10: 摘除 | I10: 公司主营防伪溯源、商务信息用纸及“版权家”版权综合服务，“版权家”使用AI和区块链进行确权、存证，并不等于拥有AI影视短剧产品；公司也未披露面向模型厂商的训练数据授权、数据标注或数据集交付。版权数据资源不能在没有实际交易证据时硬迁数据要素，传统营销和用纸业务亦不构成AI应用，因此原标签应摘除。 | J10: 厦门安妮股份有限公司2025年年度报告摘要 | K10: 2026-04-28 | L10: iFinD ifind_get_stock_info (as of 2026-10-27)；厦门安妮股份有限公司2025年年度报告摘要 | M10: http://static.cninfo.com.cn/finalpage/2026-04-28/1225215247.PDF
B11: 002343 | C11: 慈文传媒 | D11: AI应用：短剧；AI应用：AI影视短剧 | E11: 摘除 | F11: — | G11: — | H11: 摘除 | I11: 公司主营影视IP投资制作发行及游戏渠道，普通微短剧不能直接等同于AI影视。公告明确短剧业务规模较小且2025年亏损，AIGC平台尚未形成收入，无法证明AI影视产品已经商业化或成为主营。因此原“短剧+AI影视短剧”标签存在重复且核心定级依据不足，应整只摘除而非继续保留概念标签。 | J11: 7天6板！AI短剧热门股，紧急提示 | K11: 2026-10-19 | L11: iFinD ifind_get_stock_info (as of 2026-10-27)；7天6板！AI短剧热门股，紧急提示 | M11: https://jnzstatic.cs.com.cn/zzb/htmlInfo/135468.html
B12: 002739 | C12: 儒意电影 | D12: AI应用：AI影视短剧 | E12: 摘除 | F12: — | G12: — | H12: 摘除 | I12: 公司主营院线放映、影视剧、潮玩和游戏，观影餐饮商品收入占73.73%，影视剧制作发行仅占3.62%。年报未披露公司自身AI影视短剧产品或收入，数字化经营平台及参股“拍立方”也不足以构成AI影视业务，港股关联公司的产品更不能归入本A股公司。因此原AI影视标签缺乏直接主营和商业化依据，应整只摘除。 | J12: 儒意电影：2025年年度报告 | K12: 2026-04-27 | L12: iFinD ifind_get_stock_info (as of 2026-10-27)；儒意电影：2025年年度报告 | M12: https://vip.stock.finance.sina.com.cn/corp/view/vCB_AllBulletinDetail.php?stockid=002739&id=12204536
B13: 002952 | C13: 亚世光电 | D13: AI应用：AI终端 | E13: 摘除 | F13: — | G13: — | H13: 摘除 | I13: 公司主营定制化液晶显示器件和电子纸显示模组，产品用于智慧零售、智慧办公等下游场景，但终端应用场景包含智能化并不等于公司自身拥有AI产品。2025年披露的研发项目仍集中于显示、检测、切割及贴合等工艺，未见可核验的AI终端产品、AI客户项目或AI收入，原有AI应用标签缺乏业务证据，因此应从AI应用池摘除而非继续按相关保留。 | J13: 亚世光电(集团)股份有限公司2025年年度报告全文 | K13: 2026-04-27 | L13: iFinD ifind_get_stock_info (as of 2026-10-27)；亚世光电(集团)股份有限公司2025年年度报告全文 | M13: http://file.finance.sina.com.cn/211.154.219.97:9494/MRGG/CNSESZ_STOCK/2026/2026-4/2026-04-27/12203335.PDF
B14: 300242 | C14: 佳云科技 | D14: AI应用：AI营销 | E14: 摘除 | F14: — | G14: — | H14: 摘除 | I14: 公司2025年互联网营销收入17.07亿元、占94.24%，成本中98.95%为媒介采购，收入本质仍来自主流媒体广告投放和流量代理。年报涉及AI的内容主要是行业趋势描述，研发投入为零，未披露自有AI产品、具体AI客户项目或AI收入，不能把普通广告消耗及平台算法能力归作公司的AI营销能力。原标签缺少可核验业务支撑，因此直接摘除，而非以相关等级继续保留。 | J14: 广东佳云科技股份有限公司2025年年度报告全文 | K14: 2026-04-08 | L14: iFinD ifind_get_stock_info (as of 2026-10-27)；广东佳云科技股份有限公司2025年年度报告全文 | M14: http://static.cninfo.com.cn/finalpage/2026-04-08/1225083243.PDF
B15: 300291 | C15: 百纳千成 | D15: AI应用：AI影视短剧 | E15: 摘除 | F15: — | G15: — | H15: 摘除 | I15: 公司主营电影、剧集、动漫、文旅和营销，已披露项目主要是传统影视剧、动画电影及真人互动影游。半年报虽提出围绕互动加战略构建涵盖影视、游戏、AIGC的内容生态，但这属于合作方向和战略表述，未对应公司自有AI产品、明确AI影视作品、客户合同或收入，合作方采用AIGC也不能直接归作百纳千成的AI能力。原核心判断主要由影视内容推断，证据不足，故直接摘除。 | J15: 百纳千成：2025年半年度报告 | K15: 2025-08-26 | L15: iFinD ifind_get_stock_info (as of 2026-10-27)；百纳千成：2025年半年度报告 | M15: http://money.finance.sina.com.cn/corp/view/vCB_AllBulletinDetail.php?stockid=300291&id=11354447
... B21: 605577 | C21: 龙版传媒 | D21: AI应用：AI影视短剧 | E21: 摘除 | F21: — | G21: — | H21: 摘除 | I21: iFinD及2025年报显示，公司主营教材教辅、一般图书出版印刷发行和物资贸易，数字出版属于出版业态延伸。年报仅将人工智能列为影响数字出版行业的外部技术趋势，未披露自制或联合制作AI短剧、AI影视产品、相关客户、项目或收入，原有“出版业务”理由也不能证明AI影视关联，因此摘除AI影视短剧。 | J21: 黑龙江出版传媒股份有限公司2025年年度报告 | K21: 2026-04-25 | L21: iFinD ifind_get_stock_info (as of 2026-10-27)；黑龙江出版传媒股份有限公司2025年年度报告 | M21: https://static.cninfo.com.cn/finalpage/2026-04-25/1225195929.PDF

Sheet 概念展开
A1: 一级分类 | B1: 二级概念 | C1: 判词 | D1: 代码 | E1: 名称
A2: AI应用 | B2: AI营销 | C2: 相关 | D2: 000676 | E2: 智度股份
A3: AI应用 | B3: AI视觉 | C3: 核心 | D3: 000681 | E3: 视觉中国
A4: 数据要素 | B4: 数据要素_训练数据 | C4: 核心 | D4: 000681 | E4: 视觉中国
A5: 数据要素 | B5: 数据要素_内容数据 | C5: 核心 | D5: 000681 | E5: 视觉中国
A6: AI应用 | B6: AI影视短剧 | C6: 相关 | D6: 000892 | E6: 欢瑞世纪
A7: 物理AI | B7: 物理AI_机器视觉 | C7: 相关 | D7: 001229 | E7: 魅视科技
A8: 物理AI | B8: 物理AI_智能终端 | C8: 相关 | D8: 001314 | E8: 亿道信息
A9: AI应用 | B9: AI影视短剧 | C9: 相关 | D9: 001330 | E9: 博纳影业
A10: AI应用 | B10: AI营销 | C10: 相关 | D10: 002027 | E10: 分众传媒
A11: AI应用 | B11: AI养老 | C11: 相关 | D11: 002093 | E11: 国脉科技
A12: AI应用 | B12: AI营销 | C12: 相关 | D12: 002131 | E12: 利欧股份
... A114: 数据要素 | B114: 数据要素_训练数据 | C114: 核心 | D114: 688787 | E114: 海天瑞声

Sheet 概念统计
B2: 概念统计 · 核心/相关分布
B3: 公式引用隐藏展开表精确计数；一只股票可对应多个概念。
B4: 一级分类 | C4: 二级概念 | D4: 核心（只） | E4: 相关（只） | F4: 合计（只）
B5: AI应用 | C5: AI会展 | D5: =COUNTIFS('概念展开'!$A$2:$A$114,B5,'概念展开'!$B$2:$B$114,C5,'概念展开'!$C$2:$C$114,"核心") | E5: =COUNTIFS('概念展开'!$A$2:$A$114,B5,'概念展开'!$B$2:$B$114,C5,'概念展开'!$C$2:$C$114,"相关") | F5: =SUM(D5:E5)
B6: AI应用 | C6: AI养老 | D6: =COUNTIFS('概念展开'!$A$2:$A$114,B6,'概念展开'!$B$2:$B$114,C6,'概念展开'!$C$2:$C$114,"核心") | E6: =COUNTIFS('概念展开'!$A$2:$A$114,B6,'概念展开'!$B$2:$B$114,C6,'概念展开'!$C$2:$C$114,"相关") | F6: =SUM(D6:E6)
B7: AI应用 | C7: AI内容审核 | D7: =COUNTIFS('概念展开'!$A$2:$A$114,B7,'概念展开'!$B$2:$B$114,C7,'概念展开'!$C$2:$C$114,"核心") | E7: =COUNTIFS('概念展开'!$A$2:$A$114,B7,'概念展开'!$B$2:$B$114,C7,'概念展开'!$C$2:$C$114,"相关") | F7: =SUM(D7:E7)
B8: AI应用 | C8: AI出版 | D8: =COUNTIFS('概念展开'!$A$2:$A$114,B8,'概念展开'!$B$2:$B$114,C8,'概念展开'!$C$2:$C$114,"核心") | E8: =COUNTIFS('概念展开'!$A$2:$A$114,B8,'概念展开'!$B$2:$B$114,C8,'概念展开'!$C$2:$C$114,"相关") | F8: =SUM(D8:E8)
B9: AI应用 | C9: AI制造 | D9: =COUNTIFS('概念展开'!$A$2:$A$114,B9,'概念展开'!$B$2:$B$114,C9,'概念展开'!$C$2:$C$114,"核心") | E9: =COUNTIFS('概念展开'!$A$2:$A$114,B9,'概念展开'!$B$2:$B$114,C9,'概念展开'!$C$2:$C$114,"相关") | F9: =SUM(D9:E9)
B10: AI应用 | C10: AI办公 | D10: =COUNTIFS('概念展开'!$A$2:$A$114,B10,'概念展开'!$B$2:$B$114,C10,'概念展开'!$C$2:$C$114,"核心") | E10: =COUNTIFS('概念展开'!$A$2:$A$114,B10,'概念展开'!$B$2:$B$114,C10,'概念展开'!$C$2:$C$114,"相关") | F10: =SUM(D10:E10)
B11: AI应用 | C11: AI大模型 | D11: =COUNTIFS('概念展开'!$A$2:$A$114,B11,'概念展开'!$B$2:$B$114,C11,'概念展开'!$C$2:$C$114,"核心") | E11: =COUNTIFS('概念展开'!$A$2:$A$114,B11,'概念展开'!$B$2:$B$114,C11,'概念展开'!$C$2:$C$114,"相关") | F11: =SUM(D11:E11)
B12: AI应用 | C12: AI影视短剧 | D12: =COUNTIFS('概念展开'!$A$2:$A$114,B12,'概念展开'!$B$2:$B$114,C12,'概念展开'!$C$2:$C$114,"核心") | E12: =COUNTIFS('概念展开'!$A$2:$A$114,B12,'概念展开'!$B$2:$B$114,C12,'概念展开'!$C$2:$C$114,"相关") | F12: =SUM(D12:E12)
B13: AI应用 | C13: AI政务 | D13: =COUNTIFS('概念展开'!$A$2:$A$114,B13,'概念展开'!$B$2:$B$114,C13,'概念展开'!$C$2:$C$114,"核心") | E13: =COUNTIFS('概念展开'!$A$2:$A$114,B13,'概念展开'!$B$2:$B$114,C13,'概念展开'!$C$2:$C$114,"相关") | F13: =SUM(D13:E13)
B14: AI应用 | C14: AI教育 | D14: =COUNTIFS('概念展开'!$A$2:$A$114,B14,'概念展开'!$B$2:$B$114,C14,'概念展开'!$C$2:$C$114,"核心") | E14: =COUNTIFS('概念展开'!$A$2:$A$114,B14,'概念展开'!$B$2:$B$114,C14,'概念展开'!$C$2:$C$114,"相关") | F14: =SUM(D14:E14)
B15: AI应用 | C15: AI数据分析 | D15: =COUNTIFS('概念展开'!$A$2:$A$114,B15,'概念展开'!$B$2:$B$114,C15,'概念展开'!$C$2:$C$114,"核心") | E15: =COUNTIFS('概念展开'!$A$2:$A$114,B15,'概念展开'!$B$2:$B$114,C15,'概念展开'!$C$2:$C$114,"相关") | F15: =SUM(D15:E15)
B16: AI应用 | C16: AI智慧城市 | D16: =COUNTIFS('概念展开'!$A$2:$A$114,B16,'概念展开'!$B$2:$B$114,C16,'概念展开'!$C$2:$C$114,"核心") | E16: =COUNTIFS('概念展开'!$A$2:$A$114,B16,'概念展开'!$B$2:$B$114,C16,'概念展开'!$C$2:$C$114,"相关") | F16: =SUM(D16:E16)
... B30: 物理AI | C30: 物理AI_通信模组 | D30: =COUNTIFS('概念展开'!$A$2:$A$114,B30,'概念展开'!$B$2:$B$114,C30,'概念展开'!$C$2:$C$114,"核心") | E30: =COUNTIFS('概念展开'!$A$2:$A$114,B30,'概念展开'!$B$2:$B$114,C30,'概念展开'!$C$2:$C$114,"相关") | F30: =SUM(D30:E30)
B31: 合计（概念次数，非股票去重数） | D31: =SUM(D5:D30) | E31: =SUM(E5:E30) | F31: =SUM(F5:F30)
