Workbook

Sheet 封面
B2: PCB概念深度清洗报告
B3: 复核日期：2026-10-27｜范围：89只｜重点：业务实质、产品层级、商业订单与二次边界复审
B6: 复核股票（只） | C6: =COUNTA('清洗总表'!$B$5:$B$93)
B7: 保留PCB（只） | C7: =COUNTA('PCB'!$B$5:$B$80)
B8: 核心判词（只） | C8: =COUNTIF('PCB'!$H$5:$H$80,"核心")
B9: 相关判词（只） | C9: =COUNTIF('PCB'!$H$5:$H$80,"相关")
B10: 纠错动作（只） | C10: =COUNTIF('清洗总表'!$E$5:$E$93,"纠错")
B11: 完全摘除（只） | C11: =COUNTA('摘除清单'!$B$5:$B$17)
B15: 工作表索引
B16: 清洗总表 | C16: 89只旧概念、新概念、动作、判词、详细理由和证据
B17: PCB | C17: 76只清洗后PCB公司
B18: 摘除清单 | C18: 13只通用业务或PCB证据不足公司
B19: 概念统计 | C19: 23个实际使用的二级概念
B23: 核心：PCB产业链是明确主营、重要收入来源，或已有规模化核心产品；相关：有真实PCB产品、订单、客户验证或交付，但早期、低占比、未拆分或其他行业为主。
B24: 摘除：MLCC、SOFC、MPO本身不属于PCB；只有潜在用途的粉体、树脂、设备，以及没有独立PCB业务的被动元件公司均摘除。AI服务器相关按真实板型重标。
B25: 二次复审：13只摘除结论全部维持；德福科技由相关上调核心，另补充12处真实产品标签并修正少量数字与理由。动作含纠错70只、保留6只、摘除13只。
B26: 主营与2025分部：iFinD ifind_get_stock_info、ifind_get_stock_business_segmentation（2026-10-27）；逐股公告与证据见Source列。

Sheet 清洗总表
B2: PCB · 89只逐项复核
B3: 逐股核对真实产品、订单、客户、交付、运营与股权；区分PCB、传统军工航天和潜在联想。
B4: 代码 | C4: 名称 | D4: 旧PCB概念 | E4: 动作 | F4: 新一级分类 | G4: 新概念 | H4: 判词 | I4: 详细理由 | J4: 证据名称 | K4: 证据日期 | L4: Source Name | M4: Source URL
B5: 000636 | C5: 风华高科 | D5: PCB：MLCC | E5: 摘除 | F5: — | G5: — | H5: 摘除 | I5: 公司真实产品是片式多层陶瓷电容器、片式电阻器、电感器及其他电子元器件和电子材料，MLCC属于被动元件，不是印制电路板，也不属于覆铜板、电子布、铜箔、PCB化学品、设备或刀具。2025年电子元器件收入56.5238亿元，其他业务1.0403亿元，合计营业收入57.5641亿元，元器件约占98.19%，但该口径包含多类被动元件，不能全部视为MLCC，更不能转换为PCB收入。公司虽具备电子材料平台属性，现有正式资料未显示独立PCB制造或直接专用材料、设备业务，因此按产业链排除规则定级为摘除。旧“PCB-MLCC”把下游元件与电路板混同，本次只删除该错误交叉标签，不处理公司其他产业分类。 | J5: 广东风华高新科技股份有限公司2025年度审计报告 | K5: 2026-04-21 | L5: iFinD ifind_get_stock_info + ifind_get_stock_business_segmentation (as of 2026-10-27)；广东风华高新科技股份有限公司2025年度审计报告 | M5: https://disc.static.szse.cn/disc/disk03/finalpage/2026-04-21/7f212725-e703-4a11-b8f5-5f873701e825.pdf
B6: 000657 | C6: 中钨高新 | D6: PCB：钻针 | E6: 纠错 | F6: PCB | G6: PCB刀具-钻针与铣刀 | H6: 核心 | I6: 公司旗下金洲公司直接生产PCB微型钻针等精密加工刀具，产品用于印制电路板微孔钻削，并非仅提供钨粉或硬质合金原料，具备真实规模化产品和经营收入。2025年集团营业收入176.3851亿元，切削刀具及工具收入36.1144亿元、占20.47%，其中还包含数控刀片和其他刀具；金洲公司营业收入约14.2亿元、约占集团8.05%，净利润约3.6亿元，该主体口径比刀具大类更接近PCB微钻业务，但也不能把集团全部钨产业链收入计入PCB。基于直接产品、独立经营主体及规模，定级为核心。旧“钨上游、微钻原料”明显低估业务环节，应纠正为PCB微钻及直接加工刀具，而非保留泛有色金属解释。 | J6: 中钨高新材料股份有限公司2025年年度报告 | K6: 2026-04-27 | L6: iFinD ifind_get_stock_info + ifind_get_stock_business_segmentation (as of 2026-10-27)；中钨高新材料股份有限公司2025年年度报告 | M6: http://notice.10jqka.com.cn/api/pdf/1fefdb8f1bbe9358.pdf
B7: 000733 | C7: 振华科技 | D7: PCB：MLCC | E7: 摘除 | F7: — | G7: — | H7: 摘除 | I7: 公司新型电子元器件包括电阻、电容、电感、半导体分立器件、继电器、连接器及混合集成电路等，MLCC和军用被动元件即使用于军工电子或服务器，也仍是安装在电路板上的元器件，不等于PCB本体或其直接材料、设备、刀具。2025年新型电子元器件收入57.0999亿元，现代服务业0.4499亿元，合计57.5497亿元，元器件约占99.22%，但这是多产品混合口径，未单列MLCC收入，也不存在可辨认的PCB收入。正式年报未显示公司有独立印制电路板制造或覆铜板等强相关业务，故按排除规则定级为摘除。旧“PCB-MLCC”属于产业环节错配，本次删除该PCB标签，不触碰其军工电子等其他标签。 | J7: 中国振华(集团)科技股份有限公司2025年年度报告 | K7: 2026-04-29 | L7: iFinD ifind_get_stock_info + ifind_get_stock_business_segmentation (as of 2026-10-27)；中国振华(集团)科技股份有限公司2025年年度报告 | M7: http://file.finance.sina.com.cn/211.154.219.97:9494/MRGG/CNSESZ_STOCK/2026/2026-4/2026-04-29/12267545.PDF
B8: 000823 | C8: 超声电子 | D8: PCB：AI服务器相关 | E8: 纠错 | F8: PCB | G8: PCB-HDI与任意层互连、覆铜板与粘结片 | H8: 核心 | I8: 公司直接生产双面及多层印制线路板、HDI高密度互连板，并生产覆铜板和半固化片，既覆盖PCB制造又覆盖其关键基材，产品和收入均有正式披露。2025年印制线路板收入31.4951亿元，占营业收入约49.75%；覆铜板收入11.0944亿元，占约17.52%，两项合计约67.27%，其余主要为液晶显示器17.4402亿元、超声电子仪器3.2805亿元，不能把公司全部63.3102亿元收入都归为PCB。印刷板与覆铜板分别构成重要收入来源，故定级为核心。旧“AI服务器相关”过于笼统且会把显示器等业务误带入算力链条，应改按实际板型列HDI与任意层互连，并补充覆铜板与粘结片，不额外推定服务器收入。 | J8: 超声电子：2025年年度报告 | K8: 2026-03-21 | L8: iFinD ifind_get_stock_info + ifind_get_stock_business_segmentation (as of 2026-10-27)；超声电子：2025年年度报告 | M8: http://money.finance.sina.com.cn/corp/view/vCB_AllBulletinDetail.php?stockid=000823&id=12007875
B9: 001212 | C9: 中旗新材 | D9: PCB：硅微粉 | E9: 摘除 | F9: — | G9: — | H9: 摘除 | I9: 公司现有人造石英石板材和台面是真实主营产品，高纯砂或石英砂粉也不能仅凭化学成分就自动认定为覆铜板用硅微粉。2025年板材收入3.2807亿元、占约78.58%，台面0.8177亿元、占约19.59%，高纯砂约0.0527亿元、占约1.26%，合计营业收入4.1751亿元；砂粉收入占比很小，且公司正式互动回复明确相关硅微粉尚未在PCB领域应用，因此没有真实供货或收入可支撑PCB标签。混合口径中绝大多数为建材产品，不能当作电子填料业务。按只有潜在用途即排除的规则定级为摘除。旧“硅微粉”虽指出材料形态，却错误暗示PCB应用，本次删除该标签，不另行扩展石英材料分类。 | J9: 中旗新材关于硅微粉应用领域的投资者互动回复 | K9: 2026-06-08 | L9: iFinD ifind_get_stock_info + ifind_get_stock_business_segmentation (as of 2026-10-27)；中旗新材关于硅微粉应用领域的投资者互动回复 | M9: https://api3.cls.cn/share/article/2400946?os=androids&sv=860&app=
B10: 001216 | C10: 华瓷股份 | D10: PCB：MLCC | E10: 摘除 | F10: — | G10: — | H10: 摘除 | I10: 公司主要产品为色釉陶瓷、釉下五彩瓷等日用陶瓷，另有电瓷和陶瓷新材料，陶瓷材料身份并不代表生产MLCC，更不代表生产PCB或其专用材料。2025年色釉陶瓷收入13.9364亿元，釉下五彩瓷0.3876亿元，电瓷0.2021亿元，陶瓷新材料0.1251亿元，营业收入合计14.7154亿元；日用陶瓷占绝对主体，电瓷属于电力绝缘器材，也不能转为电子元件或电路板收入。年报未显示印制电路板、覆铜板、电子布、PCB设备或刀具等独立业务，故按真实产品和产业边界定级为摘除。旧“PCB-MLCC”没有任何对应主营产品支撑，是把陶瓷概念错误映射到电子元件后再错配到PCB，本次删除该标签，不处理其他产业属性。 | J10: 湖南华联瓷业股份有限公司2025年年度报告 | K10: 2026-04-29 | L10: iFinD ifind_get_stock_info + ifind_get_stock_business_segmentation (as of 2026-10-27)；湖南华联瓷业股份有限公司2025年年度报告 | M10: http://file.finance.sina.com.cn/211.154.219.97:9494/MRGG/CNSESZ_STOCK/2026/2026-4/2026-04-29/12246740.PDF
B11: 001359 | C11: 平安电工 | D11: PCB：电子布 | E11: 纠错 | F11: PCB | G11: 电子布与玻纤材料 | H11: 核心 | I11: 公司除云母绝缘材料外，还实际生产特种纤维及电子布，电子级玻纤布可作为覆铜板增强材料，属于PCB上游直接材料而非仅凭绝缘用途形成的潜在线索。2025年特种纤维及电子布收入1.3875亿元，占营业收入11.8940亿元的约11.67%；云母绝缘材料7.4543亿元、新能源绝缘材料2.9783亿元仍是更大收入来源，且上述分部同时含特种纤维，不能把1.3875亿元全部无条件视作PCB电子布。尽管如此，该产品已形成独立披露和亿元级销售规模，符合规模化核心产品标准，故定级为核心，同时保留混合收入边界。旧“云母绝缘材料、边缘”忽略已落地电子布，应纠正为电子布与玻纤材料，而非继续用主营云母否定全部PCB关联。 | J11: 平安电工：2025年年度报告 | K11: 2026-04-29 | L11: iFinD ifind_get_stock_info + ifind_get_stock_business_segmentation (as of 2026-10-27)；平安电工：2025年年度报告 | M11: http://money.finance.sina.com.cn/corp/view/vCB_AllBulletinDetail.php?stockid=001359&id=12252614
B12: 001389 | C12: 广合科技 | D12: PCB：PCB | E12: 纠错 | F12: PCB | G12: PCB-高多层与服务器板、PCB-HDI与任意层互连 | H12: 核心 | I12: 公司主营多高层印制电路板，真实产品覆盖服务器用高多层板及HDI等高密度互连产品，服务器板已有规模销售而非研发储备。2025年PCB板收入51.0189亿元，占营业收入93.0090%，其他业务收入3.8348亿元；年报进一步说明服务器用PCB约占产品收入八成，因此服务器板是公司最重要应用方向，但该比例口径是产品收入而非含其他业务的合并营收，不能机械把全部PCB都称为AI服务器板。PCB收入占绝对主导且服务器产品规模化，定级为核心。旧“PCB、多高层”方向正确但粒度过粗，应细化为高多层与服务器板，并按实际产品补充HDI与任意层互连，保留普通服务器、其他算力设备及非服务器板之间的收入边界。 | J12: 广合科技：2025年年度报告 | K12: 2026-03-28 | L12: iFinD ifind_get_stock_info + ifind_get_stock_business_segmentation (as of 2026-10-27)；广合科技：2025年年度报告 | M12: http://money.finance.sina.com.cn/corp/view/vCB_AllBulletinDetail.php?stockid=001389&id=12033054
B13: 002080 | C13: 中材科技 | D13: PCB：电子布 | E13: 纠错 | F13: PCB | G13: 电子布与玻纤材料 | H13: 相关 | I13: 公司全资子公司泰山玻纤实际销售电子布和特种纤维布，产品可用于覆铜板增强体系，具有真实PCB材料收入，不是把全部玻纤业务潜在用途都映射到PCB。2025年公司营业收入301.9549亿元，风电叶片125.9500亿元、无碱玻璃纤维及制品89.0494亿元、隔膜23.9782亿元构成主要混合业务；正式异动公告单列电子布收入3.60亿元、占1.19%，特种纤维布6.28亿元、占2.08%，合计9.88亿元、约3.27%，公司明确提示总体占比较小。由于产品真实且已有销售，但上市公司占比低，定级为相关。旧“电子布”方向可保留，但需用白名单统一名称，并纠正把全部玻纤或风电复合材料纳入PCB的宽泛理解。 | J13: 中材科技股份有限公司关于股票交易异常波动公告 | K13: 2026-06-29 | L13: iFinD ifind_get_stock_info + ifind_get_stock_business_segmentation (as of 2026-10-27)；中材科技股份有限公司关于股票交易异常波动公告 | M13: http://static.cninfo.com.cn/finalpage/2026-06-29/1225391023.PDF
B14: 002134 | C14: 天津普林 | D14: PCB：PCB | E14: 纠错 | F14: PCB | G14: PCB-通用刚性板、PCB-HDI与任意层互连 | H14: 核心 | I14: 公司直接从事印制电路板研发、生产和销售，产品包括多层刚性板及HDI等高密度互连板，属于标准PCB制造企业，不是上游材料或仅提供潜在配套。2025年印制电路板收入13.7868亿元，占营业收入100%，收入来源高度集中，未混入需要剔除的其他产业板块；不过公司PCB下游包括工控、医疗、汽车、通信等多种场景，不能因行业景气就将全部收入描述为AI服务器或高阶算力板。基于全部主营收入和规模化制造能力，定级为核心。旧“PCB”标签方向正确但缺乏板型区分，本次按证据拆为通用刚性板与HDI和任意层互连，未获得明确服务器产品或客户证据的部分不追加服务器标签，避免把技术优势等同于特定终端收入。 | J14: 天津普林电路股份有限公司2025年年度报告 | K14: 2026-03-27 | L14: iFinD ifind_get_stock_info + ifind_get_stock_business_segmentation (as of 2026-10-27)；天津普林电路股份有限公司2025年年度报告 | M14: http://file.finance.sina.com.cn/211.154.219.97:9494/MRGG/CNSESZ_STOCK/2026/2026-3/2026-03-27/12022060.PDF
B15: 002141 | C15: 贤丰控股 | D15: PCB：覆铜板 | E15: 纠错 | F15: PCB | G15: 覆铜板与粘结片 | H15: 核心 | I15: 公司通过高硕航宇等经营主体实际生产覆铜板及PP，PP即半固化片或粘结片，属于PCB直接基材，已形成大额销售而不是产业投资或规划项目。2025年覆铜板及PP收入7.4893亿元，占营业收入11.5562亿元的64.8073%；其余包括饲料3.2099亿元、猪苗0.4013亿元和其他0.4557亿元，这些养殖及其他收入不能计入电子材料。覆铜板业务已成为上市公司第一大收入来源和重要经营板块，故定级为核心，同时明确合并报表仍是混合业务结构。旧“覆铜板”方向正确但遗漏PP，应统一纠正为白名单“覆铜板与粘结片”，不能因公司历史主营或其他板块而否定当前真实电子材料主业，也不把全部营收当作PCB。 | J15: 贤丰控股：2025年年度报告 | K15: 2026-04-22 | L15: iFinD ifind_get_stock_info + ifind_get_stock_business_segmentation (as of 2026-10-27)；贤丰控股：2025年年度报告 | M15: https://money.finance.sina.com.cn/corp/view/vCB_AllBulletinDetail.php?stockid=002141&id=12135633
... B93: 920821 | C93: 则成电子 | D93: PCB：FPC | E93: 纠错 | F93: PCB | G93: PCB-FPC与刚挠结合、PCB-HDI与任意层互连、PCB-IC载板 | H93: 核心 | I93: 公司真实业务是基于柔性应用的定制化模组及印制电路板设计、研发、生产和销售，iFinD主营资料明确为FPC及FPC产业链延伸的FPC组件，年报还披露HDI、SLP和RF软硬结合板研发及医疗多层、超长尺寸FPC项目，不是仅采购FPC组装普通电子模组。二〇二五年印制电路板收入九千〇六十六万元，约占总收入百分之二十三；消费电子、食品医疗、交通工具等模组分类中还包含基于柔性板的定制产品，但不能把这些分类收入全部当作裸板或全部重复计算。FPC裸板已有重要收入，FPC组件又是主营方向，故定核心并保留模组混合边界。旧“FPC与电子模组”现按白名单归为PCB-FPC与刚挠结合，避免误标为通用刚性板。 | J93: 则成电子：2025年年度报告 | K93: 2026-04-24 | L93: iFinD ifind_get_stock_info + ifind_get_stock_business_segmentation (as of 2026-10-27)；则成电子：2025年年度报告 | M93: https://money.finance.sina.com.cn/corp/view/vCB_AllBulletinDetail.php?stockid=920821&id=12196512

Sheet PCB
B2: PCB · 清洗后1513只股池
B3: 核心52只、相关24只；按卫星、火箭、地面系统、运营服务和产业配套细化为23个二级概念。
B4: 代码 | C4: 名称 | D4: 旧PCB概念 | E4: 动作 | F4: 新一级分类 | G4: 新概念 | H4: 判词 | I4: 详细理由 | J4: 证据名称 | K4: 证据日期 | L4: Source Name | M4: Source URL
B5: 000657 | C5: 中钨高新 | D5: PCB：钻针 | E5: 纠错 | F5: PCB | G5: PCB刀具-钻针与铣刀 | H5: 核心 | I5: 公司旗下金洲公司直接生产PCB微型钻针等精密加工刀具，产品用于印制电路板微孔钻削，并非仅提供钨粉或硬质合金原料，具备真实规模化产品和经营收入。2025年集团营业收入176.3851亿元，切削刀具及工具收入36.1144亿元、占20.47%，其中还包含数控刀片和其他刀具；金洲公司营业收入约14.2亿元、约占集团8.05%，净利润约3.6亿元，该主体口径比刀具大类更接近PCB微钻业务，但也不能把集团全部钨产业链收入计入PCB。基于直接产品、独立经营主体及规模，定级为核心。旧“钨上游、微钻原料”明显低估业务环节，应纠正为PCB微钻及直接加工刀具，而非保留泛有色金属解释。 | J5: 中钨高新材料股份有限公司2025年年度报告 | K5: 2026-04-27 | L5: iFinD ifind_get_stock_info + ifind_get_stock_business_segmentation (as of 2026-10-27)；中钨高新材料股份有限公司2025年年度报告 | M5: http://notice.10jqka.com.cn/api/pdf/1fefdb8f1bbe9358.pdf
B6: 000823 | C6: 超声电子 | D6: PCB：AI服务器相关 | E6: 纠错 | F6: PCB | G6: PCB-HDI与任意层互连、覆铜板与粘结片 | H6: 核心 | I6: 公司直接生产双面及多层印制线路板、HDI高密度互连板，并生产覆铜板和半固化片，既覆盖PCB制造又覆盖其关键基材，产品和收入均有正式披露。2025年印制线路板收入31.4951亿元，占营业收入约49.75%；覆铜板收入11.0944亿元，占约17.52%，两项合计约67.27%，其余主要为液晶显示器17.4402亿元、超声电子仪器3.2805亿元，不能把公司全部63.3102亿元收入都归为PCB。印刷板与覆铜板分别构成重要收入来源，故定级为核心。旧“AI服务器相关”过于笼统且会把显示器等业务误带入算力链条，应改按实际板型列HDI与任意层互连，并补充覆铜板与粘结片，不额外推定服务器收入。 | J6: 超声电子：2025年年度报告 | K6: 2026-03-21 | L6: iFinD ifind_get_stock_info + ifind_get_stock_business_segmentation (as of 2026-10-27)；超声电子：2025年年度报告 | M6: http://money.finance.sina.com.cn/corp/view/vCB_AllBulletinDetail.php?stockid=000823&id=12007875
B7: 001359 | C7: 平安电工 | D7: PCB：电子布 | E7: 纠错 | F7: PCB | G7: 电子布与玻纤材料 | H7: 核心 | I7: 公司除云母绝缘材料外，还实际生产特种纤维及电子布，电子级玻纤布可作为覆铜板增强材料，属于PCB上游直接材料而非仅凭绝缘用途形成的潜在线索。2025年特种纤维及电子布收入1.3875亿元，占营业收入11.8940亿元的约11.67%；云母绝缘材料7.4543亿元、新能源绝缘材料2.9783亿元仍是更大收入来源，且上述分部同时含特种纤维，不能把1.3875亿元全部无条件视作PCB电子布。尽管如此，该产品已形成独立披露和亿元级销售规模，符合规模化核心产品标准，故定级为核心，同时保留混合收入边界。旧“云母绝缘材料、边缘”忽略已落地电子布，应纠正为电子布与玻纤材料，而非继续用主营云母否定全部PCB关联。 | J7: 平安电工：2025年年度报告 | K7: 2026-04-29 | L7: iFinD ifind_get_stock_info + ifind_get_stock_business_segmentation (as of 2026-10-27)；平安电工：2025年年度报告 | M7: http://money.finance.sina.com.cn/corp/view/vCB_AllBulletinDetail.php?stockid=001359&id=12252614
B8: 001389 | C8: 广合科技 | D8: PCB：PCB | E8: 纠错 | F8: PCB | G8: PCB-高多层与服务器板、PCB-HDI与任意层互连 | H8: 核心 | I8: 公司主营多高层印制电路板，真实产品覆盖服务器用高多层板及HDI等高密度互连产品，服务器板已有规模销售而非研发储备。2025年PCB板收入51.0189亿元，占营业收入93.0090%，其他业务收入3.8348亿元；年报进一步说明服务器用PCB约占产品收入八成，因此服务器板是公司最重要应用方向，但该比例口径是产品收入而非含其他业务的合并营收，不能机械把全部PCB都称为AI服务器板。PCB收入占绝对主导且服务器产品规模化，定级为核心。旧“PCB、多高层”方向正确但粒度过粗，应细化为高多层与服务器板，并按实际产品补充HDI与任意层互连，保留普通服务器、其他算力设备及非服务器板之间的收入边界。 | J8: 广合科技：2025年年度报告 | K8: 2026-03-28 | L8: iFinD ifind_get_stock_info + ifind_get_stock_business_segmentation (as of 2026-10-27)；广合科技：2025年年度报告 | M8: http://money.finance.sina.com.cn/corp/view/vCB_AllBulletinDetail.php?stockid=001389&id=12033054
B9: 002080 | C9: 中材科技 | D9: PCB：电子布 | E9: 纠错 | F9: PCB | G9: 电子布与玻纤材料 | H9: 相关 | I9: 公司全资子公司泰山玻纤实际销售电子布和特种纤维布，产品可用于覆铜板增强体系，具有真实PCB材料收入，不是把全部玻纤业务潜在用途都映射到PCB。2025年公司营业收入301.9549亿元，风电叶片125.9500亿元、无碱玻璃纤维及制品89.0494亿元、隔膜23.9782亿元构成主要混合业务；正式异动公告单列电子布收入3.60亿元、占1.19%，特种纤维布6.28亿元、占2.08%，合计9.88亿元、约3.27%，公司明确提示总体占比较小。由于产品真实且已有销售，但上市公司占比低，定级为相关。旧“电子布”方向可保留，但需用白名单统一名称，并纠正把全部玻纤或风电复合材料纳入PCB的宽泛理解。 | J9: 中材科技股份有限公司关于股票交易异常波动公告 | K9: 2026-06-29 | L9: iFinD ifind_get_stock_info + ifind_get_stock_business_segmentation (as of 2026-10-27)；中材科技股份有限公司关于股票交易异常波动公告 | M9: http://static.cninfo.com.cn/finalpage/2026-06-29/1225391023.PDF
B10: 002134 | C10: 天津普林 | D10: PCB：PCB | E10: 纠错 | F10: PCB | G10: PCB-通用刚性板、PCB-HDI与任意层互连 | H10: 核心 | I10: 公司直接从事印制电路板研发、生产和销售，产品包括多层刚性板及HDI等高密度互连板，属于标准PCB制造企业，不是上游材料或仅提供潜在配套。2025年印制电路板收入13.7868亿元，占营业收入100%，收入来源高度集中，未混入需要剔除的其他产业板块；不过公司PCB下游包括工控、医疗、汽车、通信等多种场景，不能因行业景气就将全部收入描述为AI服务器或高阶算力板。基于全部主营收入和规模化制造能力，定级为核心。旧“PCB”标签方向正确但缺乏板型区分，本次按证据拆为通用刚性板与HDI和任意层互连，未获得明确服务器产品或客户证据的部分不追加服务器标签，避免把技术优势等同于特定终端收入。 | J10: 天津普林电路股份有限公司2025年年度报告 | K10: 2026-03-27 | L10: iFinD ifind_get_stock_info + ifind_get_stock_business_segmentation (as of 2026-10-27)；天津普林电路股份有限公司2025年年度报告 | M10: http://file.finance.sina.com.cn/211.154.219.97:9494/MRGG/CNSESZ_STOCK/2026/2026-3/2026-03-27/12022060.PDF
B11: 002141 | C11: 贤丰控股 | D11: PCB：覆铜板 | E11: 纠错 | F11: PCB | G11: 覆铜板与粘结片 | H11: 核心 | I11: 公司通过高硕航宇等经营主体实际生产覆铜板及PP，PP即半固化片或粘结片，属于PCB直接基材，已形成大额销售而不是产业投资或规划项目。2025年覆铜板及PP收入7.4893亿元，占营业收入11.5562亿元的64.8073%；其余包括饲料3.2099亿元、猪苗0.4013亿元和其他0.4557亿元，这些养殖及其他收入不能计入电子材料。覆铜板业务已成为上市公司第一大收入来源和重要经营板块，故定级为核心，同时明确合并报表仍是混合业务结构。旧“覆铜板”方向正确但遗漏PP，应统一纠正为白名单“覆铜板与粘结片”，不能因公司历史主营或其他板块而否定当前真实电子材料主业，也不把全部营收当作PCB。 | J11: 贤丰控股：2025年年度报告 | K11: 2026-04-22 | L11: iFinD ifind_get_stock_info + ifind_get_stock_business_segmentation (as of 2026-10-27)；贤丰控股：2025年年度报告 | M11: https://money.finance.sina.com.cn/corp/view/vCB_AllBulletinDetail.php?stockid=002141&id=12135633
B12: 002409 | C12: 雅克科技 | D12: PCB：硅微粉 | E12: 纠错 | F12: PCB | G12: 填料-硅微粉与功能粉体 | H12: 相关 | I12: 公司实际生产硅微粉等功能粉体，可用于覆铜板和电子封装树脂体系，具备真实PCB材料应用，但同一产品也服务半导体封装等下游，不能全部归入PCB。2025年硅微粉收入2.8824亿元，约占营业收入86.14亿元的3.35%；半导体化学材料21.1076亿元、光刻胶及配套19.5966亿元、电子特气4.1737亿元、LNG板材23.7044亿元构成其他主要混合收入，硅微粉虽单列金额，却未按覆铜板与封装用途进一步拆分。考虑直接材料真实、收入占比不高且下游混合，定级为相关。旧“硅微粉”可保留实质，但应规范为填料-硅微粉与功能粉体，并纠正以公司整体电子材料收入证明PCB核心地位的做法。 | J12: 雅克科技：2025年年度报告 | K12: 2026-04-28 | L12: iFinD ifind_get_stock_info + ifind_get_stock_business_segmentation (as of 2026-10-27)；雅克科技：2025年年度报告 | M12: http://money.finance.sina.com.cn/corp/view/vCB_AllBulletinDetail.php?stockid=002409&id=12232855
B13: 002463 | C13: 沪电股份 | D13: PCB：AI服务器相关 | E13: 纠错 | F13: PCB | G13: PCB-高多层与服务器板、PCB-HDI与任意层互连 | H13: 核心 | I13: 公司直接生产高多层、高速及HDI印制电路板，真实用于AI服务器、高性能计算、通用服务器和高速交换机路由器，具备明确产品与收入证据。2025年PCB收入181.43亿元，占营业收入约95.77%；其中企业通讯市场板146.5630亿元、汽车板30.4458亿元、工控及其他4.4243亿元。总经理工作报告进一步披露AI服务器及HPC相关收入30.06亿元、通用服务器25.40亿元、高速交换机及路由器81.69亿元，这些是企业通讯板内部的应用拆分，不能与企业通讯板收入重复相加，也不能把汽车板纳入算力。PCB主业占绝对主导，定级为核心。旧“AI服务器相关”过窄且笼统，应改按实际板型归高多层与服务器板并补充HDI。 | J13: 沪电股份：2025年度总经理工作报告 | K13: 2026-03-25 | L13: iFinD ifind_get_stock_info + ifind_get_stock_business_segmentation (as of 2026-10-27)；沪电股份：2025年度总经理工作报告 | M13: http://money.finance.sina.com.cn/corp/view/vCB_AllBulletinDetail.php?stockid=002463&id=12014861
B14: 002552 | C14: 宝鼎科技 | D14: PCB：HVLP | E14: 纠错 | F14: PCB | G14: 覆铜板与粘结片、铜箔-通用PCB、铜箔-HVLP与高频高速 | H14: 核心 | I14: 公司实际生产FR-4及复合基覆铜板、HTE等普通电子电路铜箔，并有少量HVLP低轮廓铜箔销售，产品均与PCB直接相关。2025年覆铜板收入20.7091亿元、占65.81%，铜箔5.1798亿元、占16.46%，成品金5.0848亿元，合并营业收入31.4677亿元，黄金等业务不能计入PCB。核心定级由覆铜板和通用铜箔的规模收入支撑，而非HVLP；正式公告明确2025年HVLP销量仅占铜箔销量0.03%，尚处认证及市场拓展阶段、未形成批量生产，M7和M9亦无订单及收入，故高频高速标签只保留早期业务边界。旧“HVLP”单独突出会严重夸大高端化，应补齐覆铜板与通用铜箔并明确极小占比。 | J14: 宝鼎科技股份有限公司股票交易异常波动公告 | K14: 2026-05-13 | L14: iFinD ifind_get_stock_info + ifind_get_stock_business_segmentation (as of 2026-10-27)；宝鼎科技股份有限公司股票交易异常波动公告 | M14: https://money.finance.sina.com.cn/corp/view/vCB_AllBulletinDetail.php?stockid=002552&id=12314801
B15: 002579 | C15: 中京电子 | D15: PCB：AI服务器相关 | E15: 纠错 | F15: PCB | G15: PCB-通用刚性板、PCB-HDI与任意层互连、PCB-FPC与刚挠结合、PCB-高多层与服务器板 | H15: 核心 | I15: 公司直接制造刚性印制电路板、HDI、柔性电路板及刚挠结合产品，并披露AI加速卡、交换机等高端应用产品，板型和算力应用均有真实业务基础。2025年刚性电路板收入20.7345亿元，占约66.02%；柔性电路板及其应用模组8.6068亿元，占约27.40%，其他收入2.0652亿元，合计营业收入31.4065亿元，PCB构成主营。刚性板是包含不同层数和终端的宽口径，柔性模组也包含非服务器应用，不能将两部分全部视为AI收入；AI相关板型未单列金额。基于PCB整体主业定级为核心。旧“AI服务器相关”过度聚焦单一应用，应改为通用刚性板、HDI、FPC与刚挠结合，并对有证据的算力产品补充高多层与服务器板。 | J15: 惠州中京电子科技股份有限公司2025年年度报告 | K15: 2026-04-24 | L15: iFinD ifind_get_stock_info + ifind_get_stock_business_segmentation (as of 2026-10-27)；惠州中京电子科技股份有限公司2025年年度报告 | M15: https://static.cninfo.com.cn/finalpage/2026-04-24/1225167909.PDF
... B80: 920821 | C80: 则成电子 | D80: PCB：FPC | E80: 纠错 | F80: PCB | G80: PCB-FPC与刚挠结合、PCB-HDI与任意层互连、PCB-IC载板 | H80: 核心 | I80: 公司真实业务是基于柔性应用的定制化模组及印制电路板设计、研发、生产和销售，iFinD主营资料明确为FPC及FPC产业链延伸的FPC组件，年报还披露HDI、SLP和RF软硬结合板研发及医疗多层、超长尺寸FPC项目，不是仅采购FPC组装普通电子模组。二〇二五年印制电路板收入九千〇六十六万元，约占总收入百分之二十三；消费电子、食品医疗、交通工具等模组分类中还包含基于柔性板的定制产品，但不能把这些分类收入全部当作裸板或全部重复计算。FPC裸板已有重要收入，FPC组件又是主营方向，故定核心并保留模组混合边界。旧“FPC与电子模组”现按白名单归为PCB-FPC与刚挠结合，避免误标为通用刚性板。 | J80: 则成电子：2025年年度报告 | K80: 2026-04-24 | L80: iFinD ifind_get_stock_info + ifind_get_stock_business_segmentation (as of 2026-10-27)；则成电子：2025年年度报告 | M80: https://money.finance.sina.com.cn/corp/view/vCB_AllBulletinDetail.php?stockid=920821&id=12196512

Sheet 摘除清单
B2: 摘除清单 · 13只证据不足或业务错标
B3: 通用产品潜在用途、央企背景、SpaceX预期、太空光伏设备及未决投资不直接计入PCB。
B4: 代码 | C4: 名称 | D4: 旧PCB概念 | E4: 动作 | F4: 新一级分类 | G4: 新概念 | H4: 判词 | I4: 详细理由 | J4: 证据名称 | K4: 证据日期 | L4: Source Name | M4: Source URL
B5: 000636 | C5: 风华高科 | D5: PCB：MLCC | E5: 摘除 | F5: — | G5: — | H5: 摘除 | I5: 公司真实产品是片式多层陶瓷电容器、片式电阻器、电感器及其他电子元器件和电子材料，MLCC属于被动元件，不是印制电路板，也不属于覆铜板、电子布、铜箔、PCB化学品、设备或刀具。2025年电子元器件收入56.5238亿元，其他业务1.0403亿元，合计营业收入57.5641亿元，元器件约占98.19%，但该口径包含多类被动元件，不能全部视为MLCC，更不能转换为PCB收入。公司虽具备电子材料平台属性，现有正式资料未显示独立PCB制造或直接专用材料、设备业务，因此按产业链排除规则定级为摘除。旧“PCB-MLCC”把下游元件与电路板混同，本次只删除该错误交叉标签，不处理公司其他产业分类。 | J5: 广东风华高新科技股份有限公司2025年度审计报告 | K5: 2026-04-21 | L5: iFinD ifind_get_stock_info + ifind_get_stock_business_segmentation (as of 2026-10-27)；广东风华高新科技股份有限公司2025年度审计报告 | M5: https://disc.static.szse.cn/disc/disk03/finalpage/2026-04-21/7f212725-e703-4a11-b8f5-5f873701e825.pdf
B6: 000733 | C6: 振华科技 | D6: PCB：MLCC | E6: 摘除 | F6: — | G6: — | H6: 摘除 | I6: 公司新型电子元器件包括电阻、电容、电感、半导体分立器件、继电器、连接器及混合集成电路等，MLCC和军用被动元件即使用于军工电子或服务器，也仍是安装在电路板上的元器件，不等于PCB本体或其直接材料、设备、刀具。2025年新型电子元器件收入57.0999亿元，现代服务业0.4499亿元，合计57.5497亿元，元器件约占99.22%，但这是多产品混合口径，未单列MLCC收入，也不存在可辨认的PCB收入。正式年报未显示公司有独立印制电路板制造或覆铜板等强相关业务，故按排除规则定级为摘除。旧“PCB-MLCC”属于产业环节错配，本次删除该PCB标签，不触碰其军工电子等其他标签。 | J6: 中国振华(集团)科技股份有限公司2025年年度报告 | K6: 2026-04-29 | L6: iFinD ifind_get_stock_info + ifind_get_stock_business_segmentation (as of 2026-10-27)；中国振华(集团)科技股份有限公司2025年年度报告 | M6: http://file.finance.sina.com.cn/211.154.219.97:9494/MRGG/CNSESZ_STOCK/2026/2026-4/2026-04-29/12267545.PDF
B7: 001212 | C7: 中旗新材 | D7: PCB：硅微粉 | E7: 摘除 | F7: — | G7: — | H7: 摘除 | I7: 公司现有人造石英石板材和台面是真实主营产品，高纯砂或石英砂粉也不能仅凭化学成分就自动认定为覆铜板用硅微粉。2025年板材收入3.2807亿元、占约78.58%，台面0.8177亿元、占约19.59%，高纯砂约0.0527亿元、占约1.26%，合计营业收入4.1751亿元；砂粉收入占比很小，且公司正式互动回复明确相关硅微粉尚未在PCB领域应用，因此没有真实供货或收入可支撑PCB标签。混合口径中绝大多数为建材产品，不能当作电子填料业务。按只有潜在用途即排除的规则定级为摘除。旧“硅微粉”虽指出材料形态，却错误暗示PCB应用，本次删除该标签，不另行扩展石英材料分类。 | J7: 中旗新材关于硅微粉应用领域的投资者互动回复 | K7: 2026-06-08 | L7: iFinD ifind_get_stock_info + ifind_get_stock_business_segmentation (as of 2026-10-27)；中旗新材关于硅微粉应用领域的投资者互动回复 | M7: https://api3.cls.cn/share/article/2400946?os=androids&sv=860&app=
B8: 001216 | C8: 华瓷股份 | D8: PCB：MLCC | E8: 摘除 | F8: — | G8: — | H8: 摘除 | I8: 公司主要产品为色釉陶瓷、釉下五彩瓷等日用陶瓷，另有电瓷和陶瓷新材料，陶瓷材料身份并不代表生产MLCC，更不代表生产PCB或其专用材料。2025年色釉陶瓷收入13.9364亿元，釉下五彩瓷0.3876亿元，电瓷0.2021亿元，陶瓷新材料0.1251亿元，营业收入合计14.7154亿元；日用陶瓷占绝对主体，电瓷属于电力绝缘器材，也不能转为电子元件或电路板收入。年报未显示印制电路板、覆铜板、电子布、PCB设备或刀具等独立业务，故按真实产品和产业边界定级为摘除。旧“PCB-MLCC”没有任何对应主营产品支撑，是把陶瓷概念错误映射到电子元件后再错配到PCB，本次删除该标签，不处理其他产业属性。 | J8: 湖南华联瓷业股份有限公司2025年年度报告 | K8: 2026-04-29 | L8: iFinD ifind_get_stock_info + ifind_get_stock_business_segmentation (as of 2026-10-27)；湖南华联瓷业股份有限公司2025年年度报告 | M8: http://file.finance.sina.com.cn/211.154.219.97:9494/MRGG/CNSESZ_STOCK/2026/2026-4/2026-04-29/12246740.PDF
B9: 002859 | C9: 洁美科技 | D9: PCB：MLCC | E9: 摘除 | F9: — | G9: — | H9: 摘除 | I9: 公司真实产品为纸质载带、塑料载带、上下胶带及离型膜等电子封装和薄膜材料，主要服务MLCC等被动元件的包装、运输和制造过程；载带不是印制电路板，离型膜也不能仅因用于电子元件就归为PCB材料。2025年电子封装材料收入17.3910亿元，占约82.80%，膜材料2.5977亿元，占约12.37%，其他1.0155亿元，合计约21.0042亿元；这些收入口径均不能转换成PCB制造、覆铜板、电子布、设备或刀具收入。公司虽有电子材料主业，但现有正式资料不支持独立PCB业务，故定级为摘除。旧“PCB-MLCC”虽提到真实下游元件，却把元件封装耗材错接到PCB链条，本次删除该交叉标签，不处理其MLCC耗材等其他产业属性。 | J9: 洁美科技：2025年年度报告 | K9: 2026-04-21 | L9: iFinD ifind_get_stock_info + ifind_get_stock_business_segmentation (as of 2026-10-27)；洁美科技：2025年年度报告 | M9: https://money.finance.sina.com.cn/corp/view/vCB_AllBulletinDetail.php?stockid=002859&id=12122734
B10: 300408 | C10: 三环集团 | D10: PCB：MLCC、SOFC、MPO/连接器 | E10: 摘除 | F10: — | G10: — | H10: 摘除 | I10: 公司真实产品包括MLCC、陶瓷插芯及配套件、MT插芯、陶瓷封装管壳和SOFC相关陶瓷部件，这些分别属于被动元件、光通信和燃料电池领域，本身均不是PCB制造、覆铜板材料、PCB设备或刀具。2025年营业收入90.0715亿元，电子元件收入33.0809亿元、通信器件25.9431亿元、电子及陶瓷材料19.5938亿元、设备组件6.0175亿元，均为混合产品口径，不能全部归为MLCC或MPO，更不存在可辨认的PCB收入。即使MLCC用于服务器、MT插芯用于数据中心，终端相同也不改变产业环节。按无独立PCB业务必须排除的规则定级为摘除。旧PCB项下MLCC、SOFC和MPO均为交叉错标，本次仅删除这些PCB标签，不处理其他产业分类。 | J10: 三环集团：2025年年度报告 | K10: 2026-03-28 | L10: iFinD ifind_get_stock_info + ifind_get_stock_business_segmentation (as of 2026-10-27)；三环集团：2025年年度报告 | M10: https://money.finance.sina.com.cn/corp/view/vCB_AllBulletinDetail.php?stockid=300408&id=12028356
B11: 301013 | C11: 利和兴 | D11: PCB：MLCC | E11: 摘除 | F11: — | G11: — | H11: 摘除 | I11: 公司2025年真实业务为移动智能终端等自动化测试、组装设备以及MLCC电子元器件，专用设备制造业收入3.0935亿元、占65.8114%，电子元器件制造业收入1.6071亿元、占34.1886%。年报所列MLCC包括高频高容、高强度、射频微波高Q等电容器，应用于通信、消费电子、汽车及工业电源；MLCC是贴装到电路板上的元器件，不是PCB裸板、覆铜板、PCB材料或PCB专用设备，产品用于PCB布局或承受PCB弯曲也不改变其产业分类。公司没有披露独立PCB制造或PCB专用设备收入，智能制造设备收入也不能因涉及PCBA组装工序就全部归入PCB。旧“MLCC”标签属于跨概念误映射，故本次摘除PCB标签，其他超节点或服务器分类不在本次处理范围。 | J11: 利和兴：2025年年度报告 | K11: 2026-04-27 | L11: iFinD ifind_get_stock_info + ifind_get_stock_business_segmentation (as of 2026-10-27)；利和兴：2025年年度报告 | M11: https://pdf.dfcfw.com/pdf/H2_AN202604261821591854_1.pdf
B12: 301566 | C12: 达利凯普 | D12: PCB：MLCC | E12: 摘除 | F12: — | G12: — | H12: 摘除 | I12: 公司真实主营是射频微波瓷介电容器研发、制造和销售，产品包括片式射频微波MLCC及带金属引脚的电容器，主要服务射频微波、通信、医疗和军工等电子整机。2025年瓷介电容器收入3.5782亿元，按营业收入3.6236亿元计算约占98.75%，其他收入0.0454亿元，主业高度集中且边界清楚。MLCC属于安装在PCB上的电子元器件，不是印制电路板、覆铜板、铜箔、树脂、加工刀具或PCB生产设备；其产品用于电路板贴装并不意味着公司具有独立PCB业务。年报没有披露PCB制造、PCB材料或PCB设备销售收入，因此旧“MLCC”被放入PCB体系属于概念错配，且原“核心”定级放大了错误，本次直接摘除PCB标签。 | J12: 达利凯普：2025年年度报告 | K12: 2026-04-27 | L12: iFinD ifind_get_stock_info + ifind_get_stock_business_segmentation (as of 2026-10-27)；达利凯普：2025年年度报告 | M12: https://pdf.dfcfw.com/pdf/H2_AN202604261821588733_1.pdf
B13: 301678 | C13: 新恒汇 | D13: PCB：曝光 | E13: 摘除 | F13: — | G13: — | H13: 摘除 | I13: 公司真实业务为智能卡模块、蚀刻引线框架和物联网eSIM芯片封测，2025年智能卡业务收入4.8353亿元、约占营业收入52.37%，蚀刻引线框架3.1321亿元、约占33.92%，物联网eSIM封测0.6510亿元、约占7.05%。年报所述LDI曝光、卷式真空连续蚀刻和选择性电镀是公司制造蚀刻引线框架的内部核心工艺，用于芯片封装载体生产，并非对外销售PCB直接成像或曝光设备；年报亦未出现PCB产品业务。引线框架与普通PCB、IC载板不能仅因工艺相似而混同，相关制造收入也不能归入PCB设备或PCB收入。旧“曝光”把生产工序误映射为PCB设备产品，缺少独立PCB业务证据，故本次摘除PCB标签。 | J13: 新恒汇：2025年年度报告 | K13: 2026-04-22 | L13: iFinD ifind_get_stock_info + ifind_get_stock_business_segmentation (as of 2026-10-27)；新恒汇：2025年年度报告 | M13: https://pdf.dfcfw.com/pdf/H2_AN202604211821395269_1.pdf
B14: 603267 | C14: 鸿远电子 | D14: PCB：MLCC | E14: 摘除 | F14: — | G14: — | H14: 摘除 | I14: 公司真实产品是多层及单层瓷介电容器、滤波器、微波模块、集成电路和陶瓷管壳，年报将MLCC明确界定为在电路中实现调谐、旁路、耦合和滤波的被动元件，并未披露印制电路板、覆铜板、PCB材料或PCB设备业务。MLCC可贴装在PCB上只是下游装配关系，不能据此把电容器制造商归入PCB产业链。iFinD二〇二五年电子元器件行业收入占百分之九十九点一一，其中自产电子元器件十点八八亿元、代理产品六点九〇亿元，这些均为元器件及代理口径而非PCB收入，混合边界不得偷换。因缺少真实PCB产品和收入，判定摘除；旧“MLCC”放在PCB类别属于明确错标，应删除而非改列相关。 | J14: 鸿远电子：2025年年度报告 | K14: 2026-03-28 | L14: iFinD ifind_get_stock_info + ifind_get_stock_business_segmentation (as of 2026-10-27)；鸿远电子：2025年年度报告 | M14: https://money.finance.sina.com.cn/corp/view/vCB_AllBulletinDetail.php?stockid=603267&id=12031215
B15: 603678 | C15: 火炬电子 | D15: PCB：MLCC | E15: 摘除 | F15: — | G15: — | H15: 摘除 | I15: 公司真实自产元器件包括陶瓷电容器、钽电容器、超级电容器、微波芯片电容器、薄膜电路和滤波器等，年报将相关业务放在电子元器件及新材料体系内，没有披露PCB裸板、覆铜板或PCB专用材料设备收入。陶瓷电容器和MLCC是贴装于电路板的被动元件，薄膜电路也不等同印制电路板，不能因下游电子设备存在PCB就把公司产品归入PCB。iFinD二〇二五年贸易收入占百分之六十一点四三，自产元器件占百分之三十三点〇八，自产新材料占百分之四点九六，均不是PCB分部，混合贸易额更不能转成PCB收入。由此判定摘除；旧“MLCC”置于PCB类别是产品层级错标，应删除，而不是因元器件规模较大保留相关。 | J15: 火炬电子：2025年年度报告 | K15: 2026-03-31 | L15: iFinD ifind_get_stock_info + ifind_get_stock_business_segmentation (as of 2026-10-27)；火炬电子：2025年年度报告 | M15: https://money.finance.sina.com.cn/corp/view/vCB_AllBulletinDetail.php?stockid=603678&id=12039732
... B17: 688260 | C17: 昀冢科技 | D17: PCB：MLCC | E17: 摘除 | F17: — | G17: — | H17: 摘除 | I17: 公司真实业务包括手机光学精密零部件、汽车电子、电子陶瓷和引线框架等；年报明确电子陶瓷方向包含MLCC及DPC，MLCC即片式多层陶瓷电容器，产能规模较小且尚未盈利。陶瓷电容器、陶瓷热沉或DPC陶瓷基板均不等于印制电路板，SMT定义中出现印刷电路板也只是说明元器件贴装工艺，不能构成PCB产品证据。iFinD二〇二五年电子陶瓷器件收入一点六五亿元、约占总收入百分之二十九点三二，但该口径混合MLCC和其他陶瓷产品，不能转成PCB收入，精密零部件等其余收入同样无PCB归属。因缺少真实PCB产品或供货证据，判定摘除；旧“MLCC”及“消费电子精密件”放在PCB类别均属错标。 | J17: 昀冢科技：2025年年度报告 | K17: 2026-04-22 | L17: iFinD ifind_get_stock_info + ifind_get_stock_business_segmentation (as of 2026-10-27)；昀冢科技：2025年年度报告 | M17: https://money.finance.sina.com.cn/corp/view/vCB_AllBulletinDetail.php?stockid=688260&id=12132027

Sheet 概念展开
A1: 一级分类 | B1: 二级概念 | C1: 判词 | D1: 代码 | E1: 名称
A2: PCB | B2: PCB刀具-钻针与铣刀 | C2: 核心 | D2: 000657 | E2: 中钨高新
A3: PCB | B3: PCB-HDI与任意层互连 | C3: 核心 | D3: 000823 | E3: 超声电子
A4: PCB | B4: 覆铜板与粘结片 | C4: 核心 | D4: 000823 | E4: 超声电子
A5: PCB | B5: 电子布与玻纤材料 | C5: 核心 | D5: 001359 | E5: 平安电工
A6: PCB | B6: PCB-高多层与服务器板 | C6: 核心 | D6: 001389 | E6: 广合科技
A7: PCB | B7: PCB-HDI与任意层互连 | C7: 核心 | D7: 001389 | E7: 广合科技
A8: PCB | B8: 电子布与玻纤材料 | C8: 相关 | D8: 002080 | E8: 中材科技
A9: PCB | B9: PCB-通用刚性板 | C9: 核心 | D9: 002134 | E9: 天津普林
A10: PCB | B10: PCB-HDI与任意层互连 | C10: 核心 | D10: 002134 | E10: 天津普林
A11: PCB | B11: 覆铜板与粘结片 | C11: 核心 | D11: 002141 | E11: 贤丰控股
A12: PCB | B12: 填料-硅微粉与功能粉体 | C12: 相关 | D12: 002409 | E12: 雅克科技
... A145: PCB | B145: PCB-IC载板 | C145: 核心 | D145: 920821 | E145: 则成电子

Sheet 概念统计
B2: 概念统计 · 核心/相关分布
B3: 公式引用隐藏展开表精确计数；一只股票可对应多个概念。
B4: 一级分类 | C4: 二级概念 | D4: 核心（只） | E4: 相关（只） | F4: 合计（只）
B5: PCB | C5: PCB-FPC与刚挠结合 | D5: =COUNTIFS('概念展开'!$A$2:$A$145,B5,'概念展开'!$B$2:$B$145,C5,'概念展开'!$C$2:$C$145,"核心") | E5: =COUNTIFS('概念展开'!$A$2:$A$145,B5,'概念展开'!$B$2:$B$145,C5,'概念展开'!$C$2:$C$145,"相关") | F5: =SUM(D5:E5)
B6: PCB | C6: PCB-HDI与任意层互连 | D6: =COUNTIFS('概念展开'!$A$2:$A$145,B6,'概念展开'!$B$2:$B$145,C6,'概念展开'!$C$2:$C$145,"核心") | E6: =COUNTIFS('概念展开'!$A$2:$A$145,B6,'概念展开'!$B$2:$B$145,C6,'概念展开'!$C$2:$C$145,"相关") | F6: =SUM(D6:E6)
B7: PCB | C7: PCB-IC载板 | D7: =COUNTIFS('概念展开'!$A$2:$A$145,B7,'概念展开'!$B$2:$B$145,C7,'概念展开'!$C$2:$C$145,"核心") | E7: =COUNTIFS('概念展开'!$A$2:$A$145,B7,'概念展开'!$B$2:$B$145,C7,'概念展开'!$C$2:$C$145,"相关") | F7: =SUM(D7:E7)
B8: PCB | C8: PCB-通用刚性板 | D8: =COUNTIFS('概念展开'!$A$2:$A$145,B8,'概念展开'!$B$2:$B$145,C8,'概念展开'!$C$2:$C$145,"核心") | E8: =COUNTIFS('概念展开'!$A$2:$A$145,B8,'概念展开'!$B$2:$B$145,C8,'概念展开'!$C$2:$C$145,"相关") | F8: =SUM(D8:E8)
B9: PCB | C9: PCB-高多层与服务器板 | D9: =COUNTIFS('概念展开'!$A$2:$A$145,B9,'概念展开'!$B$2:$B$145,C9,'概念展开'!$C$2:$C$145,"核心") | E9: =COUNTIFS('概念展开'!$A$2:$A$145,B9,'概念展开'!$B$2:$B$145,C9,'概念展开'!$C$2:$C$145,"相关") | F9: =SUM(D9:E9)
B10: PCB | C10: PCB刀具-钻针与铣刀 | D10: =COUNTIFS('概念展开'!$A$2:$A$145,B10,'概念展开'!$B$2:$B$145,C10,'概念展开'!$C$2:$C$145,"核心") | E10: =COUNTIFS('概念展开'!$A$2:$A$145,B10,'概念展开'!$B$2:$B$145,C10,'概念展开'!$C$2:$C$145,"相关") | F10: =SUM(D10:E10)
B11: PCB | C11: PCB化学品-电镀与湿制程 | D11: =COUNTIFS('概念展开'!$A$2:$A$145,B11,'概念展开'!$B$2:$B$145,C11,'概念展开'!$C$2:$C$145,"核心") | E11: =COUNTIFS('概念展开'!$A$2:$A$145,B11,'概念展开'!$B$2:$B$145,C11,'概念展开'!$C$2:$C$145,"相关") | F11: =SUM(D11:E11)
B12: PCB | C12: PCB材料-其他关键材料 | D12: =COUNTIFS('概念展开'!$A$2:$A$145,B12,'概念展开'!$B$2:$B$145,C12,'概念展开'!$C$2:$C$145,"核心") | E12: =COUNTIFS('概念展开'!$A$2:$A$145,B12,'概念展开'!$B$2:$B$145,C12,'概念展开'!$C$2:$C$145,"相关") | F12: =SUM(D12:E12)
B13: PCB | C13: PCB股权与产业投资 | D13: =COUNTIFS('概念展开'!$A$2:$A$145,B13,'概念展开'!$B$2:$B$145,C13,'概念展开'!$C$2:$C$145,"核心") | E13: =COUNTIFS('概念展开'!$A$2:$A$145,B13,'概念展开'!$B$2:$B$145,C13,'概念展开'!$C$2:$C$145,"相关") | F13: =SUM(D13:E13)
B14: PCB | C14: PCB设备-SMT与贴装 | D14: =COUNTIFS('概念展开'!$A$2:$A$145,B14,'概念展开'!$B$2:$B$145,C14,'概念展开'!$C$2:$C$145,"核心") | E14: =COUNTIFS('概念展开'!$A$2:$A$145,B14,'概念展开'!$B$2:$B$145,C14,'概念展开'!$C$2:$C$145,"相关") | F14: =SUM(D14:E14)
B15: PCB | C15: PCB设备-曝光与成像 | D15: =COUNTIFS('概念展开'!$A$2:$A$145,B15,'概念展开'!$B$2:$B$145,C15,'概念展开'!$C$2:$C$145,"核心") | E15: =COUNTIFS('概念展开'!$A$2:$A$145,B15,'概念展开'!$B$2:$B$145,C15,'概念展开'!$C$2:$C$145,"相关") | F15: =SUM(D15:E15)
B16: PCB | C16: PCB设备-检测与测试 | D16: =COUNTIFS('概念展开'!$A$2:$A$145,B16,'概念展开'!$B$2:$B$145,C16,'概念展开'!$C$2:$C$145,"核心") | E16: =COUNTIFS('概念展开'!$A$2:$A$145,B16,'概念展开'!$B$2:$B$145,C16,'概念展开'!$C$2:$C$145,"相关") | F16: =SUM(D16:E16)
... B27: PCB | C27: 铜箔-通用PCB | D27: =COUNTIFS('概念展开'!$A$2:$A$145,B27,'概念展开'!$B$2:$B$145,C27,'概念展开'!$C$2:$C$145,"核心") | E27: =COUNTIFS('概念展开'!$A$2:$A$145,B27,'概念展开'!$B$2:$B$145,C27,'概念展开'!$C$2:$C$145,"相关") | F27: =SUM(D27:E27)
B28: 合计（概念次数，非股票去重数） | D28: =SUM(D5:D27) | E28: =SUM(E5:E27) | F28: =SUM(F5:F27)
