Workbook

Sheet 封面
B2: 云计算概念深度清洗报告
B3: 复核日期：2026-10-27｜范围：45只｜重点：云交付实质、服务层级、分类边界与GUI科普
B6: 复核股票（只） | C6: =COUNTA('清洗总表'!$B$5:$B$49)
B7: 保留云计算（只） | C7: =COUNTA('云计算'!$B$5:$B$41)
B8: 核心判词（只） | C8: =COUNTIF('云计算'!$H$5:$H$41,"核心")
B9: 相关判词（只） | C9: =COUNTIF('云计算'!$H$5:$H$41,"相关")
B10: 跨分类迁移（只） | C10: =COUNTA('跨分类迁移'!$B$5:$B$5)
B11: 完全摘除（只） | C11: =COUNTA('摘除清单'!$B$5:$B$11)
B12: 纠错动作（只） | C12: =COUNTIF('清洗总表'!$E$5:$E$49,"纠错")
B15: 工作表索引
B16: 清洗总表 | C16: 45只旧概念、新概念、动作、判词、详细理由和证据
B17: 云计算 | C17: 37只清洗后云计算公司
B18: 跨分类迁移 | C18: 1只云安全迁移公司
B19: 摘除清单 | C19: 7只传统业务或落地不足公司
B20: 概念统计 | C20: 24个二级概念（含1个网安迁移概念）
B23: 云计算：把服务器、存储、数据库和软件放在远端数据中心，通过网络按需使用，并按用量或订阅付费。
B24: IaaS=租计算、存储和网络；PaaS=租开发运行平台；SaaS=直接使用线上软件。IDC和CDN是相关基础设施，但不自动等于IaaS。
B25: 普通硬件销售、系统集成、传统软件授权、DeepSeek合作不等于云计算；云安全与SASE归网络安全。
B26: GUI：选股猎手展开“云计算”后显示“什么是云计算？”科普卡；今日和历史视图采用同一口径。
B27: 主营资料：iFinD ifind_get_stock_info（2026-10-27）；逐股证据名称、日期及URL见Source列。

Sheet 清洗总表
B2: 云计算 · 45只逐项复核
B3: 逐股核对云产品、交付方式、客户与收入；区分IaaS、PaaS、SaaS、IDC和云安全。
B4: 代码 | C4: 名称 | D4: 旧云计算概念 | E4: 动作 | F4: 新一级分类 | G4: 新概念 | H4: 判词 | I4: 详细理由 | J4: 证据名称 | K4: 证据日期 | L4: Source Name | M4: Source URL
B5: 000034 | C5: 神州数码 | D5: 云计算：SaaS软件与服务 | E5: 纠错 | F5: 云计算 | G5: 云平台与多云管理 | H5: 相关 | I5: 公司主营仍以IT分销及增值服务为主，真实云业务是面向企业客户的云管理、云迁移、云原生改造和持续运维服务，并非旧标签暗示的通用SaaS软件。2025年数云服务及软件收入36.73亿元、同比增长23.87%，已持续商业化且覆盖医疗、制造、汽车、零售等客户，但该板块仅占总营收2.56%，且还包含非云数字化方案，故改标云平台与多云管理并维持相关。 | J5: 神州数码：2025年年度报告 | K5: 2026-03-31 | L5: iFinD ifind_get_stock_info (as of 2026-10-27)；神州数码：2025年年度报告 | M5: http://vip.stock.finance.sina.com.cn/corp/view/vCB_AllBulletinDetail.php?stockid=000034&id=12044900
B6: 000815 | C6: 美利云 | D6: 云计算：IaaS基础设施服务 | E6: 纠错 | F6: 云计算 | G6: IDC与云基础设施 | H6: 核心 | I6: 公司已于2024年底停止造纸，现由誉成云创经营中卫数据中心，通过机柜、网络接入及运维合同向客户收费，属于真实IDC云基础设施服务，不能直接称为IaaS计算资源平台。2025年云业务收入3.24亿元，占总营收94.65%，E1、E3、C1已交付客户使用，云业务已是绝对主营和主要利润来源，因此将旧IaaS标签纠正为IDC与云基础设施，并由相关升级为核心。 | J6: 美利云：2025年年度报告 | K6: 2026-04-24 | L6: iFinD ifind_get_stock_info (as of 2026-10-27)；美利云：2025年年度报告 | M6: https://money.finance.sina.com.cn/corp/view/vCB_AllBulletinDetail.php?stockid=000815&id=12164556
B7: 000938 | C7: 紫光股份 | D7: 云计算：国资云 | E7: 纠错 | F7: 云计算 | G7: 云平台与多云管理、IaaS计算与存储 | H7: 核心 | I7: 新华三明确将云与智能列为主要产品线，自研CloudOS云操作系统、CAS虚拟化、UIS超融合、桌面云及分布式存储，为政府、能源、交通、运营商等客户交付私有云、混合云和多云场景，并非单纯销售服务器。CloudOS已广泛行业落地，超融合市场份额位居前列，属于规模化核心产品；虽然云收入未单独拆分，但符合核心产品标准，故以云平台及IaaS能力替代笼统国资云标签。 | J7: 紫光股份有限公司2025年年度报告摘要 | K7: 2026-04-15 | L7: iFinD ifind_get_stock_info (as of 2026-10-27)；紫光股份有限公司2025年年度报告摘要 | M7: http://static.cninfo.com.cn/finalpage/2026-04-15/1225101865.PDF
B8: 002123 | C8: 梦网科技 | D8: 云计算：PaaS平台即服务 | E8: 纠错 | F8: 云计算 | G8: 云通信与消息服务 | H8: 核心 | I8: 公司通过自有云通信平台向企业客户提供行业短信、5G阅信、5G RCS及国际消息触达服务，本质是按消息和通信能力交付的CPaaS，而非泛化的开发运行PaaS。2025年云通信服务业收入26.09亿元，占营业收入100%，国际通信收入同比增长25.80%，5G阅信平台已在三大运营商建成并商用上线，虽有传统短信收缩和新产品培育压力，仍属明确主营和规模化收入，故改标并升级为核心。 | J8: 梦网科技：2025年年度报告 | K8: 2026-04-29 | L8: iFinD ifind_get_stock_info (as of 2026-10-27)；梦网科技：2025年年度报告 | M8: https://money.finance.sina.com.cn/corp/view/vCB_AllBulletinDetail.php?stockid=002123&id=12251556
B9: 002131 | C9: 利欧股份 | D9: 云计算：DeepSeek | E9: 摘除 | F9: — | G9: — | H9: 摘除 | I9: 公司2025年主营仍为机械制造和数字营销，收入主要来自媒体代理、整合营销及泵业产品。AI创意、投放优化和智能体虽已进入营销流程，但公司明确其主要以间接方式融入既有业务，直接收入较小且难以拆分；这些属于AI营销工具，不是自营云平台、云计算资源或在线软件订阅服务。旧DeepSeek标签仅反映模型或投资联想，未形成可核验云计算产品、客户和收入，故摘除云计算标签。 | J9: 利欧股份：2025年年度报告 | K9: 2026-04-29 | L9: iFinD ifind_get_stock_info (as of 2026-10-27)；利欧股份：2025年年度报告 | M9: https://money.finance.sina.com.cn/corp/view/vCB_AllBulletinDetail.php?stockid=002131&id=12249389
B10: 002153 | C10: 石基信息 | D10: 云计算：SaaS软件与服务 | E10: 纠错 | F10: 云计算 | G10: SaaS-酒店与餐饮管理 | H10: 核心 | I10: 公司将酒店PMS、餐饮POS等主营信息系统以云架构和订阅方式交付，DAYLIGHT PMS、Infrasys POS均已在国际酒店集团实际上线，不是传统软件授权的换名。2025年末SaaS年度可重复订阅费约6.27亿元、同比增长约20%，企业客户门店超过8万家、平均续费率超过90%；DAYLIGHT PMS已上线878家酒店，云POS上线4972家门店，已达规模化核心产品标准，故细化标签并由相关升级为核心。 | J10: 石基信息：2025年年度报告 | K10: 2026-03-26 | L10: iFinD ifind_get_stock_info (as of 2026-10-27)；石基信息：2025年年度报告 | M10: https://money.finance.sina.com.cn/corp/view/vCB_AllBulletinDetail.php?stockid=002153&id=12019337
B11: 002315 | C11: 焦点科技 | D11: 云计算：SaaS软件与服务 | E11: 纠错 | F11: 云计算 | G11: SaaS-外贸营销与获客 | H11: 相关 | I11: 中国制造网主要是按会员和认证服务收费的B2B电子商务平台，不能仅因在线运营就全部认定为SaaS；真正符合云交付的是AI麦可等面向外贸企业的在线营销、内容生成和获客工具。2025年AI麦可现金收入9083.24万元、同比增长88.49%，累计购买会员18494位，商业化和客户证据充分，但相对19.21亿元总营收仍属较小新业务，故保留真实SaaS部分并将核心下调为相关。 | J11: 焦点科技股份有限公司2025年年度报告 | K11: 2026-03-20 | L11: iFinD ifind_get_stock_info (as of 2026-10-27)；焦点科技股份有限公司2025年年度报告 | M11: https://static.cninfo.com.cn/finalpage/2026-03-20/1225018374.PDF
B12: 002335 | C12: 科华数据 | D12: 云计算：IaaS基础设施服务 | E12: 纠错 | F12: 云计算 | G12: IDC与云基础设施 | H12: 核心 | I12: 公司智算业务同时包括数据中心供配电、温控等产品销售和自营IDC服务，其中IDC通过专业机房、通信线路和带宽为企业及政府提供服务器托管、租用与运维，按机柜上架数和带宽用量结算，并非当然的IaaS。2025年IDC服务收入12.84亿元、占总营收15.73%，数据中心行业收入35.23亿元，已有互联网、运营商、金融和政务客户持续交付，构成重要收入板块，故改为IDC与云基础设施并保留核心。 | J12: 科华数据：2025年年度报告 | K12: 2026-04-27 | L12: iFinD ifind_get_stock_info (as of 2026-10-27)；科华数据：2025年年度报告 | M12: https://money.finance.sina.com.cn/corp/view/vCB_AllBulletinDetail.php?stockid=002335&id=12205218
B13: 002410 | C13: 广联达 | D13: 云计算：SaaS软件与服务 | E13: 纠错 | F13: 云计算 | G13: SaaS-建筑工程造价与成本管理 | H13: 核心 | I13: 公司数字成本业务已将算量、计价、清标和成本管理产品转为在线SaaS订阅及持续服务，直接面向建筑施工和造价客户，不是传统本地授权软件的简单包装。2025年数字成本业务收入47.79亿元，其中云收入34.57亿元、占该业务72%，约占公司总营收57%，新签云合同33.8亿元，续费率稳中有升，云交付已成为主营收入主体，故保留核心并将泛SaaS标签细化为建筑工程造价与成本管理。 | J13: 广联达获79家机构调研：2025年数字成本业务收入是47.79亿，其中云收入34.57亿，占比72% | K13: 2026-03-25 | L13: iFinD ifind_get_stock_info (as of 2026-10-27)；广联达获79家机构调研：2025年数字成本业务收入是47.79亿，其中云收入34.57亿，占比72% | M13: https://m.10jqka.com.cn/20260325/c675521155.shtml
B14: 002439 | C14: 启明星辰 | D14: 云计算：SaaS软件与服务 | E14: 迁移 | F14: 网络安全 | G14: 云安全与SaaS安全服务 | H14: 相关 | I14: 公司主营是网络安全产品和安全运营服务，实际拥有云安全管理平台、云安全资源池、安星网站安全SaaS及云子可信等云交付产品，可向云端、IDC和传统地端提供安全订阅与运营服务，但保护对象和安全能力不等于向客户提供云计算平台或通用在线软件。2025年收入仍集中于安全产品及安全运营，未证明存在独立云计算主营，因此摘除云计算下的泛SaaS标签，迁移为更准确的网络安全云安全与SaaS安全服务。 | J14: 启明星辰：2025年年度报告 | K14: 2026-04-13 | L14: iFinD ifind_get_stock_info (as of 2026-10-27)；启明星辰：2025年年度报告 | M14: http://money.finance.sina.com.cn/corp/view/vCB_AllBulletinDetail.php?stockid=002439&id=12082100
B15: 002757 | C15: 南兴股份 | D15: 云计算：IaaS基础设施服务 | E15: 纠错 | F15: 云计算 | G15: IDC与云基础设施、云平台与多云管理 | H15: 核心 | I15: 子公司唯一网络实际运营自建及租用数据中心，并提供公有云、私有云、混合云、云联网、云管理和自动化运维服务，兼有80余个边缘节点，不是仅有家具装备或普通系统集成。2025年IDC及云计算收入19.66亿元、同比增长29.79%，占总营收57.62%，首次超过传统专用设备成为第一大收入来源，已形成规模化持续经营，故由相关升级为核心，并用IDC及多云管理标签替代笼统IaaS。 | J15: 南兴股份：2025年年度报告 | K15: 2026-04-25 | L15: iFinD ifind_get_stock_info (as of 2026-10-27)；南兴股份：2025年年度报告 | M15: https://vip.stock.finance.sina.com.cn/corp/view/vCB_AllBulletinDetail.php?stockid=002757&id=12190607
... B49: 688561 | C49: 奇安信-U | D49: 云计算：SaaS软件与服务 | E49: 摘除 | F49: — | G49: — | H49: 摘除 | I49: 公司2025年主营业务分为网络安全产品、网络安全服务及配套硬件，信息安全行业收入43.81亿元。CSMP、CNAPP、CWPP、云安全运营中心和SaaS终端安全管理系统均用于云基础设施、云主机、容器或终端的安全防护，虽然已有正式上市版本和政企客户，但不构成独立通用云计算、存储、PaaS或非安全SaaS产品。依据云安全不等于云计算的标准，摘除云计算标签，终端安全、数据安全与云安全等网安分类不在本轮重复输出。 | J49: 奇安信科技集团股份有限公司2025年年度报告 | K49: 2026-04-30 | L49: iFinD ifind_get_stock_info (as of 2026-10-27)；奇安信科技集团股份有限公司2025年年度报告 | M49: http://file.finance.sina.com.cn/211.154.219.97:9494/MRGG/CNSESH_STOCK/2026/2026-4/2026-04-30/12285369.PDF

Sheet 云计算
B2: 云计算 · 清洗后37只股池
B3: 核心28只、相关9只；按真实云交付细化为23个二级概念。
B4: 代码 | C4: 名称 | D4: 旧云计算概念 | E4: 动作 | F4: 新一级分类 | G4: 新概念 | H4: 判词 | I4: 详细理由 | J4: 证据名称 | K4: 证据日期 | L4: Source Name | M4: Source URL
B5: 000034 | C5: 神州数码 | D5: 云计算：SaaS软件与服务 | E5: 纠错 | F5: 云计算 | G5: 云平台与多云管理 | H5: 相关 | I5: 公司主营仍以IT分销及增值服务为主，真实云业务是面向企业客户的云管理、云迁移、云原生改造和持续运维服务，并非旧标签暗示的通用SaaS软件。2025年数云服务及软件收入36.73亿元、同比增长23.87%，已持续商业化且覆盖医疗、制造、汽车、零售等客户，但该板块仅占总营收2.56%，且还包含非云数字化方案，故改标云平台与多云管理并维持相关。 | J5: 神州数码：2025年年度报告 | K5: 2026-03-31 | L5: iFinD ifind_get_stock_info (as of 2026-10-27)；神州数码：2025年年度报告 | M5: http://vip.stock.finance.sina.com.cn/corp/view/vCB_AllBulletinDetail.php?stockid=000034&id=12044900
B6: 000815 | C6: 美利云 | D6: 云计算：IaaS基础设施服务 | E6: 纠错 | F6: 云计算 | G6: IDC与云基础设施 | H6: 核心 | I6: 公司已于2024年底停止造纸，现由誉成云创经营中卫数据中心，通过机柜、网络接入及运维合同向客户收费，属于真实IDC云基础设施服务，不能直接称为IaaS计算资源平台。2025年云业务收入3.24亿元，占总营收94.65%，E1、E3、C1已交付客户使用，云业务已是绝对主营和主要利润来源，因此将旧IaaS标签纠正为IDC与云基础设施，并由相关升级为核心。 | J6: 美利云：2025年年度报告 | K6: 2026-04-24 | L6: iFinD ifind_get_stock_info (as of 2026-10-27)；美利云：2025年年度报告 | M6: https://money.finance.sina.com.cn/corp/view/vCB_AllBulletinDetail.php?stockid=000815&id=12164556
B7: 000938 | C7: 紫光股份 | D7: 云计算：国资云 | E7: 纠错 | F7: 云计算 | G7: 云平台与多云管理、IaaS计算与存储 | H7: 核心 | I7: 新华三明确将云与智能列为主要产品线，自研CloudOS云操作系统、CAS虚拟化、UIS超融合、桌面云及分布式存储，为政府、能源、交通、运营商等客户交付私有云、混合云和多云场景，并非单纯销售服务器。CloudOS已广泛行业落地，超融合市场份额位居前列，属于规模化核心产品；虽然云收入未单独拆分，但符合核心产品标准，故以云平台及IaaS能力替代笼统国资云标签。 | J7: 紫光股份有限公司2025年年度报告摘要 | K7: 2026-04-15 | L7: iFinD ifind_get_stock_info (as of 2026-10-27)；紫光股份有限公司2025年年度报告摘要 | M7: http://static.cninfo.com.cn/finalpage/2026-04-15/1225101865.PDF
B8: 002123 | C8: 梦网科技 | D8: 云计算：PaaS平台即服务 | E8: 纠错 | F8: 云计算 | G8: 云通信与消息服务 | H8: 核心 | I8: 公司通过自有云通信平台向企业客户提供行业短信、5G阅信、5G RCS及国际消息触达服务，本质是按消息和通信能力交付的CPaaS，而非泛化的开发运行PaaS。2025年云通信服务业收入26.09亿元，占营业收入100%，国际通信收入同比增长25.80%，5G阅信平台已在三大运营商建成并商用上线，虽有传统短信收缩和新产品培育压力，仍属明确主营和规模化收入，故改标并升级为核心。 | J8: 梦网科技：2025年年度报告 | K8: 2026-04-29 | L8: iFinD ifind_get_stock_info (as of 2026-10-27)；梦网科技：2025年年度报告 | M8: https://money.finance.sina.com.cn/corp/view/vCB_AllBulletinDetail.php?stockid=002123&id=12251556
B9: 002153 | C9: 石基信息 | D9: 云计算：SaaS软件与服务 | E9: 纠错 | F9: 云计算 | G9: SaaS-酒店与餐饮管理 | H9: 核心 | I9: 公司将酒店PMS、餐饮POS等主营信息系统以云架构和订阅方式交付，DAYLIGHT PMS、Infrasys POS均已在国际酒店集团实际上线，不是传统软件授权的换名。2025年末SaaS年度可重复订阅费约6.27亿元、同比增长约20%，企业客户门店超过8万家、平均续费率超过90%；DAYLIGHT PMS已上线878家酒店，云POS上线4972家门店，已达规模化核心产品标准，故细化标签并由相关升级为核心。 | J9: 石基信息：2025年年度报告 | K9: 2026-03-26 | L9: iFinD ifind_get_stock_info (as of 2026-10-27)；石基信息：2025年年度报告 | M9: https://money.finance.sina.com.cn/corp/view/vCB_AllBulletinDetail.php?stockid=002153&id=12019337
B10: 002315 | C10: 焦点科技 | D10: 云计算：SaaS软件与服务 | E10: 纠错 | F10: 云计算 | G10: SaaS-外贸营销与获客 | H10: 相关 | I10: 中国制造网主要是按会员和认证服务收费的B2B电子商务平台，不能仅因在线运营就全部认定为SaaS；真正符合云交付的是AI麦可等面向外贸企业的在线营销、内容生成和获客工具。2025年AI麦可现金收入9083.24万元、同比增长88.49%，累计购买会员18494位，商业化和客户证据充分，但相对19.21亿元总营收仍属较小新业务，故保留真实SaaS部分并将核心下调为相关。 | J10: 焦点科技股份有限公司2025年年度报告 | K10: 2026-03-20 | L10: iFinD ifind_get_stock_info (as of 2026-10-27)；焦点科技股份有限公司2025年年度报告 | M10: https://static.cninfo.com.cn/finalpage/2026-03-20/1225018374.PDF
B11: 002335 | C11: 科华数据 | D11: 云计算：IaaS基础设施服务 | E11: 纠错 | F11: 云计算 | G11: IDC与云基础设施 | H11: 核心 | I11: 公司智算业务同时包括数据中心供配电、温控等产品销售和自营IDC服务，其中IDC通过专业机房、通信线路和带宽为企业及政府提供服务器托管、租用与运维，按机柜上架数和带宽用量结算，并非当然的IaaS。2025年IDC服务收入12.84亿元、占总营收15.73%，数据中心行业收入35.23亿元，已有互联网、运营商、金融和政务客户持续交付，构成重要收入板块，故改为IDC与云基础设施并保留核心。 | J11: 科华数据：2025年年度报告 | K11: 2026-04-27 | L11: iFinD ifind_get_stock_info (as of 2026-10-27)；科华数据：2025年年度报告 | M11: https://money.finance.sina.com.cn/corp/view/vCB_AllBulletinDetail.php?stockid=002335&id=12205218
B12: 002410 | C12: 广联达 | D12: 云计算：SaaS软件与服务 | E12: 纠错 | F12: 云计算 | G12: SaaS-建筑工程造价与成本管理 | H12: 核心 | I12: 公司数字成本业务已将算量、计价、清标和成本管理产品转为在线SaaS订阅及持续服务，直接面向建筑施工和造价客户，不是传统本地授权软件的简单包装。2025年数字成本业务收入47.79亿元，其中云收入34.57亿元、占该业务72%，约占公司总营收57%，新签云合同33.8亿元，续费率稳中有升，云交付已成为主营收入主体，故保留核心并将泛SaaS标签细化为建筑工程造价与成本管理。 | J12: 广联达获79家机构调研：2025年数字成本业务收入是47.79亿，其中云收入34.57亿，占比72% | K12: 2026-03-25 | L12: iFinD ifind_get_stock_info (as of 2026-10-27)；广联达获79家机构调研：2025年数字成本业务收入是47.79亿，其中云收入34.57亿，占比72% | M12: https://m.10jqka.com.cn/20260325/c675521155.shtml
B13: 002757 | C13: 南兴股份 | D13: 云计算：IaaS基础设施服务 | E13: 纠错 | F13: 云计算 | G13: IDC与云基础设施、云平台与多云管理 | H13: 核心 | I13: 子公司唯一网络实际运营自建及租用数据中心，并提供公有云、私有云、混合云、云联网、云管理和自动化运维服务，兼有80余个边缘节点，不是仅有家具装备或普通系统集成。2025年IDC及云计算收入19.66亿元、同比增长29.79%，占总营收57.62%，首次超过传统专用设备成为第一大收入来源，已形成规模化持续经营，故由相关升级为核心，并用IDC及多云管理标签替代笼统IaaS。 | J13: 南兴股份：2025年年度报告 | K13: 2026-04-25 | L13: iFinD ifind_get_stock_info (as of 2026-10-27)；南兴股份：2025年年度报告 | M13: https://vip.stock.finance.sina.com.cn/corp/view/vCB_AllBulletinDetail.php?stockid=002757&id=12190607
B14: 300017 | C14: 网宿科技 | D14: 云计算：IaaS基础设施服务 | E14: 纠错 | F14: 云计算 | G14: 边缘计算与CDN、IaaS计算与存储 | H14: 核心 | I14: 公司基本盘虽是CDN，但并非仅据CDN贴云标签：其边缘计算平台ECP已实际提供边缘云主机、容器、存储和云手机，算力云亦覆盖GPU/CPU云算力、企业云、混合云及容器云，具有直接云资源交付。2025年CDN及边缘计算收入28.95亿元、占总营收62.11%，另有IDC及液冷收入2.83亿元，属于规模化核心业务；MSP剥离不影响保留真实边缘云和IaaS能力，故作精确纠错。 | J14: 网宿科技股份有限公司2025年年度报告全文 | K14: 2026-04-15 | L14: iFinD ifind_get_stock_info (as of 2026-10-27)；网宿科技股份有限公司2025年年度报告全文 | M14: https://static.cninfo.com.cn/finalpage/2026-04-15/1225101555.PDF
B15: 300036 | C15: 超图软件 | D15: 云计算：SaaS软件与服务 | E15: 纠错 | F15: 云计算 | G15: SaaS-地图选址与物流调度 | H15: 相关 | I15: 公司主体收入仍来自GIS基础平台授权、行业应用软件及定制项目，不能将全部GIS软件视为SaaS；真实云交付证据主要是地图慧在线平台，为企业提供门店选址、智能分单、路线规划和人员轨迹管理。2025年地图慧用户和合同连续三年双增长，累计注册用户74万家，发布5.0 SaaS平台并签约海信集团，商业落地明确，但SaaS收入未单列且不足以证明占主营重要比重，故由核心下调为相关并细化场景。 | J15: 超图软件：2025年年度报告 | K15: 2026-04-17 | L15: iFinD ifind_get_stock_info (as of 2026-10-27)；超图软件：2025年年度报告 | M15: https://money.finance.sina.com.cn/corp/view/vCB_AllBulletinDetail.php?stockid=300036&id=12100106
... B41: 688369 | C41: 致远互联 | D41: 云计算：SaaS软件与服务 | E41: 纠错 | F41: 云计算 | G41: SaaS-办公协同、SaaS-人力资源 | H41: 相关 | I41: 公司主营协同管理软件，2025年协同管理软件产品收入7.80亿元，主要仍按软件许可、实施和项目验收交付，不能整体视为SaaS。真实云业务包括支持在线订阅的薪事力人力资源云平台，当年新增客户百余家；iForm亦已获得多行业客户并主要采用公有云SaaS订阅。由于云订阅收入未单独披露且传统协同授权仍占主体，保留协同办公与人力资源两个具体SaaS标签，但由核心降为相关。 | J41: 北京致远互联软件股份有限公司2025年年度报告 | K41: 2026-04-21 | L41: iFinD ifind_get_stock_info (as of 2026-10-27)；北京致远互联软件股份有限公司2025年年度报告 | M41: http://money.finance.sina.com.cn/corp/view/vCB_AllBulletinDetail.php?stockid=688369&id=12123996

Sheet 跨分类迁移
B2: 跨分类迁移 · 云安全归网络安全
B3: 保护云环境不等于提供云计算；启明星辰迁移至云安全与SaaS安全服务。
B4: 代码 | C4: 名称 | D4: 旧云计算概念 | E4: 动作 | F4: 新一级分类 | G4: 新概念 | H4: 判词 | I4: 详细理由 | J4: 证据名称 | K4: 证据日期 | L4: Source Name | M4: Source URL
B5: 002439 | C5: 启明星辰 | D5: 云计算：SaaS软件与服务 | E5: 迁移 | F5: 网络安全 | G5: 云安全与SaaS安全服务 | H5: 相关 | I5: 公司主营是网络安全产品和安全运营服务，实际拥有云安全管理平台、云安全资源池、安星网站安全SaaS及云子可信等云交付产品，可向云端、IDC和传统地端提供安全订阅与运营服务，但保护对象和安全能力不等于向客户提供云计算平台或通用在线软件。2025年收入仍集中于安全产品及安全运营，未证明存在独立云计算主营，因此摘除云计算下的泛SaaS标签，迁移为更准确的网络安全云安全与SaaS安全服务。 | J5: 启明星辰：2025年年度报告 | K5: 2026-04-13 | L5: iFinD ifind_get_stock_info (as of 2026-10-27)；启明星辰：2025年年度报告 | M5: http://money.finance.sina.com.cn/corp/view/vCB_AllBulletinDetail.php?stockid=002439&id=12082100

Sheet 摘除清单
B2: 摘除清单 · 7只错标与落地不足
B3: 普通行业软件、硬件与集成、DeepSeek合作及安全SaaS不直接计入云计算。
B4: 代码 | C4: 名称 | D4: 旧云计算概念 | E4: 动作 | F4: 新一级分类 | G4: 新概念 | H4: 判词 | I4: 详细理由 | J4: 证据名称 | K4: 证据日期 | L4: Source Name | M4: Source URL
B5: 002131 | C5: 利欧股份 | D5: 云计算：DeepSeek | E5: 摘除 | F5: — | G5: — | H5: 摘除 | I5: 公司2025年主营仍为机械制造和数字营销，收入主要来自媒体代理、整合营销及泵业产品。AI创意、投放优化和智能体虽已进入营销流程，但公司明确其主要以间接方式融入既有业务，直接收入较小且难以拆分；这些属于AI营销工具，不是自营云平台、云计算资源或在线软件订阅服务。旧DeepSeek标签仅反映模型或投资联想，未形成可核验云计算产品、客户和收入，故摘除云计算标签。 | J5: 利欧股份：2025年年度报告 | K5: 2026-04-29 | L5: iFinD ifind_get_stock_info (as of 2026-10-27)；利欧股份：2025年年度报告 | M5: https://money.finance.sina.com.cn/corp/view/vCB_AllBulletinDetail.php?stockid=002131&id=12249389
B6: 300075 | C6: 数字政通 | D6: 云计算：国资云 | E6: 摘除 | F6: — | G6: — | H6: 摘除 | I6: 公司主营为智慧城市应用软件、系统集成及城市运营服务，2025年系统软件、系统集成和运营服务收入占比分别为47.94%、5.31%和46.74%，交付对象是城市治理、地下管网等具体项目。相关产品虽可部署于政务云或采用平台架构，但属于行业应用软件和项目运营，不等于公司自营国资云、通用云平台或订阅制云服务；年报亦未披露可核验的云资源产品、独立云客户及云收入，故摘除旧国资云标签。 | J6: 数字政通：2025年年度报告 | K6: 2026-04-16 | L6: iFinD ifind_get_stock_info (as of 2026-10-27)；数字政通：2025年年度报告 | M6: http://money.finance.sina.com.cn/corp/view/vCB_AllBulletinDetail.php?stockid=300075&id=12095162
B7: 300339 | C7: 润和软件 | D7: 云计算：SaaS软件与服务 | E7: 摘除 | F7: — | G7: — | H7: 摘除 | I7: 公司主营为金融科技、智能物联、智慧能源等软件技术服务与行业解决方案，交付方式主要包括研发项目整包、人力技术服务及软硬件项目。2025年披露的HopeOS数据中心AI版、云边协同操作系统、算力调度和私有云定制，本质是服务器操作系统及云基础设施建设配套，并非公司自营IaaS、通用PaaS或在线SaaS；云桌面和DeepSeek适配也不能单独证明云服务商业化。未见独立云计算产品收入或规模云客户证据，故摘除原SaaS标签。 | J7: 润和软件：2025年年度报告 | K7: 2026-04-22 | L7: iFinD ifind_get_stock_info (as of 2026-10-27)；润和软件：2025年年度报告 | M7: https://money.finance.sina.com.cn/corp/view/vCB_AllBulletinDetail.php?stockid=300339&id=12136200
B8: 300560 | C8: 中富通 | D8: 云计算：IaaS基础设施服务 | E8: 摘除 | F8: — | G8: — | H8: 摘除 | I8: 公司主要收入来自通信网络建设维护、网络优化、公安等信息化软件服务、系统集成和渠道销售。2025年边缘计算相关产品收入约4699万元，仅占营收4.12%，产品为边缘终端、网关、服务器、AI视觉检测及云计算终端盒子，属于硬件和行业解决方案；规划建设智算中心也不能替代已经运营云服务的证据。年报未显示自营云主机、云存储、开发运行平台或在线订阅软件收入，因此原IaaS标签缺乏直接业务支撑，应予摘除。 | J8: 中富通：2025年年度报告 | K8: 2026-04-30 | L8: iFinD ifind_get_stock_info (as of 2026-10-27)；中富通：2025年年度报告 | M8: https://stock.stockstar.com/notice/SN2026043000016182.shtml
B9: 300730 | C9: 科创信息 | D9: 云计算：SaaS软件与服务 | E9: 摘除 | F9: — | G9: — | H9: 摘除 | I9: 公司2025年收入仍按数字政府和智慧企业划分，合计占主营绝大部分，交付内容是软件开发、系统集成及IT运维项目，并非标准化公有云或在线订阅产品。年报中个别财政项目提出由项目制交付向SaaS服务加数据运营模式转型，属于未来业务方向，不能据此认定已经形成商业SaaS；大数据平台、互联网数据服务经营范围和AI中台也不等同于自营云计算。未见独立云产品客户、订阅收入或持续云运营规模，故摘除原泛化SaaS标签。 | J9: 科创信息：2025年年度报告 | K9: 2026-04-25 | L9: iFinD ifind_get_stock_info (as of 2026-10-27)；科创信息：2025年年度报告 | M9: https://static.cninfo.com.cn/finalpage/2026-04-25/1225181172.PDF
B10: 688023 | C10: 安恒信息 | D10: 云计算：SaaS软件与服务 | E10: 摘除 | F10: — | G10: — | H10: 摘除 | I10: 公司主营始终是网络信息安全产品及服务，2025年报所列天池云安全管理平台、云密码、云数据安全和玄武盾均用于保护客户的云环境；在线SaaS与MSS也是按订阅交付安全检测、防护和运营能力。上述产品有真实客户和项目，但不提供通用云计算、存储、开发运行平台或在线非安全软件，云安全和安全SaaS不能等同于云计算，故摘除云计算分类，现有网络安全及数据安全定位另行保留。 | J10: 杭州安恒信息技术股份有限公司2025年年度报告 | K10: 2026-03-26 | L10: iFinD ifind_get_stock_info (as of 2026-10-27)；杭州安恒信息技术股份有限公司2025年年度报告 | M10: http://file.finance.sina.com.cn/211.154.219.97:9494/MRGG/CNSESH_STOCK/2026/2026-3/2026-03-26/12018515.PDF
B11: 688561 | C11: 奇安信-U | D11: 云计算：SaaS软件与服务 | E11: 摘除 | F11: — | G11: — | H11: 摘除 | I11: 公司2025年主营业务分为网络安全产品、网络安全服务及配套硬件，信息安全行业收入43.81亿元。CSMP、CNAPP、CWPP、云安全运营中心和SaaS终端安全管理系统均用于云基础设施、云主机、容器或终端的安全防护，虽然已有正式上市版本和政企客户，但不构成独立通用云计算、存储、PaaS或非安全SaaS产品。依据云安全不等于云计算的标准，摘除云计算标签，终端安全、数据安全与云安全等网安分类不在本轮重复输出。 | J11: 奇安信科技集团股份有限公司2025年年度报告 | K11: 2026-04-30 | L11: iFinD ifind_get_stock_info (as of 2026-10-27)；奇安信科技集团股份有限公司2025年年度报告 | M11: http://file.finance.sina.com.cn/211.154.219.97:9494/MRGG/CNSESH_STOCK/2026/2026-4/2026-04-30/12285369.PDF

Sheet 概念展开
A1: 一级分类 | B1: 二级概念 | C1: 判词 | D1: 代码 | E1: 名称
A2: 云计算 | B2: 云平台与多云管理 | C2: 相关 | D2: 000034 | E2: 神州数码
A3: 云计算 | B3: IDC与云基础设施 | C3: 核心 | D3: 000815 | E3: 美利云
A4: 云计算 | B4: 云平台与多云管理 | C4: 核心 | D4: 000938 | E4: 紫光股份
A5: 云计算 | B5: IaaS计算与存储 | C5: 核心 | D5: 000938 | E5: 紫光股份
A6: 云计算 | B6: 云通信与消息服务 | C6: 核心 | D6: 002123 | E6: 梦网科技
A7: 云计算 | B7: SaaS-酒店与餐饮管理 | C7: 核心 | D7: 002153 | E7: 石基信息
A8: 云计算 | B8: SaaS-外贸营销与获客 | C8: 相关 | D8: 002315 | E8: 焦点科技
A9: 云计算 | B9: IDC与云基础设施 | C9: 核心 | D9: 002335 | E9: 科华数据
A10: 云计算 | B10: SaaS-建筑工程造价与成本管理 | C10: 核心 | D10: 002410 | E10: 广联达
A11: 网络安全 | B11: 云安全与SaaS安全服务 | C11: 相关 | D11: 002439 | E11: 启明星辰
A12: 云计算 | B12: IDC与云基础设施 | C12: 核心 | D12: 002757 | E12: 南兴股份
... A60: 云计算 | B60: SaaS-人力资源 | C60: 相关 | D60: 688369 | E60: 致远互联

Sheet 概念统计
B2: 概念统计 · 核心/相关分布
B3: 公式引用隐藏展开表精确计数；含跨分类迁移，一只股票可对应多个概念。
B4: 一级分类 | C4: 二级概念 | D4: 核心（只） | E4: 相关（只） | F4: 合计（只）
B5: 云计算 | C5: IDC与云基础设施 | D5: =COUNTIFS('概念展开'!$A$2:$A$60,B5,'概念展开'!$B$2:$B$60,C5,'概念展开'!$C$2:$C$60,"核心") | E5: =COUNTIFS('概念展开'!$A$2:$A$60,B5,'概念展开'!$B$2:$B$60,C5,'概念展开'!$C$2:$C$60,"相关") | F5: =SUM(D5:E5)
B6: 云计算 | C6: IaaS计算与存储 | D6: =COUNTIFS('概念展开'!$A$2:$A$60,B6,'概念展开'!$B$2:$B$60,C6,'概念展开'!$C$2:$C$60,"核心") | E6: =COUNTIFS('概念展开'!$A$2:$A$60,B6,'概念展开'!$B$2:$B$60,C6,'概念展开'!$C$2:$C$60,"相关") | F6: =SUM(D6:E6)
B7: 云计算 | C7: PaaS-企业应用开发 | D7: =COUNTIFS('概念展开'!$A$2:$A$60,B7,'概念展开'!$B$2:$B$60,C7,'概念展开'!$C$2:$C$60,"核心") | E7: =COUNTIFS('概念展开'!$A$2:$A$60,B7,'概念展开'!$B$2:$B$60,C7,'概念展开'!$C$2:$C$60,"相关") | F7: =SUM(D7:E7)
B8: 云计算 | C8: PaaS-容器与AI开发平台 | D8: =COUNTIFS('概念展开'!$A$2:$A$60,B8,'概念展开'!$B$2:$B$60,C8,'概念展开'!$C$2:$C$60,"核心") | E8: =COUNTIFS('概念展开'!$A$2:$A$60,B8,'概念展开'!$B$2:$B$60,C8,'概念展开'!$C$2:$C$60,"相关") | F8: =SUM(D8:E8)
B9: 云计算 | C9: PaaS-工业低代码与数智底座 | D9: =COUNTIFS('概念展开'!$A$2:$A$60,B9,'概念展开'!$B$2:$B$60,C9,'概念展开'!$C$2:$C$60,"核心") | E9: =COUNTIFS('概念展开'!$A$2:$A$60,B9,'概念展开'!$B$2:$B$60,C9,'概念展开'!$C$2:$C$60,"相关") | F9: =SUM(D9:E9)
B10: 云计算 | C10: PaaS-应用开发与运维 | D10: =COUNTIFS('概念展开'!$A$2:$A$60,B10,'概念展开'!$B$2:$B$60,C10,'概念展开'!$C$2:$C$60,"核心") | E10: =COUNTIFS('概念展开'!$A$2:$A$60,B10,'概念展开'!$B$2:$B$60,C10,'概念展开'!$C$2:$C$60,"相关") | F10: =SUM(D10:E10)
B11: 云计算 | C11: PaaS-应用集成 | D11: =COUNTIFS('概念展开'!$A$2:$A$60,B11,'概念展开'!$B$2:$B$60,C11,'概念展开'!$C$2:$C$60,"核心") | E11: =COUNTIFS('概念展开'!$A$2:$A$60,B11,'概念展开'!$B$2:$B$60,C11,'概念展开'!$C$2:$C$60,"相关") | F11: =SUM(D11:E11)
B12: 云计算 | C12: PaaS-数据开发与分析 | D12: =COUNTIFS('概念展开'!$A$2:$A$60,B12,'概念展开'!$B$2:$B$60,C12,'概念展开'!$C$2:$C$60,"核心") | E12: =COUNTIFS('概念展开'!$A$2:$A$60,B12,'概念展开'!$B$2:$B$60,C12,'概念展开'!$C$2:$C$60,"相关") | F12: =SUM(D12:E12)
B13: 云计算 | C13: SaaS-互联网医疗与医院云服务 | D13: =COUNTIFS('概念展开'!$A$2:$A$60,B13,'概念展开'!$B$2:$B$60,C13,'概念展开'!$C$2:$C$60,"核心") | E13: =COUNTIFS('概念展开'!$A$2:$A$60,B13,'概念展开'!$B$2:$B$60,C13,'概念展开'!$C$2:$C$60,"相关") | F13: =SUM(D13:E13)
B14: 云计算 | C14: SaaS-人力资源 | D14: =COUNTIFS('概念展开'!$A$2:$A$60,B14,'概念展开'!$B$2:$B$60,C14,'概念展开'!$C$2:$C$60,"核心") | E14: =COUNTIFS('概念展开'!$A$2:$A$60,B14,'概念展开'!$B$2:$B$60,C14,'概念展开'!$C$2:$C$60,"相关") | F14: =SUM(D14:E14)
B15: 云计算 | C15: SaaS-企业管理 | D15: =COUNTIFS('概念展开'!$A$2:$A$60,B15,'概念展开'!$B$2:$B$60,C15,'概念展开'!$C$2:$C$60,"核心") | E15: =COUNTIFS('概念展开'!$A$2:$A$60,B15,'概念展开'!$B$2:$B$60,C15,'概念展开'!$C$2:$C$60,"相关") | F15: =SUM(D15:E15)
B16: 云计算 | C16: SaaS-办公协同 | D16: =COUNTIFS('概念展开'!$A$2:$A$60,B16,'概念展开'!$B$2:$B$60,C16,'概念展开'!$C$2:$C$60,"核心") | E16: =COUNTIFS('概念展开'!$A$2:$A$60,B16,'概念展开'!$B$2:$B$60,C16,'概念展开'!$C$2:$C$60,"相关") | F16: =SUM(D16:E16)
... B28: 网络安全 | C28: 云安全与SaaS安全服务 | D28: =COUNTIFS('概念展开'!$A$2:$A$60,B28,'概念展开'!$B$2:$B$60,C28,'概念展开'!$C$2:$C$60,"核心") | E28: =COUNTIFS('概念展开'!$A$2:$A$60,B28,'概念展开'!$B$2:$B$60,C28,'概念展开'!$C$2:$C$60,"相关") | F28: =SUM(D28:E28)
B29: 合计（概念次数，非股票去重数） | D29: =SUM(D5:D28) | E29: =SUM(E5:E28) | F29: =SUM(F5:F28)
