Workbook

Sheet 封面
B2: 光通信概念深度清洗报告
B3: 复核日期：2026-10-27｜范围：45只｜重点：业务实质、产品层级、商业订单与二次边界复审
B6: 复核股票（只） | C6: =COUNTA('清洗总表'!$B$5:$B$49)
B7: 保留光通信（只） | C7: =COUNTA('光通信'!$B$5:$B$46)
B8: 核心判词（只） | C8: =COUNTIF('光通信'!$H$5:$H$46,"核心")
B9: 相关判词（只） | C9: =COUNTIF('光通信'!$H$5:$H$46,"相关")
B10: 纠错动作（只） | C10: =COUNTIF('清洗总表'!$E$5:$E$49,"纠错")
B11: 完全摘除（只） | C11: =COUNTA('摘除清单'!$B$5:$B$7)
B15: 工作表索引
B16: 清洗总表 | C16: 45只旧概念、新概念、动作、判词、详细理由和证据
B17: 光通信 | C17: 42只清洗后光通信公司
B18: 摘除清单 | C18: 3只通用业务或光通信证据不足公司
B19: 概念统计 | C19: 19个实际使用的二级概念
B23: 核心：光通信是明确主营、重要收入来源，或已有规模化核心产品；相关：有真实光通信产品、订单、客户验证或交付，但早期、低占比、未拆分或其他行业为主。
B24: 摘除：只有通用晶振、材料、零部件或设备的潜在用途，以及算力租赁、SOFC、MLCC、千帆星座、SpaceX等跨概念联想；参股不等于自身经营。
B25: 二次复审：30只核心、12只相关和3只摘除均维持；修正亨通光电总收入数量级、长飞光纤光互联组件收入、太辰光总收入及占比三处数字。
B26: 主营与2025分部：iFinD ifind_get_stock_info、ifind_get_stock_business_segmentation（2026-10-27）；逐股公告与证据见Source列。

Sheet 清洗总表
B2: 光通信 · 45只逐项复核
B3: 逐股核对真实产品、订单、客户、交付、运营与股权；区分光通信、传统军工航天和潜在联想。
B4: 代码 | C4: 名称 | D4: 旧光通信概念 | E4: 动作 | F4: 新一级分类 | G4: 新概念 | H4: 判词 | I4: 详细理由 | J4: 证据名称 | K4: 证据日期 | L4: Source Name | M4: Source URL
B5: 000070 | C5: 特发信息 | D5: 光通信：光纤光缆 | E5: 纠错 | F5: 光通信、光通信 | G5: 光缆与线缆；光纤预制棒与光纤 | H5: 核心 | I5: 公司真实产品包括光纤、光缆、光连接器及配线产品，线缆板块同时覆盖通信与电力传输，属于光通信物理链路的重要制造环节，而不是仅凭名称关联的概念标的。2025年线缆板块收入35.2179亿元，公司总收入约44.1655亿元，占比约79.74%，业务规模和对收入的重要性均足以支持核心定级；但该板块还含电力传输等产品，不能把35.2179亿元全部认定为光通信收入，也不能进一步虚构光纤、光缆各自收入。此次纠错应将旧“相关、光纤光缆”粗标签提升为核心，并拆分为光缆与线缆、光纤预制棒与光纤两个白名单概念，同时保留板块收入不可全归属光通信的边界。 | J5: 特发信息：2025年年度报告 | K5: 2026-04-22 | L5: iFinD ifind_get_stock_info + ifind_get_stock_business_segmentation (as of 2026-10-27)；特发信息：2025年年度报告 | M5: http://money.finance.sina.com.cn/corp/view/vCB_AllBulletinDetail.php?stockid=000070&id=12133674
B6: 000586 | C6: 汇源通信 | D6: 光通信：光纤光缆 | E6: 纠错 | F6: 光通信、光通信 | G6: 光缆与线缆；光纤预制棒与光纤 | H6: 核心 | I6: 公司实际经营电力光缆、塑料光纤以及光纤光缆相关产品，这些产品直接构成通信和电力专网的光传输介质，传统光通信业务具有真实且重要的收入基础。2025年光纤光缆及相关产品收入2.2488亿元，总收入约5.1255亿元，占比43.88%；在线监测收入2.2980亿元则属于另一业务，不能混入光通信。2026年异动公告又明确公司没有石英光纤制造产能，也不涉及算力数据中心光纤光缆，因此不得借核心定级追加石英光纤、CPO或数通光模块标签。此次纠错是把旧“相关”提升为核心，保留光缆与线缆、光纤预制棒与光纤的既有产业事实，同时以公告限定产品能力边界。 | J6: 汇源通信：2025年年度报告 | K6: 2026-04-22 | L6: iFinD ifind_get_stock_info + ifind_get_stock_business_segmentation (as of 2026-10-27)；汇源通信：2025年年度报告 | M6: https://money.finance.sina.com.cn/corp/view/vCB_AllBulletinDetail.php?stockid=000586&id=12132149
B7: 000988 | C7: 华工科技 | D7: 光通信：光模块/CPO、光通信 | E7: 纠错 | F7: 光通信、光通信、光通信 | G7: 光模块-数通与AI算力；光模块-电信与传输；CPO与硅光集成 | H7: 核心 | I7: 公司光电器件系列覆盖电信传输和数据中心用光模块，年报披露800G硅光LPO、1.6T模块规模交付以及3.2T CPO光引擎，说明数通、电信和硅光集成均有明确产品依据，并非泛化的激光或传感器概念。2025年光电器件系列收入60.9682亿元，公司总收入143.55亿元，占比42.47%，已构成重要收入支柱，定为核心有充分规模依据。不过光电器件是合并披露口径，不能把激光装备、敏感元器件等其他收入算入，也不能从该收入中虚构CPO或1.6T的单独金额。此次纠错应以核心替代过宽的旧粗标签，并分别落到数通与AI算力、电信与传输、CPO与硅光集成三个真实方向。 | J7: 华工科技：2025年年度报告 | K7: 2026-03-26 | L7: iFinD ifind_get_stock_info + ifind_get_stock_business_segmentation (as of 2026-10-27)；华工科技：2025年年度报告 | M7: https://vip.stock.finance.sina.com.cn/corp/view/vCB_AllBulletinDetail.php?stockid=000988&id=12018524
B8: 002179 | C8: 中航光电 | D8: 光通信：MPO/连接器、连接器、军工电子 | E8: 纠错 | F8: 光通信 | G8: 光连接器与陶瓷插芯 | H8: 核心 | I8: 公司具有光连接器、光传输器件与组件等真实产品，应用于防务、无线基站和数据中心，2025年数据中心光纤产品取得突破，光连接属于其规模化互连产品体系，而非偶发研发概念。2025年光连接器及其他光器件以及光电设备混合分部收入36.5877亿元，总收入213.86亿元，占比17.11%；该口径还包含其他光器件和光电设备，只能视为相关业务规模上限，不能全部计作光通信，也不能据此推算MPO收入。此次定为核心依据的是光连接产品的持续经营和实际应用，不是把整个公司等同光通信企业。纠错时仅保留光连接器与陶瓷插芯这一白名单概念，不沿用旧MPO粗标签，也不把防务或全部连接器收入迁移到光通信。 | J8: 中航光电科技股份有限公司2025年年度报告全文 | K8: 2026-03-28 | L8: iFinD ifind_get_stock_info + ifind_get_stock_business_segmentation (as of 2026-10-27)；中航光电科技股份有限公司2025年年度报告全文 | M8: https://static.cninfo.com.cn/finalpage/2026-03-28/1225044952.PDF
B9: 002199 | C9: 东晶电子 | D9: 光通信：石英晶振 | E9: 摘除 | F9: — | G9: — | H9: 摘除 | I9: 公司主营石英晶体谐振器和振荡器，产品确实可广泛用于通讯、消费电子、汽车电子等领域，但2025年年报没有将光模块或光通信列作专门用途，也没有披露光通信客户、订单或对应产品收入。2025年石英晶体元器件收入2.4086亿元，总收入3.5527亿元，占比约67.79%，其中谐振器2.3593亿元、振荡器493.35万元；这些数字证明的是通用晶振主业，不能转换成光通信收入，光通信占比亦无法可靠拆分。通用电子元器件在理论上能够进入某种设备，不足以证明已经形成可识别产业暴露，因此本次应摘除旧“时钟晶振与频率器件”标签，不保留任何光通信二级概念，纠错点是消除由潜在用途推导现实业务的误判。 | J9: *ST东晶：2025年年度报告摘要 | K9: 2026-04-28 | L9: iFinD ifind_get_stock_info + ifind_get_stock_business_segmentation (as of 2026-10-27)；*ST东晶：2025年年度报告摘要 | M9: http://money.finance.sina.com.cn/corp/view/vCB_AllBulletinDetail.php?stockid=002199&id=12233410
B10: 002281 | C10: 光迅科技 | D10: 光通信：光模块/CPO、光通信 | E10: 纠错 | F10: 光通信、光通信、光通信、光通信 | G10: 光模块-数通与AI算力；光模块-电信与传输；光器件-无源器件；CPO与硅光集成 | H10: 核心 | I10: 公司产品覆盖全系列光模块、无源光器件和光波导集成产品，接入与数据业务对应数通及接入场景，传输业务对应电信传输，年报另有CPO和硅光布局，因此四个标签均建立在明确产品体系上。2025年接入和数据收入84.6289亿元、传输收入34.1165亿元，合计118.7454亿元，总收入约119.29亿元，占比约99.54%，光通信是绝对主业，核心定级明确。不可拆分的边界在于接入和数据分部并非全部等于AI数通模块，传输分部也不能再细拆到单一器件，CPO与硅光更没有被单列收入。此次纠错应淘汰笼统的旧光通信标签，按数通、电信、无源和CPO硅光细分，但不把研发或布局描述伪装成独立营收。 | J10: 光迅科技：2025年年度报告 | K10: 2026-04-23 | L10: iFinD ifind_get_stock_info + ifind_get_stock_business_segmentation (as of 2026-10-27)；光迅科技：2025年年度报告 | M10: https://vip.stock.finance.sina.com.cn/corp/view/vCB_AllBulletinDetail.php?stockid=002281&id=12145451
B11: 002384 | C11: 东山精密 | D11: 光通信：光芯片 | E11: 纠错 | F11: 光通信、光通信、光通信 | G11: 光模块-数通与AI算力；光模块-电信与传输；光芯片-激光器与探测器 | H11: 核心 | I11: 公司2025年收购索尔思后形成真实光模块及光芯片业务，产品覆盖数通和电信光模块，并包含激光器、探测器等光芯片能力，不能再仅按PCB企业理解而摘除光通信暴露。2025年光模块含光芯片收入14.3553亿元，总收入401.25亿元，占比3.58%，而且仅第四季度并表；收入占比虽低，但已是规模化经营产品，核心表示业务真实性而非其在集团中的收入支配程度。需要严守的边界是通信设备组件及其他收入59.3024亿元不能整体算成光通信，PCB、触控显示和新能源等业务更不能并入。此次纠错应保留核心并按数通、电信、激光器与探测器细分，同时在解释中披露低占比和部分年度并表，避免夸大集团光通信纯度。 | J11: 东山精密：2025年年度报告 | K11: 2026-04-22 | L11: iFinD ifind_get_stock_info + ifind_get_stock_business_segmentation (as of 2026-10-27)；东山精密：2025年年度报告 | M11: http://money.finance.sina.com.cn/corp/view/vCB_AllBulletinDetail.php?stockid=002384&id=12133235
B12: 002428 | C12: 云南锗业 | D12: 光通信：光材料、锗、锗电池 | E12: 纠错 | F12: 光通信 | G12: 光通信材料-光学与晶体 | H12: 核心 | I12: 公司光纤用四氯化锗是光纤预制棒制造的关键掺杂原料，具有直接、可验证的光通信材料用途，与仅有间接半导体想象的锗概念不同。2025年光纤用四氯化锗收入1.9986亿元，总收入10.6588亿元，占比18.75%，并披露60吨每年产能，真实收入和产能足以支持核心定级。边界必须限定在该具体材料：锗锭、太阳能锗片、红外级锗产品以及砷化镓、磷化铟业务不能因为同属锗或化合物半导体就并入光通信，相关收入也不可推算为光纤材料收入。此次纠错保留旧“相关程度核心”所反映的重要业务地位，但把概念统一为光通信材料中的光学与晶体，并删除旧“锗、锗电池”等跨概念污染，避免把其他终端用途混入。 | J12: 云南锗业：2025年年度报告 | K12: 2026-04-23 | L12: iFinD ifind_get_stock_info + ifind_get_stock_business_segmentation (as of 2026-10-27)；云南锗业：2025年年度报告 | M12: https://money.finance.sina.com.cn/corp/view/vCB_AllBulletinDetail.php?stockid=002428&id=12150108
B13: 002491 | C13: 通鼎互联 | D13: 光通信：光纤光缆 | E13: 纠错 | F13: 光通信、光通信 | G13: 光纤预制棒与光纤；光缆与线缆 | H13: 相关 | I13: 公司具备光纤、光缆及通信线缆产业链业务，产品与光通信传输介质直接相关，因此不能因业务多元而完全摘除；但核心定级还要看当年可量化暴露。2025年光纤收入1.8253亿元，总收入34.13亿元，占比5.35%；通信电缆收入9.0726亿元、通信设备收入2.5868亿元均为较宽口径，不能全部认作光通信，电力电缆13.0614亿元和安全业务6.6919亿元更明确属于其他板块。全产业链叙述并不等于全部收入具有光通信属性，现有可拆分数据支持相关而非核心。此次纠错保留光纤预制棒与光纤、光缆与线缆两个真实概念，纠正把通信、电缆或安全板块笼统并入光通信的旧粗标签，并以5.35%的可核实光纤占比约束定级。 | J13: 通鼎互联：2025年年度报告 | K13: 2026-04-28 | L13: iFinD ifind_get_stock_info + ifind_get_stock_business_segmentation (as of 2026-10-27)；通鼎互联：2025年年度报告 | M13: https://vip.stock.finance.sina.com.cn/corp/view/vCB_AllBulletinDetail.php?stockid=002491&id=12232603
B14: 300265 | C14: 通光线缆 | D14: 光通信：光纤光缆 | E14: 纠错 | F14: 光通信、光通信 | G14: 光缆与线缆；光纤预制棒与光纤 | H14: 核心 | I14: 公司光纤光缆业务直接提供通信传输介质，是持续经营且有独立收入披露的光通信产品，不应因输电线缆规模更大而被忽略，也不应仅凭公司名称判断。2025年光纤光缆收入6.7828亿元，总收入25.4363亿元，占比26.67%，这一收入体量及占比足以支持核心定级；同期输电线缆收入13.2083亿元、装备线缆收入3.3358亿元必须排除在光通信之外，不能把公司全部线缆收入统一贴成光纤光缆。此次纠错将旧“相关”提升为核心，概念细分为光缆与线缆、光纤预制棒与光纤，同时明确26.67%是可归属分部的口径，不能进一步虚构光纤与光缆各自金额，也不能用核心标签掩盖公司多业务结构。 | J14: 通光线缆：2025年年度报告 | K14: 2026-04-18 | L14: iFinD ifind_get_stock_info + ifind_get_stock_business_segmentation (as of 2026-10-27)；通光线缆：2025年年度报告 | M14: http://money.finance.sina.com.cn/corp/view/vCB_AllBulletinDetail.php?stockid=300265&id=12111702
B15: 300292 | C15: 吴通控股 | D15: 光通信：其他 | E15: 纠错 | F15: 光通信、光通信 | G15: MPO/MTP与高密度连接；光缆与线缆 | H15: 相关 | I15: 正式投资者关系记录确认公司销售光跳线、尾纤、预端接光缆和光缆，并具有MPO/MTP跳线、光分路器等产品，这些是真实的光通信连接与线缆业务；但公司明确不生产光模块，不能借光通信标签延伸到模块或CPO。2025年上述光通信相关收入仅占公司约2%至3%，因此只能定为相关；通讯基础连接产品分部收入3.0140亿元、占比6.92%，口径更宽，不能全部替代光通信收入，移动信息服务收入35.3199亿元、占比81.14%则反映集团主业仍在信息服务。此次纠错把旧“边缘、其他”调整为有证据支持的相关，并精确落到MPO/MTP与高密度连接、光缆与线缆，同时保留低收入占比和不生产光模块的边界。 | J15: 吴通控股集团股份有限公司投资者关系活动记录表 | K15: 2026-05-18 | L15: iFinD ifind_get_stock_info + ifind_get_stock_business_segmentation (as of 2026-10-27)；吴通控股集团股份有限公司投资者关系活动记录表 | M15: http://static.cninfo.com.cn/finalpage/2026-05-18/1225314733.PDF
... B49: 920045 | C49: 蘅东光 | D49: 光通信：光器件 | E49: 纠错 | F49: 光通信 | G49: 光器件-无源器件、MPO/MTP与高密度连接、光连接器与陶瓷插芯、CPO与硅光集成 | H49: 核心 | I49: 公司主营就是光通信无源光器件，真实产品包括光纤连接器、Shuffle光纤柔性线路、配线管理、多光纤并行及波分复用无源内连器件；MT-FA产品可与硅光芯片耦合，PM MT-FA可与交换机芯片共封装，具有明确CPO无源内连产品，不是仅凭硅光趋势加标。iFinD所列2025年无源光器件收入19.6325亿元，配套产品2.5252亿元，按合计22.1577亿元计算无源器件占约88.60%，主营高度集中。配套及其他产品含光缆和连接器注塑零部件，不能全部并入核心无源器件收入，但不影响核心认定。旧“光器件”过于笼统，现细化为无源器件、MPO高密度连接、光连接和真实硅光/CPO内连布局。 | J49: 蘅东光：招股说明书 | K49: 2025-12-19 | L49: iFinD ifind_get_stock_info + ifind_get_stock_business_segmentation (as of 2026-10-27)；蘅东光：招股说明书 | M49: https://money.finance.sina.com.cn/corp/view/vCB_AllBulletinDetail.php?stockid=920045&id=11861167

Sheet 光通信
B2: 光通信 · 清洗后42只股池
B3: 核心30只、相关12只；按卫星、火箭、地面系统、运营服务和产业配套细化为19个二级概念。
B4: 代码 | C4: 名称 | D4: 旧光通信概念 | E4: 动作 | F4: 新一级分类 | G4: 新概念 | H4: 判词 | I4: 详细理由 | J4: 证据名称 | K4: 证据日期 | L4: Source Name | M4: Source URL
B5: 000070 | C5: 特发信息 | D5: 光通信：光纤光缆 | E5: 纠错 | F5: 光通信、光通信 | G5: 光缆与线缆；光纤预制棒与光纤 | H5: 核心 | I5: 公司真实产品包括光纤、光缆、光连接器及配线产品，线缆板块同时覆盖通信与电力传输，属于光通信物理链路的重要制造环节，而不是仅凭名称关联的概念标的。2025年线缆板块收入35.2179亿元，公司总收入约44.1655亿元，占比约79.74%，业务规模和对收入的重要性均足以支持核心定级；但该板块还含电力传输等产品，不能把35.2179亿元全部认定为光通信收入，也不能进一步虚构光纤、光缆各自收入。此次纠错应将旧“相关、光纤光缆”粗标签提升为核心，并拆分为光缆与线缆、光纤预制棒与光纤两个白名单概念，同时保留板块收入不可全归属光通信的边界。 | J5: 特发信息：2025年年度报告 | K5: 2026-04-22 | L5: iFinD ifind_get_stock_info + ifind_get_stock_business_segmentation (as of 2026-10-27)；特发信息：2025年年度报告 | M5: http://money.finance.sina.com.cn/corp/view/vCB_AllBulletinDetail.php?stockid=000070&id=12133674
B6: 000586 | C6: 汇源通信 | D6: 光通信：光纤光缆 | E6: 纠错 | F6: 光通信、光通信 | G6: 光缆与线缆；光纤预制棒与光纤 | H6: 核心 | I6: 公司实际经营电力光缆、塑料光纤以及光纤光缆相关产品，这些产品直接构成通信和电力专网的光传输介质，传统光通信业务具有真实且重要的收入基础。2025年光纤光缆及相关产品收入2.2488亿元，总收入约5.1255亿元，占比43.88%；在线监测收入2.2980亿元则属于另一业务，不能混入光通信。2026年异动公告又明确公司没有石英光纤制造产能，也不涉及算力数据中心光纤光缆，因此不得借核心定级追加石英光纤、CPO或数通光模块标签。此次纠错是把旧“相关”提升为核心，保留光缆与线缆、光纤预制棒与光纤的既有产业事实，同时以公告限定产品能力边界。 | J6: 汇源通信：2025年年度报告 | K6: 2026-04-22 | L6: iFinD ifind_get_stock_info + ifind_get_stock_business_segmentation (as of 2026-10-27)；汇源通信：2025年年度报告 | M6: https://money.finance.sina.com.cn/corp/view/vCB_AllBulletinDetail.php?stockid=000586&id=12132149
B7: 000988 | C7: 华工科技 | D7: 光通信：光模块/CPO、光通信 | E7: 纠错 | F7: 光通信、光通信、光通信 | G7: 光模块-数通与AI算力；光模块-电信与传输；CPO与硅光集成 | H7: 核心 | I7: 公司光电器件系列覆盖电信传输和数据中心用光模块，年报披露800G硅光LPO、1.6T模块规模交付以及3.2T CPO光引擎，说明数通、电信和硅光集成均有明确产品依据，并非泛化的激光或传感器概念。2025年光电器件系列收入60.9682亿元，公司总收入143.55亿元，占比42.47%，已构成重要收入支柱，定为核心有充分规模依据。不过光电器件是合并披露口径，不能把激光装备、敏感元器件等其他收入算入，也不能从该收入中虚构CPO或1.6T的单独金额。此次纠错应以核心替代过宽的旧粗标签，并分别落到数通与AI算力、电信与传输、CPO与硅光集成三个真实方向。 | J7: 华工科技：2025年年度报告 | K7: 2026-03-26 | L7: iFinD ifind_get_stock_info + ifind_get_stock_business_segmentation (as of 2026-10-27)；华工科技：2025年年度报告 | M7: https://vip.stock.finance.sina.com.cn/corp/view/vCB_AllBulletinDetail.php?stockid=000988&id=12018524
B8: 002179 | C8: 中航光电 | D8: 光通信：MPO/连接器、连接器、军工电子 | E8: 纠错 | F8: 光通信 | G8: 光连接器与陶瓷插芯 | H8: 核心 | I8: 公司具有光连接器、光传输器件与组件等真实产品，应用于防务、无线基站和数据中心，2025年数据中心光纤产品取得突破，光连接属于其规模化互连产品体系，而非偶发研发概念。2025年光连接器及其他光器件以及光电设备混合分部收入36.5877亿元，总收入213.86亿元，占比17.11%；该口径还包含其他光器件和光电设备，只能视为相关业务规模上限，不能全部计作光通信，也不能据此推算MPO收入。此次定为核心依据的是光连接产品的持续经营和实际应用，不是把整个公司等同光通信企业。纠错时仅保留光连接器与陶瓷插芯这一白名单概念，不沿用旧MPO粗标签，也不把防务或全部连接器收入迁移到光通信。 | J8: 中航光电科技股份有限公司2025年年度报告全文 | K8: 2026-03-28 | L8: iFinD ifind_get_stock_info + ifind_get_stock_business_segmentation (as of 2026-10-27)；中航光电科技股份有限公司2025年年度报告全文 | M8: https://static.cninfo.com.cn/finalpage/2026-03-28/1225044952.PDF
B9: 002281 | C9: 光迅科技 | D9: 光通信：光模块/CPO、光通信 | E9: 纠错 | F9: 光通信、光通信、光通信、光通信 | G9: 光模块-数通与AI算力；光模块-电信与传输；光器件-无源器件；CPO与硅光集成 | H9: 核心 | I9: 公司产品覆盖全系列光模块、无源光器件和光波导集成产品，接入与数据业务对应数通及接入场景，传输业务对应电信传输，年报另有CPO和硅光布局，因此四个标签均建立在明确产品体系上。2025年接入和数据收入84.6289亿元、传输收入34.1165亿元，合计118.7454亿元，总收入约119.29亿元，占比约99.54%，光通信是绝对主业，核心定级明确。不可拆分的边界在于接入和数据分部并非全部等于AI数通模块，传输分部也不能再细拆到单一器件，CPO与硅光更没有被单列收入。此次纠错应淘汰笼统的旧光通信标签，按数通、电信、无源和CPO硅光细分，但不把研发或布局描述伪装成独立营收。 | J9: 光迅科技：2025年年度报告 | K9: 2026-04-23 | L9: iFinD ifind_get_stock_info + ifind_get_stock_business_segmentation (as of 2026-10-27)；光迅科技：2025年年度报告 | M9: https://vip.stock.finance.sina.com.cn/corp/view/vCB_AllBulletinDetail.php?stockid=002281&id=12145451
B10: 002384 | C10: 东山精密 | D10: 光通信：光芯片 | E10: 纠错 | F10: 光通信、光通信、光通信 | G10: 光模块-数通与AI算力；光模块-电信与传输；光芯片-激光器与探测器 | H10: 核心 | I10: 公司2025年收购索尔思后形成真实光模块及光芯片业务，产品覆盖数通和电信光模块，并包含激光器、探测器等光芯片能力，不能再仅按PCB企业理解而摘除光通信暴露。2025年光模块含光芯片收入14.3553亿元，总收入401.25亿元，占比3.58%，而且仅第四季度并表；收入占比虽低，但已是规模化经营产品，核心表示业务真实性而非其在集团中的收入支配程度。需要严守的边界是通信设备组件及其他收入59.3024亿元不能整体算成光通信，PCB、触控显示和新能源等业务更不能并入。此次纠错应保留核心并按数通、电信、激光器与探测器细分，同时在解释中披露低占比和部分年度并表，避免夸大集团光通信纯度。 | J10: 东山精密：2025年年度报告 | K10: 2026-04-22 | L10: iFinD ifind_get_stock_info + ifind_get_stock_business_segmentation (as of 2026-10-27)；东山精密：2025年年度报告 | M10: http://money.finance.sina.com.cn/corp/view/vCB_AllBulletinDetail.php?stockid=002384&id=12133235
B11: 002428 | C11: 云南锗业 | D11: 光通信：光材料、锗、锗电池 | E11: 纠错 | F11: 光通信 | G11: 光通信材料-光学与晶体 | H11: 核心 | I11: 公司光纤用四氯化锗是光纤预制棒制造的关键掺杂原料，具有直接、可验证的光通信材料用途，与仅有间接半导体想象的锗概念不同。2025年光纤用四氯化锗收入1.9986亿元，总收入10.6588亿元，占比18.75%，并披露60吨每年产能，真实收入和产能足以支持核心定级。边界必须限定在该具体材料：锗锭、太阳能锗片、红外级锗产品以及砷化镓、磷化铟业务不能因为同属锗或化合物半导体就并入光通信，相关收入也不可推算为光纤材料收入。此次纠错保留旧“相关程度核心”所反映的重要业务地位，但把概念统一为光通信材料中的光学与晶体，并删除旧“锗、锗电池”等跨概念污染，避免把其他终端用途混入。 | J11: 云南锗业：2025年年度报告 | K11: 2026-04-23 | L11: iFinD ifind_get_stock_info + ifind_get_stock_business_segmentation (as of 2026-10-27)；云南锗业：2025年年度报告 | M11: https://money.finance.sina.com.cn/corp/view/vCB_AllBulletinDetail.php?stockid=002428&id=12150108
B12: 002491 | C12: 通鼎互联 | D12: 光通信：光纤光缆 | E12: 纠错 | F12: 光通信、光通信 | G12: 光纤预制棒与光纤；光缆与线缆 | H12: 相关 | I12: 公司具备光纤、光缆及通信线缆产业链业务，产品与光通信传输介质直接相关，因此不能因业务多元而完全摘除；但核心定级还要看当年可量化暴露。2025年光纤收入1.8253亿元，总收入34.13亿元，占比5.35%；通信电缆收入9.0726亿元、通信设备收入2.5868亿元均为较宽口径，不能全部认作光通信，电力电缆13.0614亿元和安全业务6.6919亿元更明确属于其他板块。全产业链叙述并不等于全部收入具有光通信属性，现有可拆分数据支持相关而非核心。此次纠错保留光纤预制棒与光纤、光缆与线缆两个真实概念，纠正把通信、电缆或安全板块笼统并入光通信的旧粗标签，并以5.35%的可核实光纤占比约束定级。 | J12: 通鼎互联：2025年年度报告 | K12: 2026-04-28 | L12: iFinD ifind_get_stock_info + ifind_get_stock_business_segmentation (as of 2026-10-27)；通鼎互联：2025年年度报告 | M12: https://vip.stock.finance.sina.com.cn/corp/view/vCB_AllBulletinDetail.php?stockid=002491&id=12232603
B13: 300265 | C13: 通光线缆 | D13: 光通信：光纤光缆 | E13: 纠错 | F13: 光通信、光通信 | G13: 光缆与线缆；光纤预制棒与光纤 | H13: 核心 | I13: 公司光纤光缆业务直接提供通信传输介质，是持续经营且有独立收入披露的光通信产品，不应因输电线缆规模更大而被忽略，也不应仅凭公司名称判断。2025年光纤光缆收入6.7828亿元，总收入25.4363亿元，占比26.67%，这一收入体量及占比足以支持核心定级；同期输电线缆收入13.2083亿元、装备线缆收入3.3358亿元必须排除在光通信之外，不能把公司全部线缆收入统一贴成光纤光缆。此次纠错将旧“相关”提升为核心，概念细分为光缆与线缆、光纤预制棒与光纤，同时明确26.67%是可归属分部的口径，不能进一步虚构光纤与光缆各自金额，也不能用核心标签掩盖公司多业务结构。 | J13: 通光线缆：2025年年度报告 | K13: 2026-04-18 | L13: iFinD ifind_get_stock_info + ifind_get_stock_business_segmentation (as of 2026-10-27)；通光线缆：2025年年度报告 | M13: http://money.finance.sina.com.cn/corp/view/vCB_AllBulletinDetail.php?stockid=300265&id=12111702
B14: 300292 | C14: 吴通控股 | D14: 光通信：其他 | E14: 纠错 | F14: 光通信、光通信 | G14: MPO/MTP与高密度连接；光缆与线缆 | H14: 相关 | I14: 正式投资者关系记录确认公司销售光跳线、尾纤、预端接光缆和光缆，并具有MPO/MTP跳线、光分路器等产品，这些是真实的光通信连接与线缆业务；但公司明确不生产光模块，不能借光通信标签延伸到模块或CPO。2025年上述光通信相关收入仅占公司约2%至3%，因此只能定为相关；通讯基础连接产品分部收入3.0140亿元、占比6.92%，口径更宽，不能全部替代光通信收入，移动信息服务收入35.3199亿元、占比81.14%则反映集团主业仍在信息服务。此次纠错把旧“边缘、其他”调整为有证据支持的相关，并精确落到MPO/MTP与高密度连接、光缆与线缆，同时保留低收入占比和不生产光模块的边界。 | J14: 吴通控股集团股份有限公司投资者关系活动记录表 | K14: 2026-05-18 | L14: iFinD ifind_get_stock_info + ifind_get_stock_business_segmentation (as of 2026-10-27)；吴通控股集团股份有限公司投资者关系活动记录表 | M14: http://static.cninfo.com.cn/finalpage/2026-05-18/1225314733.PDF
B15: 300308 | C15: 中际旭创 | D15: 光通信：光模块/CPO、光通信 | E15: 纠错 | F15: 光通信、光通信、光通信 | G15: 光模块-数通与AI算力；光模块-电信与传输；CPO与硅光集成 | H15: 核心 | I15: 公司主营光通信收发模块，产品直接服务于AI数据中心和电信传输，1.6T已经批量交付，硅光方案占比较高，年报还明确继续研发CPO，数通、电信和CPO硅光标签均有正式产品依据。2025年光通信收发模块收入374.5652亿元，总收入382.40亿元，占比97.95%，光通信收入纯度和规模均支持核心定级。需要区分的是，批量交付的1.6T与硅光产品不能全部称为CPO，CPO研发方向也没有独立收入披露，不能把374.5652亿元再包装成CPO收入；电机绕组装备等剩余业务同样不得混入。此次纠错应将旧的宽泛光模块或高速模块标签拆成数通与AI算力、电信与传输、CPO与硅光集成，并在理由中保留研发与收入不可混同的限制。 | J15: 中际旭创：2025年年度报告 | K15: 2026-03-31 | L15: iFinD ifind_get_stock_info + ifind_get_stock_business_segmentation (as of 2026-10-27)；中际旭创：2025年年度报告 | M15: https://vip.stock.finance.sina.com.cn/corp/view/vCB_AllBulletinDetail.php?stockid=300308&id=12041853
... B46: 920045 | C46: 蘅东光 | D46: 光通信：光器件 | E46: 纠错 | F46: 光通信 | G46: 光器件-无源器件、MPO/MTP与高密度连接、光连接器与陶瓷插芯、CPO与硅光集成 | H46: 核心 | I46: 公司主营就是光通信无源光器件，真实产品包括光纤连接器、Shuffle光纤柔性线路、配线管理、多光纤并行及波分复用无源内连器件；MT-FA产品可与硅光芯片耦合，PM MT-FA可与交换机芯片共封装，具有明确CPO无源内连产品，不是仅凭硅光趋势加标。iFinD所列2025年无源光器件收入19.6325亿元，配套产品2.5252亿元，按合计22.1577亿元计算无源器件占约88.60%，主营高度集中。配套及其他产品含光缆和连接器注塑零部件，不能全部并入核心无源器件收入，但不影响核心认定。旧“光器件”过于笼统，现细化为无源器件、MPO高密度连接、光连接和真实硅光/CPO内连布局。 | J46: 蘅东光：招股说明书 | K46: 2025-12-19 | L46: iFinD ifind_get_stock_info + ifind_get_stock_business_segmentation (as of 2026-10-27)；蘅东光：招股说明书 | M46: https://money.finance.sina.com.cn/corp/view/vCB_AllBulletinDetail.php?stockid=920045&id=11861167

Sheet 摘除清单
B2: 摘除清单 · 3只证据不足或业务错标
B3: 通用产品潜在用途、央企背景、SpaceX预期、太空光伏设备及未决投资不直接计入光通信。
B4: 代码 | C4: 名称 | D4: 旧光通信概念 | E4: 动作 | F4: 新一级分类 | G4: 新概念 | H4: 判词 | I4: 详细理由 | J4: 证据名称 | K4: 证据日期 | L4: Source Name | M4: Source URL
B5: 002199 | C5: 东晶电子 | D5: 光通信：石英晶振 | E5: 摘除 | F5: — | G5: — | H5: 摘除 | I5: 公司主营石英晶体谐振器和振荡器，产品确实可广泛用于通讯、消费电子、汽车电子等领域，但2025年年报没有将光模块或光通信列作专门用途，也没有披露光通信客户、订单或对应产品收入。2025年石英晶体元器件收入2.4086亿元，总收入3.5527亿元，占比约67.79%，其中谐振器2.3593亿元、振荡器493.35万元；这些数字证明的是通用晶振主业，不能转换成光通信收入，光通信占比亦无法可靠拆分。通用电子元器件在理论上能够进入某种设备，不足以证明已经形成可识别产业暴露，因此本次应摘除旧“时钟晶振与频率器件”标签，不保留任何光通信二级概念，纠错点是消除由潜在用途推导现实业务的误判。 | J5: *ST东晶：2025年年度报告摘要 | K5: 2026-04-28 | L5: iFinD ifind_get_stock_info + ifind_get_stock_business_segmentation (as of 2026-10-27)；*ST东晶：2025年年度报告摘要 | M5: http://money.finance.sina.com.cn/corp/view/vCB_AllBulletinDetail.php?stockid=002199&id=12233410
B6: 600345 | C6: 长江通信 | D6: 光通信：光纤光缆、千帆星座 | E6: 摘除 | F6: — | G6: — | H6: 摘除 | I6: 公司当前真实产品为智慧应急通信与指挥、排队调度机、应急通信网关、消防应急指挥终端、卫星定位终端及智慧城市运营系统，主要服务公安、应急和城运指挥场景，并未披露光纤、光缆、光模块、光器件或光传输设备的生产销售。2025年信息技术服务收入9.9526亿元、占97.4302%，其中系统集成9.2178亿元、运维与技术服务0.5542亿元，这些混合收入主要对应行业指挥和数字化项目，不能因名称含“通信”就全部认作光通信，也没有可拆分的光网络工程收入。旧“光纤光缆”与公司产品不符，卫星信关站或地面系统项目同样不能跨概念证明光纤光缆业务，故摘除光通信标签；其他商业航天分类不在本次处理范围。 | J6: 长江通信2025年年度报告 | K6: 2026-04-28 | L6: iFinD ifind_get_stock_info + ifind_get_stock_business_segmentation (as of 2026-10-27)；长江通信2025年年度报告 | M6: https://static.cninfo.com.cn/finalpage/2026-04-28/1225209052.PDF
B7: 603330 | C7: 天洋新材 | D7: 光通信：光材料 | E7: 摘除 | F7: — | G7: — | H7: 摘除 | I7: 公司主营是纺织和汽车用热熔胶、电子级胶黏剂、光伏封装胶膜及环保墙布。2025年热熔胶收入4.0996亿元、反应型胶黏剂1.7218亿元、光伏封装胶膜1.9316亿元；工业领域收入占90.0853%，但工业领域并不等于光通信。年报所列电子胶主要用于电路板保护、电池组装、电子器件结构粘接、电机组装，并披露新拓展半导体、汽车电子和储能导热应用，全文未核验到光通信、光模块或CPO产品、订单、供货和收入披露。通用环氧、丙烯酸或有机硅胶理论上可用于多种电子封装，不能据此认定光通信封装胶材。旧“光材料”及CPO联想缺乏真实业务支撑，故摘除，而不是把反应型胶黏剂收入全部归入光通信。 | J7: 2025年年度报告 | K7: 2026-04-23 | L7: iFinD ifind_get_stock_info + ifind_get_stock_business_segmentation (as of 2026-10-27)；2025年年度报告 | M7: https://static.cninfo.com.cn/finalpage/2026-04-23/1225148563.PDF

Sheet 概念展开
A1: 一级分类 | B1: 二级概念 | C1: 判词 | D1: 代码 | E1: 名称
A2: 光通信 | B2: 光缆与线缆 | C2: 核心 | D2: 000070 | E2: 特发信息
A3: 光通信 | B3: 光纤预制棒与光纤 | C3: 核心 | D3: 000070 | E3: 特发信息
A4: 光通信 | B4: 光缆与线缆 | C4: 核心 | D4: 000586 | E4: 汇源通信
A5: 光通信 | B5: 光纤预制棒与光纤 | C5: 核心 | D5: 000586 | E5: 汇源通信
A6: 光通信 | B6: 光模块-数通与AI算力 | C6: 核心 | D6: 000988 | E6: 华工科技
A7: 光通信 | B7: 光模块-电信与传输 | C7: 核心 | D7: 000988 | E7: 华工科技
A8: 光通信 | B8: CPO与硅光集成 | C8: 核心 | D8: 000988 | E8: 华工科技
A9: 光通信 | B9: 光连接器与陶瓷插芯 | C9: 核心 | D9: 002179 | E9: 中航光电
A10: 光通信 | B10: 光模块-数通与AI算力 | C10: 核心 | D10: 002281 | E10: 光迅科技
A11: 光通信 | B11: 光模块-电信与传输 | C11: 核心 | D11: 002281 | E11: 光迅科技
A12: 光通信 | B12: 光器件-无源器件 | C12: 核心 | D12: 002281 | E12: 光迅科技
... A99: 光通信 | B99: CPO与硅光集成 | C99: 核心 | D99: 920045 | E99: 蘅东光

Sheet 概念统计
B2: 概念统计 · 核心/相关分布
B3: 公式引用隐藏展开表精确计数；一只股票可对应多个概念。
B4: 一级分类 | C4: 二级概念 | D4: 核心（只） | E4: 相关（只） | F4: 合计（只）
B5: 光通信 | C5: CPO与硅光集成 | D5: =COUNTIFS('概念展开'!$A$2:$A$99,B5,'概念展开'!$B$2:$B$99,C5,'概念展开'!$C$2:$C$99,"核心") | E5: =COUNTIFS('概念展开'!$A$2:$A$99,B5,'概念展开'!$B$2:$B$99,C5,'概念展开'!$C$2:$C$99,"相关") | F5: =SUM(D5:E5)
B6: 光通信 | C6: MPO/MTP与高密度连接 | D6: =COUNTIFS('概念展开'!$A$2:$A$99,B6,'概念展开'!$B$2:$B$99,C6,'概念展开'!$C$2:$C$99,"核心") | E6: =COUNTIFS('概念展开'!$A$2:$A$99,B6,'概念展开'!$B$2:$B$99,C6,'概念展开'!$C$2:$C$99,"相关") | F6: =SUM(D6:E6)
B7: 光通信 | C7: 光传输与接入设备 | D7: =COUNTIFS('概念展开'!$A$2:$A$99,B7,'概念展开'!$B$2:$B$99,C7,'概念展开'!$C$2:$C$99,"核心") | E7: =COUNTIFS('概念展开'!$A$2:$A$99,B7,'概念展开'!$B$2:$B$99,C7,'概念展开'!$C$2:$C$99,"相关") | F7: =SUM(D7:E7)
B8: 光通信 | C8: 光器件-无源器件 | D8: =COUNTIFS('概念展开'!$A$2:$A$99,B8,'概念展开'!$B$2:$B$99,C8,'概念展开'!$C$2:$C$99,"核心") | E8: =COUNTIFS('概念展开'!$A$2:$A$99,B8,'概念展开'!$B$2:$B$99,C8,'概念展开'!$C$2:$C$99,"相关") | F8: =SUM(D8:E8)
B9: 光通信 | C9: 光器件-有源器件 | D9: =COUNTIFS('概念展开'!$A$2:$A$99,B9,'概念展开'!$B$2:$B$99,C9,'概念展开'!$C$2:$C$99,"核心") | E9: =COUNTIFS('概念展开'!$A$2:$A$99,B9,'概念展开'!$B$2:$B$99,C9,'概念展开'!$C$2:$C$99,"相关") | F9: =SUM(D9:E9)
B10: 光通信 | C10: 光模块-数通与AI算力 | D10: =COUNTIFS('概念展开'!$A$2:$A$99,B10,'概念展开'!$B$2:$B$99,C10,'概念展开'!$C$2:$C$99,"核心") | E10: =COUNTIFS('概念展开'!$A$2:$A$99,B10,'概念展开'!$B$2:$B$99,C10,'概念展开'!$C$2:$C$99,"相关") | F10: =SUM(D10:E10)
B11: 光通信 | C11: 光模块-电信与传输 | D11: =COUNTIFS('概念展开'!$A$2:$A$99,B11,'概念展开'!$B$2:$B$99,C11,'概念展开'!$C$2:$C$99,"核心") | E11: =COUNTIFS('概念展开'!$A$2:$A$99,B11,'概念展开'!$B$2:$B$99,C11,'概念展开'!$C$2:$C$99,"相关") | F11: =SUM(D11:E11)
B12: 光通信 | C12: 光纤预制棒与光纤 | D12: =COUNTIFS('概念展开'!$A$2:$A$99,B12,'概念展开'!$B$2:$B$99,C12,'概念展开'!$C$2:$C$99,"核心") | E12: =COUNTIFS('概念展开'!$A$2:$A$99,B12,'概念展开'!$B$2:$B$99,C12,'概念展开'!$C$2:$C$99,"相关") | F12: =SUM(D12:E12)
B13: 光通信 | C13: 光缆与线缆 | D13: =COUNTIFS('概念展开'!$A$2:$A$99,B13,'概念展开'!$B$2:$B$99,C13,'概念展开'!$C$2:$C$99,"核心") | E13: =COUNTIFS('概念展开'!$A$2:$A$99,B13,'概念展开'!$B$2:$B$99,C13,'概念展开'!$C$2:$C$99,"相关") | F13: =SUM(D13:E13)
B14: 光通信 | C14: 光网络系统与工程服务 | D14: =COUNTIFS('概念展开'!$A$2:$A$99,B14,'概念展开'!$B$2:$B$99,C14,'概念展开'!$C$2:$C$99,"核心") | E14: =COUNTIFS('概念展开'!$A$2:$A$99,B14,'概念展开'!$B$2:$B$99,C14,'概念展开'!$C$2:$C$99,"相关") | F14: =SUM(D14:E14)
B15: 光通信 | C15: 光芯片-PLC与AWG | D15: =COUNTIFS('概念展开'!$A$2:$A$99,B15,'概念展开'!$B$2:$B$99,C15,'概念展开'!$C$2:$C$99,"核心") | E15: =COUNTIFS('概念展开'!$A$2:$A$99,B15,'概念展开'!$B$2:$B$99,C15,'概念展开'!$C$2:$C$99,"相关") | F15: =SUM(D15:E15)
B16: 光通信 | C16: 光芯片-激光器与探测器 | D16: =COUNTIFS('概念展开'!$A$2:$A$99,B16,'概念展开'!$B$2:$B$99,C16,'概念展开'!$C$2:$C$99,"核心") | E16: =COUNTIFS('概念展开'!$A$2:$A$99,B16,'概念展开'!$B$2:$B$99,C16,'概念展开'!$C$2:$C$99,"相关") | F16: =SUM(D16:E16)
... B23: 光通信 | C23: 特种光纤与光纤环 | D23: =COUNTIFS('概念展开'!$A$2:$A$99,B23,'概念展开'!$B$2:$B$99,C23,'概念展开'!$C$2:$C$99,"核心") | E23: =COUNTIFS('概念展开'!$A$2:$A$99,B23,'概念展开'!$B$2:$B$99,C23,'概念展开'!$C$2:$C$99,"相关") | F23: =SUM(D23:E23)
B24: 合计（概念次数，非股票去重数） | D24: =SUM(D5:D23) | E24: =SUM(E5:E23) | F24: =SUM(F5:F23)
