Workbook

Sheet 封面
B2: 军工概念深度清洗报告
B3: 复核日期：2026-10-27｜范围：97只｜重点：军工实质、产品层级、军民边界与二次复审
B6: 复核股票（只） | C6: =COUNTA('清洗总表'!$B$5:$B$101)
B7: 保留军工（只） | C7: =COUNTA('军工'!$B$5:$B$93)
B8: 核心判词（只） | C8: =COUNTIF('军工'!$H$5:$H$93,"核心")
B9: 相关判词（只） | C9: =COUNTIF('军工'!$H$5:$H$93,"相关")
B10: 纠错动作（只） | C10: =COUNTIF('清洗总表'!$E$5:$E$101,"纠错")
B11: 完全摘除（只） | C11: =COUNTA('摘除清单'!$B$5:$B$12)
B15: 工作表索引
B16: 清洗总表 | C16: 97只旧概念、新概念、动作、判词、详细理由和证据
B17: 军工 | C17: 89只清洗后军工公司
B18: 摘除清单 | C18: 8只通用业务或军工证据不足公司
B19: 概念统计 | C19: 31个二级概念
B23: 核心：军工是明确主营、重要收入来源，或已有规模化核心产品；相关：有真实军工产品、订单或交付，但民用为主或收入未独立拆分。
B24: 摘除：只有集团背景、军工资质、潜在供应、通用产品可军用，或当前只有民用机器人、导航、材料等联想。
B25: 二次复审：威海广泰、江龙船艇、纵横股份依据真实历史订单或2025年军工交付证据，由初审摘除修正为相关。
B26: 主营与2025分部：iFinD ifind_get_stock_info、ifind_get_stock_business_segmentation（2026-10-27）；逐股证据见Source列。

Sheet 清洗总表
B2: 军工 · 97只逐项复核
B3: 逐股核对军工产品、军用场景、客户与收入；区分真实军工配套和通用产品联想。
B4: 代码 | C4: 名称 | D4: 旧军工概念 | E4: 动作 | F4: 新一级分类 | G4: 新概念 | H4: 判词 | I4: 详细理由 | J4: 证据名称 | K4: 证据日期 | L4: Source Name | M4: Source URL
B5: 000519 | C5: 中兵红箭 | D5: 军工：陆军 | E5: 纠错 | F5: 军工 | G5: 弹药与特种装备 | H5: 核心 | I5: 公司特种装备并非一般机械制造，年报明确其承担多个国家重点型号研发和生产，多型装备由科研转入首批生产，部分产品国内独家，直接服务部队装备建设；结合原资料所列弹药属性，应归入弹药与特种装备，而非宽泛的“陆军”。2025年特种装备收入72.6944亿元，占营业收入78.3856%；超硬材料16.1573亿元，占17.4223%，汽车制造占4.1921%，军工特种装备已是绝对主业，故列核心。旧标签只按军种分类，既不能体现弹药及特种装备产品实质，也把超硬材料民品混入印象，需细化为具体装备概念。 | J5: 中兵红箭：2025年年度报告 | K5: 2026-04-24 | L5: iFinD ifind_get_stock_info + ifind_get_stock_business_segmentation (as of 2026-10-27)；中兵红箭：2025年年度报告 | M5: https://static.cninfo.com.cn/finalpage/2026-04-24/1225160985.PDF
B6: 000547 | C6: 航天发展 | D6: 军工：军工电子-电子对抗 | E6: 纠错 | F6: 军工 | G6: 电子对抗与蓝军仿真、军用通信与指挥控制 | H6: 核心 | I6: 公司蓝军体系面向军队实战化训练、武器试验鉴定和体系对抗，产品包括数字及半实物仿真、靶标、复杂电磁环境构设、目标模拟和干扰设备，客户包括部队与军工科研院所；新一代通信与指控产品包括车船载及无人机通信节点、交换控制和军网终端，军用场景明确。2025年防务装备产业收入10.7674亿元，占43.0536%；其中蓝军装备及相关产品5.5495亿元、通信与指控5.6032亿元，合计构成重要收入来源，故列核心。旧“军工电子-电子对抗”只覆盖一部分，需补出蓝军仿真和军用通信指控两条实质产品线。 | J6: 航天发展：2025年年度报告 | K6: 2026-04-29 | L6: iFinD ifind_get_stock_info + ifind_get_stock_business_segmentation (as of 2026-10-27)；航天发展：2025年年度报告 | M6: https://static.cninfo.com.cn/finalpage/2026-04-29/1225247825.PDF
B7: 000561 | C7: 烽火电子 | D7: 军工：军工电子 | E7: 纠错 | F7: 军工 | G7: 军用通信与指挥控制、雷达与预警探测、航空机载系统与航电 | H7: 核心 | I7: 公司为通信装备、雷达及电声器材科研生产骨干企业，产品包括特种短波及无线通信设备、航空搜救定位设备、无线电高度表、多普勒雷达和导航设备，既服务部队通信与后勤保障，也直接配装航空平台，不是普通民用通信企业。2025年通信行业收入9.4464亿元，占56.4544%，雷达行业6.5467亿元，占39.1250%；分产品通信及配套6.9080亿元、雷达及配套6.5467亿元、电声器材2.5384亿元，通信和雷达合计占绝对主体，故列核心。旧“军工电子”过粗，且未反映2025年并入雷达业务后的结构，应拆为通信指控、雷达探测和航空机载航电。 | J7: 烽火电子：2025年年度报告 | K7: 2026-04-29 | L7: iFinD ifind_get_stock_info + ifind_get_stock_business_segmentation (as of 2026-10-27)；烽火电子：2025年年度报告 | M7: https://static.cninfo.com.cn/finalpage/2026-04-29/1225250693.PDF
B8: 000576 | C8: 甘化科工 | D8: 军工：军工电子 | E8: 纠错 | F8: 军工 | G8: 军工电源与电机电气、弹药与特种装备、红外光电与激光 | H8: 核心 | I8: 公司年报明确三块主营均为军工产品：升华电源的模块及定制电源用于机载、舰载、弹载武器平台，客户为军工企业、科研院所和军工厂；沈阳含能的钨球、钨环、钨柱预制破片用于炮弹、火箭弹和导弹毁伤部件；甘鑫科技红外等光电成像组件用于弹载、车载、无人装备的目标探测、定位和瞄准。2025年电源及相关产品收入2.5090亿元，高性能特种合金材料制品2.1078亿元，光电成像系统0.2888亿元，制造业整体占97.0509%，军工已是主营业务，故由旧“相关”上调为核心。旧“军工电子”无法覆盖弹药破片，需按电源、弹药和光电三条产品线纠正。 | J8: 甘化科工：2025年年度报告 | K8: 2026-04-20 | L8: iFinD ifind_get_stock_info + ifind_get_stock_business_segmentation (as of 2026-10-27)；甘化科工：2025年年度报告 | M8: https://static.cninfo.com.cn/finalpage/2026-04-20/1225119259.PDF
B9: 000733 | C9: 振华科技 | D9: 军工：军工电子 | E9: 纠错 | F9: 军工 | G9: 军工被动元件与连接器、军工芯片与特种集成电路、军工电源与电机电气 | H9: 核心 | I9: 公司新型电子元器件直接服务国家战略重点型号，基础产品包括电阻、电容、电感、半导体分立器件、继电器和连接器，混合集成电路包括厚膜电源、微电路模块、电源组件、射频模块及电机驱动，年报明确应用于航空、航天、兵器、船舶和核工业等重点领域，已有实际型号配套而非潜在军用。2025年电子元器件制造业收入57.5497亿元，占100.0000%，其中新型电子元器件57.0999亿元，现代服务业仅0.4499亿元；但未单列军品收入，不能把全部收入等同军工。基于规模化的重点型号元器件主业列核心。旧“军工电子”和“MLCC”只指向单一元件，应扩展为被动元件、特种集成电路及电源电机控制。 | J9: 振华科技：2025年年度报告 | K9: 2026-04-29 | L9: iFinD ifind_get_stock_info + ifind_get_stock_business_segmentation (as of 2026-10-27)；振华科技：2025年年度报告 | M9: https://static.cninfo.com.cn/finalpage/2026-04-29/1225246300.PDF
B10: 000738 | C10: 航发控制 | D10: 军工：航空发动机 | E10: 纠错 | F10: 军工 | G10: 航空发动机与燃气轮机 | H10: 核心 | I10: 公司核心产品是军民用航空发动机及燃气轮机控制系统，承担在研在役型号研制、生产、维修和保障，产品配装涡喷、涡扇、涡轴、涡桨发动机以及无人机、舰船和弹用动力装置；衍生产品还包括地面战车电液作动装置和弹用动力控制部件，均为明确装备场景。2025年发动机控制系统及部件收入45.8190亿元，按年报分产品口径占88.60%；国际合作4.0232亿元，控制系统技术衍生品1.8741亿元，主营集中度很高，故列核心。旧“航空发动机”容易误解为公司制造整台发动机，实际壁垒在控制、燃油调节及作动系统，应统一细化到航空发动机与燃气轮机概念。 | J10: 航发控制：2025年年度报告 | K10: 2026-03-27 | L10: iFinD ifind_get_stock_info + ifind_get_stock_business_segmentation (as of 2026-10-27)；航发控制：2025年年度报告 | M10: https://static.cninfo.com.cn/finalpage/2026-03-27/1225036461.PDF
B11: 000768 | C11: 中航西飞 | D11: 军工：军贸 | E11: 纠错 | F11: 军工 | G11: 航空整机-固定翼、航空结构件与锻铸件 | H11: 核心 | I11: 公司直接研制生产军用大中型运输机、轰炸机和特种飞机，运输机承担远程投送、兵力部署，轰炸机承担远程打击，特种飞机承担空基指挥、空中受油、海空侦察和电磁制压，同时生产军民用航空零部件，属于真实整机总装与结构件业务。2025年航空工业产品收入405.4801亿元，占98.8645%，其他工业产品4.6572亿元，占1.1355%；飞机产品分部没有将军机和民机收入独立拆开，不能将全部航空收入都视作军品，但军用大中型固定翼整机是公司明确核心产品，故列核心。旧“军贸”“空军”只描述销售区域或军种，遗漏整机与航空结构件实质，需据产品重新标注。 | J11: 中航西飞：2025年年度报告 | K11: 2026-03-31 | L11: iFinD ifind_get_stock_info + ifind_get_stock_business_segmentation (as of 2026-10-27)；中航西飞：2025年年度报告 | M11: https://static.cninfo.com.cn/finalpage/2026-03-31/1225052459.PDF
B12: 000901 | C12: 航天科技 | D12: 军工：惯性导航 | E12: 纠错 | F12: 军工 | G12: 军用导航与惯导、航天装备与分系统 | H12: 相关 | I12: 公司航天应用板块就是军工业务，加速度传感器主要面向军品，用于航天、航空、船舶和兵器的惯性导航系统；另有发动机及舵机零部件、伺服装配、军用电缆、光纤环圈，以及服务航天研究院武器研制和批产保障的测试测控系统，军工落地清晰。2025年航天产品收入8.7787亿元，占15.8971%；汽车电子仪表42.4814亿元，占76.9282%，平台软件及感知设备3.7289亿元，占6.7526%，说明收入仍以汽车电子为主，军工虽是重要板块但未占主导，故由旧“核心”下调为相关。旧“惯性导航”“航天配套”方向基本正确，但需明确惯导器件与航天分系统、测试保障的产品边界。 | J12: 航天科技：2025年年度报告 | K12: 2026-04-29 | L12: iFinD ifind_get_stock_info + ifind_get_stock_business_segmentation (as of 2026-10-27)；航天科技：2025年年度报告 | M12: https://static.cninfo.com.cn/finalpage/2026-04-29/1225227513.PDF
B13: 002025 | C13: 航天电器 | D13: 军工：军工电子 | E13: 纠错 | F13: 军工 | G13: 军工被动元件与连接器、军工电源与电机电气 | H13: 核心 | I13: 公司高端连接器、线缆组件、微特电机与控制组件、密封及特种继电器、光电器件已实际销售给航天、航空、电子、舰船和兵器客户，年报明确军品基本覆盖全部防务装备领域，并承担载人航天、探月、北斗和火星探测等工程配套，不是通用连接器可军用的推断。2025年连接器收入39.8420亿元，电机13.5794亿元，继电器2.4040亿元，光通信器件1.3175亿元；电子元器件制造业收入57.1429亿元，占98.1864%，但未独立拆分军品与民品。防务配套是规模化核心业务，故列核心。旧“军工电子”“连接器”需要收敛为军工被动元件与连接器，并补充微特电机和控制组件对应的电源电机电气概念。 | J13: 航天电器：2025年年度报告 | K13: 2026-03-31 | L13: iFinD ifind_get_stock_info + ifind_get_stock_business_segmentation (as of 2026-10-27)；航天电器：2025年年度报告 | M13: https://static.cninfo.com.cn/finalpage/2026-03-31/1225054265.PDF
B14: 002049 | C14: 紫光国微 | D14: 军工：军工电子-军工芯片 | E14: 纠错 | F14: 军工 | G14: 军工芯片与特种集成电路 | H14: 核心 | I14: 公司特种集成电路已形成处理器、可编程器件、存储器、网络与接口、模拟器件、ASIC及SoPC等八百多个货架品种，宇航用耐辐照FPGA、回读刷新芯片、存储器和总线接口已获得核心用户应用并产生持续收入，属于高可靠特种芯片实际供货，而非把普通安全芯片泛化为军工。2025年特种集成电路收入32.1201亿元，占52.26%；智能安全芯片25.4714亿元，占41.45%，晶体元器件3.2029亿元，占5.2116%，特种集成电路已超过半数且为两大主业之一，故列核心。旧“军工电子-军工芯片”与业务一致，但应改用产品实质更明确的军工芯片与特种集成电路，并避免把民用智能安全芯片一并计入军工。 | J14: 紫光国微：2025年年度报告 | K14: 2026-04-21 | L14: iFinD ifind_get_stock_info + ifind_get_stock_business_segmentation (as of 2026-10-27)；紫光国微：2025年年度报告 | M14: https://static.cninfo.com.cn/finalpage/2026-04-21/1225133393.PDF
B15: 002111 | C15: 威海广泰 | D15: 军工：航空地面装备 | E15: 纠错 | F15: 军工 | G15: 航空地面保障装备、军用无人装备与机器人 | H15: 相关 | I15: 公司军工相关性来自真实历史军用空港装备、靶机和军品特种装备订单，而不是把民航地勤设备直接军工化。2024年官方投资者关系记录仍将军队、武警列为客户，2019年军方靶机及军品特种装备中标也证明已有军工交付；但2025年披露重点已转向民航空港、消防应急和民用无人机，空港地面设备收入21.0201亿元、消防设备10.7719亿元，军品收入未独立拆分，当前民用业务明显为主，故由初审摘除修正为相关而非核心。旧航空地面装备方向可保留，并补充军用无人装备与机器人，同时剔除全部空港收入皆属军工的错误理解。 | J15: 威海广泰空港设备股份有限公司投资者关系活动记录表 | K15: 2024-05-16 | L15: iFinD ifind_get_stock_info + ifind_get_stock_business_segmentation (as of 2026-10-27)；威海广泰空港设备股份有限公司投资者关系活动记录表 | M15: http://notice.10jqka.com.cn/api/pdf/76e3ea0cfcc94665.pdf
... B101: 688709 | C101: 成都华微 | D101: 军工：军工电子-特种集成电路 | E101: 纠错 | F101: 军工 | G101: 军工芯片与特种集成电路 | H101: 核心 | I101: 公司主营特种集成电路，产品覆盖FPGA、CPLD、SoPC、MCU、存储器、AD/DA转换器、接口驱动及电源管理芯片，用于特种装备的可编程逻辑、信号采集转换、控制和供电管理，服务高可靠电子系统，已有真实产品谱系和销售，而非一般消费芯片可军用。2025年集成电路行业收入7.5846亿元、占99.7994%；数字集成电路4.0428亿元、约占总收入53.20%，模拟集成电路2.7555亿元、约占36.26%，技术服务0.5031亿元，特种芯片构成绝对主营和规模化核心产品，故判核心。旧“军工电子-特种集成电路”虽方向正确，但仍叠加宽泛的军工电子层级，现统一为军工芯片与特种集成电路，保留全部数字和模拟产品实质，不额外虚增雷达、导航或通信整机概念。 | J101: 成都华微电子科技股份有限公司2025年年度报告 | K101: 2026-04-30 | L101: iFinD ifind_get_stock_info + ifind_get_stock_business_segmentation (as of 2026-10-27)；成都华微电子科技股份有限公司2025年年度报告 | M101: http://file.finance.sina.com.cn/211.154.219.97:9494/MRGG/CNSESH_STOCK/2026/2026-4/2026-04-30/12277763.PDF

Sheet 军工
B2: 军工 · 清洗后89只股池
B3: 核心74只、相关15只；按装备、分系统、材料和软件细化为31个二级概念。
B4: 代码 | C4: 名称 | D4: 旧军工概念 | E4: 动作 | F4: 新一级分类 | G4: 新概念 | H4: 判词 | I4: 详细理由 | J4: 证据名称 | K4: 证据日期 | L4: Source Name | M4: Source URL
B5: 000519 | C5: 中兵红箭 | D5: 军工：陆军 | E5: 纠错 | F5: 军工 | G5: 弹药与特种装备 | H5: 核心 | I5: 公司特种装备并非一般机械制造，年报明确其承担多个国家重点型号研发和生产，多型装备由科研转入首批生产，部分产品国内独家，直接服务部队装备建设；结合原资料所列弹药属性，应归入弹药与特种装备，而非宽泛的“陆军”。2025年特种装备收入72.6944亿元，占营业收入78.3856%；超硬材料16.1573亿元，占17.4223%，汽车制造占4.1921%，军工特种装备已是绝对主业，故列核心。旧标签只按军种分类，既不能体现弹药及特种装备产品实质，也把超硬材料民品混入印象，需细化为具体装备概念。 | J5: 中兵红箭：2025年年度报告 | K5: 2026-04-24 | L5: iFinD ifind_get_stock_info + ifind_get_stock_business_segmentation (as of 2026-10-27)；中兵红箭：2025年年度报告 | M5: https://static.cninfo.com.cn/finalpage/2026-04-24/1225160985.PDF
B6: 000547 | C6: 航天发展 | D6: 军工：军工电子-电子对抗 | E6: 纠错 | F6: 军工 | G6: 电子对抗与蓝军仿真、军用通信与指挥控制 | H6: 核心 | I6: 公司蓝军体系面向军队实战化训练、武器试验鉴定和体系对抗，产品包括数字及半实物仿真、靶标、复杂电磁环境构设、目标模拟和干扰设备，客户包括部队与军工科研院所；新一代通信与指控产品包括车船载及无人机通信节点、交换控制和军网终端，军用场景明确。2025年防务装备产业收入10.7674亿元，占43.0536%；其中蓝军装备及相关产品5.5495亿元、通信与指控5.6032亿元，合计构成重要收入来源，故列核心。旧“军工电子-电子对抗”只覆盖一部分，需补出蓝军仿真和军用通信指控两条实质产品线。 | J6: 航天发展：2025年年度报告 | K6: 2026-04-29 | L6: iFinD ifind_get_stock_info + ifind_get_stock_business_segmentation (as of 2026-10-27)；航天发展：2025年年度报告 | M6: https://static.cninfo.com.cn/finalpage/2026-04-29/1225247825.PDF
B7: 000561 | C7: 烽火电子 | D7: 军工：军工电子 | E7: 纠错 | F7: 军工 | G7: 军用通信与指挥控制、雷达与预警探测、航空机载系统与航电 | H7: 核心 | I7: 公司为通信装备、雷达及电声器材科研生产骨干企业，产品包括特种短波及无线通信设备、航空搜救定位设备、无线电高度表、多普勒雷达和导航设备，既服务部队通信与后勤保障，也直接配装航空平台，不是普通民用通信企业。2025年通信行业收入9.4464亿元，占56.4544%，雷达行业6.5467亿元，占39.1250%；分产品通信及配套6.9080亿元、雷达及配套6.5467亿元、电声器材2.5384亿元，通信和雷达合计占绝对主体，故列核心。旧“军工电子”过粗，且未反映2025年并入雷达业务后的结构，应拆为通信指控、雷达探测和航空机载航电。 | J7: 烽火电子：2025年年度报告 | K7: 2026-04-29 | L7: iFinD ifind_get_stock_info + ifind_get_stock_business_segmentation (as of 2026-10-27)；烽火电子：2025年年度报告 | M7: https://static.cninfo.com.cn/finalpage/2026-04-29/1225250693.PDF
B8: 000576 | C8: 甘化科工 | D8: 军工：军工电子 | E8: 纠错 | F8: 军工 | G8: 军工电源与电机电气、弹药与特种装备、红外光电与激光 | H8: 核心 | I8: 公司年报明确三块主营均为军工产品：升华电源的模块及定制电源用于机载、舰载、弹载武器平台，客户为军工企业、科研院所和军工厂；沈阳含能的钨球、钨环、钨柱预制破片用于炮弹、火箭弹和导弹毁伤部件；甘鑫科技红外等光电成像组件用于弹载、车载、无人装备的目标探测、定位和瞄准。2025年电源及相关产品收入2.5090亿元，高性能特种合金材料制品2.1078亿元，光电成像系统0.2888亿元，制造业整体占97.0509%，军工已是主营业务，故由旧“相关”上调为核心。旧“军工电子”无法覆盖弹药破片，需按电源、弹药和光电三条产品线纠正。 | J8: 甘化科工：2025年年度报告 | K8: 2026-04-20 | L8: iFinD ifind_get_stock_info + ifind_get_stock_business_segmentation (as of 2026-10-27)；甘化科工：2025年年度报告 | M8: https://static.cninfo.com.cn/finalpage/2026-04-20/1225119259.PDF
B9: 000733 | C9: 振华科技 | D9: 军工：军工电子 | E9: 纠错 | F9: 军工 | G9: 军工被动元件与连接器、军工芯片与特种集成电路、军工电源与电机电气 | H9: 核心 | I9: 公司新型电子元器件直接服务国家战略重点型号，基础产品包括电阻、电容、电感、半导体分立器件、继电器和连接器，混合集成电路包括厚膜电源、微电路模块、电源组件、射频模块及电机驱动，年报明确应用于航空、航天、兵器、船舶和核工业等重点领域，已有实际型号配套而非潜在军用。2025年电子元器件制造业收入57.5497亿元，占100.0000%，其中新型电子元器件57.0999亿元，现代服务业仅0.4499亿元；但未单列军品收入，不能把全部收入等同军工。基于规模化的重点型号元器件主业列核心。旧“军工电子”和“MLCC”只指向单一元件，应扩展为被动元件、特种集成电路及电源电机控制。 | J9: 振华科技：2025年年度报告 | K9: 2026-04-29 | L9: iFinD ifind_get_stock_info + ifind_get_stock_business_segmentation (as of 2026-10-27)；振华科技：2025年年度报告 | M9: https://static.cninfo.com.cn/finalpage/2026-04-29/1225246300.PDF
B10: 000738 | C10: 航发控制 | D10: 军工：航空发动机 | E10: 纠错 | F10: 军工 | G10: 航空发动机与燃气轮机 | H10: 核心 | I10: 公司核心产品是军民用航空发动机及燃气轮机控制系统，承担在研在役型号研制、生产、维修和保障，产品配装涡喷、涡扇、涡轴、涡桨发动机以及无人机、舰船和弹用动力装置；衍生产品还包括地面战车电液作动装置和弹用动力控制部件，均为明确装备场景。2025年发动机控制系统及部件收入45.8190亿元，按年报分产品口径占88.60%；国际合作4.0232亿元，控制系统技术衍生品1.8741亿元，主营集中度很高，故列核心。旧“航空发动机”容易误解为公司制造整台发动机，实际壁垒在控制、燃油调节及作动系统，应统一细化到航空发动机与燃气轮机概念。 | J10: 航发控制：2025年年度报告 | K10: 2026-03-27 | L10: iFinD ifind_get_stock_info + ifind_get_stock_business_segmentation (as of 2026-10-27)；航发控制：2025年年度报告 | M10: https://static.cninfo.com.cn/finalpage/2026-03-27/1225036461.PDF
B11: 000768 | C11: 中航西飞 | D11: 军工：军贸 | E11: 纠错 | F11: 军工 | G11: 航空整机-固定翼、航空结构件与锻铸件 | H11: 核心 | I11: 公司直接研制生产军用大中型运输机、轰炸机和特种飞机，运输机承担远程投送、兵力部署，轰炸机承担远程打击，特种飞机承担空基指挥、空中受油、海空侦察和电磁制压，同时生产军民用航空零部件，属于真实整机总装与结构件业务。2025年航空工业产品收入405.4801亿元，占98.8645%，其他工业产品4.6572亿元，占1.1355%；飞机产品分部没有将军机和民机收入独立拆开，不能将全部航空收入都视作军品，但军用大中型固定翼整机是公司明确核心产品，故列核心。旧“军贸”“空军”只描述销售区域或军种，遗漏整机与航空结构件实质，需据产品重新标注。 | J11: 中航西飞：2025年年度报告 | K11: 2026-03-31 | L11: iFinD ifind_get_stock_info + ifind_get_stock_business_segmentation (as of 2026-10-27)；中航西飞：2025年年度报告 | M11: https://static.cninfo.com.cn/finalpage/2026-03-31/1225052459.PDF
B12: 000901 | C12: 航天科技 | D12: 军工：惯性导航 | E12: 纠错 | F12: 军工 | G12: 军用导航与惯导、航天装备与分系统 | H12: 相关 | I12: 公司航天应用板块就是军工业务，加速度传感器主要面向军品，用于航天、航空、船舶和兵器的惯性导航系统；另有发动机及舵机零部件、伺服装配、军用电缆、光纤环圈，以及服务航天研究院武器研制和批产保障的测试测控系统，军工落地清晰。2025年航天产品收入8.7787亿元，占15.8971%；汽车电子仪表42.4814亿元，占76.9282%，平台软件及感知设备3.7289亿元，占6.7526%，说明收入仍以汽车电子为主，军工虽是重要板块但未占主导，故由旧“核心”下调为相关。旧“惯性导航”“航天配套”方向基本正确，但需明确惯导器件与航天分系统、测试保障的产品边界。 | J12: 航天科技：2025年年度报告 | K12: 2026-04-29 | L12: iFinD ifind_get_stock_info + ifind_get_stock_business_segmentation (as of 2026-10-27)；航天科技：2025年年度报告 | M12: https://static.cninfo.com.cn/finalpage/2026-04-29/1225227513.PDF
B13: 002025 | C13: 航天电器 | D13: 军工：军工电子 | E13: 纠错 | F13: 军工 | G13: 军工被动元件与连接器、军工电源与电机电气 | H13: 核心 | I13: 公司高端连接器、线缆组件、微特电机与控制组件、密封及特种继电器、光电器件已实际销售给航天、航空、电子、舰船和兵器客户，年报明确军品基本覆盖全部防务装备领域，并承担载人航天、探月、北斗和火星探测等工程配套，不是通用连接器可军用的推断。2025年连接器收入39.8420亿元，电机13.5794亿元，继电器2.4040亿元，光通信器件1.3175亿元；电子元器件制造业收入57.1429亿元，占98.1864%，但未独立拆分军品与民品。防务配套是规模化核心业务，故列核心。旧“军工电子”“连接器”需要收敛为军工被动元件与连接器，并补充微特电机和控制组件对应的电源电机电气概念。 | J13: 航天电器：2025年年度报告 | K13: 2026-03-31 | L13: iFinD ifind_get_stock_info + ifind_get_stock_business_segmentation (as of 2026-10-27)；航天电器：2025年年度报告 | M13: https://static.cninfo.com.cn/finalpage/2026-03-31/1225054265.PDF
B14: 002049 | C14: 紫光国微 | D14: 军工：军工电子-军工芯片 | E14: 纠错 | F14: 军工 | G14: 军工芯片与特种集成电路 | H14: 核心 | I14: 公司特种集成电路已形成处理器、可编程器件、存储器、网络与接口、模拟器件、ASIC及SoPC等八百多个货架品种，宇航用耐辐照FPGA、回读刷新芯片、存储器和总线接口已获得核心用户应用并产生持续收入，属于高可靠特种芯片实际供货，而非把普通安全芯片泛化为军工。2025年特种集成电路收入32.1201亿元，占52.26%；智能安全芯片25.4714亿元，占41.45%，晶体元器件3.2029亿元，占5.2116%，特种集成电路已超过半数且为两大主业之一，故列核心。旧“军工电子-军工芯片”与业务一致，但应改用产品实质更明确的军工芯片与特种集成电路，并避免把民用智能安全芯片一并计入军工。 | J14: 紫光国微：2025年年度报告 | K14: 2026-04-21 | L14: iFinD ifind_get_stock_info + ifind_get_stock_business_segmentation (as of 2026-10-27)；紫光国微：2025年年度报告 | M14: https://static.cninfo.com.cn/finalpage/2026-04-21/1225133393.PDF
B15: 002111 | C15: 威海广泰 | D15: 军工：航空地面装备 | E15: 纠错 | F15: 军工 | G15: 航空地面保障装备、军用无人装备与机器人 | H15: 相关 | I15: 公司军工相关性来自真实历史军用空港装备、靶机和军品特种装备订单，而不是把民航地勤设备直接军工化。2024年官方投资者关系记录仍将军队、武警列为客户，2019年军方靶机及军品特种装备中标也证明已有军工交付；但2025年披露重点已转向民航空港、消防应急和民用无人机，空港地面设备收入21.0201亿元、消防设备10.7719亿元，军品收入未独立拆分，当前民用业务明显为主，故由初审摘除修正为相关而非核心。旧航空地面装备方向可保留，并补充军用无人装备与机器人，同时剔除全部空港收入皆属军工的错误理解。 | J15: 威海广泰空港设备股份有限公司投资者关系活动记录表 | K15: 2024-05-16 | L15: iFinD ifind_get_stock_info + ifind_get_stock_business_segmentation (as of 2026-10-27)；威海广泰空港设备股份有限公司投资者关系活动记录表 | M15: http://notice.10jqka.com.cn/api/pdf/76e3ea0cfcc94665.pdf
... B93: 688709 | C93: 成都华微 | D93: 军工：军工电子-特种集成电路 | E93: 纠错 | F93: 军工 | G93: 军工芯片与特种集成电路 | H93: 核心 | I93: 公司主营特种集成电路，产品覆盖FPGA、CPLD、SoPC、MCU、存储器、AD/DA转换器、接口驱动及电源管理芯片，用于特种装备的可编程逻辑、信号采集转换、控制和供电管理，服务高可靠电子系统，已有真实产品谱系和销售，而非一般消费芯片可军用。2025年集成电路行业收入7.5846亿元、占99.7994%；数字集成电路4.0428亿元、约占总收入53.20%，模拟集成电路2.7555亿元、约占36.26%，技术服务0.5031亿元，特种芯片构成绝对主营和规模化核心产品，故判核心。旧“军工电子-特种集成电路”虽方向正确，但仍叠加宽泛的军工电子层级，现统一为军工芯片与特种集成电路，保留全部数字和模拟产品实质，不额外虚增雷达、导航或通信整机概念。 | J93: 成都华微电子科技股份有限公司2025年年度报告 | K93: 2026-04-30 | L93: iFinD ifind_get_stock_info + ifind_get_stock_business_segmentation (as of 2026-10-27)；成都华微电子科技股份有限公司2025年年度报告 | M93: http://file.finance.sina.com.cn/211.154.219.97:9494/MRGG/CNSESH_STOCK/2026/2026-4/2026-04-30/12277763.PDF

Sheet 摘除清单
B2: 摘除清单 · 8只证据不足或业务错标
B3: 通用光电、索具、民用导航、工业机器人及集团背景不直接计入军工。
B4: 代码 | C4: 名称 | D4: 旧军工概念 | E4: 动作 | F4: 新一级分类 | G4: 新概念 | H4: 判词 | I4: 详细理由 | J4: 证据名称 | K4: 证据日期 | L4: Source Name | M4: Source URL
B5: 002222 | C5: 福晶科技 | D5: 军工：军工电子-激光晶体 | E5: 摘除 | F5: — | G5: — | H5: 摘除 | I5: 公司主营晶体元器件、精密光学元件和激光器件，年报列示用途为固体及光纤激光器、光通信、AR、激光雷达、半导体设备、工业测量、生命科学和精密仪器等，未披露军用激光器、武器装备型号、军工客户或军品合同，不能因激光晶体具有潜在军事用途就归入红外光电与激光军工概念。2025年光电子行业收入11.5778亿元，占100%；激光光学元器件4.5501亿元，非线性光学晶体2.6669亿元，激光器件2.0405亿元，激光晶体2.0194亿元，其他0.3008亿元，所有分部均未独立披露军工收入。基于现有可核验资料应摘除。旧“军工电子-激光晶体”把通用光电元器件直接等同军工核心，证据不足且定位过度。 | J5: 福晶科技：2025年年度报告 | K5: 2026-04-29 | L5: iFinD ifind_get_stock_info + ifind_get_stock_business_segmentation (as of 2026-10-27)；福晶科技：2025年年度报告 | M5: https://static.cninfo.com.cn/finalpage/2026-04-29/1225227139.pdf
B6: 002342 | C6: 巨力索具 | D6: 军工：军工材料 | E6: 摘除 | F6: — | G6: — | H6: 摘除 | I6: 公司实际产品为工程及金属索具、钢丝绳及索具、合成纤维吊装带、链条和夹具吊梁等，应用于工程吊装和通用装备连接，2025年报未披露军用索具型号、军工客户、军品合同或武器装备批量配套，不能仅因索具可能用于舰船、航空或重型装备吊装就认定为军工材料。2025年金属制品业收入10.2495亿元，占39.8764%，通用设备制造业9.9819亿元，占38.8350%，纺织业3.9918亿元，占15.5301%；分产品工程及金属索具12.4897亿元、钢丝绳及索具7.3060亿元、合成纤维吊装带3.9918亿元，均无军工独立拆分。故摘除。旧“军工材料”在产品和材料属性上均不准确，且旧“边缘”也不足以表达缺乏军工落地证据。 | J6: 巨力索具：2025年年度报告 | K6: 2026-04-10 | L6: iFinD ifind_get_stock_info + ifind_get_stock_business_segmentation (as of 2026-10-27)；巨力索具：2025年年度报告 | M6: https://static.cninfo.com.cn/finalpage/2026-04-10/1225088185.PDF
B7: 002383 | C7: 合众思壮 | D7: 军工：军工电子 | E7: 摘除 | F7: — | G7: — | H7: 摘除 | I7: 公司主营卫星导航定位软硬件，当前产品集中于测量测绘、建筑施工、资源与公共事业、农机和工程机械智能控制。年报虽提到施工系统可用于国防、机场等工程建设，但这只是高精度定位设备的应用范围描述，未给出军用导航终端、抗干扰军品、军队客户、型号配套或军品合同，不能据此确认军工业务。2025年测量测绘与建筑工程收入5.7122亿元，占41.7133%，资源与公共事业4.3390亿元，占31.6855%，智能制造2.0019亿元，占14.6188%，其他1.6409亿元；卫星导航系统技术及设备收入13.6941亿元，未独立披露军工收入。民用为主且缺乏可核验军用落地，故摘除。旧“军工电子”和“军民两用”表述把潜在用途误作实际业务。 | J7: 合众思壮：2025年年度报告 | K7: 2026-04-23 | L7: iFinD ifind_get_stock_info + ifind_get_stock_business_segmentation (as of 2026-10-27)；合众思壮：2025年年度报告 | M7: https://static.cninfo.com.cn/finalpage/2026-04-23/1225151761.PDF
B8: 002724 | C8: 海洋王 | D8: 军工：军工配套 | E8: 摘除 | F8: — | G8: — | H8: 摘除 | I8: 公司实际业务是特殊环境专业照明设备及照明工程，年报虽把军工与石化、电力、煤矿等并列为下游行业，并提到产品应用于部队，但没有披露专门军用照明型号、军队采购项目或军用产品收入，不能由通用防爆、防腐、防水照明可用于部队就推定军工落地。2025年电气机械和器材制造业收入16.0232亿元、占93.0604%，其中照明设备16.0126亿元；建筑工程1.1949亿元、占6.9396%，军工未独立拆分。旧“军工配套”仅概括应用场景，缺乏产品级和订单级证据，且会把多行业工业照明供应商误标为军工企业，故摘除。 | J8: 海洋王照明科技股份有限公司2025年年度报告 | K8: 2026-04-29 | L8: iFinD ifind_get_stock_info + ifind_get_stock_business_segmentation (as of 2026-10-27)；海洋王照明科技股份有限公司2025年年度报告 | M8: https://static.cninfo.com.cn/finalpage/2026-04-29/1225242473.PDF
B9: 002747 | C9: 埃斯顿 | D9: 军工：军用机器人 | E9: 摘除 | F9: — | G9: — | H9: 摘除 | I9: 公司主营自动化核心部件、运动控制、工业机器人及智能制造系统，2025年报未检索到军工、国防、防务或军用特种机器人业务披露，现有机器人面向光伏、汽车、锂电、3C等工业制造场景，不能把工业机器人本体和运动控制能力直接等同于军用机器人。2025年仪器仪表制造业收入48.8801亿元、占100%，其中工业机器人及成套设备39.9683亿元、约81.77%，智能装备核心控制功能部件8.9118亿元、约18.23%，没有军工分部。旧“军用机器人”且判核心没有真实军工产品、客户和收入支撑，属于由通用机器人技术作军用想象，故摘除而非改为相关。 | J9: 南京埃斯顿自动化股份有限公司2025年年度报告 | K9: 2026-03-31 | L9: iFinD ifind_get_stock_info + ifind_get_stock_business_segmentation (as of 2026-10-27)；南京埃斯顿自动化股份有限公司2025年年度报告 | M9: https://static.cninfo.com.cn/finalpage/2026-03-31/1225059898.PDF
B10: 300627 | C10: 华测导航 | D10: 军工：卫星-卫星导航 | E10: 摘除 | F10: — | G10: — | H10: 摘除 | I10: 公司是高精度GNSS软硬件和时空信息解决方案供应商，2025年报业务板块全部面向智能建造、地理信息、农机导航、机器人和定位服务，未披露军用导航型号、军方客户、军工订单或抗干扰军用终端，不能因北斗/GNSS技术具有潜在军事用途就保留。2025年智能建造与数字施工收入12.6567亿元、占34.2152%，地信与时空智能11.5120亿元、占31.1206%，农机导航与机器人7.5184亿元、占20.3248%，时空感知与定位服务5.3044亿元、占14.3394%，无军工分部。旧“卫星-卫星导航”属于民用技术标签而非军工证据，判相关也缺乏落地支撑，故摘除。 | J10: 上海华测导航技术股份有限公司2025年年度报告 | K10: 2026-04-17 | L10: iFinD ifind_get_stock_info + ifind_get_stock_business_segmentation (as of 2026-10-27)；上海华测导航技术股份有限公司2025年年度报告 | M10: https://static.cninfo.com.cn/finalpage/2026-04-17/1225114088.PDF
B11: 600343 | C11: 航天动力 | D11: 军工：航天-航天发动机 | E11: 摘除 | F11: — | G11: — | H11: 摘除 | I11: 年报所列产品为工业往复泵、化工流程泵、大型水利泵、消防泵、工程及乘用车液力变矩器和高压电机，应用与客户主要是油田、水利、工程机械、乘用车等民用领域；输入资料也没有给出导弹、火箭或军用装备的已交付产品、军用场景及主机厂客户。2025年泵及泵系统收入3.9311亿元、液力变矩器2.1554亿元、电机1.3357亿元、流体装备0.5683亿元，制造业收入7.9904亿元、占97.0131%，未独立拆分任何军工或航天发动机收入。航天液体动力技术转化、航天六院背景和GJB体系不能替代军工落地证据，因此摘除。旧“航天-航天发动机”“导弹-动力”把技术来源误当成产品事实，必须纠正。 | J11: 航天动力2025年年度报告 | K11: 2026-03-31 | L11: iFinD ifind_get_stock_info + ifind_get_stock_business_segmentation (as of 2026-10-27)；航天动力2025年年度报告 | M11: https://www.sse.com.cn/disclosure/listedinfo/announcement/c/new/2026-03-31/600343_20260331_GHRW.pdf
B12: 600698 | C12: 湖南天雁 | D12: 军工：军工配套 | E12: 摘除 | F12: — | G12: — | H12: 摘除 | I12: 公司当前可核验产品为发动机涡轮增压器、气门以及汽车热管理、底盘和电驱系统的泵阀、执行元件，2025年报经营与客户描述集中于汽车整车配套和售后市场，没有披露具体军用型号、军工主机厂客户或军品交付金额。“国家特种涡轮增压器定点研制生产基地”等历史表述不能单独证明当期形成军工业务，也不能把普通增压器可装特种车辆作为落地证据。2025年汽车零部件收入5.1271亿元、占99.3689%，增压器4.3934亿元、气门0.5364亿元，未独立拆分军品收入。基于民用主业与证据不足应摘除；旧“军工配套”主要依赖兵装背景和泛化配套想象，必须纠正而非保留。 | J12: 湖南天雁机械股份有限公司2025年年度报告 | K12: 2026-04-25 | L12: iFinD ifind_get_stock_info + ifind_get_stock_business_segmentation (as of 2026-10-27)；湖南天雁机械股份有限公司2025年年度报告 | M12: https://www.sse.com.cn/disclosure/listedinfo/announcement/c/new/2026-04-25/600698_20260425_54WK.pdf

Sheet 概念展开
A1: 一级分类 | B1: 二级概念 | C1: 判词 | D1: 代码 | E1: 名称
A2: 军工 | B2: 弹药与特种装备 | C2: 核心 | D2: 000519 | E2: 中兵红箭
A3: 军工 | B3: 电子对抗与蓝军仿真 | C3: 核心 | D3: 000547 | E3: 航天发展
A4: 军工 | B4: 军用通信与指挥控制 | C4: 核心 | D4: 000547 | E4: 航天发展
A5: 军工 | B5: 军用通信与指挥控制 | C5: 核心 | D5: 000561 | E5: 烽火电子
A6: 军工 | B6: 雷达与预警探测 | C6: 核心 | D6: 000561 | E6: 烽火电子
A7: 军工 | B7: 航空机载系统与航电 | C7: 核心 | D7: 000561 | E7: 烽火电子
A8: 军工 | B8: 军工电源与电机电气 | C8: 核心 | D8: 000576 | E8: 甘化科工
A9: 军工 | B9: 弹药与特种装备 | C9: 核心 | D9: 000576 | E9: 甘化科工
A10: 军工 | B10: 红外光电与激光 | C10: 核心 | D10: 000576 | E10: 甘化科工
A11: 军工 | B11: 军工被动元件与连接器 | C11: 核心 | D11: 000733 | E11: 振华科技
A12: 军工 | B12: 军工芯片与特种集成电路 | C12: 核心 | D12: 000733 | E12: 振华科技
... A151: 军工 | B151: 军工芯片与特种集成电路 | C151: 核心 | D151: 688709 | E151: 成都华微

Sheet 概念统计
B2: 概念统计 · 核心/相关分布
B3: 公式引用隐藏展开表精确计数；一只股票可对应多个概念。
B4: 一级分类 | C4: 二级概念 | D4: 核心（只） | E4: 相关（只） | F4: 合计（只）
B5: 军工 | C5: 军事仿真与军工软件 | D5: =COUNTIFS('概念展开'!$A$2:$A$151,B5,'概念展开'!$B$2:$B$151,C5,'概念展开'!$C$2:$C$151,"核心") | E5: =COUNTIFS('概念展开'!$A$2:$A$151,B5,'概念展开'!$B$2:$B$151,C5,'概念展开'!$C$2:$C$151,"相关") | F5: =SUM(D5:E5)
B6: 军工 | C6: 军工材料-其他关键材料 | D6: =COUNTIFS('概念展开'!$A$2:$A$151,B6,'概念展开'!$B$2:$B$151,C6,'概念展开'!$C$2:$C$151,"核心") | E6: =COUNTIFS('概念展开'!$A$2:$A$151,B6,'概念展开'!$B$2:$B$151,C6,'概念展开'!$C$2:$C$151,"相关") | F6: =SUM(D6:E6)
B7: 军工 | C7: 军工材料-特种玻璃与石英 | D7: =COUNTIFS('概念展开'!$A$2:$A$151,B7,'概念展开'!$B$2:$B$151,C7,'概念展开'!$C$2:$C$151,"核心") | E7: =COUNTIFS('概念展开'!$A$2:$A$151,B7,'概念展开'!$B$2:$B$151,C7,'概念展开'!$C$2:$C$151,"相关") | F7: =SUM(D7:E7)
B8: 军工 | C8: 军工材料-碳纤维与复合材料 | D8: =COUNTIFS('概念展开'!$A$2:$A$151,B8,'概念展开'!$B$2:$B$151,C8,'概念展开'!$C$2:$C$151,"核心") | E8: =COUNTIFS('概念展开'!$A$2:$A$151,B8,'概念展开'!$B$2:$B$151,C8,'概念展开'!$C$2:$C$151,"相关") | F8: =SUM(D8:E8)
B9: 军工 | C9: 军工材料-超材料与隐身材料 | D9: =COUNTIFS('概念展开'!$A$2:$A$151,B9,'概念展开'!$B$2:$B$151,C9,'概念展开'!$C$2:$C$151,"核心") | E9: =COUNTIFS('概念展开'!$A$2:$A$151,B9,'概念展开'!$B$2:$B$151,C9,'概念展开'!$C$2:$C$151,"相关") | F9: =SUM(D9:E9)
B10: 军工 | C10: 军工材料-钛合金与高温合金 | D10: =COUNTIFS('概念展开'!$A$2:$A$151,B10,'概念展开'!$B$2:$B$151,C10,'概念展开'!$C$2:$C$151,"核心") | E10: =COUNTIFS('概念展开'!$A$2:$A$151,B10,'概念展开'!$B$2:$B$151,C10,'概念展开'!$C$2:$C$151,"相关") | F10: =SUM(D10:E10)
B11: 军工 | C11: 军工电源与电机电气 | D11: =COUNTIFS('概念展开'!$A$2:$A$151,B11,'概念展开'!$B$2:$B$151,C11,'概念展开'!$C$2:$C$151,"核心") | E11: =COUNTIFS('概念展开'!$A$2:$A$151,B11,'概念展开'!$B$2:$B$151,C11,'概念展开'!$C$2:$C$151,"相关") | F11: =SUM(D11:E11)
B12: 军工 | C12: 军工芯片与特种集成电路 | D12: =COUNTIFS('概念展开'!$A$2:$A$151,B12,'概念展开'!$B$2:$B$151,C12,'概念展开'!$C$2:$C$151,"核心") | E12: =COUNTIFS('概念展开'!$A$2:$A$151,B12,'概念展开'!$B$2:$B$151,C12,'概念展开'!$C$2:$C$151,"相关") | F12: =SUM(D12:E12)
B13: 军工 | C13: 军工被动元件与连接器 | D13: =COUNTIFS('概念展开'!$A$2:$A$151,B13,'概念展开'!$B$2:$B$151,C13,'概念展开'!$C$2:$C$151,"核心") | E13: =COUNTIFS('概念展开'!$A$2:$A$151,B13,'概念展开'!$B$2:$B$151,C13,'概念展开'!$C$2:$C$151,"相关") | F13: =SUM(D13:E13)
B14: 军工 | C14: 军工配套-通用零部件 | D14: =COUNTIFS('概念展开'!$A$2:$A$151,B14,'概念展开'!$B$2:$B$151,C14,'概念展开'!$C$2:$C$151,"核心") | E14: =COUNTIFS('概念展开'!$A$2:$A$151,B14,'概念展开'!$B$2:$B$151,C14,'概念展开'!$C$2:$C$151,"相关") | F14: =SUM(D14:E14)
B15: 军工 | C15: 军用导航与惯导 | D15: =COUNTIFS('概念展开'!$A$2:$A$151,B15,'概念展开'!$B$2:$B$151,C15,'概念展开'!$C$2:$C$151,"核心") | E15: =COUNTIFS('概念展开'!$A$2:$A$151,B15,'概念展开'!$B$2:$B$151,C15,'概念展开'!$C$2:$C$151,"相关") | F15: =SUM(D15:E15)
B16: 军工 | C16: 军用无人装备与机器人 | D16: =COUNTIFS('概念展开'!$A$2:$A$151,B16,'概念展开'!$B$2:$B$151,C16,'概念展开'!$C$2:$C$151,"核心") | E16: =COUNTIFS('概念展开'!$A$2:$A$151,B16,'概念展开'!$B$2:$B$151,C16,'概念展开'!$C$2:$C$151,"相关") | F16: =SUM(D16:E16)
... B35: 军工 | C35: 雷达与预警探测 | D35: =COUNTIFS('概念展开'!$A$2:$A$151,B35,'概念展开'!$B$2:$B$151,C35,'概念展开'!$C$2:$C$151,"核心") | E35: =COUNTIFS('概念展开'!$A$2:$A$151,B35,'概念展开'!$B$2:$B$151,C35,'概念展开'!$C$2:$C$151,"相关") | F35: =SUM(D35:E35)
B36: 合计（概念次数，非股票去重数） | D36: =SUM(D5:D35) | E36: =SUM(E5:E35) | F36: =SUM(F5:F35)
