Workbook

Sheet 封面
B2: 半导体概念深度清洗报告
B3: 复核日期：2026-10-27｜范围：161只｜重点：业务实质、产品层级、商业订单与二次边界复审
B6: 复核股票（只） | C6: =COUNTA('清洗总表'!$B$5:$B$165)
B7: 保留半导体（只） | C7: =COUNTA('半导体'!$B$5:$B$157)
B8: 核心判词（只） | C8: =COUNTIF('半导体'!$H$5:$H$157,"核心")
B9: 相关判词（只） | C9: =COUNTIF('半导体'!$H$5:$H$157,"相关")
B10: 纠错动作（只） | C10: =COUNTIF('清洗总表'!$E$5:$E$165,"纠错")
B11: 完全摘除（只） | C11: =COUNTA('摘除清单'!$B$5:$B$12)
B15: 工作表索引
B16: 清洗总表 | C16: 161只旧概念、新概念、动作、判词、详细理由和证据
B17: 半导体 | C17: 153只清洗后半导体公司
B18: 摘除清单 | C18: 8只通用业务或半导体证据不足公司
B19: 概念统计 | C19: 43个实际使用的二级概念
B23: 核心：半导体是明确主营、重要收入来源，或已有规模化核心产品；相关：有真实半导体产品、订单、客户验证或交付，但早期、低占比、未拆分或其他行业为主。
B24: 摘除：只有通用产品潜在用途、下游模组外购芯片、锂电或光伏设备联想、未落地投资；模组不写成芯片设计，分销不写成芯片，参股不等于自身经营。
B25: 二次复审：奥普光电按真实参股恢复相关，致尚科技按半导体抛光设备恢复相关，合盛硅业按量产碳化硅衬底恢复相关；同步修正多家公司概念与数字口径。
B26: 主营与2025分部：iFinD ifind_get_stock_info、ifind_get_stock_business_segmentation（2026-10-27）；逐股公告与证据见Source列。

Sheet 清洗总表
B2: 半导体 · 161只逐项复核
B3: 逐股核对真实产品、订单、客户、交付、运营与股权；区分半导体、传统军工航天和潜在联想。
B4: 代码 | C4: 名称 | D4: 旧半导体概念 | E4: 动作 | F4: 新一级分类 | G4: 新概念 | H4: 判词 | I4: 详细理由 | J4: 证据名称 | K4: 证据日期 | L4: Source Name | M4: Source URL
B5: 000021 | C5: 深科技 | D5: 半导体：存储封测 | E5: 纠错 | F5: 半导体 | G5: 封装测试 | H5: 核心 | I5: 公司真实半导体业务是存储芯片封装测试及高端制造中的相关制造服务，具备存储封测量产与客户交付基础，并非存储晶圆设计或存储颗粒制造。iFinD二〇二五年分部显示，存储半导体收入四十点九一亿元，占营业收入百分之二十五点九八；高端制造收入八十五点三五亿元，占百分之五十四点二零，后者还含其他电子制造，不能全部并入半导体口径。收入规模和独立分部足以支持核心定级，但必须保留混合业务边界。旧标签若把公司泛化为芯片设计、晶圆制造或全部高端制造均属半导体，均应纠正为封装测试，仅以已披露的存储封测主业作为归类依据。 | J5: 深科技：2025年年度报告 | K5: 2026-04-29 | L5: iFinD ifind_get_stock_info + ifind_get_stock_business_segmentation (as of 2026-10-27)；深科技：2025年年度报告 | M5: https://money.finance.sina.com.cn/corp/view/vCB_AllBulletinDetail.php?stockid=000021&id=12247178
B6: 000032 | C6: 深桑达A | D6: 半导体：半导体洁净室 | E6: 纠错 | F6: 半导体 | G6: 洁净室与厂务工程 | H6: 核心 | I6: 公司通过高科技产业工程业务提供洁净室、机电安装和厂务系统建设，年报披露的真实项目覆盖半导体等高科技厂房，因此对应的是工程服务而非半导体设备或芯片制造。iFinD二〇二五年洁净室相关整体收入三百九十八点四五亿元，占营业收入百分之八十一点零四，专业化产品收入四十七点零八亿元，占百分之九点五七；但洁净室下游还包括生物医药、算力、新能源及其他电子行业，不能把上述收入全算作半导体。考虑业务体量、独立分部及真实半导体项目经验，定为核心具有依据，同时须明确这是混合下游口径。旧标签若写成半导体工艺设备、洁净设备制造或纯半导体收入，应统一纠正为洁净室与厂务工程。 | J6: 深桑达A：2025年年度报告 | K6: 2026-04-28 | L6: iFinD ifind_get_stock_info + ifind_get_stock_business_segmentation (as of 2026-10-27)；深桑达A：2025年年度报告 | M6: http://money.finance.sina.com.cn/corp/view/vCB_AllBulletinDetail.php?stockid=000032&id=12226663
B7: 000062 | C7: 深圳华强 | D7: 半导体：存储分销 | E7: 纠错 | F7: 半导体 | G7: 半导体分销与供应链 | H7: 核心 | I7: 公司的真实定位是电子元器件授权分销、交易及供应链服务，向客户销售存储、处理器等器件并提供技术与物流支持，不从事这些芯片的设计或晶圆制造。iFinD二〇二五年电子元器件交易收入二百四十点八零亿元，占营业收入百分之九十六点六七，交易服务收入五点五六亿元，占百分之二点二三，存储产品未单独披露收入，故不能把全部交易额机械归入某一芯片品类。鉴于分销是收入绝对主体且规模突出，可列半导体核心分销标的，但核心是主营重要性和规模判断，不代表自研芯片。旧标签若出现芯片设计、存储芯片制造或把分销收入等同于半导体产品收入，均应纠正为半导体分销与供应链。 | J7: 深圳华强：2025年年度报告摘要 | K7: 2026-03-27 | L7: iFinD ifind_get_stock_info + ifind_get_stock_business_segmentation (as of 2026-10-27)；深圳华强：2025年年度报告摘要 | M7: http://static.cninfo.com.cn/finalpage/2026-03-27/1225034926.PDF
B8: 000063 | C8: 中兴通讯 | D8: 半导体：算力芯片 | E8: 纠错 | F8: 半导体 | G8: 芯片设计-CPU/GPU/AI计算 | H8: 相关 | I8: 公司具备自研芯片能力，真实产品边界包括服务器及数据中心相关的中央处理器、人工智能计算等芯片研发，并服务于自身通信和算力产品体系；这与单纯采购芯片组装服务器不同，但也不能把整机或方案收入当作芯片收入。iFinD二〇二五年运营商网络收入六百二十八点五七亿元，占百分之四十六点九四，政企业务三百七十二点二二亿元，占百分之二十七点八零，消费者业务三百三十八点一六亿元，占百分之二十五点二六，芯片没有独立收入分部。半导体能力真实存在，但从上市公司收入结构看仍依附于通信设备与算力系统主业，因此定为相关而非核心。旧标签若把整个公司归为AI芯片核心股、晶圆制造或虚构独立芯片收入，均需纠正。 | J8: 中兴通讯：2025年年度报告 | K8: 2026-03-07 | L8: iFinD ifind_get_stock_info + ifind_get_stock_business_segmentation (as of 2026-10-27)；中兴通讯：2025年年度报告 | M8: https://www.zte.com.cn/content/dam/zte-site/investorrelations/cn_annual_report/2025%E5%B9%B4%E5%B9%B4%E5%BA%A6%E6%8A%A5%E5%91%8A.pdf
B9: 000066 | C9: 中国长城 | D9: 半导体：算力芯片 | E9: 纠错 | F9: 半导体 | G9: 半导体股权与产业投资 | H9: 相关 | I9: 公司与半导体的真实联系主要是持有飞腾等产业链企业股权，整机产品采购或搭载飞腾处理器并不等同于中国长城自身设计中央处理器。iFinD二〇二五年网络安全与信息化收入一百一十九点零五亿元，占营业收入百分之七十五点三一，高新电子收入三十点八七亿元，占百分之十九点五三，芯片未形成独立经营分部；飞腾收入二十五点三四亿元属于参股公司，不能并入上市公司半导体收入。基于股权联系而非自身芯片产品收入，定为相关更恰当。旧标签若写芯片设计、国产CPU制造或把飞腾全部业绩并表，均应纠正为半导体股权与产业投资，并保留整机业务与参股芯片企业的边界。 | J9: 中国长城：2025年年度报告 | K9: 2026-04-29 | L9: iFinD ifind_get_stock_info + ifind_get_stock_business_segmentation (as of 2026-10-27)；中国长城：2025年年度报告 | M9: https://money.finance.sina.com.cn/corp/view/vCB_AllBulletinDetail.php?stockid=000066&id=12262295
B10: 000551 | C10: 创元科技 | D10: 半导体：半导体洁净室 | E10: 纠错 | F10: 半导体 | G10: 洁净室与厂务工程 | H10: 相关 | I10: 公司洁净环保板块提供洁净室工程、空气净化及相关系统服务，具备高科技洁净环境建设能力，可按已有半导体项目经验归入厂务工程，而不是半导体工艺设备或芯片制造。iFinD二〇二五年洁净设备及工程收入二十点七四亿元，占营业收入百分之四十九点一二，是重要业务板块，但半导体下游收入未单独拆分，不能把该分部全部认定为半导体收入，其他洁净应用仍须排除。考虑业务具有真实关联、收入体量重要但终端口径混合且缺乏半导体独立规模证据，定为相关而非核心。旧标签若概括为半导体设备核心企业、洁净设备全部用于晶圆厂或虚构芯片收入，应纠正为洁净室与厂务工程。 | J10: 创元科技：2025年年度报告摘要 | K10: 2026-04-08 | L10: iFinD ifind_get_stock_info + ifind_get_stock_business_segmentation (as of 2026-10-27)；创元科技：2025年年度报告摘要 | M10: https://www.000551.cn/uploads/admin/202604/69d5ad4e77b58.pdf
B11: 001287 | C11: 中电港 | D11: 半导体：存储分销 | E11: 纠错 | F11: 半导体 | G11: 半导体分销与供应链 | H11: 核心 | I11: 公司主营电子元器件分销和供应链协同服务，真实业务包括存储器、处理器等产品的销售、技术支持与交付，不拥有相应芯片设计或晶圆制造收入。iFinD二〇二五年分销业务约占营业收入百分之九十九点九零，其中存储器收入二百五十一点五零亿元，占百分之三十八点三八，处理器收入一百八十八点六五亿元，占百分之二十八点七九，半导体分销的主营地位和规模均有直接数据支撑，因此列为核心。这里的核心仅指分销产业环节，不可延伸为自研存储或处理器。旧标签若写芯片设计、存储晶圆制造、CPU制造，或遗漏分销属性而按产品名称归入设计端，均应纠正为半导体分销与供应链。 | J11: 中电港：2025年年度报告 | K11: 2026-04-28 | L11: iFinD ifind_get_stock_info + ifind_get_stock_business_segmentation (as of 2026-10-27)；中电港：2025年年度报告 | M11: http://file.finance.sina.com.cn/211.154.219.97:9494/MRGG/CNSESZ_STOCK/2026/2026-4/2026-04-28/12211650.PDF
B12: 001309 | C12: 德明利 | D12: 半导体：存储模组 | E12: 纠错 | F12: 半导体 | G12: 存储模组与系统、芯片设计-存储主控与接口 | H12: 核心 | I12: 公司真实产品包括固态硬盘、嵌入式存储、移动存储和内存条，并已有自研存储主控芯片量产应用；因此兼具存储模组与主控设计属性，但不等于开展NAND或DRAM存储晶圆设计制造。iFinD二〇二五年固态硬盘收入四十五点八二亿元，占百分之四十二点四六，嵌入式存储三十六点六三亿元，占百分之三十三点九五，移动存储十四点七四亿元，占百分之十三点六六，内存条十点五一亿元，占百分之九点七四，自研主控收入未单列。模组收入占绝对主体，核心定级明确，但主控标签仅对应真实设计能力。旧标签若写成存储芯片、存储晶圆或把模组全部视作芯片设计收入，必须按上述边界纠正。 | J12: 德明利：2025年年度报告 | K12: 2026-02-28 | L12: iFinD ifind_get_stock_info + ifind_get_stock_business_segmentation (as of 2026-10-27)；德明利：2025年年度报告 | M12: https://money.finance.sina.com.cn/corp/view/vCB_AllBulletinDetail.php?stockid=001309&id=11976038
B13: 002119 | C13: 康强电子 | D13: 半导体：半导体材料 | E13: 纠错 | F13: 半导体 | G13: 半导体材料-封装材料 | H13: 核心 | I13: 公司真实产品为半导体封装用引线框架和键合丝，分别承担芯片封装中的承载互连与电气连接功能，属于封装关键材料，不是封装设备、芯片设计或晶圆制造。iFinD二〇二五年引线框架收入十三点二二亿元，占营业收入百分之六十点一二，键合丝收入五点四四亿元，占百分之二十四点七四，两项合计占绝大部分收入，产品用途和收入结构均直接支持半导体核心定级。引线框架、键合丝内部还可能有不同规格与应用，但不改变其封装材料属性，亦不应虚构为前道材料。旧标签若把公司归入封装测试服务、半导体设备或泛化为全部金属材料，应纠正为半导体封装材料，并以两项实际产品收入为边界。 | J13: 康强电子：2025年年度报告 | K13: 2026-03-31 | L13: iFinD ifind_get_stock_info + ifind_get_stock_business_segmentation (as of 2026-10-27)；康强电子：2025年年度报告 | M13: https://money.finance.sina.com.cn/corp/view/vCB_AllBulletinDetail.php?stockid=002119&id=12039120
B14: 002129 | C14: TCL中环 | D14: 半导体：半导体材料 | E14: 纠错 | F14: 半导体 | G14: 半导体材料-硅片与硅部件 | H14: 核心 | I14: 公司半导体业务的真实产品是半导体硅片等硅材料，服务集成电路及功率器件等制造环节；光伏硅片虽然也属硅材料，却不能与半导体硅片混为同一终端口径。iFinD二〇二五年半导体材料收入五十七点零七亿元，占营业收入百分之十九点六四，光伏硅片收入一百二十二点三八亿元，占百分之四十二点一三，组件收入九十三点二四亿元，占百分之三十二点一零，显示公司仍是混合业务结构。半导体材料已达到重要收入规模，故可由一般相关提升为核心，但核心不代表全部营收来自半导体。旧标签若只列光伏、把全部硅片收入归入半导体，或误写为芯片制造，应纠正为半导体硅片与硅部件并明确光伏边界。 | J14: TCL中环：2025年年度报告 | K14: 2026-03-24 | L14: iFinD ifind_get_stock_info + ifind_get_stock_business_segmentation (as of 2026-10-27)；TCL中环：2025年年度报告 | M14: https://money.finance.sina.com.cn/corp/view/vCB_AllBulletinDetail.php?stockid=002129&id=12015974
B15: 002156 | C15: 通富微电 | D15: 半导体：封测 | E15: 纠错 | F15: 半导体 | G15: 封装测试 | H15: 核心 | I15: 公司真实业务是为集成电路企业提供封装与测试代工服务，覆盖多种封装形式和先进封装制造环节，不承担客户芯片产品设计，也不等同于上游晶圆制造。iFinD二〇二五年集成电路封装测试收入二百七十二点四八亿元，占营业收入百分之九十七点五九，主营集中度和收入规模均十分明确，半导体核心定级不存在依赖概念推演的问题。少量其他业务不能扩大解释为芯片设计，客户产品涉及中央处理器或人工智能芯片时，也应只确认公司提供封测服务。旧标签若出现芯片设计、晶圆代工、半导体设备，或把客户芯片收入归为公司产品收入，均应纠正为封装测试，并以独立封测分部收入作为归类依据。 | J15: 通富微电：2025年年度报告 | K15: 2026-04-17 | L15: iFinD ifind_get_stock_info + ifind_get_stock_business_segmentation (as of 2026-10-27)；通富微电：2025年年度报告 | M15: https://static.cninfo.com.cn/finalpage/2026-04-17/1225112762.PDF
... B165: 600745 | C165: 闻泰科技 | D165: 半导体：功率半导体 | E165: 纠错 | F165: 半导体 | G165: 芯片设计-功率半导体、晶圆制造与IDM | H165: 核心 | I165: 公司半导体业务以安世半导体为主体，真实产品包括二极管、双极性晶体管、ESD保护器件、MOSFET、GaN FET、SiC二极管、IGBT以及模拟和逻辑IC，具备设计、晶圆制造、封装测试一体的IDM属性，不只是功率模块组装厂。2025年半导体产品收入133.4755亿元，占总收入约312.5253亿元的42.71%；半导体行业分部收入136.1616亿元，产品集成业务收入175.2470亿元，占56.07%，两者不能混算。尽管当年产品集成收入更大，半导体产品收入绝对规模巨大且构成核心主业，故仍定为半导体核心。此次纠错保留功率半导体并补充晶圆制造与IDM，同时明确功率器件之外还有模拟、逻辑等混合产品边界。 | J165: 闻泰科技：2025年年度报告 | K165: 2026-04-30 | L165: iFinD ifind_get_stock_info + ifind_get_stock_business_segmentation (as of 2026-10-27)；闻泰科技：2025年年度报告 | M165: http://money.finance.sina.com.cn/corp/view/vCB_AllBulletinDetail.php?stockid=600745&id=12289135

Sheet 半导体
B2: 半导体 · 清洗后158只股池
B3: 核心111只、相关42只；按卫星、火箭、地面系统、运营服务和产业配套细化为43个二级概念。
B4: 代码 | C4: 名称 | D4: 旧半导体概念 | E4: 动作 | F4: 新一级分类 | G4: 新概念 | H4: 判词 | I4: 详细理由 | J4: 证据名称 | K4: 证据日期 | L4: Source Name | M4: Source URL
B5: 000021 | C5: 深科技 | D5: 半导体：存储封测 | E5: 纠错 | F5: 半导体 | G5: 封装测试 | H5: 核心 | I5: 公司真实半导体业务是存储芯片封装测试及高端制造中的相关制造服务，具备存储封测量产与客户交付基础，并非存储晶圆设计或存储颗粒制造。iFinD二〇二五年分部显示，存储半导体收入四十点九一亿元，占营业收入百分之二十五点九八；高端制造收入八十五点三五亿元，占百分之五十四点二零，后者还含其他电子制造，不能全部并入半导体口径。收入规模和独立分部足以支持核心定级，但必须保留混合业务边界。旧标签若把公司泛化为芯片设计、晶圆制造或全部高端制造均属半导体，均应纠正为封装测试，仅以已披露的存储封测主业作为归类依据。 | J5: 深科技：2025年年度报告 | K5: 2026-04-29 | L5: iFinD ifind_get_stock_info + ifind_get_stock_business_segmentation (as of 2026-10-27)；深科技：2025年年度报告 | M5: https://money.finance.sina.com.cn/corp/view/vCB_AllBulletinDetail.php?stockid=000021&id=12247178
B6: 000032 | C6: 深桑达A | D6: 半导体：半导体洁净室 | E6: 纠错 | F6: 半导体 | G6: 洁净室与厂务工程 | H6: 核心 | I6: 公司通过高科技产业工程业务提供洁净室、机电安装和厂务系统建设，年报披露的真实项目覆盖半导体等高科技厂房，因此对应的是工程服务而非半导体设备或芯片制造。iFinD二〇二五年洁净室相关整体收入三百九十八点四五亿元，占营业收入百分之八十一点零四，专业化产品收入四十七点零八亿元，占百分之九点五七；但洁净室下游还包括生物医药、算力、新能源及其他电子行业，不能把上述收入全算作半导体。考虑业务体量、独立分部及真实半导体项目经验，定为核心具有依据，同时须明确这是混合下游口径。旧标签若写成半导体工艺设备、洁净设备制造或纯半导体收入，应统一纠正为洁净室与厂务工程。 | J6: 深桑达A：2025年年度报告 | K6: 2026-04-28 | L6: iFinD ifind_get_stock_info + ifind_get_stock_business_segmentation (as of 2026-10-27)；深桑达A：2025年年度报告 | M6: http://money.finance.sina.com.cn/corp/view/vCB_AllBulletinDetail.php?stockid=000032&id=12226663
B7: 000062 | C7: 深圳华强 | D7: 半导体：存储分销 | E7: 纠错 | F7: 半导体 | G7: 半导体分销与供应链 | H7: 核心 | I7: 公司的真实定位是电子元器件授权分销、交易及供应链服务，向客户销售存储、处理器等器件并提供技术与物流支持，不从事这些芯片的设计或晶圆制造。iFinD二〇二五年电子元器件交易收入二百四十点八零亿元，占营业收入百分之九十六点六七，交易服务收入五点五六亿元，占百分之二点二三，存储产品未单独披露收入，故不能把全部交易额机械归入某一芯片品类。鉴于分销是收入绝对主体且规模突出，可列半导体核心分销标的，但核心是主营重要性和规模判断，不代表自研芯片。旧标签若出现芯片设计、存储芯片制造或把分销收入等同于半导体产品收入，均应纠正为半导体分销与供应链。 | J7: 深圳华强：2025年年度报告摘要 | K7: 2026-03-27 | L7: iFinD ifind_get_stock_info + ifind_get_stock_business_segmentation (as of 2026-10-27)；深圳华强：2025年年度报告摘要 | M7: http://static.cninfo.com.cn/finalpage/2026-03-27/1225034926.PDF
B8: 000063 | C8: 中兴通讯 | D8: 半导体：算力芯片 | E8: 纠错 | F8: 半导体 | G8: 芯片设计-CPU/GPU/AI计算 | H8: 相关 | I8: 公司具备自研芯片能力，真实产品边界包括服务器及数据中心相关的中央处理器、人工智能计算等芯片研发，并服务于自身通信和算力产品体系；这与单纯采购芯片组装服务器不同，但也不能把整机或方案收入当作芯片收入。iFinD二〇二五年运营商网络收入六百二十八点五七亿元，占百分之四十六点九四，政企业务三百七十二点二二亿元，占百分之二十七点八零，消费者业务三百三十八点一六亿元，占百分之二十五点二六，芯片没有独立收入分部。半导体能力真实存在，但从上市公司收入结构看仍依附于通信设备与算力系统主业，因此定为相关而非核心。旧标签若把整个公司归为AI芯片核心股、晶圆制造或虚构独立芯片收入，均需纠正。 | J8: 中兴通讯：2025年年度报告 | K8: 2026-03-07 | L8: iFinD ifind_get_stock_info + ifind_get_stock_business_segmentation (as of 2026-10-27)；中兴通讯：2025年年度报告 | M8: https://www.zte.com.cn/content/dam/zte-site/investorrelations/cn_annual_report/2025%E5%B9%B4%E5%B9%B4%E5%BA%A6%E6%8A%A5%E5%91%8A.pdf
B9: 000066 | C9: 中国长城 | D9: 半导体：算力芯片 | E9: 纠错 | F9: 半导体 | G9: 半导体股权与产业投资 | H9: 相关 | I9: 公司与半导体的真实联系主要是持有飞腾等产业链企业股权，整机产品采购或搭载飞腾处理器并不等同于中国长城自身设计中央处理器。iFinD二〇二五年网络安全与信息化收入一百一十九点零五亿元，占营业收入百分之七十五点三一，高新电子收入三十点八七亿元，占百分之十九点五三，芯片未形成独立经营分部；飞腾收入二十五点三四亿元属于参股公司，不能并入上市公司半导体收入。基于股权联系而非自身芯片产品收入，定为相关更恰当。旧标签若写芯片设计、国产CPU制造或把飞腾全部业绩并表，均应纠正为半导体股权与产业投资，并保留整机业务与参股芯片企业的边界。 | J9: 中国长城：2025年年度报告 | K9: 2026-04-29 | L9: iFinD ifind_get_stock_info + ifind_get_stock_business_segmentation (as of 2026-10-27)；中国长城：2025年年度报告 | M9: https://money.finance.sina.com.cn/corp/view/vCB_AllBulletinDetail.php?stockid=000066&id=12262295
B10: 000551 | C10: 创元科技 | D10: 半导体：半导体洁净室 | E10: 纠错 | F10: 半导体 | G10: 洁净室与厂务工程 | H10: 相关 | I10: 公司洁净环保板块提供洁净室工程、空气净化及相关系统服务，具备高科技洁净环境建设能力，可按已有半导体项目经验归入厂务工程，而不是半导体工艺设备或芯片制造。iFinD二〇二五年洁净设备及工程收入二十点七四亿元，占营业收入百分之四十九点一二，是重要业务板块，但半导体下游收入未单独拆分，不能把该分部全部认定为半导体收入，其他洁净应用仍须排除。考虑业务具有真实关联、收入体量重要但终端口径混合且缺乏半导体独立规模证据，定为相关而非核心。旧标签若概括为半导体设备核心企业、洁净设备全部用于晶圆厂或虚构芯片收入，应纠正为洁净室与厂务工程。 | J10: 创元科技：2025年年度报告摘要 | K10: 2026-04-08 | L10: iFinD ifind_get_stock_info + ifind_get_stock_business_segmentation (as of 2026-10-27)；创元科技：2025年年度报告摘要 | M10: https://www.000551.cn/uploads/admin/202604/69d5ad4e77b58.pdf
B11: 001287 | C11: 中电港 | D11: 半导体：存储分销 | E11: 纠错 | F11: 半导体 | G11: 半导体分销与供应链 | H11: 核心 | I11: 公司主营电子元器件分销和供应链协同服务，真实业务包括存储器、处理器等产品的销售、技术支持与交付，不拥有相应芯片设计或晶圆制造收入。iFinD二〇二五年分销业务约占营业收入百分之九十九点九零，其中存储器收入二百五十一点五零亿元，占百分之三十八点三八，处理器收入一百八十八点六五亿元，占百分之二十八点七九，半导体分销的主营地位和规模均有直接数据支撑，因此列为核心。这里的核心仅指分销产业环节，不可延伸为自研存储或处理器。旧标签若写芯片设计、存储晶圆制造、CPU制造，或遗漏分销属性而按产品名称归入设计端，均应纠正为半导体分销与供应链。 | J11: 中电港：2025年年度报告 | K11: 2026-04-28 | L11: iFinD ifind_get_stock_info + ifind_get_stock_business_segmentation (as of 2026-10-27)；中电港：2025年年度报告 | M11: http://file.finance.sina.com.cn/211.154.219.97:9494/MRGG/CNSESZ_STOCK/2026/2026-4/2026-04-28/12211650.PDF
B12: 001309 | C12: 德明利 | D12: 半导体：存储模组 | E12: 纠错 | F12: 半导体 | G12: 存储模组与系统、芯片设计-存储主控与接口 | H12: 核心 | I12: 公司真实产品包括固态硬盘、嵌入式存储、移动存储和内存条，并已有自研存储主控芯片量产应用；因此兼具存储模组与主控设计属性，但不等于开展NAND或DRAM存储晶圆设计制造。iFinD二〇二五年固态硬盘收入四十五点八二亿元，占百分之四十二点四六，嵌入式存储三十六点六三亿元，占百分之三十三点九五，移动存储十四点七四亿元，占百分之十三点六六，内存条十点五一亿元，占百分之九点七四，自研主控收入未单列。模组收入占绝对主体，核心定级明确，但主控标签仅对应真实设计能力。旧标签若写成存储芯片、存储晶圆或把模组全部视作芯片设计收入，必须按上述边界纠正。 | J12: 德明利：2025年年度报告 | K12: 2026-02-28 | L12: iFinD ifind_get_stock_info + ifind_get_stock_business_segmentation (as of 2026-10-27)；德明利：2025年年度报告 | M12: https://money.finance.sina.com.cn/corp/view/vCB_AllBulletinDetail.php?stockid=001309&id=11976038
B13: 002119 | C13: 康强电子 | D13: 半导体：半导体材料 | E13: 纠错 | F13: 半导体 | G13: 半导体材料-封装材料 | H13: 核心 | I13: 公司真实产品为半导体封装用引线框架和键合丝，分别承担芯片封装中的承载互连与电气连接功能，属于封装关键材料，不是封装设备、芯片设计或晶圆制造。iFinD二〇二五年引线框架收入十三点二二亿元，占营业收入百分之六十点一二，键合丝收入五点四四亿元，占百分之二十四点七四，两项合计占绝大部分收入，产品用途和收入结构均直接支持半导体核心定级。引线框架、键合丝内部还可能有不同规格与应用，但不改变其封装材料属性，亦不应虚构为前道材料。旧标签若把公司归入封装测试服务、半导体设备或泛化为全部金属材料，应纠正为半导体封装材料，并以两项实际产品收入为边界。 | J13: 康强电子：2025年年度报告 | K13: 2026-03-31 | L13: iFinD ifind_get_stock_info + ifind_get_stock_business_segmentation (as of 2026-10-27)；康强电子：2025年年度报告 | M13: https://money.finance.sina.com.cn/corp/view/vCB_AllBulletinDetail.php?stockid=002119&id=12039120
B14: 002129 | C14: TCL中环 | D14: 半导体：半导体材料 | E14: 纠错 | F14: 半导体 | G14: 半导体材料-硅片与硅部件 | H14: 核心 | I14: 公司半导体业务的真实产品是半导体硅片等硅材料，服务集成电路及功率器件等制造环节；光伏硅片虽然也属硅材料，却不能与半导体硅片混为同一终端口径。iFinD二〇二五年半导体材料收入五十七点零七亿元，占营业收入百分之十九点六四，光伏硅片收入一百二十二点三八亿元，占百分之四十二点一三，组件收入九十三点二四亿元，占百分之三十二点一零，显示公司仍是混合业务结构。半导体材料已达到重要收入规模，故可由一般相关提升为核心，但核心不代表全部营收来自半导体。旧标签若只列光伏、把全部硅片收入归入半导体，或误写为芯片制造，应纠正为半导体硅片与硅部件并明确光伏边界。 | J14: TCL中环：2025年年度报告 | K14: 2026-03-24 | L14: iFinD ifind_get_stock_info + ifind_get_stock_business_segmentation (as of 2026-10-27)；TCL中环：2025年年度报告 | M14: https://money.finance.sina.com.cn/corp/view/vCB_AllBulletinDetail.php?stockid=002129&id=12015974
B15: 002156 | C15: 通富微电 | D15: 半导体：封测 | E15: 纠错 | F15: 半导体 | G15: 封装测试 | H15: 核心 | I15: 公司真实业务是为集成电路企业提供封装与测试代工服务，覆盖多种封装形式和先进封装制造环节，不承担客户芯片产品设计，也不等同于上游晶圆制造。iFinD二〇二五年集成电路封装测试收入二百七十二点四八亿元，占营业收入百分之九十七点五九，主营集中度和收入规模均十分明确，半导体核心定级不存在依赖概念推演的问题。少量其他业务不能扩大解释为芯片设计，客户产品涉及中央处理器或人工智能芯片时，也应只确认公司提供封测服务。旧标签若出现芯片设计、晶圆代工、半导体设备，或把客户芯片收入归为公司产品收入，均应纠正为封装测试，并以独立封测分部收入作为归类依据。 | J15: 通富微电：2025年年度报告 | K15: 2026-04-17 | L15: iFinD ifind_get_stock_info + ifind_get_stock_business_segmentation (as of 2026-10-27)；通富微电：2025年年度报告 | M15: https://static.cninfo.com.cn/finalpage/2026-04-17/1225112762.PDF
... B157: 600745 | C157: 闻泰科技 | D157: 半导体：功率半导体 | E157: 纠错 | F157: 半导体 | G157: 芯片设计-功率半导体、晶圆制造与IDM | H157: 核心 | I157: 公司半导体业务以安世半导体为主体，真实产品包括二极管、双极性晶体管、ESD保护器件、MOSFET、GaN FET、SiC二极管、IGBT以及模拟和逻辑IC，具备设计、晶圆制造、封装测试一体的IDM属性，不只是功率模块组装厂。2025年半导体产品收入133.4755亿元，占总收入约312.5253亿元的42.71%；半导体行业分部收入136.1616亿元，产品集成业务收入175.2470亿元，占56.07%，两者不能混算。尽管当年产品集成收入更大，半导体产品收入绝对规模巨大且构成核心主业，故仍定为半导体核心。此次纠错保留功率半导体并补充晶圆制造与IDM，同时明确功率器件之外还有模拟、逻辑等混合产品边界。 | J157: 闻泰科技：2025年年度报告 | K157: 2026-04-30 | L157: iFinD ifind_get_stock_info + ifind_get_stock_business_segmentation (as of 2026-10-27)；闻泰科技：2025年年度报告 | M157: http://money.finance.sina.com.cn/corp/view/vCB_AllBulletinDetail.php?stockid=600745&id=12289135

Sheet 摘除清单
B2: 摘除清单 · 8只证据不足或业务错标
B3: 通用产品潜在用途、央企背景、SpaceX预期、太空光伏设备及未决投资不直接计入半导体。
B4: 代码 | C4: 名称 | D4: 旧半导体概念 | E4: 动作 | F4: 新一级分类 | G4: 新概念 | H4: 判词 | I4: 详细理由 | J4: 证据名称 | K4: 证据日期 | L4: Source Name | M4: Source URL
B5: 002881 | C5: 美格智能 | D5: 半导体：端侧ai芯片 | E5: 摘除 | F5: — | G5: — | H5: 摘除 | I5: 公司真实产品是无线通信模组、智能模组及物联网解决方案，高算力模组内部采用外部CPU、GPU或NPU平台并提供软硬件集成，不等于公司自行设计端侧AI芯片或SoC。iFinD二〇二五年无线模组及解决方案收入三十六点零九亿元，占营业收入百分之九十六点三一，未披露任何独立芯片设计或半导体产品收入，年报产品口径也无法支持将模组销售额转为芯片收入。模组高算力、端侧AI应用和客户场景只能证明下游使用芯片，不能跨越芯片设计与模组集成的经营边界，因此旧端侧AI芯片或SoC设计标签缺乏真实产品依据，应予摘除。若未来正式披露自研芯片、流片量产和销售收入，再依据具体芯片类型重新建立标签。 | J5: 美格智能：2025年年度报告 | K5: 2026-03-31 | L5: iFinD ifind_get_stock_info + ifind_get_stock_business_segmentation (as of 2026-10-27)；美格智能：2025年年度报告 | M5: https://money.finance.sina.com.cn/corp/view/vCB_AllBulletinDetail.php?stockid=002881&id=12044935
B6: 300293 | C6: 蓝英装备 | D6: 半导体：半导体设备 | E6: 摘除 | F6: — | G6: — | H6: 摘除 | I6: 公司2025年披露的主营是工业清洗系统及表面处理、智能装备制造，真实应用集中在医疗、机械电子、汽车、新能源、精密光学和高精纯部件等领域。工业清洗及表面处理收入11.7260亿元，占总收入97.5463%，但这一高占比只能证明通用清洗主业规模，年报未给出晶圆清洗设备、半导体制程客户、订单或半导体收入的可核验拆分，不能把高精纯或精密光学用途外推为半导体设备收入。边界上，工业清洗与晶圆去胶、湿法清洗在工艺、客户和验证体系上并不等同，即使技术存在潜在迁移可能，也不满足本分类真实产品和供货证据要求。此次纠错对旧“半导体设备”及原相关定级一并摘除，pairs置空，避免以光刻机或高精纯概念替代正式经营证据。 | J6: 蓝英装备：2025年年度报告 | K6: 2026-04-28 | L6: iFinD ifind_get_stock_info + ifind_get_stock_business_segmentation (as of 2026-10-27)；蓝英装备：2025年年度报告 | M6: https://money.finance.sina.com.cn/corp/view/vCB_AllBulletinDetail.php?stockid=300293&id=12228803
B7: 300457 | C7: 赢合科技 | D7: 半导体：半导体设备 | E7: 摘除 | F7: — | G7: — | H7: 摘除 | I7: 公司真实产品是锂电极片涂布、辊压、分切、卷绕、叠片、PACK及MES等生产装备，并经营电子烟相关业务，年报没有形成可核验的半导体设备产品、客户、订单或收入。2025年锂电专用设备收入64.2715亿元，占总收入68.05%，其他业务收入30.1806亿元，总收入94.4522亿元，收入结构清楚指向锂电而非半导体。边界上，固态电池仍是电化学电池技术路线，其涂布、卷绕和叠片设备不能因名称中的“固态”或精密制造属性被改挂半导体设备；其他收入为混合口径，也不可拆出并无公告依据的半导体收入。此次纠错否定旧理由“锂电设备为主、半导体为延伸”的外推，将旧半导体设备标签和边缘定级一并摘除，pairs置空。 | J7: 赢合科技：2025年年度报告 | K7: 2026-03-28 | L7: iFinD ifind_get_stock_info + ifind_get_stock_business_segmentation (as of 2026-10-27)；赢合科技：2025年年度报告 | M7: https://money.finance.sina.com.cn/corp/view/vCB_AllBulletinDetail.php?stockid=300457&id=12030602
B8: 300638 | C8: 广和通 | D8: 半导体：端侧ai芯片 | E8: 摘除 | F8: — | G8: — | H8: 摘除 | I8: 公司真实产品是数传模组、智能模组、AI模组及无线通信解决方案，模组基于高通、联发科、爱芯等外部芯片平台进行集成设计，并未据此形成自研端侧AI芯片主业。2025年通讯模块收入64.4625亿元，解决方案收入4.7586亿元，总收入69.8761亿元，无线通信模组及应用业务占99.7399%；AI模组批量出货证明的是模组产品商业化，不等于芯片设计收入。边界上，通信模组与半导体芯片在产业环节、知识产权和收入确认上不可混同，本分类白名单也没有“通信模组”，不能为了保留标的而错挂SoC或端侧AI芯片。此次纠错删除旧“端侧ai芯片”及相关定级，pairs置空；这不否定其AI模组业务，只纠正把模组集成商当作半导体芯片设计公司的分类错误。 | J8: 广和通：2025年年度报告 | K8: 2026-03-31 | L8: iFinD ifind_get_stock_info + ifind_get_stock_business_segmentation (as of 2026-10-27)；广和通：2025年年度报告 | M8: https://money.finance.sina.com.cn/corp/view/vCB_AllBulletinDetail.php?stockid=300638&id=12046744
B9: 301226 | C9: 祥明智能 | D9: 半导体：半导体设备 | E9: 摘除 | F9: — | G9: — | H9: 摘除 | I9: 公司真实主营是微特电机、风机及智能化组件的研发、生产和销售，产品包括交流异步电机、直流有刷及无刷电机、离心风机、横流风机和轴流风机，主要属于通用电气机械与器材，不是半导体工艺设备、测试设备或设备专用核心零部件。2025年总收入5.0796亿元，其中风机收入2.6395亿元，占51.96%；交流异步电机1.3506亿元、直流无刷电机0.5750亿元、直流有刷电机0.2785亿元，收入结构进一步证明主业为通用电机风机。年报未披露半导体设备客户、订单、专用产品或相应收入，不能仅凭电机、风机理论上可用于厂房通风或设备散热就建立半导体暴露。按通用业务和潜在用途不计入的规则，本次摘除旧“半导体设备”标签，不保留任何半导体概念。 | J9: 常州祥明智能动力股份有限公司2025年年度报告 | K9: 2026-04-24 | L9: iFinD ifind_get_stock_info + ifind_get_stock_business_segmentation (as of 2026-10-27)；常州祥明智能动力股份有限公司2025年年度报告 | M9: https://static.cninfo.com.cn/finalpage/2026-04-24/1225161993.PDF
B10: 600619 | C10: 海立股份 | D10: 半导体：半导体设备 | E10: 摘除 | F10: — | G10: — | H10: 摘除 | I10: 公司真实主业为冷暖关联解决方案及核心零部件、汽车零部件，具体产品是制冷转子式压缩机、制冷电机、铸件、汽车空调压缩机和新能源车热管理系统，不是光刻机、半导体工艺设备或设备专用零部件。2025年制冷设备收入134.6224亿元，占总收入204.9819亿元的65.68%；汽车零部件和贸易及房产租赁收入67.2501亿元，占32.81%，其他业务占1.52%。本次检索的2025年年报未出现半导体或光刻业务披露，也没有相关客户、订单和收入可核验。压缩机、电机等通用产品即使理论上可服务不同工业场景，也不能据此推导光刻机配套；股东或市场传闻同样不能替代上市公司真实业务。按通用业务和潜在用途不计入的规则，摘除旧“半导体设备”标签。 | J10: 上海海立（集团）股份有限公司2025年年度报告 | K10: 2026-04-08 | L10: iFinD ifind_get_stock_info + ifind_get_stock_business_segmentation (as of 2026-10-27)；上海海立（集团）股份有限公司2025年年度报告 | M10: https://static.cninfo.com.cn/finalpage/2026-04-08/1225082149.PDF
B11: 603236 | C11: 移远通信 | D11: 半导体：端侧ai芯片 | E11: 摘除 | F11: — | G11: — | H11: 摘除 | I11: 公司真实产品是蜂窝通信、车载、智能、短距、GNSS、卫星等无线通信模组以及天线，模组内可以集成处理器或人工智能算力，但这不等于公司自行设计并销售端侧人工智能芯片。2025年营业收入243.2647亿元，其中模组及天线收入240.0970亿元，占98.70%，该口径覆盖各类模组与天线，不能把其中集成第三方芯片或具备边缘计算能力的产品拆成自有芯片收入，年报也未给出可辨认的端侧芯片独立收入。因此旧“端侧ai芯片”及核心定级均属于把下游模组误标成上游芯片设计，应摘除半导体标签；本次仅纠正半导体分类，不处理其物理AI通信模组标签。 | J11: 移远通信2025年年度报告 | K11: 2026-04-24 | L11: iFinD ifind_get_stock_info + ifind_get_stock_business_segmentation (as of 2026-10-27)；移远通信2025年年度报告 | M11: http://money.finance.sina.com.cn/corp/view/vCB_AllBulletinDetail.php?stockid=603236&id=12160154
B12: 688503 | C12: 聚和材料 | D12: 半导体：半导体材料 | E12: 摘除 | F12: — | G12: — | H12: 摘除 | I12: 公司2025年的真实规模化收入仍来自光伏导电银浆，主要产品为TOPCon、HJT、X-BC等太阳能电池用浆料，不能因经营范围出现“半导体材料”或后来布局空白掩膜版，就把既有收入改写为半导体收入。2025年正面银浆收入144.2219亿元，约占总收入145.9270亿元的98.83%；电子专用材料行业收入145.1504亿元同样是包含光伏浆料的宽口径，并非半导体材料收入。年报虽讨论空白掩膜版国产替代，但未披露其2025年形成可识别规模收入，属于新业务培育和潜在用途边界，不能与成熟主业等量齐观。因此本次摘除旧“半导体材料”标签，不保留任何半导体概念。 | J12: 聚和材料：2025年年度报告 | K12: 2026-03-31 | L12: iFinD ifind_get_stock_info + ifind_get_stock_business_segmentation (as of 2026-10-27)；聚和材料：2025年年度报告 | M12: http://money.finance.sina.com.cn/corp/view/vCB_AllBulletinDetail.php?stockid=688503&id=12044269

Sheet 概念展开
A1: 一级分类 | B1: 二级概念 | C1: 判词 | D1: 代码 | E1: 名称
A2: 半导体 | B2: 封装测试 | C2: 核心 | D2: 000021 | E2: 深科技
A3: 半导体 | B3: 洁净室与厂务工程 | C3: 核心 | D3: 000032 | E3: 深桑达A
A4: 半导体 | B4: 半导体分销与供应链 | C4: 核心 | D4: 000062 | E4: 深圳华强
A5: 半导体 | B5: 芯片设计-CPU/GPU/AI计算 | C5: 相关 | D5: 000063 | E5: 中兴通讯
A6: 半导体 | B6: 半导体股权与产业投资 | C6: 相关 | D6: 000066 | E6: 中国长城
A7: 半导体 | B7: 洁净室与厂务工程 | C7: 相关 | D7: 000551 | E7: 创元科技
A8: 半导体 | B8: 半导体分销与供应链 | C8: 核心 | D8: 001287 | E8: 中电港
A9: 半导体 | B9: 存储模组与系统 | C9: 核心 | D9: 001309 | E9: 德明利
A10: 半导体 | B10: 芯片设计-存储主控与接口 | C10: 核心 | D10: 001309 | E10: 德明利
A11: 半导体 | B11: 半导体材料-封装材料 | C11: 核心 | D11: 002119 | E11: 康强电子
A12: 半导体 | B12: 半导体材料-硅片与硅部件 | C12: 核心 | D12: 002129 | E12: TCL中环
... A230: 半导体 | B230: 晶圆制造与IDM | C230: 核心 | D230: 600745 | E230: 闻泰科技

Sheet 概念统计
B2: 概念统计 · 核心/相关分布
B3: 公式引用隐藏展开表精确计数；一只股票可对应多个概念。
B4: 一级分类 | C4: 二级概念 | D4: 核心（只） | E4: 相关（只） | F4: 合计（只）
B5: 半导体 | C5: EDA/IP与设计服务 | D5: =COUNTIFS('概念展开'!$A$2:$A$230,B5,'概念展开'!$B$2:$B$230,C5,'概念展开'!$C$2:$C$230,"核心") | E5: =COUNTIFS('概念展开'!$A$2:$A$230,B5,'概念展开'!$B$2:$B$230,C5,'概念展开'!$C$2:$C$230,"相关") | F5: =SUM(D5:E5)
B6: 半导体 | C6: IC载板 | D6: =COUNTIFS('概念展开'!$A$2:$A$230,B6,'概念展开'!$B$2:$B$230,C6,'概念展开'!$C$2:$C$230,"核心") | E6: =COUNTIFS('概念展开'!$A$2:$A$230,B6,'概念展开'!$B$2:$B$230,C6,'概念展开'!$C$2:$C$230,"相关") | F6: =SUM(D6:E6)
B7: 半导体 | C7: 半导体分销与供应链 | D7: =COUNTIFS('概念展开'!$A$2:$A$230,B7,'概念展开'!$B$2:$B$230,C7,'概念展开'!$C$2:$C$230,"核心") | E7: =COUNTIFS('概念展开'!$A$2:$A$230,B7,'概念展开'!$B$2:$B$230,C7,'概念展开'!$C$2:$C$230,"相关") | F7: =SUM(D7:E7)
B8: 半导体 | C8: 半导体材料-CMP材料 | D8: =COUNTIFS('概念展开'!$A$2:$A$230,B8,'概念展开'!$B$2:$B$230,C8,'概念展开'!$C$2:$C$230,"核心") | E8: =COUNTIFS('概念展开'!$A$2:$A$230,B8,'概念展开'!$B$2:$B$230,C8,'概念展开'!$C$2:$C$230,"相关") | F8: =SUM(D8:E8)
B9: 半导体 | C9: 半导体材料-光刻胶与配套试剂 | D9: =COUNTIFS('概念展开'!$A$2:$A$230,B9,'概念展开'!$B$2:$B$230,C9,'概念展开'!$C$2:$C$230,"核心") | E9: =COUNTIFS('概念展开'!$A$2:$A$230,B9,'概念展开'!$B$2:$B$230,C9,'概念展开'!$C$2:$C$230,"相关") | F9: =SUM(D9:E9)
B10: 半导体 | C10: 半导体材料-其他关键材料 | D10: =COUNTIFS('概念展开'!$A$2:$A$230,B10,'概念展开'!$B$2:$B$230,C10,'概念展开'!$C$2:$C$230,"核心") | E10: =COUNTIFS('概念展开'!$A$2:$A$230,B10,'概念展开'!$B$2:$B$230,C10,'概念展开'!$C$2:$C$230,"相关") | F10: =SUM(D10:E10)
B11: 半导体 | C11: 半导体材料-封装材料 | D11: =COUNTIFS('概念展开'!$A$2:$A$230,B11,'概念展开'!$B$2:$B$230,C11,'概念展开'!$C$2:$C$230,"核心") | E11: =COUNTIFS('概念展开'!$A$2:$A$230,B11,'概念展开'!$B$2:$B$230,C11,'概念展开'!$C$2:$C$230,"相关") | F11: =SUM(D11:E11)
B12: 半导体 | C12: 半导体材料-掩膜版 | D12: =COUNTIFS('概念展开'!$A$2:$A$230,B12,'概念展开'!$B$2:$B$230,C12,'概念展开'!$C$2:$C$230,"核心") | E12: =COUNTIFS('概念展开'!$A$2:$A$230,B12,'概念展开'!$B$2:$B$230,C12,'概念展开'!$C$2:$C$230,"相关") | F12: =SUM(D12:E12)
B13: 半导体 | C13: 半导体材料-电子特气与湿化学品 | D13: =COUNTIFS('概念展开'!$A$2:$A$230,B13,'概念展开'!$B$2:$B$230,C13,'概念展开'!$C$2:$C$230,"核心") | E13: =COUNTIFS('概念展开'!$A$2:$A$230,B13,'概念展开'!$B$2:$B$230,C13,'概念展开'!$C$2:$C$230,"相关") | F13: =SUM(D13:E13)
B14: 半导体 | C14: 半导体材料-石英与陶瓷部件 | D14: =COUNTIFS('概念展开'!$A$2:$A$230,B14,'概念展开'!$B$2:$B$230,C14,'概念展开'!$C$2:$C$230,"核心") | E14: =COUNTIFS('概念展开'!$A$2:$A$230,B14,'概念展开'!$B$2:$B$230,C14,'概念展开'!$C$2:$C$230,"相关") | F14: =SUM(D14:E14)
B15: 半导体 | C15: 半导体材料-硅片与硅部件 | D15: =COUNTIFS('概念展开'!$A$2:$A$230,B15,'概念展开'!$B$2:$B$230,C15,'概念展开'!$C$2:$C$230,"核心") | E15: =COUNTIFS('概念展开'!$A$2:$A$230,B15,'概念展开'!$B$2:$B$230,C15,'概念展开'!$C$2:$C$230,"相关") | F15: =SUM(D15:E15)
B16: 半导体 | C16: 半导体材料-金刚石与加工耗材 | D16: =COUNTIFS('概念展开'!$A$2:$A$230,B16,'概念展开'!$B$2:$B$230,C16,'概念展开'!$C$2:$C$230,"核心") | E16: =COUNTIFS('概念展开'!$A$2:$A$230,B16,'概念展开'!$B$2:$B$230,C16,'概念展开'!$C$2:$C$230,"相关") | F16: =SUM(D16:E16)
... B47: 半导体 | C47: 设备核心零部件 | D47: =COUNTIFS('概念展开'!$A$2:$A$230,B47,'概念展开'!$B$2:$B$230,C47,'概念展开'!$C$2:$C$230,"核心") | E47: =COUNTIFS('概念展开'!$A$2:$A$230,B47,'概念展开'!$B$2:$B$230,C47,'概念展开'!$C$2:$C$230,"相关") | F47: =SUM(D47:E47)
B48: 合计（概念次数，非股票去重数） | D48: =SUM(D5:D47) | E48: =SUM(E5:E47) | F48: =SUM(F5:F47)
