Workbook

Sheet 封面
B2: 商业航天概念深度清洗报告
B3: 复核日期：2026-10-27｜范围：90只｜重点：业务实质、产品层级、商业订单与二次边界复审
B6: 复核股票（只） | C6: =COUNTA('清洗总表'!$B$5:$B$94)
B7: 保留商业航天（只） | C7: =COUNTA('商业航天'!$B$5:$B$78)
B8: 核心判词（只） | C8: =COUNTIF('商业航天'!$H$5:$H$78,"核心")
B9: 相关判词（只） | C9: =COUNTIF('商业航天'!$H$5:$H$78,"相关")
B10: 纠错动作（只） | C10: =COUNTIF('清洗总表'!$E$5:$E$94,"纠错")
B11: 完全摘除（只） | C11: =COUNTA('摘除清单'!$B$5:$B$20)
B15: 工作表索引
B16: 清洗总表 | C16: 90只旧概念、新概念、动作、判词、详细理由和证据
B17: 商业航天 | C17: 74只清洗后商业航天公司
B18: 摘除清单 | C18: 16只通用业务或商业航天证据不足公司
B19: 概念统计 | C19: 23个实际使用的二级概念
B23: 核心：商业航天是明确主营、重要收入来源，或已有规模化核心产品；相关：有真实产品、订单、交付、运营或股权，但早期、低占比、未拆分或民品为主。
B24: 摘除：只有央企背景、国家队、千帆概念、SpaceX潜在供应、通用产品可上天或太空光伏联想；传统航天与军品收入不自动归入商业航天。
B25: 二次复审：航天电子由核心降为相关，避免把传统航天配套收入等同商业航天；豪能股份依据公告确认的实际商业航天应用，由摘除恢复为相关。
B26: 主营与2025分部：iFinD ifind_get_stock_info、ifind_get_stock_business_segmentation（2026-10-27）；逐股公告与证据见Source列。

Sheet 清洗总表
B2: 商业航天 · 90只逐项复核
B3: 逐股核对真实产品、订单、客户、交付、运营与股权；区分商业航天、传统军工航天和潜在联想。
B4: 代码 | C4: 名称 | D4: 旧商业航天概念 | E4: 动作 | F4: 新一级分类 | G4: 新概念 | H4: 判词 | I4: 详细理由 | J4: 证据名称 | K4: 证据日期 | L4: Source Name | M4: Source URL
B5: 000547 | C5: 航天发展 | D5: 商业航天：国家队 | E5: 纠错 | F5: 商业航天 | G5: 卫星数据与遥感应用 | H5: 相关 | I5: 公司真实可核验的商业航天业务不是凭央企或航天科工背景推定，而是天目一号商业低轨气象星座的建设运营及空间信息应用：星座已形成探测能力，并向中国气象局实时推送数据，属于卫星数据生产、传输与应用服务。2025年空间信息应用类产品收入仅0.061亿元，且年报未把其中商业气象数据运营收入进一步单独拆分，相对公司整体收入体量很小，不能据此认定商业航天已成为核心主业。因此将旧“国家队”和“核心”纠正为“卫星数据与遥感应用、相关”，保留依据是实际星座运营与气象数据交付，而非军工电子对抗、蓝军仿真或军品收入；这些军工业务不计入本次商业航天定级。 | J5: 航天发展：2025年年度报告 | K5: 2026-04-29 | L5: iFinD ifind_get_stock_info + ifind_get_stock_business_segmentation (as of 2026-10-27)；航天发展：2025年年度报告 | M5: https://money.finance.sina.com.cn/corp/view/vCB_AllBulletinDetail.php?stockid=000547&id=12268512
B6: 000901 | C6: 航天科技 | D6: 商业航天：国家队 | E6: 纠错 | F6: 商业航天 | G6: 火箭结构与紧固件、环境试验与检测服务 | H6: 相关 | I6: 公司航天应用产品包括发动机及舵机零部件、伺服装配、航天电缆等精密制造产品，并提供雷电、静电及环境可靠性测试服务；年报还明确精密制造正向商业航天业务领域延伸，故可按真实产品与试验能力保留，而不是沿用央企“国家队”身份。2025年航天产品收入8.7787亿元、占15.8971%，汽车电子仪表收入42.4814亿元，收入仍以汽车电子为主；上述航天产品还包含军品和重大工程配套，年报没有独立拆分商业航天收入，不能把8.7787亿元全部算作商业航天。综合实际延伸方向与收入不可拆分情况，旧标签纠正为火箭结构零部件和环境试验检测，并审慎定为相关而非核心。 | J6: 航天科技：2025年年度报告 | K6: 2026-04-29 | L6: iFinD ifind_get_stock_info + ifind_get_stock_business_segmentation (as of 2026-10-27)；航天科技：2025年年度报告 | M6: https://money.finance.sina.com.cn/corp/view/vCB_AllBulletinDetail.php?stockid=000901&id=12247738
B7: 001270 | C7: 铖昌科技 | D7: 商业航天：卫星-有效载荷 | E7: 纠错 | F7: 商业航天 | G7: 星载射频与微波芯片 | H7: 核心 | I7: 公司主营微波毫米波模拟相控阵T/R芯片，星载产品已在卫星中批量应用，低轨卫星通信领域产品持续交付，属于直接决定相控阵载荷收发能力的星载射频核心元器件，并非仅凭通用芯片理论上可以用于卫星而映射。2025年相控阵T/R芯片收入4.0371亿元，占营业收入99.78%，集成电路行业收入4.0462亿元；年报未把星载、低轨卫星通信与其他雷达应用收入逐项拆分，因此不能把全部T/R芯片收入都称为商业航天收入，但产品主业集中、星载批量应用和持续交付证据清晰。故保留核心，同时将过粗的旧“卫星-有效载荷”收敛为“星载射频与微波芯片”，不扩写成整星或完整载荷制造。 | J7: 铖昌科技：2025年年度报告 | K7: 2026-04-17 | L7: iFinD ifind_get_stock_info + ifind_get_stock_business_segmentation (as of 2026-10-27)；铖昌科技：2025年年度报告 | M7: https://money.finance.sina.com.cn/corp/view/vCB_AllBulletinDetail.php?stockid=001270&id=12103041
B8: 001379 | C8: 腾达科技 | D8: 商业航天：火箭 | E8: 摘除 | F8: — | G8: — | H8: 摘除 | I8: 公司实际产品是不锈钢螺栓、螺母、螺杆、垫圈等通用紧固件，主要面向通用工业和民用市场。2025年紧固件行业收入18.6918亿元，螺栓、螺母和螺杆分别为10.8206亿元、3.5936亿元和1.8476亿元，未披露商业航天或火箭收入，也没有独立可辨认的航天客户收入。公司在互动答复中明确表示暂未直接与航空航天领域客户开展合作，这直接否定了把潜在用途当成现实供应关系的做法。不锈钢紧固件在物理上可能用于火箭，并不等于公司已经进入火箭供应链，更不存在可核验的型号配套、订单或批量交付。因此旧“火箭、相关”属于通用产品可上天的推断，必须摘除，不能以未来潜在客户或行业想象空间保留。 | J8: 腾达科技：关于航空航天领域合作的互动答复 | K8: 2025-06-10 | L8: iFinD ifind_get_stock_info + ifind_get_stock_business_segmentation (as of 2026-10-27)；腾达科技：关于航空航天领域合作的互动答复 | M8: https://news.10jqka.com.cn/20250610/c668774689.shtml
B9: 002025 | C9: 航天电器 | D9: 商业航天：国家队 | E9: 纠错 | F9: 商业航天 | G9: 星载电子与核心元器件、航天电子与测控组件 | H9: 相关 | I9: 公司高端连接器、线缆组件、微特电机、控制组件及继电器已形成航天工程配套，年报还披露商业航天领域订货和收入增长，说明存在真实商业客户与产品交付，而非仅因航天央企身份保留。2025年连接器收入39.8420亿元、电机13.5794亿元、继电器2.4040亿元，电子元器件制造业主业突出，但这些数字同时覆盖航空、兵器、舰船、防务装备及其他民用市场，年报没有独立拆分商业航天收入，不能把军品或全部航天工程配套收入自动归入商业航天。基于商业订货增长已明确、具体规模尚不可辨认，将旧“国家队、核心”纠正为星载电子核心元器件及航天电子测控组件，并下调为相关。 | J9: 航天电器：2025年年度报告 | K9: 2026-03-31 | L9: iFinD ifind_get_stock_info + ifind_get_stock_business_segmentation (as of 2026-10-27)；航天电器：2025年年度报告 | M9: https://money.finance.sina.com.cn/corp/view/vCB_AllBulletinDetail.php?stockid=002025&id=12040181
B10: 002046 | C10: 国机精工 | D10: 商业航天：火箭 | E10: 纠错 | F10: 商业航天 | G10: 商业航天配套-通用零部件 | H10: 相关 | I10: 公司特种轴承已有卫星、飞船和运载火箭等实际应用，产品属于旋转与运动机构所需的专用轴承配套；年报判断商业航天常态化发展将带来增量需求，保留依据是既有航天轴承产品和供货基础，而不是把全部轴承业务想象成火箭业务。2025年特种及精密轴承收入13.2822亿元，轴承行业收入15.2572亿元，但该口径还包括风电、机床、精密加工等大量非航天用途，商业航天收入、订单及客户占比均未独立披露，无法量化航天贡献。因而将旧泛化的“火箭”标签纠正为“商业航天配套-通用零部件”，定为相关，不据此宣称公司从事火箭总体、发动机或结构制造，也不把全部特种轴承收入算作商业航天。 | J10: 国机精工：2025年年度报告摘要 | K10: 2026-04-14 | L10: iFinD ifind_get_stock_info + ifind_get_stock_business_segmentation (as of 2026-10-27)；国机精工：2025年年度报告摘要 | M10: https://static.cninfo.com.cn/finalpage/2026-04-14/1225098549.PDF
B11: 002088 | C11: 鲁阳节能 | D11: 商业航天：spacex-供应商-陶瓷纤维 | E11: 摘除 | F11: — | G11: — | H11: 摘除 | I11: 公司的真实业务是陶瓷纤维棉、毯、湿法制品及相关耐火保温材料，主要服务石化、冶金、电力等工业炉窑的保温、耐火和防火场景。2025年陶瓷纤维制品收入22.1704亿元，工业收入24.7183亿元，年报没有披露卫星、火箭、发射场或商业航天客户收入，也没有可核验的SpaceX订单、认证、供货合同或批量交付。陶瓷纤维具备耐热性能，只能说明材料存在潜在用途，不能由此推出已经向SpaceX供应；本次检索亦未找到公司正式披露能够证实旧标签所指供应关系。因此旧“spacex-供应商-陶瓷纤维”是未经证实的客户映射，商业航天收入占比更无从确认，应整体摘除，而不是改写成泛化航天材料标签继续保留。 | J11: 鲁阳节能：2025年年度报告 | K11: 2026-04-29 | L11: iFinD ifind_get_stock_info + ifind_get_stock_business_segmentation (as of 2026-10-27)；鲁阳节能：2025年年度报告 | M11: https://vip.stock.finance.sina.com.cn/corp/view/vCB_AllBulletinDetail.php?stockid=002088&id=12267359
B12: 002115 | C12: 三维通信 | D12: 商业航天：卫星 | E12: 纠错 | F12: 商业航天 | G12: 卫星运营与通信服务 | H12: 相关 | I12: 公司通过子公司海卫通提供商船卫星通信服务，真实产品包括VSAT动中通、船端通信设备、高中低轨卫星宽带接入及船岸云服务，并以持续通信运营服务形成收入，属于卫星运营与通信服务而非单纯天线制造或概念性边缘计算。2025年卫星通信业务收入1.9217亿元，相关业务净利润约4405万元；同期互联网营销收入110.3001亿元，通信技术服务行业收入3.6402亿元，说明卫星业务真实但相对整体规模较小。卫星通信收入已有独立产品口径，不过高中低轨接入和船岸云服务等细分收入未再拆分。故将旧泛“卫星、边缘”纠正为“卫星运营与通信服务、相关”，不按核心处理，也不把互联网广告收入混入商业航天。 | J12: 三维通信：投资者关系活动记录表 | K12: 2026-04-29 | L12: iFinD ifind_get_stock_info + ifind_get_stock_business_segmentation (as of 2026-10-27)；三维通信：投资者关系活动记录表 | M12: https://pdf.dfcfw.com/pdf/H2_AN202604291821736545_1.pdf
B13: 002131 | C13: 利欧股份 | D13: 商业航天：spacex | E13: 摘除 | F13: — | G13: — | H13: 摘除 | I13: 公司主营仍是泵业和数字营销，2025年互联网收入156.6083亿元、制造业收入43.2403亿元，没有商业航天产品、服务或经营收入。旧“spacex”标签对应子公司曾出资5000万美元认购TBCA基金LP份额的间接投资路径，但基金方退款后双方进入诉讼；公司2026年5月15日投资者关系口径明确案件仍在进展中，法院尚未作出终局裁决，后续公开答复亦未见确权交割完成。因此目前不能把争议中的间接投资权益当作真实持有SpaceX股权，更不能按所谓终局胜诉传闻计算持股比例或估值。由于真实参股这一保留前提尚未成立，本次予以摘除而非列为“商业航天股权与产业投资”；若未来正式公告生效裁决和份额交割，再据新证据复核。 | J13: 利欧股份：2026年5月15日投资者关系活动记录表相关公开报道 | K13: 2026-05-19 | L13: iFinD ifind_get_stock_info + ifind_get_stock_business_segmentation (as of 2026-10-27)；利欧股份：2026年5月15日投资者关系活动记录表相关公开报道 | M13: https://finance.eastmoney.com/a/202605193742316659.html
B14: 002149 | C14: 西部材料 | D14: 商业航天：spacex-供应商 | E14: 纠错 | F14: 商业航天 | G14: 航天材料与增材制造 | H14: 相关 | I14: 公司真实航天产品包括用于液体火箭发动机的高温铌合金，以及配套重大航天工程的钨铜、TZM等稀有金属材料和组件，具备明确航天应用基础，可按航天材料环节保留。2025年钛制品收入22.0974亿元、其他金属产品8.6894亿元，稀有金属压延加工收入合计32.3054亿元，但这些收入还覆盖化工、核电、舰船及其他工业用途，商业航天收入没有独立拆分，不能将钛制品或全部稀有金属收入归入商业航天。公司正式披露亦未确认SpaceX实际供货，因此旧“spacex-供应商”不能以客户传闻保留，应纠正为可核验的“航天材料与增材制造”，并因具体商业航天贡献不明而定为相关，不扩写为SpaceX供应商。 | J14: 西部材料：2025年年度报告 | K14: 2026-04-28 | L14: iFinD ifind_get_stock_info + ifind_get_stock_business_segmentation (as of 2026-10-27)；西部材料：2025年年度报告 | M14: https://money.finance.sina.com.cn/corp/view/vCB_AllBulletinDetail.php?stockid=002149&id=12229670
B15: 002245 | C15: 蔚蓝锂芯 | D15: 商业航天：spacex-供应商 | E15: 摘除 | F15: — | G15: — | H15: 摘除 | I15: 公司主营业务为锂电池、LED和金属物流配送，2025年对应收入分别为35.9658亿元、15.8385亿元和26.0514亿元，未披露卫星、火箭或商业航天收入。针对市场流传的SpaceX供应关系，公司明确表示没有直接为卫星、火箭供应锂电池，仅披露为台湾能元科技提供代工；即使能元科技自身进入低轨卫星客户体系，也不能跳过实际产品流向和客户确认，直接推定蔚蓝锂芯产品已经供给SpaceX。现有证据既不能证明直接供货，也不能证明代工产品最终用于特定火箭或卫星型号，更谈不上可量化收入占比。因此旧“spacex-供应商”及“潜在供应商”均属于客户链条外推，应摘除，而不能借锂电池通用可上天属性改写保留。 | J15: 蔚蓝锂芯：关于卫星火箭及SpaceX供货问题的互动答复 | K15: 2025-12-31 | L15: iFinD ifind_get_stock_info + ifind_get_stock_business_segmentation (as of 2026-10-27)；蔚蓝锂芯：关于卫星火箭及SpaceX供货问题的互动答复 | M15: https://stock.stockstar.com/QA/companyto_2166706805235126272.html
... B94: 688066 | C94: 航天宏图 | D94: 商业航天：卫星 | E94: 纠错 | F94: 商业航天 | G94: 卫星数据与遥感应用 | H94: 核心 | I94: 公司以PIE软件、系统设计开发、遥感数据分析和女娲星座运营形成主营业务，直接提供卫星数据处理、遥感应用和星座运营服务，商业航天业务与主营收入高度对应。2025年卫星应用收入4.4781亿元，占营业收入100%，其中数据分析应用收入1.8592亿元、系统设计开发收入2.5859亿元，收入规模和产品闭环均支持核心判定。旧“卫星”标签过于宽泛，现纠正为“卫星数据与遥感应用”，明确公司优势在数据软件、应用和运营，不将其泛化为卫星总体制造或火箭业务。 | J94: 航天宏图信息技术股份有限公司2025年年度报告 | K94: 2026-04-30 | L94: iFinD ifind_get_stock_info + ifind_get_stock_business_segmentation (as of 2026-10-27)；航天宏图信息技术股份有限公司2025年年度报告 | M94: https://static.cninfo.com.cn/finalpage/2026-04-30/1225265967.PDF

Sheet 商业航天
B2: 商业航天 · 清洗后74只股池
B3: 核心14只、相关60只；按卫星、火箭、地面系统、运营服务和产业配套细化为23个二级概念。
B4: 代码 | C4: 名称 | D4: 旧商业航天概念 | E4: 动作 | F4: 新一级分类 | G4: 新概念 | H4: 判词 | I4: 详细理由 | J4: 证据名称 | K4: 证据日期 | L4: Source Name | M4: Source URL
B5: 000547 | C5: 航天发展 | D5: 商业航天：国家队 | E5: 纠错 | F5: 商业航天 | G5: 卫星数据与遥感应用 | H5: 相关 | I5: 公司真实可核验的商业航天业务不是凭央企或航天科工背景推定，而是天目一号商业低轨气象星座的建设运营及空间信息应用：星座已形成探测能力，并向中国气象局实时推送数据，属于卫星数据生产、传输与应用服务。2025年空间信息应用类产品收入仅0.061亿元，且年报未把其中商业气象数据运营收入进一步单独拆分，相对公司整体收入体量很小，不能据此认定商业航天已成为核心主业。因此将旧“国家队”和“核心”纠正为“卫星数据与遥感应用、相关”，保留依据是实际星座运营与气象数据交付，而非军工电子对抗、蓝军仿真或军品收入；这些军工业务不计入本次商业航天定级。 | J5: 航天发展：2025年年度报告 | K5: 2026-04-29 | L5: iFinD ifind_get_stock_info + ifind_get_stock_business_segmentation (as of 2026-10-27)；航天发展：2025年年度报告 | M5: https://money.finance.sina.com.cn/corp/view/vCB_AllBulletinDetail.php?stockid=000547&id=12268512
B6: 000901 | C6: 航天科技 | D6: 商业航天：国家队 | E6: 纠错 | F6: 商业航天 | G6: 火箭结构与紧固件、环境试验与检测服务 | H6: 相关 | I6: 公司航天应用产品包括发动机及舵机零部件、伺服装配、航天电缆等精密制造产品，并提供雷电、静电及环境可靠性测试服务；年报还明确精密制造正向商业航天业务领域延伸，故可按真实产品与试验能力保留，而不是沿用央企“国家队”身份。2025年航天产品收入8.7787亿元、占15.8971%，汽车电子仪表收入42.4814亿元，收入仍以汽车电子为主；上述航天产品还包含军品和重大工程配套，年报没有独立拆分商业航天收入，不能把8.7787亿元全部算作商业航天。综合实际延伸方向与收入不可拆分情况，旧标签纠正为火箭结构零部件和环境试验检测，并审慎定为相关而非核心。 | J6: 航天科技：2025年年度报告 | K6: 2026-04-29 | L6: iFinD ifind_get_stock_info + ifind_get_stock_business_segmentation (as of 2026-10-27)；航天科技：2025年年度报告 | M6: https://money.finance.sina.com.cn/corp/view/vCB_AllBulletinDetail.php?stockid=000901&id=12247738
B7: 001270 | C7: 铖昌科技 | D7: 商业航天：卫星-有效载荷 | E7: 纠错 | F7: 商业航天 | G7: 星载射频与微波芯片 | H7: 核心 | I7: 公司主营微波毫米波模拟相控阵T/R芯片，星载产品已在卫星中批量应用，低轨卫星通信领域产品持续交付，属于直接决定相控阵载荷收发能力的星载射频核心元器件，并非仅凭通用芯片理论上可以用于卫星而映射。2025年相控阵T/R芯片收入4.0371亿元，占营业收入99.78%，集成电路行业收入4.0462亿元；年报未把星载、低轨卫星通信与其他雷达应用收入逐项拆分，因此不能把全部T/R芯片收入都称为商业航天收入，但产品主业集中、星载批量应用和持续交付证据清晰。故保留核心，同时将过粗的旧“卫星-有效载荷”收敛为“星载射频与微波芯片”，不扩写成整星或完整载荷制造。 | J7: 铖昌科技：2025年年度报告 | K7: 2026-04-17 | L7: iFinD ifind_get_stock_info + ifind_get_stock_business_segmentation (as of 2026-10-27)；铖昌科技：2025年年度报告 | M7: https://money.finance.sina.com.cn/corp/view/vCB_AllBulletinDetail.php?stockid=001270&id=12103041
B8: 002025 | C8: 航天电器 | D8: 商业航天：国家队 | E8: 纠错 | F8: 商业航天 | G8: 星载电子与核心元器件、航天电子与测控组件 | H8: 相关 | I8: 公司高端连接器、线缆组件、微特电机、控制组件及继电器已形成航天工程配套，年报还披露商业航天领域订货和收入增长，说明存在真实商业客户与产品交付，而非仅因航天央企身份保留。2025年连接器收入39.8420亿元、电机13.5794亿元、继电器2.4040亿元，电子元器件制造业主业突出，但这些数字同时覆盖航空、兵器、舰船、防务装备及其他民用市场，年报没有独立拆分商业航天收入，不能把军品或全部航天工程配套收入自动归入商业航天。基于商业订货增长已明确、具体规模尚不可辨认，将旧“国家队、核心”纠正为星载电子核心元器件及航天电子测控组件，并下调为相关。 | J8: 航天电器：2025年年度报告 | K8: 2026-03-31 | L8: iFinD ifind_get_stock_info + ifind_get_stock_business_segmentation (as of 2026-10-27)；航天电器：2025年年度报告 | M8: https://money.finance.sina.com.cn/corp/view/vCB_AllBulletinDetail.php?stockid=002025&id=12040181
B9: 002046 | C9: 国机精工 | D9: 商业航天：火箭 | E9: 纠错 | F9: 商业航天 | G9: 商业航天配套-通用零部件 | H9: 相关 | I9: 公司特种轴承已有卫星、飞船和运载火箭等实际应用，产品属于旋转与运动机构所需的专用轴承配套；年报判断商业航天常态化发展将带来增量需求，保留依据是既有航天轴承产品和供货基础，而不是把全部轴承业务想象成火箭业务。2025年特种及精密轴承收入13.2822亿元，轴承行业收入15.2572亿元，但该口径还包括风电、机床、精密加工等大量非航天用途，商业航天收入、订单及客户占比均未独立披露，无法量化航天贡献。因而将旧泛化的“火箭”标签纠正为“商业航天配套-通用零部件”，定为相关，不据此宣称公司从事火箭总体、发动机或结构制造，也不把全部特种轴承收入算作商业航天。 | J9: 国机精工：2025年年度报告摘要 | K9: 2026-04-14 | L9: iFinD ifind_get_stock_info + ifind_get_stock_business_segmentation (as of 2026-10-27)；国机精工：2025年年度报告摘要 | M9: https://static.cninfo.com.cn/finalpage/2026-04-14/1225098549.PDF
B10: 002115 | C10: 三维通信 | D10: 商业航天：卫星 | E10: 纠错 | F10: 商业航天 | G10: 卫星运营与通信服务 | H10: 相关 | I10: 公司通过子公司海卫通提供商船卫星通信服务，真实产品包括VSAT动中通、船端通信设备、高中低轨卫星宽带接入及船岸云服务，并以持续通信运营服务形成收入，属于卫星运营与通信服务而非单纯天线制造或概念性边缘计算。2025年卫星通信业务收入1.9217亿元，相关业务净利润约4405万元；同期互联网营销收入110.3001亿元，通信技术服务行业收入3.6402亿元，说明卫星业务真实但相对整体规模较小。卫星通信收入已有独立产品口径，不过高中低轨接入和船岸云服务等细分收入未再拆分。故将旧泛“卫星、边缘”纠正为“卫星运营与通信服务、相关”，不按核心处理，也不把互联网广告收入混入商业航天。 | J10: 三维通信：投资者关系活动记录表 | K10: 2026-04-29 | L10: iFinD ifind_get_stock_info + ifind_get_stock_business_segmentation (as of 2026-10-27)；三维通信：投资者关系活动记录表 | M10: https://pdf.dfcfw.com/pdf/H2_AN202604291821736545_1.pdf
B11: 002149 | C11: 西部材料 | D11: 商业航天：spacex-供应商 | E11: 纠错 | F11: 商业航天 | G11: 航天材料与增材制造 | H11: 相关 | I11: 公司真实航天产品包括用于液体火箭发动机的高温铌合金，以及配套重大航天工程的钨铜、TZM等稀有金属材料和组件，具备明确航天应用基础，可按航天材料环节保留。2025年钛制品收入22.0974亿元、其他金属产品8.6894亿元，稀有金属压延加工收入合计32.3054亿元，但这些收入还覆盖化工、核电、舰船及其他工业用途，商业航天收入没有独立拆分，不能将钛制品或全部稀有金属收入归入商业航天。公司正式披露亦未确认SpaceX实际供货，因此旧“spacex-供应商”不能以客户传闻保留，应纠正为可核验的“航天材料与增材制造”，并因具体商业航天贡献不明而定为相关，不扩写为SpaceX供应商。 | J11: 西部材料：2025年年度报告 | K11: 2026-04-28 | L11: iFinD ifind_get_stock_info + ifind_get_stock_business_segmentation (as of 2026-10-27)；西部材料：2025年年度报告 | M11: https://money.finance.sina.com.cn/corp/view/vCB_AllBulletinDetail.php?stockid=002149&id=12229670
B12: 002413 | C12: 雷科防务 | D12: 商业航天：卫星-有效载荷 | E12: 纠错 | F12: 商业航天 | G12: 卫星载荷-遥感与探测、地面站与测运控、卫星数据与遥感应用 | H12: 核心 | I12: 公司卫星应用业务覆盖星载高性能计算与智能处理、轻小型在轨处理平台、星载滤波器及低轨天线，相关在轨产品已有实际应用；2025年交付近20套地面处理设备，商业遥感入网检测设备部署到多个地面站，形成从星上遥感处理到地面接收处理的完整产品链。2025年卫星应用收入3.5480亿元、占24.36%，是年报独立披露的重要产品板块，但年报未继续拆分商业航天与传统航天、军品收入，不能将全部卫星应用收入等同商业航天。鉴于在轨产品、地面站部署和商业遥感检测设备均有落地，保留核心；旧“卫星-有效载荷”过粗，纠正为遥感探测载荷、地面测运控及遥感数据应用三个真实环节。 | J12: 雷科防务：2025年年度报告 | K12: 2026-04-18 | L12: iFinD ifind_get_stock_info + ifind_get_stock_business_segmentation (as of 2026-10-27)；雷科防务：2025年年度报告 | M12: http://money.finance.sina.com.cn/corp/view/vCB_AllBulletinDetail.php?stockid=002413&id=12110187
B13: 002446 | C13: 盛路通信 | D13: 商业航天：卫星 | E13: 纠错 | F13: 商业航天 | G13: 卫星通信终端与天线 | H13: 相关 | I13: 公司在卫星通信方向的真实产品为Ku、Ka频段阵列天线及宽窄带射频模块，并已有商用卫星“海哨二号”等配套案例，因此不是把普通基站天线或微波器件直接想象为卫星产品。公司同时明确卫星通信业务仍处起步阶段、订单量较小；2025年通信设备收入6.6616亿元、微波电子收入5.4023亿元，其中还包含大量地面通信和军工电子业务，卫星通信收入与商业航天占比没有独立拆分，不能把上述板块收入全部归入商业航天。综合真实型号配套与订单规模有限的事实，将旧泛“卫星”收敛为“卫星通信终端与天线”，定为相关而非核心，也不将军工微波电子收入自动计入商业航天。 | J13: 盛路通信：关于卫星通信产品配套及订单情况的互动答复 | K13: 2026-05-15 | L13: iFinD ifind_get_stock_info + ifind_get_stock_business_segmentation (as of 2026-10-27)；盛路通信：关于卫星通信产品配套及订单情况的互动答复 | M13: https://www.sohu.com/a/1023207074_115377
B14: 002465 | C14: 海格通信 | D14: 商业航天：卫星-地面设备 | E14: 纠错 | F14: 商业航天 | G14: 卫星通信终端与天线、导航定位与授时服务 | H14: 相关 | I14: 公司具备卫星通信产品及北斗芯片、模块、天线、终端和系统的全链条能力，并面向民用行业提供导航定位应用，产品形态与卫星终端、导航授时服务相符。2025年无线通信收入10.9990亿元、北斗导航收入5.1539亿元，但两个口径均包含特殊机构及其他非商业航天应用，年报未独立拆分民用卫星互联网和北斗商业服务收入；卫星互联网地面终端仍有产品处于研制阶段，不能把研发储备视为规模交付。因此旧“卫星-地面设备、核心”需纠正为卫星通信终端天线与导航定位授时服务，并下调为相关。定级不采用特殊机构订单或军品收入作为商业航天证据，也不把全部无线通信收入纳入。 | J14: 海格通信：2025年年度报告 | K14: 2026-03-28 | L14: iFinD ifind_get_stock_info + ifind_get_stock_business_segmentation (as of 2026-10-27)；海格通信：2025年年度报告 | M14: https://money.finance.sina.com.cn/corp/view/vCB_AllBulletinDetail.php?stockid=002465&id=12030570
B15: 002471 | C15: 中超控股 | D15: 商业航天：火箭 | E15: 纠错 | F15: 商业航天 | G15: 火箭总体与动力 | H15: 相关 | I15: 公司孙公司江苏精铸已持续向航天科工火箭、上海空间推进研究所等客户提供火箭发动机高温合金精密铸件，具体包括涡轮机匣、导向器和喷嘴等动力部件，具备真实客户、产品和持续订单，不再是电线电缆主业的概念联想。2025年精铸板块新签订单7292.41万元，而电缆行业收入50.8288亿元、电力电缆收入44.8904亿元，商业航天收入及利润没有独立拆分，且精铸订单也不能全部视为商业航天。基于火箭发动机部件供货已落地但体量较小，将旧“火箭、边缘”纠正为“火箭总体与动力、相关”；该概念仅指发动机精密铸件配套，不表示公司从事火箭总体设计或整箭制造。 | J15: 中超控股：2025年年度报告 | K15: 2026-03-31 | L15: iFinD ifind_get_stock_info + ifind_get_stock_business_segmentation (as of 2026-10-27)；中超控股：2025年年度报告 | M15: https://money.finance.sina.com.cn/corp/view/vCB_AllBulletinDetail.php?stockid=002471&id=12037035
... B78: 688066 | C78: 航天宏图 | D78: 商业航天：卫星 | E78: 纠错 | F78: 商业航天 | G78: 卫星数据与遥感应用 | H78: 核心 | I78: 公司以PIE软件、系统设计开发、遥感数据分析和女娲星座运营形成主营业务，直接提供卫星数据处理、遥感应用和星座运营服务，商业航天业务与主营收入高度对应。2025年卫星应用收入4.4781亿元，占营业收入100%，其中数据分析应用收入1.8592亿元、系统设计开发收入2.5859亿元，收入规模和产品闭环均支持核心判定。旧“卫星”标签过于宽泛，现纠正为“卫星数据与遥感应用”，明确公司优势在数据软件、应用和运营，不将其泛化为卫星总体制造或火箭业务。 | J78: 航天宏图信息技术股份有限公司2025年年度报告 | K78: 2026-04-30 | L78: iFinD ifind_get_stock_info + ifind_get_stock_business_segmentation (as of 2026-10-27)；航天宏图信息技术股份有限公司2025年年度报告 | M78: https://static.cninfo.com.cn/finalpage/2026-04-30/1225265967.PDF

Sheet 摘除清单
B2: 摘除清单 · 16只证据不足或业务错标
B3: 通用产品潜在用途、央企背景、SpaceX预期、太空光伏设备及未决投资不直接计入商业航天。
B4: 代码 | C4: 名称 | D4: 旧商业航天概念 | E4: 动作 | F4: 新一级分类 | G4: 新概念 | H4: 判词 | I4: 详细理由 | J4: 证据名称 | K4: 证据日期 | L4: Source Name | M4: Source URL
B5: 001379 | C5: 腾达科技 | D5: 商业航天：火箭 | E5: 摘除 | F5: — | G5: — | H5: 摘除 | I5: 公司实际产品是不锈钢螺栓、螺母、螺杆、垫圈等通用紧固件，主要面向通用工业和民用市场。2025年紧固件行业收入18.6918亿元，螺栓、螺母和螺杆分别为10.8206亿元、3.5936亿元和1.8476亿元，未披露商业航天或火箭收入，也没有独立可辨认的航天客户收入。公司在互动答复中明确表示暂未直接与航空航天领域客户开展合作，这直接否定了把潜在用途当成现实供应关系的做法。不锈钢紧固件在物理上可能用于火箭，并不等于公司已经进入火箭供应链，更不存在可核验的型号配套、订单或批量交付。因此旧“火箭、相关”属于通用产品可上天的推断，必须摘除，不能以未来潜在客户或行业想象空间保留。 | J5: 腾达科技：关于航空航天领域合作的互动答复 | K5: 2025-06-10 | L5: iFinD ifind_get_stock_info + ifind_get_stock_business_segmentation (as of 2026-10-27)；腾达科技：关于航空航天领域合作的互动答复 | M5: https://news.10jqka.com.cn/20250610/c668774689.shtml
B6: 002088 | C6: 鲁阳节能 | D6: 商业航天：spacex-供应商-陶瓷纤维 | E6: 摘除 | F6: — | G6: — | H6: 摘除 | I6: 公司的真实业务是陶瓷纤维棉、毯、湿法制品及相关耐火保温材料，主要服务石化、冶金、电力等工业炉窑的保温、耐火和防火场景。2025年陶瓷纤维制品收入22.1704亿元，工业收入24.7183亿元，年报没有披露卫星、火箭、发射场或商业航天客户收入，也没有可核验的SpaceX订单、认证、供货合同或批量交付。陶瓷纤维具备耐热性能，只能说明材料存在潜在用途，不能由此推出已经向SpaceX供应；本次检索亦未找到公司正式披露能够证实旧标签所指供应关系。因此旧“spacex-供应商-陶瓷纤维”是未经证实的客户映射，商业航天收入占比更无从确认，应整体摘除，而不是改写成泛化航天材料标签继续保留。 | J6: 鲁阳节能：2025年年度报告 | K6: 2026-04-29 | L6: iFinD ifind_get_stock_info + ifind_get_stock_business_segmentation (as of 2026-10-27)；鲁阳节能：2025年年度报告 | M6: https://vip.stock.finance.sina.com.cn/corp/view/vCB_AllBulletinDetail.php?stockid=002088&id=12267359
B7: 002131 | C7: 利欧股份 | D7: 商业航天：spacex | E7: 摘除 | F7: — | G7: — | H7: 摘除 | I7: 公司主营仍是泵业和数字营销，2025年互联网收入156.6083亿元、制造业收入43.2403亿元，没有商业航天产品、服务或经营收入。旧“spacex”标签对应子公司曾出资5000万美元认购TBCA基金LP份额的间接投资路径，但基金方退款后双方进入诉讼；公司2026年5月15日投资者关系口径明确案件仍在进展中，法院尚未作出终局裁决，后续公开答复亦未见确权交割完成。因此目前不能把争议中的间接投资权益当作真实持有SpaceX股权，更不能按所谓终局胜诉传闻计算持股比例或估值。由于真实参股这一保留前提尚未成立，本次予以摘除而非列为“商业航天股权与产业投资”；若未来正式公告生效裁决和份额交割，再据新证据复核。 | J7: 利欧股份：2026年5月15日投资者关系活动记录表相关公开报道 | K7: 2026-05-19 | L7: iFinD ifind_get_stock_info + ifind_get_stock_business_segmentation (as of 2026-10-27)；利欧股份：2026年5月15日投资者关系活动记录表相关公开报道 | M7: https://finance.eastmoney.com/a/202605193742316659.html
B8: 002245 | C8: 蔚蓝锂芯 | D8: 商业航天：spacex-供应商 | E8: 摘除 | F8: — | G8: — | H8: 摘除 | I8: 公司主营业务为锂电池、LED和金属物流配送，2025年对应收入分别为35.9658亿元、15.8385亿元和26.0514亿元，未披露卫星、火箭或商业航天收入。针对市场流传的SpaceX供应关系，公司明确表示没有直接为卫星、火箭供应锂电池，仅披露为台湾能元科技提供代工；即使能元科技自身进入低轨卫星客户体系，也不能跳过实际产品流向和客户确认，直接推定蔚蓝锂芯产品已经供给SpaceX。现有证据既不能证明直接供货，也不能证明代工产品最终用于特定火箭或卫星型号，更谈不上可量化收入占比。因此旧“spacex-供应商”及“潜在供应商”均属于客户链条外推，应摘除，而不能借锂电池通用可上天属性改写保留。 | J8: 蔚蓝锂芯：关于卫星火箭及SpaceX供货问题的互动答复 | K8: 2025-12-31 | L8: iFinD ifind_get_stock_info + ifind_get_stock_business_segmentation (as of 2026-10-27)；蔚蓝锂芯：关于卫星火箭及SpaceX供货问题的互动答复 | M8: https://stock.stockstar.com/QA/companyto_2166706805235126272.html
B9: 002796 | C9: 世嘉科技 | D9: 商业航天：卫星 | E9: 摘除 | F9: — | G9: — | H9: 摘除 | I9: 公司实际产品为4G、5G宏基站天线、滤波器等射频器件，以及电梯轿厢、专用设备箱体和精密金属结构件。2025年天线收入1.4891亿元、射频器件收入3.0215亿元，增长主要来自5G天线业务；年报未披露卫星通信终端、星载天线、卫星订单、商业航天客户或运营服务，相关收入占比也无独立口径。天地一体化和6G是行业技术演进方向，不能替代公司已经取得卫星订单或交付产品的证据，普通地面基站天线和滤波器也不能因未来可能支持6G就直接归入商业航天。因此旧“卫星、边缘”缺少现实业务支撑，应予摘除，而不是改写成卫星通信终端或星载射频标签继续保留。 | J9: 世嘉科技：2025年年度报告 | K9: 2026-04-27 | L9: iFinD ifind_get_stock_info + ifind_get_stock_business_segmentation (as of 2026-10-27)；世嘉科技：2025年年度报告 | M9: https://vip.stock.finance.sina.com.cn/corp/view/vCB_AllBulletinDetail.php?stockid=002796&id=12204466
B10: 002985 | C10: 北摩高科 | D10: 商业航天：千帆星座 | E10: 摘除 | F10: — | G10: — | H10: 摘除 | I10: 公司真实产品是飞机刹车盘、刹车控制系统、机轮及起落架着陆系统，2025年起降系统产品收入6.1361亿元，占66.8424%，检测试验收入2.5159亿元，占27.4068%。年报虽称全电刹车技术已应用于航天高空飞行器，但该表述没有明确商业卫星、商业火箭、商业航天客户或订单，也没有独立披露商业航天收入，不能把航空制动或一般航天装备应用直接等同于商业航天。旧“千帆星座”标签未获得公司供货证据支持，属于由航空航天主业和热点星座作出的外推，故摘除商业航天标签，军工及航空属性不在本次处理范围内。 | J10: 北摩高科：2025年年度报告摘要 | K10: 2026-03-18 | L10: iFinD ifind_get_stock_info + ifind_get_stock_business_segmentation (as of 2026-10-27)；北摩高科：2025年年度报告摘要 | M10: http://static.cninfo.com.cn/finalpage/2026-03-18/1225015258.PDF
B11: 300118 | C11: 东方日升 | D11: 商业航天：spacex-潜在供应商 | E11: 摘除 | F11: — | G11: — | H11: 摘除 | I11: 公司真实业务为地面太阳能电池片、组件、电站及储能系统，2025年太阳能电池组件收入65.6992亿元，太阳能电站收入33.5803亿元，储能系统、灯具及辅助光伏产品收入17.4340亿元，年报未披露商业卫星太阳翼、空间电源产品、商业航天客户或相关订单，也没有独立商业航天收入。地面光伏组件和钙钛矿、异质结技术即使存在未来空间应用可能，也不能据此认定公司已经供货。核验未发现公司实际向SpaceX供货的正式公告或官方证据，旧“spacex-潜在供应商”仅属市场预期，且“太空光伏组件”不能自动转换为商业航天标签，因此本次摘除。 | J11: 东方日升：2025年年度报告 | K11: 2026-04-25 | L11: iFinD ifind_get_stock_info + ifind_get_stock_business_segmentation (as of 2026-10-27)；东方日升：2025年年度报告 | M11: https://money.finance.sina.com.cn/corp/view/vCB_AllBulletinDetail.php?stockid=300118&id=12193179
B12: 300316 | C12: 晶盛机电 | D12: 商业航天：spacex-潜在供应商 | E12: 摘除 | F12: — | G12: — | H12: 摘除 | I12: 公司真实产品为晶体硅生长设备、半导体集成电路装备、化合物半导体装备、衬底材料和精密零部件。2025年设备及其服务收入84.0272亿元，蓝宝石材料收入24.6151亿元，其他收入4.9326亿元，制造业收入109.3773亿元，占96.3042%，没有独立披露商业航天收入、空间用产品或商业航天客户订单。晶体生长和光伏设备可用于地面硅片及电池制造，即使未来太空光伏技术路线可能采用相关工艺，也不代表已有航天供货。核验未发现实际向SpaceX销售的正式证据，旧“spacex-潜在供应商”和“太空光伏设备”均属于产业趋势外推，故摘除商业航天标签，半导体设备与材料标签不在本次改动范围。 | J12: 晶盛机电：2025年年度报告 | K12: 2026-04-11 | L12: iFinD ifind_get_stock_info + ifind_get_stock_business_segmentation (as of 2026-10-27)；晶盛机电：2025年年度报告 | M12: https://data.eastmoney.com/notices/detail/300316/AN202604101821124646.html
B13: 300604 | C13: 长川科技 | D13: 商业航天：spacex | E13: 摘除 | F13: — | G13: — | H13: 摘除 | I13: 公司真实业务为集成电路测试机、分选机、自动化设备和AOI光学检测设备。2025年测试机收入32.0297亿元，分选机收入15.6847亿元，其他业务5.2010亿元，集成电路电子工业专用设备收入合计52.9154亿元、占100%，年报未披露商业航天产品、卫星或火箭客户、SpaceX订单及对应收入。半导体测试设备可以服务多类芯片下游，但芯片最终可能用于卫星并不等于设备商已向商业航天供货，更不能把全部半导体设备收入映射为航天收入。核验所见SpaceX说法主要来自市场讨论，未发现公司正式公告证实实际供货，旧“spacex”及“已成交核心供应商”理由缺乏可核验依据，故摘除。 | J13: 长川科技：2025年年度报告 | K13: 2026-04-25 | L13: iFinD ifind_get_stock_info + ifind_get_stock_business_segmentation (as of 2026-10-27)；长川科技：2025年年度报告 | M13: https://money.finance.sina.com.cn/corp/view/vCB_AllBulletinDetail.php?stockid=300604&id=12197571
B14: 300751 | C14: 迈为股份 | D14: 商业航天：spacex-潜在供应商 | E14: 摘除 | F14: — | G14: — | H14: 摘除 | I14: 公司真实产品是HJT异质结电池生产线、太阳能电池丝网印刷设备、显示面板和半导体制造设备。2025年太阳能光伏行业收入74.4964亿元，占91.3845%，半导体及显示行业收入6.6204亿元，占8.1212%，太阳能电池丝网印刷成套设备收入60.2507亿元，未独立披露商业航天收入或空间用设备销售。业绩说明会上被问及约5亿美元SpaceX订单时，公司仅回复按规则履行披露义务、以巨潮公告为准，并未确认订单；对太空应用问题也只重申光伏、显示和半导体装备定位。地面光伏技术和海外订单预期不能替代实际航天供货证据，旧“spacex-潜在供应商”及太空光伏设备标签因此摘除。 | J14: 迈为股份2025年度业绩说明会投资者活动记录表 | K14: 2026-04-28 | L14: iFinD ifind_get_stock_info + ifind_get_stock_business_segmentation (as of 2026-10-27)；迈为股份2025年度业绩说明会投资者活动记录表 | M14: https://www.9fzt.com/detail/sz_300751_9_d91700be1088100082d7b6b8759c9704.html
B15: 300757 | C15: 罗博特科 | D15: 商业航天：spacex、设备、太空光伏设备 | E15: 摘除 | F15: — | G15: — | H15: 摘除 | I15: 公司真实业务为光伏电池自动化设备、光电子及半导体封测设备、光子器件耦合和测试设备。2025年光电子及半导体封测设备收入4.3913亿元，光伏设备及整体解决方案收入4.3306亿元，其他产品0.7762亿元；半导体行业收入4.8549亿元、光伏行业收入4.5985亿元，未披露商业航天产品、客户、订单或独立收入。光伏自动化及光通信设备可以面向地面制造和数据中心应用，不能因技术可能服务太空光伏或卫星通信就直接归入商业航天。核验未发现公司实际向SpaceX供货的正式公告，旧“spacex”“太空光伏设备”以及错误复制到商业航天分类的“设备”概念均缺乏事实基础，故本次全部摘除。 | J15: 罗博特科：2025年年度报告 | K15: 2026-03-31 | L15: iFinD ifind_get_stock_info + ifind_get_stock_business_segmentation (as of 2026-10-27)；罗博特科：2025年年度报告 | M15: http://static.cninfo.com.cn/finalpage/2026-03-31/1225059372.PDF
... B20: 688610 | C20: 埃科光电 | D20: 商业航天：spacex-潜在供应商 | E20: 摘除 | F20: — | G20: — | H20: 摘除 | I20: 公司主要提供工业线扫、面扫相机、采集卡和智能光学单元，应用于PCB、显示、新能源、半导体和生物医疗等工业检测场景。2025年电子制造收入1.4371亿元、新型显示收入1.0216亿元、新能源收入0.8010亿元，未见商业航天独立收入，也没有可核验的SpaceX实际供货或商业航天订单证据。通用工业相机可以用于某些航天检测，并不意味着公司已经成为航天供应商，不能据此推断商业航天业务。因真实产品、客户和收入均未形成商业航天闭环，故摘除旧“spacex-潜在供应商”标签，不保留泛化的航天配套概念。 | J20: 合肥埃科光电科技股份有限公司2025年年度报告 | K20: 2026-03-31 | L20: iFinD ifind_get_stock_info + ifind_get_stock_business_segmentation (as of 2026-10-27)；合肥埃科光电科技股份有限公司2025年年度报告 | M20: https://static.cninfo.com.cn/finalpage/2026-03-31/1225059687.PDF

Sheet 概念展开
A1: 一级分类 | B1: 二级概念 | C1: 判词 | D1: 代码 | E1: 名称
A2: 商业航天 | B2: 卫星数据与遥感应用 | C2: 相关 | D2: 000547 | E2: 航天发展
A3: 商业航天 | B3: 火箭结构与紧固件 | C3: 相关 | D3: 000901 | E3: 航天科技
A4: 商业航天 | B4: 环境试验与检测服务 | C4: 相关 | D4: 000901 | E4: 航天科技
A5: 商业航天 | B5: 星载射频与微波芯片 | C5: 核心 | D5: 001270 | E5: 铖昌科技
A6: 商业航天 | B6: 星载电子与核心元器件 | C6: 相关 | D6: 002025 | E6: 航天电器
A7: 商业航天 | B7: 航天电子与测控组件 | C7: 相关 | D7: 002025 | E7: 航天电器
A8: 商业航天 | B8: 商业航天配套-通用零部件 | C8: 相关 | D8: 002046 | E8: 国机精工
A9: 商业航天 | B9: 卫星运营与通信服务 | C9: 相关 | D9: 002115 | E9: 三维通信
A10: 商业航天 | B10: 航天材料与增材制造 | C10: 相关 | D10: 002149 | E10: 西部材料
A11: 商业航天 | B11: 卫星载荷-遥感与探测 | C11: 核心 | D11: 002413 | E11: 雷科防务
A12: 商业航天 | B12: 地面站与测运控 | C12: 核心 | D12: 002413 | E12: 雷科防务
... A112: 商业航天 | B112: 卫星数据与遥感应用 | C112: 核心 | D112: 688066 | E112: 航天宏图

Sheet 概念统计
B2: 概念统计 · 核心/相关分布
B3: 公式引用隐藏展开表精确计数；一只股票可对应多个概念。
B4: 一级分类 | C4: 二级概念 | D4: 核心（只） | E4: 相关（只） | F4: 合计（只）
B5: 商业航天 | C5: 卫星互联网网络与系统 | D5: =COUNTIFS('概念展开'!$A$2:$A$112,B5,'概念展开'!$B$2:$B$112,C5,'概念展开'!$C$2:$C$112,"核心") | E5: =COUNTIFS('概念展开'!$A$2:$A$112,B5,'概念展开'!$B$2:$B$112,C5,'概念展开'!$C$2:$C$112,"相关") | F5: =SUM(D5:E5)
B6: 商业航天 | C6: 卫星平台与核心分系统 | D6: =COUNTIFS('概念展开'!$A$2:$A$112,B6,'概念展开'!$B$2:$B$112,C6,'概念展开'!$C$2:$C$112,"核心") | E6: =COUNTIFS('概念展开'!$A$2:$A$112,B6,'概念展开'!$B$2:$B$112,C6,'概念展开'!$C$2:$C$112,"相关") | F6: =SUM(D6:E6)
B7: 商业航天 | C7: 卫星总体与制造 | D7: =COUNTIFS('概念展开'!$A$2:$A$112,B7,'概念展开'!$B$2:$B$112,C7,'概念展开'!$C$2:$C$112,"核心") | E7: =COUNTIFS('概念展开'!$A$2:$A$112,B7,'概念展开'!$B$2:$B$112,C7,'概念展开'!$C$2:$C$112,"相关") | F7: =SUM(D7:E7)
B8: 商业航天 | C8: 卫星数据与遥感应用 | D8: =COUNTIFS('概念展开'!$A$2:$A$112,B8,'概念展开'!$B$2:$B$112,C8,'概念展开'!$C$2:$C$112,"核心") | E8: =COUNTIFS('概念展开'!$A$2:$A$112,B8,'概念展开'!$B$2:$B$112,C8,'概念展开'!$C$2:$C$112,"相关") | F8: =SUM(D8:E8)
B9: 商业航天 | C9: 卫星电源与太阳翼 | D9: =COUNTIFS('概念展开'!$A$2:$A$112,B9,'概念展开'!$B$2:$B$112,C9,'概念展开'!$C$2:$C$112,"核心") | E9: =COUNTIFS('概念展开'!$A$2:$A$112,B9,'概念展开'!$B$2:$B$112,C9,'概念展开'!$C$2:$C$112,"相关") | F9: =SUM(D9:E9)
B10: 商业航天 | C10: 卫星结构与机构 | D10: =COUNTIFS('概念展开'!$A$2:$A$112,B10,'概念展开'!$B$2:$B$112,C10,'概念展开'!$C$2:$C$112,"核心") | E10: =COUNTIFS('概念展开'!$A$2:$A$112,B10,'概念展开'!$B$2:$B$112,C10,'概念展开'!$C$2:$C$112,"相关") | F10: =SUM(D10:E10)
B11: 商业航天 | C11: 卫星载荷-通信与转发 | D11: =COUNTIFS('概念展开'!$A$2:$A$112,B11,'概念展开'!$B$2:$B$112,C11,'概念展开'!$C$2:$C$112,"核心") | E11: =COUNTIFS('概念展开'!$A$2:$A$112,B11,'概念展开'!$B$2:$B$112,C11,'概念展开'!$C$2:$C$112,"相关") | F11: =SUM(D11:E11)
B12: 商业航天 | C12: 卫星载荷-遥感与探测 | D12: =COUNTIFS('概念展开'!$A$2:$A$112,B12,'概念展开'!$B$2:$B$112,C12,'概念展开'!$C$2:$C$112,"核心") | E12: =COUNTIFS('概念展开'!$A$2:$A$112,B12,'概念展开'!$B$2:$B$112,C12,'概念展开'!$C$2:$C$112,"相关") | F12: =SUM(D12:E12)
B13: 商业航天 | C13: 卫星运营与通信服务 | D13: =COUNTIFS('概念展开'!$A$2:$A$112,B13,'概念展开'!$B$2:$B$112,C13,'概念展开'!$C$2:$C$112,"核心") | E13: =COUNTIFS('概念展开'!$A$2:$A$112,B13,'概念展开'!$B$2:$B$112,C13,'概念展开'!$C$2:$C$112,"相关") | F13: =SUM(D13:E13)
B14: 商业航天 | C14: 卫星通信终端与天线 | D14: =COUNTIFS('概念展开'!$A$2:$A$112,B14,'概念展开'!$B$2:$B$112,C14,'概念展开'!$C$2:$C$112,"核心") | E14: =COUNTIFS('概念展开'!$A$2:$A$112,B14,'概念展开'!$B$2:$B$112,C14,'概念展开'!$C$2:$C$112,"相关") | F14: =SUM(D14:E14)
B15: 商业航天 | C15: 发射场与地面保障 | D15: =COUNTIFS('概念展开'!$A$2:$A$112,B15,'概念展开'!$B$2:$B$112,C15,'概念展开'!$C$2:$C$112,"核心") | E15: =COUNTIFS('概念展开'!$A$2:$A$112,B15,'概念展开'!$B$2:$B$112,C15,'概念展开'!$C$2:$C$112,"相关") | F15: =SUM(D15:E15)
B16: 商业航天 | C16: 商业航天股权与产业投资 | D16: =COUNTIFS('概念展开'!$A$2:$A$112,B16,'概念展开'!$B$2:$B$112,C16,'概念展开'!$C$2:$C$112,"核心") | E16: =COUNTIFS('概念展开'!$A$2:$A$112,B16,'概念展开'!$B$2:$B$112,C16,'概念展开'!$C$2:$C$112,"相关") | F16: =SUM(D16:E16)
... B27: 商业航天 | C27: 航天电子与测控组件 | D27: =COUNTIFS('概念展开'!$A$2:$A$112,B27,'概念展开'!$B$2:$B$112,C27,'概念展开'!$C$2:$C$112,"核心") | E27: =COUNTIFS('概念展开'!$A$2:$A$112,B27,'概念展开'!$B$2:$B$112,C27,'概念展开'!$C$2:$C$112,"相关") | F27: =SUM(D27:E27)
B28: 合计（概念次数，非股票去重数） | D28: =SUM(D5:D27) | E28: =SUM(E5:E27) | F28: =SUM(F5:F27)
