Workbook

Sheet 封面
B2: 机器人与物理AI概念深度清洗报告
B3: 复核日期：2026-10-27｜范围：137只｜口径：产品直接性、商业化证据、主营相关度、分类边界
B6: 复核股票（只） | C6: =COUNTA('清洗总表'!$B$5:$B$141)
B7: 保留机器人（只） | C7: =COUNTA('机器人'!$B$5:$B$89)
B8: 归入物理AI（只） | C8: =COUNTA('物理AI'!$B$5:$B$42)
B9: 完全摘除（只） | C9: =COUNTA('摘除清单'!$B$5:$B$24)
B10: 迁移/新增物理AI动作（只） | C10: =COUNTIF('物理AI'!$E$5:$E$42,"迁移")+COUNTIF('物理AI'!$E$5:$E$42,"新增")
B11: 纠错动作（只） | C11: =COUNTIF('清洗总表'!$E$5:$E$141,"纠错")
B14: 工作表索引
B15: 清洗总表 | C15: 137只旧分类、新分类、动作、判词、详细理由及证据
B16: 机器人 | C16: 85只保留的机器人本体、集成及硬件零部件公司
B17: 物理AI | C17: 38只感知、控制、训练、数据、终端及具身本体公司
B18: 摘除清单 | C18: 20只错标、间接映射或研发预期退出公司
B19: 概念统计 | C19: 各二级概念核心/相关数量；底层为精确展开数据
B22: 核心：相关产品是明确主营或主要收入应用；相关：有直接产品、订单、交付或收入，但仍属新业务或收入占比较低。
B23: 摘除：仅参股、通用能力映射、无直接证据，或只有研发送样且无商业化；小额真实收入与纯研发预期分开处理。
B24: 边界：硬件零部件留在机器人；具身本体、感知、数据、仿真、动作捕捉、智能控制、终端和通信模组归物理AI。
B25: 主营资料：iFinD ifind_get_stock_info（2026-10-27）；逐股证据名称、日期与URL见各明细表Source列。

Sheet 清洗总表
B2: 机器人与物理AI · 137只逐项复核
B3: 每只股票一行；保留双分类，详细说明产品关系、商业化阶段及核心/相关判词。
B4: 代码 | C4: 名称 | D4: 旧分类与概念 | E4: 动作 | F4: 新一级分类 | G4: 新概念 | H4: 判词 | I4: 详细理由 | J4: 证据名称 | K4: 证据日期 | L4: Source Name | M4: Source URL
B5: 000559 | C5: 万向钱潮 | D5: 机器人：零部件 | E5: 纠错 | F5: 机器人 | G5: 丝杠、轴承、减速器 | H5: 相关 | I5: 主营仍为汽车底盘及传动零部件，但已将精密轴、轴承技术延伸至人形机器人行星滚柱丝杠、关节万向节和专用轴承；已具备10万套滚柱丝杠及1000万套关节万向节产能，减速器仍在研发，属于有产能和送样基础的新业务，故定相关并细化零部件标签。 | J5: 万向钱潮：2026年计划建成机器人专用轴承产能120万套 | K5: 2025-12-23 | L5: iFinD ifind_get_stock_info (as of 2026-10-27)；万向钱潮：2026年计划建成机器人专用轴承产能120万套 | M5: https://finance.sina.com.cn/stock/bxjj/2025-12-23/doc-inhcuqen0790186.shtml
B6: 000678 | C6: 襄阳轴承 | D6: 机器人：轴承 | E6: 纠错 | F6: 机器人 | G6: 轴承 | H6: 相关 | I6: 主营为汽车轴承、等速万向节和轮毂轴承单元，部分精密轴承已用于谐波及RV减速器并形成16.11万元实际收入。虽然金额很小且仍处市场拓展阶段，但已越过纯研发与送样阶段，按有真实销售可保留的口径判为相关，不升级为核心。 | J6: 襄阳轴承股票交易异常波动公告 | K6: 2026-10-23 | L6: iFinD ifind_get_stock_info (as of 2026-10-27)；襄阳轴承股票交易异常波动公告 | M6: https://www.cfi.net.cn/p20261023002762.html
B7: 000700 | C7: 模塑科技 | D7: 机器人：零部件 | E7: 纠错 | F7: 机器人 | G7: 结构件 | H7: 相关 | I7: 主营汽车保险杠等外饰件，公司将塑料外饰成型能力延伸至人形机器人头部、躯干等外覆盖件，产品直接构成机器人本体外部结构；已签订采购框架协议并取得小批量订单，越过纯研发阶段，但尚非主要收入来源，故定相关并改称结构件。 | J7: 模塑科技获4家机构调研：人形机器人外覆盖件获小批量订单 | K7: 2025-12-23 | L7: iFinD ifind_get_stock_info (as of 2026-10-27)；模塑科技获4家机构调研：人形机器人外覆盖件获小批量订单 | M7: https://finance.sina.com.cn/stock/aigc/jgdy/2025-12-23/doc-inhcuqen0803427.shtml
B8: 000810 | C8: 创维数字 | D8: 物理AI：物理AI_智能终端 | E8: 新增 | F8: 物理AI | G8: 物理AI_智能终端、物理AI_数据采集 | H8: 相关 | I8: 机顶盒、XR、AI眼镜及网络摄像机属于已商业化智能终端；公司进一步推出EGO双目、六摄、九摄和腕部相机，利用空间定位、多摄像头协同及时间同步能力采集机器人训练所需第一视角数据，且相关产品已实现销售，因此保留终端并新增数据采集。 | J8: 创维数字：已推出具身智能数据采集相关产品并实现销售 | K8: 2026-10-23 | L8: iFinD ifind_get_stock_info (as of 2026-10-27)；创维数字：已推出具身智能数据采集相关产品并实现销售 | M8: https://finance.sina.com.cn/stock/relnews/dongmiqa/2026-10-23/doc-iniwfmnh8324070.shtml
B9: 000837 | C9: 秦川机床 | D9: 机器人：丝杠 | E9: 新增 | F9: 机器人 | G9: 丝杠、减速器 | H9: 相关 | I9: 主营精密数控机床、滚动功能部件和复杂刀具，BX系列产品直接用于工业机器人关节减速，滚珠丝杠及行星滚柱丝杠用于线性传动；关节减速器已形成系列化产品，丝杠具有小批量生产验证基础，属于机床主业之外的实际产品业务，故保留丝杠并新增减速器。 | J9: 秦川机器人关节减速器亮相CIIF2025上海工博会 | K9: 2025-09-24 | L9: iFinD ifind_get_stock_info (as of 2026-10-27)；秦川机器人关节减速器亮相CIIF2025上海工博会 | M9: https://www.qinchuan.com/show-28-1539-1.html
B10: 000887 | C10: 中鼎股份 | D10: 机器人：减速器 | E10: 保留 | F10: 机器人 | G10: 减速器 | H10: 相关 | I10: 主营汽车密封、减震、热管理及轻量化系统，机器人业务通过子公司提供谐波、行星减速器，直接用于人形机器人关节传动；已取得众擎、傅利叶及其他头部客户定点，截至2026年上半年订单约30万颗、年产能15万颗，商业化和订单证据明确，故定相关。 | J10: 中鼎股份投资者关系活动记录表 | K10: 2026-10-21 | L10: iFinD ifind_get_stock_info (as of 2026-10-27)；中鼎股份投资者关系活动记录表 | M10: http://static.cninfo.com.cn/finalpage/2026-10-21/1225614608.PDF
B11: 001306 | C11: 夏厦精密 | D11: 机器人：减速器 | E11: 纠错 | F11: 机器人 | G11: 减速器 | H11: 相关 | I11: 主营小模数齿轮、减速机及配件，相关产品可作为工业机器人关键传动部件，并已拓展云深处等机器人客户；但公司披露机器人领域在手及协议订单规模仍较小，汽车、电动工具齿轮仍是主要业务，因此保留减速器标签，但不按机器人核心主营定级。 | J11: 机器人“扎堆”上春晚，背后概念股抢先看 | K11: 2026-02-16 | L11: iFinD ifind_get_stock_info (as of 2026-10-27)；机器人“扎堆”上春晚，背后概念股抢先看 | M11: https://www.mrjjxw.com/articles/2026-02-16/4263911.html
B12: 001331 | C12: 胜通能源 | D12: 机器人：本体及应用；机器人：本体及应用 | E12: 摘除 | F12: — | G12: — | H12: 摘除 | I12: 上市主体现阶段仍从事LNG采购、运输、销售及运输服务，没有机器人本体或应用产品。七腾机器人通过协议转让和要约收购成为控股股东，仅代表控制权变化，不代表机器人资产或业务已经注入；公司亦明确提示不涉及机器人业务，故摘除并消除重复标签。 | J12: 8连板胜通能源：不涉及机器人相关业务 | K12: 2025-12-23 | L12: iFinD ifind_get_stock_info (as of 2026-10-27)；8连板胜通能源：不涉及机器人相关业务 | M12: https://www.jwview.com/jingwei/html/m/12-23/650789.shtml
B13: 002009 | C13: 天奇股份 | D13: 机器人：本体及应用；物理AI：物理AI_数据采集 | E13: 保留 | F13: 机器人、物理AI | G13: 本体及应用；物理AI_数据采集 | H13: 相关 | I13: 智能自动化装备及机器人用于汽车制造等工业场景，构成机器人应用业务；具身智能板块建设工业数据采集与实训中心，采集多模态真机数据并开展模型训练，中心已正式投入运行。装备交付和训练数据服务均有实际项目支撑，故保留双分类并定相关。 | J13: 天奇自动化工程股份有限公司2025年年度报告摘要 | K13: 2026-04-28 | L13: iFinD ifind_get_stock_info (as of 2026-10-27)；天奇自动化工程股份有限公司2025年年度报告摘要 | M13: https://static.cninfo.com.cn/finalpage/2026-04-28/1225218333.PDF
B14: 002031 | C14: 巨轮智能 | D14: 机器人：减速器 | E14: 新增 | F14: 机器人 | G14: 减速器、本体及应用 | H14: 相关 | I14: 主营轮胎模具、液压式硫化机及工业机器人与智能装备，RV减速器直接用于工业机器人关节；2025年RV减速器销售收入837.03万元、占营收1%，虽占比较小但已形成真实销售，并非单纯研发预期，因此定相关，并在减速器之外补充本体及应用。 | J14: 巨轮智能装备股份有限公司股票交易异常波动公告 | K14: 2026-05-11 | L14: iFinD ifind_get_stock_info (as of 2026-10-27)；巨轮智能装备股份有限公司股票交易异常波动公告 | M14: https://disc.static.szse.cn/download/disc/disk03/finalpage/2026-05-11/e39dccaf-bf1a-4f56-8459-00346cde53c7.PDF
B15: 002046 | C15: 国机精工 | D15: 机器人：丝杠设备 | E15: 纠错 | F15: 机器人 | G15: 轴承 | H15: 相关 | I15: 主营特种及精密轴承、超硬材料和高端装备，公司明确不具备滚柱丝杠生产能力，旧丝杠设备标签不准确；实际机器人产品包括RV减速器薄壁轴承、谐波减速器柔性轴承及交叉滚子轴承，2025年已实现小批量生产，故纠错为机器人轴承并定相关。 | J15: 国机精工：2025年营业收入30.19亿元，机器人轴承实现小批量生产 | K15: 2026-04-13 | L15: iFinD ifind_get_stock_info (as of 2026-10-27)；国机精工：2025年营业收入30.19亿元，机器人轴承实现小批量生产 | M15: https://static.weeklyonstock.com/26/0413/AB2618495176185.html
... B141: 920885 | C141: 星辰科技 | D141: 机器人：伺服系统 | E141: 保留 | F141: 机器人 | G141: 伺服系统 | H141: 相关 | I141: 随动控制总成、伺服驱动器和伺服电机是公司主营，产品覆盖军工、新能源和工业控制等运动控制场景，与机器人伺服系统存在直接产品关系。但特种机器人伺服电机仍处样机及研发应用阶段，机器人只是多个下游之一，故保留相关而不升级为核心。 | J141: 星辰科技：2025年年度报告 | K141: 2026-04-16 | L141: iFinD ifind_get_stock_info (as of 2026-10-27)；星辰科技：2025年年度报告 | M141: https://money.finance.sina.com.cn/corp/view/vCB_AllBulletinDetail.php?stockid=920885&id=12101644

Sheet 机器人
B2: 机器人 · 保留与纠错股池
B3: 硬件零部件不因人形机器人应用自动迁入物理AI；系统集成、本体与零部件分开。
B4: 代码 | C4: 名称 | D4: 旧分类与概念 | E4: 动作 | F4: 新一级分类 | G4: 新概念 | H4: 判词 | I4: 详细理由 | J4: 证据名称 | K4: 证据日期 | L4: Source Name | M4: Source URL
B5: 000559 | C5: 万向钱潮 | D5: 机器人：零部件 | E5: 纠错 | F5: 机器人 | G5: 丝杠、轴承、减速器 | H5: 相关 | I5: 主营仍为汽车底盘及传动零部件，但已将精密轴、轴承技术延伸至人形机器人行星滚柱丝杠、关节万向节和专用轴承；已具备10万套滚柱丝杠及1000万套关节万向节产能，减速器仍在研发，属于有产能和送样基础的新业务，故定相关并细化零部件标签。 | J5: 万向钱潮：2026年计划建成机器人专用轴承产能120万套 | K5: 2025-12-23 | L5: iFinD ifind_get_stock_info (as of 2026-10-27)；万向钱潮：2026年计划建成机器人专用轴承产能120万套 | M5: https://finance.sina.com.cn/stock/bxjj/2025-12-23/doc-inhcuqen0790186.shtml
B6: 000678 | C6: 襄阳轴承 | D6: 机器人：轴承 | E6: 纠错 | F6: 机器人 | G6: 轴承 | H6: 相关 | I6: 主营为汽车轴承、等速万向节和轮毂轴承单元，部分精密轴承已用于谐波及RV减速器并形成16.11万元实际收入。虽然金额很小且仍处市场拓展阶段，但已越过纯研发与送样阶段，按有真实销售可保留的口径判为相关，不升级为核心。 | J6: 襄阳轴承股票交易异常波动公告 | K6: 2026-10-23 | L6: iFinD ifind_get_stock_info (as of 2026-10-27)；襄阳轴承股票交易异常波动公告 | M6: https://www.cfi.net.cn/p20261023002762.html
B7: 000700 | C7: 模塑科技 | D7: 机器人：零部件 | E7: 纠错 | F7: 机器人 | G7: 结构件 | H7: 相关 | I7: 主营汽车保险杠等外饰件，公司将塑料外饰成型能力延伸至人形机器人头部、躯干等外覆盖件，产品直接构成机器人本体外部结构；已签订采购框架协议并取得小批量订单，越过纯研发阶段，但尚非主要收入来源，故定相关并改称结构件。 | J7: 模塑科技获4家机构调研：人形机器人外覆盖件获小批量订单 | K7: 2025-12-23 | L7: iFinD ifind_get_stock_info (as of 2026-10-27)；模塑科技获4家机构调研：人形机器人外覆盖件获小批量订单 | M7: https://finance.sina.com.cn/stock/aigc/jgdy/2025-12-23/doc-inhcuqen0803427.shtml
B8: 000837 | C8: 秦川机床 | D8: 机器人：丝杠 | E8: 新增 | F8: 机器人 | G8: 丝杠、减速器 | H8: 相关 | I8: 主营精密数控机床、滚动功能部件和复杂刀具，BX系列产品直接用于工业机器人关节减速，滚珠丝杠及行星滚柱丝杠用于线性传动；关节减速器已形成系列化产品，丝杠具有小批量生产验证基础，属于机床主业之外的实际产品业务，故保留丝杠并新增减速器。 | J8: 秦川机器人关节减速器亮相CIIF2025上海工博会 | K8: 2025-09-24 | L8: iFinD ifind_get_stock_info (as of 2026-10-27)；秦川机器人关节减速器亮相CIIF2025上海工博会 | M8: https://www.qinchuan.com/show-28-1539-1.html
B9: 000887 | C9: 中鼎股份 | D9: 机器人：减速器 | E9: 保留 | F9: 机器人 | G9: 减速器 | H9: 相关 | I9: 主营汽车密封、减震、热管理及轻量化系统，机器人业务通过子公司提供谐波、行星减速器，直接用于人形机器人关节传动；已取得众擎、傅利叶及其他头部客户定点，截至2026年上半年订单约30万颗、年产能15万颗，商业化和订单证据明确，故定相关。 | J9: 中鼎股份投资者关系活动记录表 | K9: 2026-10-21 | L9: iFinD ifind_get_stock_info (as of 2026-10-27)；中鼎股份投资者关系活动记录表 | M9: http://static.cninfo.com.cn/finalpage/2026-10-21/1225614608.PDF
B10: 001306 | C10: 夏厦精密 | D10: 机器人：减速器 | E10: 纠错 | F10: 机器人 | G10: 减速器 | H10: 相关 | I10: 主营小模数齿轮、减速机及配件，相关产品可作为工业机器人关键传动部件，并已拓展云深处等机器人客户；但公司披露机器人领域在手及协议订单规模仍较小，汽车、电动工具齿轮仍是主要业务，因此保留减速器标签，但不按机器人核心主营定级。 | J10: 机器人“扎堆”上春晚，背后概念股抢先看 | K10: 2026-02-16 | L10: iFinD ifind_get_stock_info (as of 2026-10-27)；机器人“扎堆”上春晚，背后概念股抢先看 | M10: https://www.mrjjxw.com/articles/2026-02-16/4263911.html
B11: 002009 | C11: 天奇股份 | D11: 机器人：本体及应用；物理AI：物理AI_数据采集 | E11: 保留 | F11: 机器人 | G11: 本体及应用 | H11: 相关 | I11: 智能自动化装备及机器人用于汽车制造等工业场景，构成机器人应用业务；具身智能板块建设工业数据采集与实训中心，采集多模态真机数据并开展模型训练，中心已正式投入运行。装备交付和训练数据服务均有实际项目支撑，故保留双分类并定相关。 | J11: 天奇自动化工程股份有限公司2025年年度报告摘要 | K11: 2026-04-28 | L11: iFinD ifind_get_stock_info (as of 2026-10-27)；天奇自动化工程股份有限公司2025年年度报告摘要 | M11: https://static.cninfo.com.cn/finalpage/2026-04-28/1225218333.PDF
B12: 002031 | C12: 巨轮智能 | D12: 机器人：减速器 | E12: 新增 | F12: 机器人 | G12: 减速器、本体及应用 | H12: 相关 | I12: 主营轮胎模具、液压式硫化机及工业机器人与智能装备，RV减速器直接用于工业机器人关节；2025年RV减速器销售收入837.03万元、占营收1%，虽占比较小但已形成真实销售，并非单纯研发预期，因此定相关，并在减速器之外补充本体及应用。 | J12: 巨轮智能装备股份有限公司股票交易异常波动公告 | K12: 2026-05-11 | L12: iFinD ifind_get_stock_info (as of 2026-10-27)；巨轮智能装备股份有限公司股票交易异常波动公告 | M12: https://disc.static.szse.cn/download/disc/disk03/finalpage/2026-05-11/e39dccaf-bf1a-4f56-8459-00346cde53c7.PDF
B13: 002046 | C13: 国机精工 | D13: 机器人：丝杠设备 | E13: 纠错 | F13: 机器人 | G13: 轴承 | H13: 相关 | I13: 主营特种及精密轴承、超硬材料和高端装备，公司明确不具备滚柱丝杠生产能力，旧丝杠设备标签不准确；实际机器人产品包括RV减速器薄壁轴承、谐波减速器柔性轴承及交叉滚子轴承，2025年已实现小批量生产，故纠错为机器人轴承并定相关。 | J13: 国机精工：2025年营业收入30.19亿元，机器人轴承实现小批量生产 | K13: 2026-04-13 | L13: iFinD ifind_get_stock_info (as of 2026-10-27)；国机精工：2025年营业收入30.19亿元，机器人轴承实现小批量生产 | M13: https://static.weeklyonstock.com/26/0413/AB2618495176185.html
B14: 002050 | C14: 三花智控 | D14: 机器人：总成 | E14: 保留 | F14: 机器人 | G14: 总成 | H14: 相关 | I14: 主营制冷空调控制部件和新能源汽车热管理，机器人业务为仿生机器人机电执行器，将驱动、传动等部件集成为关节执行总成；2026年上半年核心产品已推进批量交付和产线爬坡。其本质是机器人硬件执行环节，不属于感知或训练类物理AI，故保留机器人总成。 | J14: 三花智控2026年半年度报告 | K14: 2026-08-27 | L14: iFinD ifind_get_stock_info (as of 2026-10-27)；三花智控2026年半年度报告 | M14: https://money.finance.sina.com.cn/corp/view/vCB_AllBulletinDetail.php?stockid=002050&id=12550185
B15: 002126 | C15: 银轮股份 | D15: 机器人：其他 | E15: 纠错 | F15: 机器人 | G15: 总成 | H15: 相关 | I15: 主营汽车、工程机械及数字能源热管理，机器人业务已延伸至旋转关节、线性关节、灵巧手和热管理模组，多个品类获得客户定点；2026年上半年关节电机、关节模组和大小脑热管理产品实现小批量生产，已有明确产品与客户，故将笼统的其他纠错为总成。 | J15: 银轮股份2026年半年报点评：具身智能多品类实现小批量生产 | K15: 2026-08-28 | L15: iFinD ifind_get_stock_info (as of 2026-10-27)；银轮股份2026年半年报点评：具身智能多品类实现小批量生产 | M15: https://news.futunn.com/post/78459582/yinlun-co-ltd-002126-2026-semi-annual-report-commentary-strengthening
... B89: 920885 | C89: 星辰科技 | D89: 机器人：伺服系统 | E89: 保留 | F89: 机器人 | G89: 伺服系统 | H89: 相关 | I89: 随动控制总成、伺服驱动器和伺服电机是公司主营，产品覆盖军工、新能源和工业控制等运动控制场景，与机器人伺服系统存在直接产品关系。但特种机器人伺服电机仍处样机及研发应用阶段，机器人只是多个下游之一，故保留相关而不升级为核心。 | J89: 星辰科技：2025年年度报告 | K89: 2026-04-16 | L89: iFinD ifind_get_stock_info (as of 2026-10-27)；星辰科技：2025年年度报告 | M89: https://money.finance.sina.com.cn/corp/view/vCB_AllBulletinDetail.php?stockid=920885&id=12101644

Sheet 物理AI
B2: 物理AI · 感知、控制、训练与具身本体
B3: 统一具身本体/传感器口径；传统工业机器人收入不直接作为具身智能核心依据。
B4: 代码 | C4: 名称 | D4: 旧分类与概念 | E4: 动作 | F4: 新一级分类 | G4: 新概念 | H4: 判词 | I4: 详细理由 | J4: 证据名称 | K4: 证据日期 | L4: Source Name | M4: Source URL
B5: 000810 | C5: 创维数字 | D5: 物理AI：物理AI_智能终端 | E5: 新增 | F5: 物理AI | G5: 物理AI_智能终端、物理AI_数据采集 | H5: 相关 | I5: 机顶盒、XR、AI眼镜及网络摄像机属于已商业化智能终端；公司进一步推出EGO双目、六摄、九摄和腕部相机，利用空间定位、多摄像头协同及时间同步能力采集机器人训练所需第一视角数据，且相关产品已实现销售，因此保留终端并新增数据采集。 | J5: 创维数字：已推出具身智能数据采集相关产品并实现销售 | K5: 2026-10-23 | L5: iFinD ifind_get_stock_info (as of 2026-10-27)；创维数字：已推出具身智能数据采集相关产品并实现销售 | M5: https://finance.sina.com.cn/stock/relnews/dongmiqa/2026-10-23/doc-iniwfmnh8324070.shtml
B6: 002009 | C6: 天奇股份 | D6: 机器人：本体及应用；物理AI：物理AI_数据采集 | E6: 保留 | F6: 物理AI | G6: 物理AI_数据采集 | H6: 相关 | I6: 智能自动化装备及机器人用于汽车制造等工业场景，构成机器人应用业务；具身智能板块建设工业数据采集与实训中心，采集多模态真机数据并开展模型训练，中心已正式投入运行。装备交付和训练数据服务均有实际项目支撑，故保留双分类并定相关。 | J6: 天奇自动化工程股份有限公司2025年年度报告摘要 | K6: 2026-04-28 | L6: iFinD ifind_get_stock_info (as of 2026-10-27)；天奇自动化工程股份有限公司2025年年度报告摘要 | M6: https://static.cninfo.com.cn/finalpage/2026-04-28/1225218333.PDF
B7: 002139 | C7: 拓邦股份 | D7: 机器人：电机 | E7: 迁移 | F7: 物理AI | G7: 物理AI_智能控制 | H7: 相关 | I7: 智能控制器是核心主业，机器人方向已形成伺服驱动、电机和运动控制平台；空心杯电机及灵驱微擎用于灵巧手执行，并与国内头部客户形成量产订单意向。电机属于机器人硬件，驱动与运动控制直接承担动作决策执行，故保留电机并迁移新增物理AI智能控制。 | J7: 深圳拓邦股份有限公司投资者关系活动记录：空心杯电机及灵驱微擎量产订单意向 | K7: 2026-04-13 | L7: iFinD ifind_get_stock_info (as of 2026-10-27)；深圳拓邦股份有限公司投资者关系活动记录：空心杯电机及灵驱微擎量产订单意向 | M7: http://file.finance.sina.com.cn/cn/diaoyan/jgdy/2026/2026-04/2026-04-13/10177134_1.PDF
B8: 002354 | C8: 天娱数科 | D8: 物理AI：物理AI_数据采集 | E8: 保留 | F8: 物理AI | G8: 物理AI_数据采集 | H8: 相关 | I8: 主营仍包括AI营销和应用分发，物理AI业务由Behavision平台承载，通过真实机器人操作与Isaac Sim仿真生成、优化3D及多模态具身数据，用于模型训练和测试；已形成机器人任务数据并完成多项数据资产登记，属于训练数据服务而非一般营销数据，故保留。 | J8: 天娱数科2025年年度报告 | K8: 2026-04-21 | L8: iFinD ifind_get_stock_info (as of 2026-10-27)；天娱数科2025年年度报告 | M8: https://money.finance.sina.com.cn/corp/view/vCB_AllBulletinDetail.php?stockid=002354&id=12121578
B9: 002380 | C9: 科远智慧 | D9: 物理AI：物理AI_数据采集 | E9: 纠错 | F9: 物理AI | G9: 物理AI_智能控制 | H9: 相关 | I9: 主营工业自动化、工业互联网和工业软件，NT6000 DCS及PLC承担现场数据采集和指令执行；公司进一步开发具身智能驱控一体化平台，以云边端协同进行分析决策并联动现场装备。与一般工业数据采集相比，智能驱控更能准确体现其物理AI直接关系，故纠错。 | J9: 南京科远智慧科技集团股份有限公司2025年年度报告 | K9: 2026-04-15 | L9: iFinD ifind_get_stock_info (as of 2026-10-27)；南京科远智慧科技集团股份有限公司2025年年度报告 | M9: https://static.cninfo.com.cn/finalpage/2026-04-15/1225103023.PDF
B10: 002527 | C10: 新时达 | D10: 机器人：本体及应用 | E10: 迁移 | F10: 物理AI | G10: 物理AI_具身本体 | H10: 相关 | I10: 2025年机器人产品及系统收入8.495亿元、占24.03%，2026年上半年占24.31%，传统机器人业务仍有实质收入。SYNDA R1已具备自主导航、多模态感知，并能协同环境感知、任务决策与高精度运控，符合具身智能特征；但具身产品尚非收入主体，故保留传统机器人标签并新增物理AI具身本体，判相关。 | J10: 新时达：2026年半年度报告 | K10: 2026-08-28 | L10: iFinD ifind_get_stock_info (as of 2026-10-27)；新时达：2026年半年度报告 | M10: https://money.finance.sina.com.cn/corp/view/vCB_AllBulletinDetail.php?stockid=002527&id=12558223
B11: 002681 | C11: 奋达科技 | D11: 机器人：本体及应用 | E11: 迁移 | F11: 物理AI | G11: 物理AI_智能终端 | H11: 相关 | I11: 元萝卜棋类机器人持续出货，AI桌面机器人、萌宠陪伴产品及头部客户代工整机或模组已量产或小规模出货，具备明确智能终端产品和商业化交付。其定位是具备交互与智能功能的消费级终端，而非通用机器人本体；业务仍处开拓期，故迁入物理AI智能终端并判相关。 | J11: 奋达科技：2025年年度报告 | K11: 2026-04-29 | L11: iFinD ifind_get_stock_info (as of 2026-10-27)；奋达科技：2025年年度报告 | M11: https://vip.stock.finance.sina.com.cn/corp/view/vCB_AllBulletinDetail.php?stockid=002681&id=12263747
B12: 002829 | C12: 星网宇达 | D12: 机器人：传感器 | E12: 迁移 | F12: 物理AI | G12: 物理AI_传感器、物理AI_具身本体 | H12: 核心 | I12: IMU、组合惯导和光电吊舱构成环境感知层，无人机、无人车、无人船构成自主执行系统；2025年信息感知与无人系统收入分别为1.191亿元、2.053亿元，合计约85.9%。无人车采用多传感融合并支持自主避障，产品体系、主营业务和收入均直接支撑物理AI核心定位。 | J12: 星网宇达：2025年年度报告摘要 | K12: 2026-04-24 | L12: iFinD ifind_get_stock_info (as of 2026-10-27)；星网宇达：2025年年度报告摘要 | M12: https://stock.stockstar.com/notice/SN2026042400006904.shtml
B13: 300007 | C13: 汉威科技 | D13: 机器人：传感器 | E13: 迁移 | F13: 物理AI | G13: 物理AI_传感器 | H13: 相关 | I13: 苏州能斯达柔性触觉传感器、电子皮肤和指尖压力采集模块已于2025年小批量供货，自动化产线投入使用；IMU已送样并取得少量订单。产品直接承担机器人对压力、触觉及运动状态的物理环境感知，已有早期商业交付但规模有限，故迁入物理AI传感器并判相关。 | J13: 汉威科技集团股份有限公司2025年年度报告摘要 | K13: 2026-04-18 | L13: iFinD ifind_get_stock_info (as of 2026-10-27)；汉威科技集团股份有限公司2025年年度报告摘要 | M13: https://disc.static.szse.cn/disc/disk03/finalpage/2026-04-18/3267f777-2903-4324-beed-5b7b67bf01cf.PDF
B14: 300024 | C14: 机器人 | D14: 机器人：本体及应用 | E14: 迁移 | F14: 物理AI | G14: 物理AI_具身本体 | H14: 相关 | I14: 传统工业机器人和自动化业务仍占主要位置，但公司已披露“松羿”轮式、“松行”双足及智能类人双臂平台；双臂平台具备自主环境感知与任务推理，轮式产品配置多模态传感，直接对应具身智能。2025年仍属前沿技术与成果储备，尚未形成主业收入，故保留传统机器人并新增物理AI具身本体，判相关。 | J14: 机器人：2025年年度报告 | K14: 2026-04-24 | L14: iFinD ifind_get_stock_info (as of 2026-10-27)；机器人：2025年年度报告 | M14: http://money.finance.sina.com.cn/corp/view/vCB_AllBulletinDetail.php?stockid=300024&id=12171947
B15: 300296 | C15: 利亚德 | D15: 机器人：本体及应用 | E15: 迁移 | F15: 物理AI | G15: 物理AI_动作捕捉 | H15: 相关 | I15: NP及虚拟动点OptiTrack提供光学动作捕捉，并形成光学与无标记、光学与惯性方案及Lydia动作大模型，可用于机器人动作数据采集和训练，并非机器人本体。2025年AI与空间计算收入3.166亿元、占4.48%，已有真实商业收入但非主业，故迁至物理AI动作捕捉并判相关。 | J15: 利亚德：2025年年度报告 | K15: 2026-04-16 | L15: iFinD ifind_get_stock_info (as of 2026-10-27)；利亚德：2025年年度报告 | M15: https://vip.stock.finance.sina.com.cn/corp/view/vCB_AllBulletinDetail.php?stockid=300296&id=12096411
... B42: 688836 | C42: 宇树科技-W | D42: 机器人：本体及应用 | E42: 迁移 | F42: 物理AI | G42: 物理AI_具身本体 | H42: 核心 | I42: 人形机器人、四足机器人及具身智能模型构成公司明确主营，产品已规模销售。2025年人形机器人收入86783.19万元、四足机器人收入69762.56万元，两类本体合计占主营约93.4%，既有具身产品直接性又有高度主营集中度，故迁入物理AI具身本体并保留核心。 | J42: 宇树科技股份有限公司首次公开发行股票并在科创板上市招股说明书 | K42: 2026年 | L42: iFinD ifind_get_stock_info (as of 2026-10-27)；宇树科技股份有限公司首次公开发行股票并在科创板上市招股说明书 | M42: https://dataclouds.cninfo.com.cn/sjother2/documents/2026/2026-05-25/3d7fc0538abe281340a95c9c77a90525.pdf

Sheet 摘除清单
B2: 摘除清单 · 错标、间接映射与研发预期
B3: 仅参股、通用能力映射、无直接产品证据或仍处研发送样且无商业化的标签退出。
B4: 代码 | C4: 名称 | D4: 旧分类与概念 | E4: 动作 | F4: 新一级分类 | G4: 新概念 | H4: 判词 | I4: 详细理由 | J4: 证据名称 | K4: 证据日期 | L4: Source Name | M4: Source URL
B5: 001331 | C5: 胜通能源 | D5: 机器人：本体及应用；机器人：本体及应用 | E5: 摘除 | F5: — | G5: — | H5: 摘除 | I5: 上市主体现阶段仍从事LNG采购、运输、销售及运输服务，没有机器人本体或应用产品。七腾机器人通过协议转让和要约收购成为控股股东，仅代表控制权变化，不代表机器人资产或业务已经注入；公司亦明确提示不涉及机器人业务，故摘除并消除重复标签。 | J5: 8连板胜通能源：不涉及机器人相关业务 | K5: 2025-12-23 | L5: iFinD ifind_get_stock_info (as of 2026-10-27)；8连板胜通能源：不涉及机器人相关业务 | M5: https://www.jwview.com/jingwei/html/m/12-23/650789.shtml
B6: 002079 | C6: 苏州固锝 | D6: 机器人：传感器 | E6: 摘除 | F6: — | G6: — | H6: 摘除 | I6: 上市主体主营二极管、功率半导体器件及集成电路封测，机器人口径主要是功率器件的通用下游应用；MEMS感知产品主要来自参股明皜传感，上市公司传感器封装能力不能直接等同机器人专用传感器产品，按少量参股和上游间接映射口径摘除。 | J6: 苏州固锝电子股份有限公司投资者关系活动记录表 | K6: 2026-05-08 | L6: iFinD ifind_get_stock_info (as of 2026-10-27)；苏州固锝电子股份有限公司投资者关系活动记录表 | M6: https://pdf.dfcfw.com/pdf/H2_AN202605081822074722_1.pdf
B7: 002249 | C7: 大洋电机 | D7: 机器人：电机 | E7: 摘除 | F7: — | G7: — | H7: 摘除 | I7: 主营建筑家居电机、汽车起动机及新能源车辆动力总成，通用电机业务不能直接视作机器人产品；人形机器人项目主要完成关节模组方案设计和研发测试，公司2026年10月仍明确相关业务尚未形成营业收入、短期不影响业绩，按研发预期和未商业化口径摘除。 | J7: 大洋电机：具身智能机器人关节模组业务处于研发/测试阶段，尚未形成营业收入 | K7: 2026-10-23 | L7: iFinD ifind_get_stock_info (as of 2026-10-27)；大洋电机：具身智能机器人关节模组业务处于研发/测试阶段，尚未形成营业收入 | M7: https://www.cls.cn/detail/2513855
B8: 002850 | C8: 科达利 | D8: 机器人：减速器 | E8: 摘除 | F8: — | G8: — | H8: 摘除 | I8: 公司主业仍是锂电池精密结构件，机器人方向布局减速器旋转关节、丝杠直线关节和灵巧手，但2025年谐波减速器仍处样品测试验证阶段，尚无充分量产、订单或收入支撑。按仅研发送样退出的统一口径摘除，避免把技术布局当作已落地业务。 | J8: 科达利：2025年年度报告 | K8: 2026-03-28 | L8: iFinD ifind_get_stock_info (as of 2026-10-27)；科达利：2025年年度报告 | M8: https://money.finance.sina.com.cn/corp/view/vCB_AllBulletinDetail.php?stockid=002850&id=12027902
B9: 002931 | C9: 锋龙股份 | D9: 机器人：零部件 | E9: 摘除 | F9: — | G9: — | H9: 摘除 | I9: 优必选控股不等于上市公司已形成机器人业务。2026年上半年新锋龙尚未注资经营，8100万元关联销售预案虽聚焦机电组件和结构件，但报告期未形成收入；公司缺少可核验的机器人产品交付、量产和销售，原泛零部件标签依据不足，故摘除。 | J9: 锋龙股份：2026年半年度报告摘要 | K9: 2026-08-18 | L9: iFinD ifind_get_stock_info (as of 2026-10-27)；锋龙股份：2026年半年度报告摘要 | M9: http://money.finance.sina.com.cn/corp/view/vCB_AllBulletinDetail.php?stockid=002931&id=12499587
B10: 002965 | C10: 祥鑫科技 | D10: 机器人：结构件 | E10: 摘除 | F10: — | G10: — | H10: 摘除 | I10: 公司主营仍是汽车、储能等领域的冲压模具和金属结构件。虽然设立祥鑫（东莞）智能机器人并开展联合创新合作，但2025年报及2026年半年报均无可核验的机器人收入或量产交付，设立主体和合作平台不能替代业务证据，因此摘除原机器人结构件标签。 | J10: 祥鑫科技：2026年半年度报告 | K10: 2026-08-26 | L10: iFinD ifind_get_stock_info (as of 2026-10-27)；祥鑫科技：2026年半年度报告 | M10: https://money.finance.sina.com.cn/corp/view/vCB_AllBulletinDetail.php?stockid=002965&id=12533661
B11: 002988 | C11: 豪美新材 | D11: 机器人：结构件 | E11: 摘除 | F11: — | G11: — | H11: 摘除 | I11: 公司现有产品主要是汽车轻量化、建筑及工业铝型材。2025年仅提出加强机器人等新兴领域材料研发、为进入新领域创造条件，未披露具体机器人结构件产品、订单或量产交付；研发方向不能直接等同于机器人业务和商业化收入，故摘除原结构件标签。 | J11: 豪美新材：2025年年度报告 | K11: 2026-04-27 | L11: iFinD ifind_get_stock_info (as of 2026-10-27)；豪美新材：2025年年度报告 | M11: http://money.finance.sina.com.cn/corp/view/vCB_AllBulletinDetail.php?stockid=002988&id=12202238
B12: 300258 | C12: 精锻科技 | D12: 机器人：减速器 | E12: 摘除 | F12: — | G12: — | H12: 摘除 | I12: 摆线针轮、行星减速器和滚柱丝杠仍处样品开发、交付验证及持续优化阶段，2026年4月30日业绩说明会明确尚未形成销售收入，网传特斯拉独供也被否认。相关产品尚处研发验证期，缺少量产、订单和收入支撑，原减速器标签容易放大业务成熟度，故摘除。 | J12: 江苏太平洋精锻科技股份有限公司投资者关系活动记录表 | K12: 2026-05-04 | L12: iFinD ifind_get_stock_info (as of 2026-10-27)；江苏太平洋精锻科技股份有限公司投资者关系活动记录表 | M12: https://static.cninfo.com.cn/finalpage/2026-05-04/1225275988.PDF
B13: 300403 | C13: 汉宇集团 | D13: 机器人：减速器 | E13: 摘除 | F13: — | G13: — | H13: 摘除 | I13: 上市公司自身主营家电排水泵等产品，谐波减速器、机电关节等机器人业务由同川科技开展，公告明确同川科技仅为参股公司；现有证据只能形成参股间接敞口，不能等同于上市公司自产减速器或关节产品交付，按参股边界摘除。 | J13: 关于公司2026年度日常关联交易预计的补充公告 | K13: 2026-04-27 | L13: iFinD ifind_get_stock_info (as of 2026-10-27)；关于公司2026年度日常关联交易预计的补充公告 | M13: https://www.cnfin.com/announ/detail/index.html?id=830533942050&code=300403&dannoun=lcdetail&announ=lc
B14: 300445 | C14: 康斯特 | D14: 机器人：传感器 | E14: 摘除 | F14: — | G14: — | H14: 摘除 | I14: 公司主营高精度压力传感器、校准仪表和工业校准测试系统，直接应用是工业计量、压力检测及设备运维；机器人至多是潜在校准测试对象，现有披露未见用于机器人的力觉、触觉或环境感知产品，也无相关订单和交付证据，不能由工业校准能力推导机器人传感器标签。 | J14: 康斯特：公司主营业务的校准测试产品已在产业端广泛验证并被全球用户认可 | K14: 2025-04-24 | L14: iFinD ifind_get_stock_info (as of 2026-10-27)；康斯特：公司主营业务的校准测试产品已在产业端广泛验证并被全球用户认可 | M14: http://m.10jqka.com.cn/20250424/c667707575.shtml
B15: 301502 | C15: 华阳智能 | D15: 机器人：无框电机 | E15: 摘除 | F15: — | G15: — | H15: 摘除 | I15: 公司主营微特电机及应用产品，多款无框电机和机器人模组电机虽已完成开发并具备量产条件，但2025年报仍称推进客户对接，此前亦明确尚未应用于人形机器人，未见正式订单、交付或收入。微特电机主营不能直接外推为机器人核心，具备量产能力不等于商业化落地，原核心标签依据不足，故摘除。 | J15: 华阳智能：2025年年度报告 | K15: 2026-04-29 | L15: iFinD ifind_get_stock_info (as of 2026-10-27)；华阳智能：2025年年度报告 | M15: http://money.finance.sina.com.cn/corp/view/vCB_AllBulletinDetail.php?stockid=301502&id=12268645
... B24: 688585 | C24: 上纬新材 | D24: 机器人：本体及应用 | E24: 摘除 | F24: — | G24: — | H24: 摘除 | I24: 公司2025年组建消费级具身机器人团队并形成小型人形样机，2026年推出启元Q1、T1，说明并非完全无产品证据。但机器人仍处研发阶段，尚未量产，也未形成收入和利润，新材料主业未改变，按研发预期和边缘标签应摘除的规则取消分类。 | J24: 上纬新材：2025年年度报告 | K24: 2026-03-31 | L24: iFinD ifind_get_stock_info (as of 2026-10-27)；上纬新材：2025年年度报告 | M24: https://vip.stock.finance.sina.com.cn/corp/view/vCB_AllBulletinDetail.php?stockid=688585&id=12047836

Sheet 概念展开
A1: 一级分类 | B1: 二级概念 | C1: 判词 | D1: 代码 | E1: 名称
A2: 机器人 | B2: 丝杠 | C2: 相关 | D2: 000559 | E2: 万向钱潮
A3: 机器人 | B3: 轴承 | C3: 相关 | D3: 000559 | E3: 万向钱潮
A4: 机器人 | B4: 减速器 | C4: 相关 | D4: 000559 | E4: 万向钱潮
A5: 机器人 | B5: 轴承 | C5: 相关 | D5: 000678 | E5: 襄阳轴承
A6: 机器人 | B6: 结构件 | C6: 相关 | D6: 000700 | E6: 模塑科技
A7: 物理AI | B7: 物理AI_智能终端 | C7: 相关 | D7: 000810 | E7: 创维数字
A8: 物理AI | B8: 物理AI_数据采集 | C8: 相关 | D8: 000810 | E8: 创维数字
A9: 机器人 | B9: 丝杠 | C9: 相关 | D9: 000837 | E9: 秦川机床
A10: 机器人 | B10: 减速器 | C10: 相关 | D10: 000837 | E10: 秦川机床
A11: 机器人 | B11: 减速器 | C11: 相关 | D11: 000887 | E11: 中鼎股份
A12: 机器人 | B12: 减速器 | C12: 相关 | D12: 001306 | E12: 夏厦精密
... A130: 机器人 | B130: 伺服系统 | C130: 相关 | D130: 920885 | E130: 星辰科技

Sheet 概念统计
B2: 概念统计 · 核心/相关分布
B3: 公式引用隐藏的概念展开表精确计数；一只股票可对应多个概念。
B4: 一级分类 | C4: 二级概念 | D4: 核心（只） | E4: 相关（只） | F4: 合计（只）
B5: 机器人 | C5: 丝杠 | D5: =COUNTIFS('概念展开'!$A$2:$A$130,B5,'概念展开'!$B$2:$B$130,C5,'概念展开'!$C$2:$C$130,"核心") | E5: =COUNTIFS('概念展开'!$A$2:$A$130,B5,'概念展开'!$B$2:$B$130,C5,'概念展开'!$C$2:$C$130,"相关") | F5: =SUM(D5:E5)
B6: 机器人 | C6: 丝杠设备 | D6: =COUNTIFS('概念展开'!$A$2:$A$130,B6,'概念展开'!$B$2:$B$130,C6,'概念展开'!$C$2:$C$130,"核心") | E6: =COUNTIFS('概念展开'!$A$2:$A$130,B6,'概念展开'!$B$2:$B$130,C6,'概念展开'!$C$2:$C$130,"相关") | F6: =SUM(D6:E6)
B7: 机器人 | C7: 丝杠零部件 | D7: =COUNTIFS('概念展开'!$A$2:$A$130,B7,'概念展开'!$B$2:$B$130,C7,'概念展开'!$C$2:$C$130,"核心") | E7: =COUNTIFS('概念展开'!$A$2:$A$130,B7,'概念展开'!$B$2:$B$130,C7,'概念展开'!$C$2:$C$130,"相关") | F7: =SUM(D7:E7)
B8: 机器人 | C8: 伺服系统 | D8: =COUNTIFS('概念展开'!$A$2:$A$130,B8,'概念展开'!$B$2:$B$130,C8,'概念展开'!$C$2:$C$130,"核心") | E8: =COUNTIFS('概念展开'!$A$2:$A$130,B8,'概念展开'!$B$2:$B$130,C8,'概念展开'!$C$2:$C$130,"相关") | F8: =SUM(D8:E8)
B9: 机器人 | C9: 关节模组 | D9: =COUNTIFS('概念展开'!$A$2:$A$130,B9,'概念展开'!$B$2:$B$130,C9,'概念展开'!$C$2:$C$130,"核心") | E9: =COUNTIFS('概念展开'!$A$2:$A$130,B9,'概念展开'!$B$2:$B$130,C9,'概念展开'!$C$2:$C$130,"相关") | F9: =SUM(D9:E9)
B10: 机器人 | C10: 减速器 | D10: =COUNTIFS('概念展开'!$A$2:$A$130,B10,'概念展开'!$B$2:$B$130,C10,'概念展开'!$C$2:$C$130,"核心") | E10: =COUNTIFS('概念展开'!$A$2:$A$130,B10,'概念展开'!$B$2:$B$130,C10,'概念展开'!$C$2:$C$130,"相关") | F10: =SUM(D10:E10)
B11: 机器人 | C11: 减速器零部件 | D11: =COUNTIFS('概念展开'!$A$2:$A$130,B11,'概念展开'!$B$2:$B$130,C11,'概念展开'!$C$2:$C$130,"核心") | E11: =COUNTIFS('概念展开'!$A$2:$A$130,B11,'概念展开'!$B$2:$B$130,C11,'概念展开'!$C$2:$C$130,"相关") | F11: =SUM(D11:E11)
B12: 机器人 | C12: 加工刀具 | D12: =COUNTIFS('概念展开'!$A$2:$A$130,B12,'概念展开'!$B$2:$B$130,C12,'概念展开'!$C$2:$C$130,"核心") | E12: =COUNTIFS('概念展开'!$A$2:$A$130,B12,'概念展开'!$B$2:$B$130,C12,'概念展开'!$C$2:$C$130,"相关") | F12: =SUM(D12:E12)
B13: 机器人 | C13: 场景应用 | D13: =COUNTIFS('概念展开'!$A$2:$A$130,B13,'概念展开'!$B$2:$B$130,C13,'概念展开'!$C$2:$C$130,"核心") | E13: =COUNTIFS('概念展开'!$A$2:$A$130,B13,'概念展开'!$B$2:$B$130,C13,'概念展开'!$C$2:$C$130,"相关") | F13: =SUM(D13:E13)
B14: 机器人 | C14: 工业自动化 | D14: =COUNTIFS('概念展开'!$A$2:$A$130,B14,'概念展开'!$B$2:$B$130,C14,'概念展开'!$C$2:$C$130,"核心") | E14: =COUNTIFS('概念展开'!$A$2:$A$130,B14,'概念展开'!$B$2:$B$130,C14,'概念展开'!$C$2:$C$130,"相关") | F14: =SUM(D14:E14)
B15: 机器人 | C15: 弹性元件 | D15: =COUNTIFS('概念展开'!$A$2:$A$130,B15,'概念展开'!$B$2:$B$130,C15,'概念展开'!$C$2:$C$130,"核心") | E15: =COUNTIFS('概念展开'!$A$2:$A$130,B15,'概念展开'!$B$2:$B$130,C15,'概念展开'!$C$2:$C$130,"相关") | F15: =SUM(D15:E15)
B16: 机器人 | C16: 微型链/灵巧手 | D16: =COUNTIFS('概念展开'!$A$2:$A$130,B16,'概念展开'!$B$2:$B$130,C16,'概念展开'!$C$2:$C$130,"核心") | E16: =COUNTIFS('概念展开'!$A$2:$A$130,B16,'概念展开'!$B$2:$B$130,C16,'概念展开'!$C$2:$C$130,"相关") | F16: =SUM(D16:E16)
... B39: 物理AI | C39: 物理AI_通信模组 | D39: =COUNTIFS('概念展开'!$A$2:$A$130,B39,'概念展开'!$B$2:$B$130,C39,'概念展开'!$C$2:$C$130,"核心") | E39: =COUNTIFS('概念展开'!$A$2:$A$130,B39,'概念展开'!$B$2:$B$130,C39,'概念展开'!$C$2:$C$130,"相关") | F39: =SUM(D39:E39)
B40: 合计（概念次数，非股票去重数） | D40: =SUM(D5:D39) | E40: =SUM(E5:E39) | F40: =SUM(F5:F39)
