Workbook

Sheet 封面
B2: 网络安全概念深度清洗报告
B3: 复核日期：2026-10-27｜范围：45只｜重点：真实产品、商业化、分类边界与详细理由
B6: 复核股票（只） | C6: =COUNTA('清洗总表'!$B$5:$B$49)
B7: 保留网络安全（只） | C7: =COUNTA('网络安全'!$B$5:$B$42)
B8: 核心判词（只） | C8: =COUNTIF('清洗总表'!$H$5:$H$49,"核心")
B9: 相关判词（只） | C9: =COUNTIF('清洗总表'!$H$5:$H$49,"相关")
B10: 完全摘除（只） | C10: =COUNTA('摘除清单'!$B$5:$B$11)
B11: 纠错动作（只） | C11: =COUNTIF('清洗总表'!$E$5:$E$49,"纠错")
B12: 新增动作（只） | C12: =COUNTIF('清洗总表'!$E$5:$E$49,"新增")
B15: 工作表索引
B16: 清洗总表 | C16: 45只旧概念、新概念、动作、判词、详细理由和证据
B17: 网络安全 | C17: 38只清洗后网络安全公司
B18: 摘除清单 | C18: 7只错标、内部治理或落地不足公司
B19: 概念统计 | C19: 47个二级概念的核心/相关数量
B23: 核心：网络安全产品或服务是明确主营、重要收入或规模化核心产品；相关：有真实产品、客户、项目或收入，但仍属新业务或占比较低。
B24: 普通安防、IDC托管、信息化集成、传媒VR、内部审核和纸币鉴伪不直接纳入；央企或国资背景也不再作为独立二级概念。
B25: “其他”“国家队”“字节生态”等泛标签已按防火墙、密码、数据安全、内容安全、安全运营、DPI等真实业务重新归类。
B26: 主营资料：iFinD ifind_get_stock_info（2026-10-27）；逐股证据名称、日期及URL见Source列。

Sheet 清洗总表
B2: 网络安全 · 45只逐项复核
B3: 逐股核对主营、产品、客户与商业化证据；重写详细理由并清理泛化、错标标签。
B4: 代码 | C4: 名称 | D4: 旧网络安全概念 | E4: 动作 | F4: 新一级分类 | G4: 新概念 | H4: 判词 | I4: 详细理由 | J4: 证据名称 | K4: 证据日期 | L4: Source Name | M4: Source URL
B5: 000156 | C5: 华数传媒 | D5: 网络安全：AI监管-内容审核 | E5: 纠错 | F5: 网络安全 | G5: 内容安全与智能审核 | H5: 相关 | I5: 公司主营仍是有线电视、新媒体、宽带和智慧城市，并非通用网络安全厂商；但2025年报披露文盾大模型已完成文化市场综合执法国家级试点阶段研发并取得一定规模合同营收，同时升级智能审核与播控治理体系，说明内容安全监管已有真实客户项目和商业化，而非仅内部制度或战略设想。因未披露该业务独立收入且相对九十余亿元营收仍属新业务，新增内容安全标签并定相关。 | J5: 华数传媒：2025年年度报告 | K5: 2026-03-21 | L5: iFinD ifind_get_stock_info (as of 2026-10-27)；华数传媒：2025年年度报告 | M5: https://money.finance.sina.com.cn/corp/view/vCB_AllBulletinDetail.php?stockid=000156&id=12009319
B6: 000681 | C6: 视觉中国 | D6: 网络安全：字节生态 | E6: 摘除 | F6: — | G6: — | H6: 摘除 | I6: 公司主营是正版图片、视频等视觉内容授权、创意定制及数据服务。年报中的AI质量审核、版权查重和合规审核主要服务于自有素材平台入库与交易治理，光厂创意的智能审核也用于自身作品管理，未证明向外部客户销售独立内容安全产品或审核服务；可信时间戳等能力还涉及战略投资企业。版权授权、内部平台审核和AI训练素材经营不能直接等同网络安全主营，故删除错误的字节生态标签且不新增网安概念。 | J6: 视觉中国：2025年年度报告 | K6: 2026-03-31 | L6: iFinD ifind_get_stock_info (as of 2026-10-27)；视觉中国：2025年年度报告 | M6: https://money.finance.sina.com.cn/corp/view/vCB_AllBulletinDetail.php?stockid=000681&id=12047786
B7: 000839 | C7: 国安股份 | D7: 网络安全：AI监管-内容审核 | E7: 纠错 | F7: 网络安全 | G7: 内容安全与审核服务 | H7: 相关 | I7: 公司通过子公司鸿联九五开展企业数智综合服务，2025年半年报明确列示内容审核业务，面向互联网平台、社交应用和电商提供文本、图片、视频、音频及直播内容安全审核，属于已实际经营的外包审核服务，与内容安全直接相关，并非传统电信业务贴安全标签。不过公司收入还包含有线电视、房地产及其他企业综合服务，未单独披露审核收入占比，因此保留为相关，并将泛化的AI监管表述纠正为内容安全与审核服务。 | J7: 国安股份：2025年半年度报告 | K7: 2025-08-23 | L7: iFinD ifind_get_stock_info (as of 2026-10-27)；国安股份：2025年半年度报告 | M7: http://money.finance.sina.com.cn/corp/view/vCB_AllBulletinDetail.php?stockid=000839&id=11339850
B8: 002212 | C8: 天融信 | D8: 网络安全：其他 | E8: 纠错 | F8: 网络安全 | G8: 防火墙与零信任、数据安全、安全运营与托管服务 | H8: 核心 | I8: 公司长期提供防火墙、VPN、WAF、零信任、数据安全及安全运营等产品和服务，网络安全是明确主营而非概念延伸。2025年网络安全行业收入25.56亿元，占营业收入99.37%，其中网络安全产品收入21.52亿元，智算云为另一产品线；安全服务亦按运营、维护、咨询等合同确认收入，商业化规模充分。原“其他”完全不能体现实际业务，故按优势产品及交付形态细化为防火墙与零信任、数据安全和安全运营与托管服务，维持核心。 | J8: 天融信：2025年年度报告 | K8: 2026-04-24 | L8: iFinD ifind_get_stock_info (as of 2026-10-27)；天融信：2025年年度报告 | M8: http://money.finance.sina.com.cn/corp/view/vCB_AllBulletinDetail.php?stockid=002212&id=12168962
B9: 002268 | C9: 电科网安 | D9: 网络安全：国家队 | E9: 纠错 | F9: 网络安全 | G9: 密码与身份认证、数据安全、网络安全运营 | H9: 核心 | I9: 公司以密码为核心提供网络安全和数据安全产品、服务及解决方案，实际产品覆盖密码基础算力、纵向加密、网络防护、数据安全合规平台和安全运营中心。2025年数据安全与网络安全行业收入占营收100%，其中密码收入10.36亿元、网络安全收入11.76亿元、数据安全收入0.56亿元，主营和规模化收入证据充分。保留核心不是因为央企背景，而是基于完整产品体系和收入结构；将“国家队”改为密码与身份认证、数据安全及网络安全运营。 | J9: 电科网安：2025年年度报告 | K9: 2026-04-18 | L9: iFinD ifind_get_stock_info (as of 2026-10-27)；电科网安：2025年年度报告 | M9: http://money.finance.sina.com.cn/corp/view/vCB_AllBulletinDetail.php?stockid=002268&id=12113837
B10: 002279 | C10: 久其软件 | D10: 网络安全：其他 | E10: 摘除 | F10: — | G10: — | H10: 摘除 | I10: 公司主要向政企客户提供数字政府、数智财务、资产管理、数据智能和数字传播产品。2025年报所述安全底座、DevOps加固、灾备、应急响应和项目安全巡检，主要用于保障女娲平台及既有信息化项目交付；新获软件安全开发、安全集成资质也只是交付能力证明，未显示独立网络安全产品、客户项目收入或规模化安全服务。庭审音视频脱敏属于智慧司法应用，不足以支撑通用网安标签，故摘除原“其他”。 | J10: 北京久其软件股份有限公司2025年年度报告全文 | K10: 2026-04-25 | L10: iFinD ifind_get_stock_info (as of 2026-10-27)；北京久其软件股份有限公司2025年年度报告全文 | M10: https://static.cninfo.com.cn/finalpage/2026-04-25/1225189930.PDF
B11: 002362 | C11: 汉王科技 | D11: 网络安全：AI监管-内容标识 | E11: 摘除 | F11: — | G11: — | H11: 摘除 | I11: 公司以模式识别和智能交互为基础，2025年收入主要来自笔智能交互、AI终端和多模态大数据，应用包括数字绘画、无纸化签批、智慧司法及数字人文。年报及现有主营资料未证明AI生成内容标识、深度伪造检测或内容安全审核已形成对外销售产品，更无对应客户、项目或收入；电子签名、OCR、档案数字化及商用密码经营范围也不能替代实际网安业务证据。因此原“AI监管-内容标识”属于技术印象延伸，予以摘除。 | J11: 汉王科技股份有限公司2025年年度报告全文 | K11: 2026-03-28 | L11: iFinD ifind_get_stock_info (as of 2026-10-27)；汉王科技股份有限公司2025年年度报告全文 | M11: http://static.cninfo.com.cn/finalpage/2026-03-28/1225045555.PDF
B12: 002439 | C12: 启明星辰 | D12: 网络安全：国家队 | E12: 纠错 | F12: 网络安全 | G12: 安全运营与托管服务、防火墙与零信任、数据安全 | H12: 核心 | I12: 公司安全产品和安全运营与托管服务两条主线覆盖安全网关、IDS/IPS、日志审计、零信任、数据安全和托管安全。2025年信息网络安全收入23.17亿元，占营收99.10%，其中安全产品12.67亿元、安全运营与服务10.50亿元；专线卫士已服务超过7.2万家政企客户，数据安全和密评密改亦有项目落地。核心判断依据是主营收入及规模化客户，而非中国移动控股背景，故将“国家队”纠正为具体产品与运营标签。 | J12: 启明星辰：2025年年度报告 | K12: 2026-04-13 | L12: iFinD ifind_get_stock_info (as of 2026-10-27)；启明星辰：2025年年度报告 | M12: https://money.finance.sina.com.cn/corp/view/vCB_AllBulletinDetail.php?stockid=002439&id=12082100
B13: 002912 | C13: 中新赛克 | D13: 网络安全：网安细分-网络可视化 | E13: 纠错 | F13: 网络安全 | G13: 网络可视化、网络内容安全、数据安全 | H13: 核心 | I13: 公司宽带网和移动网产品直接提取、解析网络流量，构成网络可视化基础架构；网络内容安全和数据与网络安全产品则面向政府、运营商及海外客户交付。2025年网络内容安全收入1.95亿元，占25.94%，数据与网络安全收入0.16亿元，网络可视化基础架构仍是主要收入来源，相关产品合计已构成明确主营和重要收入，不应再仅定相关。故升级为核心，并保留网络可视化、补充网络内容安全及数据安全三个具体方向。 | J13: 中新赛克：2025年年度报告 | K13: 2026-03-18 | L13: iFinD ifind_get_stock_info (as of 2026-10-27)；中新赛克：2025年年度报告 | M13: https://money.finance.sina.com.cn/corp/view/vCB_AllBulletinDetail.php?stockid=002912&id=12001026
B14: 003029 | C14: 吉大正元 | D14: 网络安全：抗量子密码 | E14: 纠错 | F14: 网络安全 | G14: 密码与身份认证、抗量子密码 | H14: 核心 | I14: 公司以密码技术为核心，主营PKI、数字证书、签名、身份认证、安全网关及网络安全服务，并通过子公司实际开展电子认证服务。2025年上半年全部收入均归入信息安全行业，网络安全产品、生态和服务分别占53.97%、9.83%和36.19%，商业化主营属性明确；同时将传统密码、量子密码与抗量子密码能力整合，抗量子属于真实技术布局但不能替代其PKI主业标签。因此维持核心，将单一抗量子标签纠正为密码与身份认证并保留抗量子密码。 | J14: 吉大正元：2025年半年度报告 | K14: 2025-08-28 | L14: iFinD ifind_get_stock_info (as of 2026-10-27)；吉大正元：2025年半年度报告 | M14: http://vip.stock.finance.sina.com.cn/corp/view/vCB_AllBulletinDetail.php?stockid=003029&id=11384651
B15: 300017 | C15: 网宿科技 | D15: 网络安全：网安细分-云安全CDN | E15: 纠错 | F15: 网络安全 | G15: 云安全与CDN、零信任与SASE | H15: 核心 | I15: 公司以CDN及边缘计算为基本盘，同时实际提供WAAP、DDoS防护、Web及API安全、零信任、SASE和SD-WAN等产品，依托全球节点以直销和订阅方式收费，不是给普通CDN简单贴安全标签。2025年安全及增值服务收入13.80亿元，同比增长18.65%，占营收29.61%，公司亦将安全列为核心业务之一，已达到重要收入和规模化产品标准。故由相关升级为核心，将旧称规范为云安全与CDN、零信任与SASE。 | J15: 网宿科技股份有限公司2025年年度报告全文 | K15: 2026-04-15 | L15: iFinD ifind_get_stock_info (as of 2026-10-27)；网宿科技股份有限公司2025年年度报告全文 | M15: https://static.cninfo.com.cn/finalpage/2026-04-15/1225101555.PDF
... B49: 000004 | C49: 国华网安 | D49: 网络安全：其他 | E49: 纠错 | F49: 网络安全 | G49: 移动应用安全 | H49: 核心 | I49: 公司拥有移动应用安全工具和平台产品，2025年报显示爱加密覆盖APP漏洞与隐私合规检测、安全加固、渠道监测和移动威胁感知，服务监管、测评及企业客户；移动应用安全业务收入1.005亿元、占56.82%，加固与检测平台均达到预定用途，属于规模化主营而非普通移动信息化。即使公司新增医药等业务并处于退市状态，本轮仍按业务实质定为核心，将其他纠错为移动应用安全。 | J49: *ST国华：2025年年度报告 | K49: 2026-04-28 | L49: iFinD ifind_get_stock_info (as of 2026-10-27)；*ST国华：2025年年度报告 | M49: https://vip.stock.finance.sina.com.cn/corp/view/vCB_AllBulletinDetail.php?stockid=000004&id=12235717

Sheet 网络安全
B2: 网络安全 · 清洗后38只股池
B3: 核心30只、相关8只；按实际产品与交付细化为47个二级概念。
B4: 代码 | C4: 名称 | D4: 旧网络安全概念 | E4: 动作 | F4: 新一级分类 | G4: 新概念 | H4: 判词 | I4: 详细理由 | J4: 证据名称 | K4: 证据日期 | L4: Source Name | M4: Source URL
B5: 000156 | C5: 华数传媒 | D5: 网络安全：AI监管-内容审核 | E5: 纠错 | F5: 网络安全 | G5: 内容安全与智能审核 | H5: 相关 | I5: 公司主营仍是有线电视、新媒体、宽带和智慧城市，并非通用网络安全厂商；但2025年报披露文盾大模型已完成文化市场综合执法国家级试点阶段研发并取得一定规模合同营收，同时升级智能审核与播控治理体系，说明内容安全监管已有真实客户项目和商业化，而非仅内部制度或战略设想。因未披露该业务独立收入且相对九十余亿元营收仍属新业务，新增内容安全标签并定相关。 | J5: 华数传媒：2025年年度报告 | K5: 2026-03-21 | L5: iFinD ifind_get_stock_info (as of 2026-10-27)；华数传媒：2025年年度报告 | M5: https://money.finance.sina.com.cn/corp/view/vCB_AllBulletinDetail.php?stockid=000156&id=12009319
B6: 000839 | C6: 国安股份 | D6: 网络安全：AI监管-内容审核 | E6: 纠错 | F6: 网络安全 | G6: 内容安全与审核服务 | H6: 相关 | I6: 公司通过子公司鸿联九五开展企业数智综合服务，2025年半年报明确列示内容审核业务，面向互联网平台、社交应用和电商提供文本、图片、视频、音频及直播内容安全审核，属于已实际经营的外包审核服务，与内容安全直接相关，并非传统电信业务贴安全标签。不过公司收入还包含有线电视、房地产及其他企业综合服务，未单独披露审核收入占比，因此保留为相关，并将泛化的AI监管表述纠正为内容安全与审核服务。 | J6: 国安股份：2025年半年度报告 | K6: 2025-08-23 | L6: iFinD ifind_get_stock_info (as of 2026-10-27)；国安股份：2025年半年度报告 | M6: http://money.finance.sina.com.cn/corp/view/vCB_AllBulletinDetail.php?stockid=000839&id=11339850
B7: 002212 | C7: 天融信 | D7: 网络安全：其他 | E7: 纠错 | F7: 网络安全 | G7: 防火墙与零信任、数据安全、安全运营与托管服务 | H7: 核心 | I7: 公司长期提供防火墙、VPN、WAF、零信任、数据安全及安全运营等产品和服务，网络安全是明确主营而非概念延伸。2025年网络安全行业收入25.56亿元，占营业收入99.37%，其中网络安全产品收入21.52亿元，智算云为另一产品线；安全服务亦按运营、维护、咨询等合同确认收入，商业化规模充分。原“其他”完全不能体现实际业务，故按优势产品及交付形态细化为防火墙与零信任、数据安全和安全运营与托管服务，维持核心。 | J7: 天融信：2025年年度报告 | K7: 2026-04-24 | L7: iFinD ifind_get_stock_info (as of 2026-10-27)；天融信：2025年年度报告 | M7: http://money.finance.sina.com.cn/corp/view/vCB_AllBulletinDetail.php?stockid=002212&id=12168962
B8: 002268 | C8: 电科网安 | D8: 网络安全：国家队 | E8: 纠错 | F8: 网络安全 | G8: 密码与身份认证、数据安全、网络安全运营 | H8: 核心 | I8: 公司以密码为核心提供网络安全和数据安全产品、服务及解决方案，实际产品覆盖密码基础算力、纵向加密、网络防护、数据安全合规平台和安全运营中心。2025年数据安全与网络安全行业收入占营收100%，其中密码收入10.36亿元、网络安全收入11.76亿元、数据安全收入0.56亿元，主营和规模化收入证据充分。保留核心不是因为央企背景，而是基于完整产品体系和收入结构；将“国家队”改为密码与身份认证、数据安全及网络安全运营。 | J8: 电科网安：2025年年度报告 | K8: 2026-04-18 | L8: iFinD ifind_get_stock_info (as of 2026-10-27)；电科网安：2025年年度报告 | M8: http://money.finance.sina.com.cn/corp/view/vCB_AllBulletinDetail.php?stockid=002268&id=12113837
B9: 002439 | C9: 启明星辰 | D9: 网络安全：国家队 | E9: 纠错 | F9: 网络安全 | G9: 安全运营与托管服务、防火墙与零信任、数据安全 | H9: 核心 | I9: 公司安全产品和安全运营与托管服务两条主线覆盖安全网关、IDS/IPS、日志审计、零信任、数据安全和托管安全。2025年信息网络安全收入23.17亿元，占营收99.10%，其中安全产品12.67亿元、安全运营与服务10.50亿元；专线卫士已服务超过7.2万家政企客户，数据安全和密评密改亦有项目落地。核心判断依据是主营收入及规模化客户，而非中国移动控股背景，故将“国家队”纠正为具体产品与运营标签。 | J9: 启明星辰：2025年年度报告 | K9: 2026-04-13 | L9: iFinD ifind_get_stock_info (as of 2026-10-27)；启明星辰：2025年年度报告 | M9: https://money.finance.sina.com.cn/corp/view/vCB_AllBulletinDetail.php?stockid=002439&id=12082100
B10: 002912 | C10: 中新赛克 | D10: 网络安全：网安细分-网络可视化 | E10: 纠错 | F10: 网络安全 | G10: 网络可视化、网络内容安全、数据安全 | H10: 核心 | I10: 公司宽带网和移动网产品直接提取、解析网络流量，构成网络可视化基础架构；网络内容安全和数据与网络安全产品则面向政府、运营商及海外客户交付。2025年网络内容安全收入1.95亿元，占25.94%，数据与网络安全收入0.16亿元，网络可视化基础架构仍是主要收入来源，相关产品合计已构成明确主营和重要收入，不应再仅定相关。故升级为核心，并保留网络可视化、补充网络内容安全及数据安全三个具体方向。 | J10: 中新赛克：2025年年度报告 | K10: 2026-03-18 | L10: iFinD ifind_get_stock_info (as of 2026-10-27)；中新赛克：2025年年度报告 | M10: https://money.finance.sina.com.cn/corp/view/vCB_AllBulletinDetail.php?stockid=002912&id=12001026
B11: 003029 | C11: 吉大正元 | D11: 网络安全：抗量子密码 | E11: 纠错 | F11: 网络安全 | G11: 密码与身份认证、抗量子密码 | H11: 核心 | I11: 公司以密码技术为核心，主营PKI、数字证书、签名、身份认证、安全网关及网络安全服务，并通过子公司实际开展电子认证服务。2025年上半年全部收入均归入信息安全行业，网络安全产品、生态和服务分别占53.97%、9.83%和36.19%，商业化主营属性明确；同时将传统密码、量子密码与抗量子密码能力整合，抗量子属于真实技术布局但不能替代其PKI主业标签。因此维持核心，将单一抗量子标签纠正为密码与身份认证并保留抗量子密码。 | J11: 吉大正元：2025年半年度报告 | K11: 2025-08-28 | L11: iFinD ifind_get_stock_info (as of 2026-10-27)；吉大正元：2025年半年度报告 | M11: http://vip.stock.finance.sina.com.cn/corp/view/vCB_AllBulletinDetail.php?stockid=003029&id=11384651
B12: 300017 | C12: 网宿科技 | D12: 网络安全：网安细分-云安全CDN | E12: 纠错 | F12: 网络安全 | G12: 云安全与CDN、零信任与SASE | H12: 核心 | I12: 公司以CDN及边缘计算为基本盘，同时实际提供WAAP、DDoS防护、Web及API安全、零信任、SASE和SD-WAN等产品，依托全球节点以直销和订阅方式收费，不是给普通CDN简单贴安全标签。2025年安全及增值服务收入13.80亿元，同比增长18.65%，占营收29.61%，公司亦将安全列为核心业务之一，已达到重要收入和规模化产品标准。故由相关升级为核心，将旧称规范为云安全与CDN、零信任与SASE。 | J12: 网宿科技股份有限公司2025年年度报告全文 | K12: 2026-04-15 | L12: iFinD ifind_get_stock_info (as of 2026-10-27)；网宿科技股份有限公司2025年年度报告全文 | M12: https://static.cninfo.com.cn/finalpage/2026-04-15/1225101555.PDF
B13: 300079 | C13: 数码视讯 | D13: 网络安全：AI监管-AI鉴伪 | E13: 纠错 | F13: 网络安全 | G13: 内容安全与AI鉴伪、数字版权保护与数字水印 | H13: 相关 | I13: 公司主体仍是视频技术、广电设备、应急广播和通信服务，但公共安全产品已形成内容版权标识、DRM加密、数字水印、版权监测、电子证据采集及音视频AI鉴伪标识系统，能够直接服务内容安全和传播溯源。2025年报披露DRM及条件接收系统已在数十个电信、广电运营商落地，证明并非仅有研发预期；AI鉴伪为新增产品且未单列收入，整体安全业务占比也未充分披露，因此维持相关，并细分AI鉴伪与数字版权水印标签。 | J13: 数码视讯：2025年年度报告 | K13: 2026-04-17 | L13: iFinD ifind_get_stock_info (as of 2026-10-27)；数码视讯：2025年年度报告 | M13: http://money.finance.sina.com.cn/corp/view/vCB_AllBulletinDetail.php?stockid=300079&id=12100785
B14: 300188 | C14: 国投智能 | D14: 网络安全：国家队 | E14: 纠错 | F14: 网络安全 | G14: 电子数据取证、网络空间安全 | H14: 核心 | I14: 公司电子数据取证和网络信息安全产品是明确主营，手机取证大师、计算机取证大师、取证云及新网络空间安全产品均有销售、交付和订单转化，不是依靠国投背景归类。2025年电子数据取证收入5.48亿元，占38.80%；新网络空间安全收入1.18亿元，占8.37%，另有公共安全大数据业务支撑司法与执法场景，核心产品及收入证据充分。因此维持核心，将泛化“国家队”纠正为电子数据取证和网络空间安全两个真实业务标签。 | J14: 国投智能：2025年年度报告 | K14: 2026-04-18 | L14: iFinD ifind_get_stock_info (as of 2026-10-27)；国投智能：2025年年度报告 | M14: https://money.finance.sina.com.cn/corp/view/vCB_AllBulletinDetail.php?stockid=300188&id=12112119
B15: 300229 | C15: 拓尔思 | D15: 网络安全：AI监管-内容审核 | E15: 纠错 | F15: 网络安全 | G15: 数据安全、安全隔离与数据交换 | H15: 核心 | I15: 公司虽以人工智能和大数据软件为更大业务板块，但全资子公司天行网安实际销售安全隔离网闸、单向光闸、安全数据与视频交换、边界监管及隐私计算产品，直接对应数据安全和跨域边界防护。2025年安全产品收入0.94亿元，占营收18.32%，同比增长26.97%；天行网安营业收入1.15亿元，已形成重要收入而非概念性布局，按统一标准应定核心。原内容审核表述过窄，改标数据安全、安全隔离与数据交换。 | J15: 拓尔思：2025年年度报告 | K15: 2026-04-15 | L15: iFinD ifind_get_stock_info (as of 2026-10-27)；拓尔思：2025年年度报告 | M15: https://vip.stock.finance.sina.com.cn/corp/view/vCB_AllBulletinDetail.php?stockid=300229&id=12089699
... B42: 000004 | C42: 国华网安 | D42: 网络安全：其他 | E42: 纠错 | F42: 网络安全 | G42: 移动应用安全 | H42: 核心 | I42: 公司拥有移动应用安全工具和平台产品，2025年报显示爱加密覆盖APP漏洞与隐私合规检测、安全加固、渠道监测和移动威胁感知，服务监管、测评及企业客户；移动应用安全业务收入1.005亿元、占56.82%，加固与检测平台均达到预定用途，属于规模化主营而非普通移动信息化。即使公司新增医药等业务并处于退市状态，本轮仍按业务实质定为核心，将其他纠错为移动应用安全。 | J42: *ST国华：2025年年度报告 | K42: 2026-04-28 | L42: iFinD ifind_get_stock_info (as of 2026-10-27)；*ST国华：2025年年度报告 | M42: https://vip.stock.finance.sina.com.cn/corp/view/vCB_AllBulletinDetail.php?stockid=000004&id=12235717

Sheet 摘除清单
B2: 摘除清单 · 7只错标与落地不足
B3: 普通信息化、内部平台治理、纸币鉴伪、传媒VR及参股关系不直接计入网络安全。
B4: 代码 | C4: 名称 | D4: 旧网络安全概念 | E4: 动作 | F4: 新一级分类 | G4: 新概念 | H4: 判词 | I4: 详细理由 | J4: 证据名称 | K4: 证据日期 | L4: Source Name | M4: Source URL
B5: 000681 | C5: 视觉中国 | D5: 网络安全：字节生态 | E5: 摘除 | F5: — | G5: — | H5: 摘除 | I5: 公司主营是正版图片、视频等视觉内容授权、创意定制及数据服务。年报中的AI质量审核、版权查重和合规审核主要服务于自有素材平台入库与交易治理，光厂创意的智能审核也用于自身作品管理，未证明向外部客户销售独立内容安全产品或审核服务；可信时间戳等能力还涉及战略投资企业。版权授权、内部平台审核和AI训练素材经营不能直接等同网络安全主营，故删除错误的字节生态标签且不新增网安概念。 | J5: 视觉中国：2025年年度报告 | K5: 2026-03-31 | L5: iFinD ifind_get_stock_info (as of 2026-10-27)；视觉中国：2025年年度报告 | M5: https://money.finance.sina.com.cn/corp/view/vCB_AllBulletinDetail.php?stockid=000681&id=12047786
B6: 002279 | C6: 久其软件 | D6: 网络安全：其他 | E6: 摘除 | F6: — | G6: — | H6: 摘除 | I6: 公司主要向政企客户提供数字政府、数智财务、资产管理、数据智能和数字传播产品。2025年报所述安全底座、DevOps加固、灾备、应急响应和项目安全巡检，主要用于保障女娲平台及既有信息化项目交付；新获软件安全开发、安全集成资质也只是交付能力证明，未显示独立网络安全产品、客户项目收入或规模化安全服务。庭审音视频脱敏属于智慧司法应用，不足以支撑通用网安标签，故摘除原“其他”。 | J6: 北京久其软件股份有限公司2025年年度报告全文 | K6: 2026-04-25 | L6: iFinD ifind_get_stock_info (as of 2026-10-27)；北京久其软件股份有限公司2025年年度报告全文 | M6: https://static.cninfo.com.cn/finalpage/2026-04-25/1225189930.PDF
B7: 002362 | C7: 汉王科技 | D7: 网络安全：AI监管-内容标识 | E7: 摘除 | F7: — | G7: — | H7: 摘除 | I7: 公司以模式识别和智能交互为基础，2025年收入主要来自笔智能交互、AI终端和多模态大数据，应用包括数字绘画、无纸化签批、智慧司法及数字人文。年报及现有主营资料未证明AI生成内容标识、深度伪造检测或内容安全审核已形成对外销售产品，更无对应客户、项目或收入；电子签名、OCR、档案数字化及商用密码经营范围也不能替代实际网安业务证据。因此原“AI监管-内容标识”属于技术印象延伸，予以摘除。 | J7: 汉王科技股份有限公司2025年年度报告全文 | K7: 2026-03-28 | L7: iFinD ifind_get_stock_info (as of 2026-10-27)；汉王科技股份有限公司2025年年度报告全文 | M7: http://static.cninfo.com.cn/finalpage/2026-03-28/1225045555.PDF
B8: 300551 | C8: 古鳌科技 | D8: 网络安全：AI监管-AI鉴伪 | E8: 摘除 | F8: — | G8: — | H8: 摘除 | I8: iFinD主营为金融设备研发、生产、销售与服务，2025年报进一步列示金融机具设备及服务收入占比90.06%，所谓“鉴伪”主要是点验钞机、清分机利用图像、荧光、磁性、红外等技术识别纸币真伪，并非AIGC内容鉴伪、数据安全或网络防护。印鉴卡授权管理、档案柜防调包也只是金融实物设备功能，未找到可商业化的网络安全产品、客户或项目，因此摘除旧AI鉴伪标签。 | J8: 上海古鳌电子科技股份有限公司2025年年度报告 | K8: 2026-04-28 | L8: iFinD ifind_get_stock_info (as of 2026-10-27)；上海古鳌电子科技股份有限公司2025年年度报告 | M8: https://static.cninfo.com.cn/finalpage/2026-04-28/1225223150.PDF
B9: 600728 | C9: 佳都科技 | D9: 网络安全：AI监管-内容标识 | E9: 摘除 | F9: — | G9: — | H9: 摘除 | I9: iFinD及2025年报显示公司主营企业数智化、智慧轨道交通和城市交通管理，核心产品为交通佳鸿操作系统、知行交通大模型、信号控制及轨交综合监控等，未找到AIGC内容标识、内容溯源或鉴伪产品及对应客户项目。企业数智化业务虽渠道集成网络、安全、安防产品并拓展360数字安全等合作厂商，但属于通用ICT分销集成，不等于自身网络安全主营；内部数据安全治理也不能作为对外产品证据，故摘除旧内容标识标签。 | J9: 佳都科技：2025年年度报告 | K9: 2026-04-10 | L9: iFinD ifind_get_stock_info (as of 2026-10-27)；佳都科技：2025年年度报告 | M9: https://money.finance.sina.com.cn/corp/view/vCB_AllBulletinDetail.php?stockid=600728&id=12074772
B10: 600736 | C10: 苏州高新 | D10: 网络安全：AI监管-内容审核 | E10: 摘除 | F10: — | G10: — | H10: 摘除 | I10: iFinD主营为房地产开发及基础设施经营，2025年报披露的业务板块是产业园运营、高端装备、产业投资、产城综合开发、环保和融资租赁，未见上市公司自营内容审核、内容安全或其他网络安全产品、项目及收入。园区招商、基金投资和参股科技企业只形成财务投资或产业生态关系，不能把被投企业业务上升为上市公司主营，也没有证据支持旧“AI监管-内容审核”标签，因此予以摘除。 | J10: 苏州高新：2025年年度报告 | K10: 2026-04-28 | L10: iFinD ifind_get_stock_info (as of 2026-10-27)；苏州高新：2025年年度报告 | M10: https://money.finance.sina.com.cn/corp/view/vCB_AllBulletinDetail.php?stockid=600736&id=12216791
B11: 300081 | C11: 恒信东方 | D11: 网络安全：AI监管-数字水印 | E11: 摘除 | F11: — | G11: — | H11: 摘除 | I11: 公司2025年报显示业务为数字创意、互联网视频应用及算力系统集成，具体包括LBE文旅场馆、VR/CG内容、AI合家欢、VR游戏和影视视效制作；报告期内项目亦集中于博物馆、景区、动画与AI短片。未找到可核验的数字水印安全产品、客户、项目或收入，经营范围中的网络与信息安全软件开发不能替代落地证据，因此旧AI监管-数字水印属于把普通传媒及VR业务贴上安全标签，本轮直接摘除网络安全分类。 | J11: 恒信东方文化股份有限公司2025年年度报告摘要 | K11: 2026-04-28 | L11: iFinD ifind_get_stock_info (as of 2026-10-27)；恒信东方文化股份有限公司2025年年度报告摘要 | M11: http://static.cninfo.com.cn/finalpage/2026-04-28/1225220515.PDF

Sheet 概念展开
A1: 一级分类 | B1: 二级概念 | C1: 判词 | D1: 代码 | E1: 名称
A2: 网络安全 | B2: 内容安全与智能审核 | C2: 相关 | D2: 000156 | E2: 华数传媒
A3: 网络安全 | B3: 内容安全与审核服务 | C3: 相关 | D3: 000839 | E3: 国安股份
A4: 网络安全 | B4: 防火墙与零信任 | C4: 核心 | D4: 002212 | E4: 天融信
A5: 网络安全 | B5: 数据安全 | C5: 核心 | D5: 002212 | E5: 天融信
A6: 网络安全 | B6: 安全运营与托管服务 | C6: 核心 | D6: 002212 | E6: 天融信
A7: 网络安全 | B7: 密码与身份认证 | C7: 核心 | D7: 002268 | E7: 电科网安
A8: 网络安全 | B8: 数据安全 | C8: 核心 | D8: 002268 | E8: 电科网安
A9: 网络安全 | B9: 网络安全运营 | C9: 核心 | D9: 002268 | E9: 电科网安
A10: 网络安全 | B10: 安全运营与托管服务 | C10: 核心 | D10: 002439 | E10: 启明星辰
A11: 网络安全 | B11: 防火墙与零信任 | C11: 核心 | D11: 002439 | E11: 启明星辰
A12: 网络安全 | B12: 数据安全 | C12: 核心 | D12: 002439 | E12: 启明星辰
... A68: 网络安全 | B68: 移动应用安全 | C68: 核心 | D68: 000004 | E68: 国华网安

Sheet 概念统计
B2: 概念统计 · 核心/相关分布
B3: 公式引用隐藏展开表精确计数；一只股票可对应多个概念。
B4: 一级分类 | C4: 二级概念 | D4: 核心（只） | E4: 相关（只） | F4: 合计（只）
B5: 网络安全 | C5: AI安全 | D5: =COUNTIFS('概念展开'!$A$2:$A$68,B5,'概念展开'!$B$2:$B$68,C5,'概念展开'!$C$2:$C$68,"核心") | E5: =COUNTIFS('概念展开'!$A$2:$A$68,B5,'概念展开'!$B$2:$B$68,C5,'概念展开'!$C$2:$C$68,"相关") | F5: =SUM(D5:E5)
B6: 网络安全 | C6: DPI与流量智能 | D6: =COUNTIFS('概念展开'!$A$2:$A$68,B6,'概念展开'!$B$2:$B$68,C6,'概念展开'!$C$2:$C$68,"核心") | E6: =COUNTIFS('概念展开'!$A$2:$A$68,B6,'概念展开'!$B$2:$B$68,C6,'概念展开'!$C$2:$C$68,"相关") | F6: =SUM(D6:E6)
B7: 网络安全 | C7: Web应用安全 | D7: =COUNTIFS('概念展开'!$A$2:$A$68,B7,'概念展开'!$B$2:$B$68,C7,'概念展开'!$C$2:$C$68,"核心") | E7: =COUNTIFS('概念展开'!$A$2:$A$68,B7,'概念展开'!$B$2:$B$68,C7,'概念展开'!$C$2:$C$68,"相关") | F7: =SUM(D7:E7)
B8: 网络安全 | C8: 专用安全终端与测控安全 | D8: =COUNTIFS('概念展开'!$A$2:$A$68,B8,'概念展开'!$B$2:$B$68,C8,'概念展开'!$C$2:$C$68,"核心") | E8: =COUNTIFS('概念展开'!$A$2:$A$68,B8,'概念展开'!$B$2:$B$68,C8,'概念展开'!$C$2:$C$68,"相关") | F8: =SUM(D8:E8)
B9: 网络安全 | C9: 云安全 | D9: =COUNTIFS('概念展开'!$A$2:$A$68,B9,'概念展开'!$B$2:$B$68,C9,'概念展开'!$C$2:$C$68,"核心") | E9: =COUNTIFS('概念展开'!$A$2:$A$68,B9,'概念展开'!$B$2:$B$68,C9,'概念展开'!$C$2:$C$68,"相关") | F9: =SUM(D9:E9)
B10: 网络安全 | C10: 云安全与CDN | D10: =COUNTIFS('概念展开'!$A$2:$A$68,B10,'概念展开'!$B$2:$B$68,C10,'概念展开'!$C$2:$C$68,"核心") | E10: =COUNTIFS('概念展开'!$A$2:$A$68,B10,'概念展开'!$B$2:$B$68,C10,'概念展开'!$C$2:$C$68,"相关") | F10: =SUM(D10:E10)
B11: 网络安全 | C11: 云安全与SASE | D11: =COUNTIFS('概念展开'!$A$2:$A$68,B11,'概念展开'!$B$2:$B$68,C11,'概念展开'!$C$2:$C$68,"核心") | E11: =COUNTIFS('概念展开'!$A$2:$A$68,B11,'概念展开'!$B$2:$B$68,C11,'概念展开'!$C$2:$C$68,"相关") | F11: =SUM(D11:E11)
B12: 网络安全 | C12: 保密安全 | D12: =COUNTIFS('概念展开'!$A$2:$A$68,B12,'概念展开'!$B$2:$B$68,C12,'概念展开'!$C$2:$C$68,"核心") | E12: =COUNTIFS('概念展开'!$A$2:$A$68,B12,'概念展开'!$B$2:$B$68,C12,'概念展开'!$C$2:$C$68,"相关") | F12: =SUM(D12:E12)
B13: 网络安全 | C13: 内容安全与AI鉴伪 | D13: =COUNTIFS('概念展开'!$A$2:$A$68,B13,'概念展开'!$B$2:$B$68,C13,'概念展开'!$C$2:$C$68,"核心") | E13: =COUNTIFS('概念展开'!$A$2:$A$68,B13,'概念展开'!$B$2:$B$68,C13,'概念展开'!$C$2:$C$68,"相关") | F13: =SUM(D13:E13)
B14: 网络安全 | C14: 内容安全与审核服务 | D14: =COUNTIFS('概念展开'!$A$2:$A$68,B14,'概念展开'!$B$2:$B$68,C14,'概念展开'!$C$2:$C$68,"核心") | E14: =COUNTIFS('概念展开'!$A$2:$A$68,B14,'概念展开'!$B$2:$B$68,C14,'概念展开'!$C$2:$C$68,"相关") | F14: =SUM(D14:E14)
B15: 网络安全 | C15: 内容安全与智能审核 | D15: =COUNTIFS('概念展开'!$A$2:$A$68,B15,'概念展开'!$B$2:$B$68,C15,'概念展开'!$C$2:$C$68,"核心") | E15: =COUNTIFS('概念展开'!$A$2:$A$68,B15,'概念展开'!$B$2:$B$68,C15,'概念展开'!$C$2:$C$68,"相关") | F15: =SUM(D15:E15)
B16: 网络安全 | C16: 内容安全与模型安全 | D16: =COUNTIFS('概念展开'!$A$2:$A$68,B16,'概念展开'!$B$2:$B$68,C16,'概念展开'!$C$2:$C$68,"核心") | E16: =COUNTIFS('概念展开'!$A$2:$A$68,B16,'概念展开'!$B$2:$B$68,C16,'概念展开'!$C$2:$C$68,"相关") | F16: =SUM(D16:E16)
... B51: 网络安全 | C51: 零信任与SASE | D51: =COUNTIFS('概念展开'!$A$2:$A$68,B51,'概念展开'!$B$2:$B$68,C51,'概念展开'!$C$2:$C$68,"核心") | E51: =COUNTIFS('概念展开'!$A$2:$A$68,B51,'概念展开'!$B$2:$B$68,C51,'概念展开'!$C$2:$C$68,"相关") | F51: =SUM(D51:E51)
B52: 合计（概念次数，非股票去重数） | D52: =SUM(D5:D51) | E52: =SUM(E5:E51) | F52: =SUM(F5:F51)
